Workbook

Sheet START HERE
A1: AI Automation Pricing Calculator - SAFE VERSION
A3: Purpose | B3: Clean, Excel-safe pricing workbook. It avoids advanced lookup formulas, tables, and data-validation objects that can sometimes trigger Excel repair messages.
A4: How to use | B4: Use Package Reference to select the package. Then manually copy the base low/high values into Quote Calculator yellow cells.
A5: Yellow cells | B5: Editable input cells.
A6: Blue cells | B6: Calculated output cells.
A7: Grey/reference sheets | B7: Internal reference and examples.
A8: Why this safe version | B8: Previous workbook likely had a compatibility/repair issue caused by advanced formulas or workbook metadata. This version uses simple formulas only.
A9: Client sharing | B9: Do not send internal pricing logic to client. Use Client Quote Summary as a clean external view.
A10: Version | B10: safe v4 - editable reference lists + auto lookup
A11: Created | B11: 2026-06-23
A12: Recommended workflow | B12: 1) pick package → 2) copy base ranges → 3) enter complexity → 4) review calculated quote → 5) copy client summary.
A13: Audit note | B13: Use 'Quote Calculator FIXED' for commercial quotes. Original calculator is retained as legacy/comparison.

Sheet Package Reference
A1: Package Pricing Reference
A2: EDITABLE RANGE: update package names, price ranges, scope notes and access model here. Quote Calculator reads columns A:E by package name.
A3: Package | B3: Setup Low | C3: Setup High | D3: Monthly Low | E3: Monthly High | F3: Typical scope | G3: Best for | H3: Access model | I3: Internal note | J3: Commercial label | K3: Typical use by automation type
A4: Basic Intake | B4: 750 | C4: 1800 | D4: 150 | E4: 450 | F4: Email/forms intake, rule-based routing, booking link, simple folders/labels | G4: Simple intake, low complexity | H4: Results/dashboard only | I4: Keep scope tight | J4: AI Intake Basic | K4: Communication & Intake; Document routing (no AI extraction); E-commerce order notifications; Finance reminders. Rule-based only — no AI required.
A5: Basic+ AI Triage | B5: 1500 | C5: 3500 | D5: 300 | E5: 750 | F5: AI classification, CRM/Notion log, folder routing, draft support | G5: MG Red Shift-style workflow | H5: Results/dashboard + workflow summary | I5: Good first AI package | J5: AI Intake Triage Basic+ | K5: Communication & Intake (AI classify); Lead & Sales Pipeline (CRM log); Document Processing (AI field extraction); Customer Support (ticket triage); E-commerce (AI categorisation).
A6: Pro Multi-Channel | B6: 3500 | C6: 7500 | D6: 750 | E6: 1500 | F6: Email + social media, AI classification, drafts, approval workflow | G6: Multiple channels, repeated questions | H6: Dashboard + workflow chart | I6: Needs fallback and approval gates | J6: AI Workflow Pro | K6: Communication & Intake (multi-source); Content & Marketing (AI draft + publish review); Lead & Sales Pipeline (multi-source pipeline); Document Processing (multi-source); Customer Support (multi-channel triage).
A7: Managed Operations | B7: 7500 | C7: 15000 | D7: 1500 | E7: 3500 | F7: CRM, monitoring, reports, monthly improvements, support | G7: Ongoing operational support | H7: Dashboard, reports, limited logic visibility | I7: Define support limits | J7: Managed AI Operations | K7: Reporting & Analytics (KPI digests, management reports); Finance & Admin (reconciliation, overdue reminders); Internal Ops & Approvals (ongoing routing); Scheduling & Booking (managed flows). Any category requiring ongoing monitoring and improvement.
A8: Agentic Automation | B8: 12000 | C8: 30000 | D8: 2500 | E8: 6000 | F8: Calendar/CRM actions, multi-step decisions, audit and governance | G8: Complex controlled actions | H8: Approval console + blueprint summary | I8: Quote individually | J8: Agentic AI Operations | K8: Scheduling & Booking (AI slot proposals, calendar actions); Lead & Sales Pipeline (autonomous follow-up sequences); Finance & Admin (exception detection + action); Internal Ops (conditional approval chains). Any category needing multi-step AI decisions with audit.
A9: Build-and-Transfer | B9: 4500 | C9: 15000 | D9: 0 | E9: 1000 | F9: Automation built in client workspace and handed over | G9: Client wants ownership | H9: Full access/export/documentation | I9: LEGACY — do not select as package. Use a scope package in C5 and set Access model = Build-and-transfer in C6. | J9: Build & Transfer | K9: All automation categories — applies when client requires full IP and operational ownership post-handover, regardless of automation type.

Sheet Complexity Reference
A1: Complexity Adders & Multipliers | K1: Support Model Lookup - Editable
A3: Factor | B3: Setup Low | C3: Setup High | D3: Monthly Low | E3: Monthly High | F3: Rule | G3: When to apply | H3: Notes | I3: Example | K3: Support Model | L3: Monthly Multiplier | M3: Setup Handover Multiplier | N3: Typical Use | O3: Client Access | P3: Support Responsibility | Q3: Pricing Note | R3: Internal Note
A4: Extra data sources / triggers | B4: 500 | C4: 1500 | D4: 100 | E4: 300 | F4: per source / trigger | G4: Additional data source, trigger, or inbound channel beyond the scope included in the package | H4: Email inbox, social DM, document upload trigger, API feed, scheduled database poll | I4: invoice email trigger + webhook + Instagram DM = 3 sources | K4: No support | L4: 0 | M4: 1 | N4: Build-and-transfer with no monthly support | O4: Full handover | P4: None after handover | Q4: 0x monthly | R4: Legacy setup multiplier normalized to 1. Setup premium now belongs to Access Models / fixed calculator.
A5: AI generation steps | B5: 500 | C5: 2000 | D5: 150 | E5: 500 | F5: per workflow type | G5: AI generates any output: reply drafts, extracted document fields, summarised text, repurposed content | H5: Each distinct AI generation type adds complexity — count per type, not per execution | I5: invoice field extraction + booking reply draft = 2 generation steps | K5: Light support | L5: 0.5 | M5: 1 | N5: Client owns automation, occasional help | O5: Full/limited | P5: Limited fixes | Q5: 0.5x monthly | R5: Legacy setup multiplier normalized to 1. Setup premium now belongs to Access Models / fixed calculator.
A6: CRM integration | B6: 750 | C6: 2500 | D6: 200 | E6: 600 | F6: per CRM | G6: Notion/Airtable/HubSpot records | H6: Status and field mapping | I6: Notion DB | K6: Normal managed support | L6: 1 | M6: 1 | N6: Default managed service | O6: Dashboard/results | P6: Normal monitoring/support | Q6: 1.0x monthly | R6: Default.
A7: Approval workflow | B7: 750 | C7: 2000 | D7: 150 | E7: 500 | F7: per approval path | G7: Human review needed | H7: Important for sensitive sectors | I7: approve before send | K7: High-responsibility maintenance | L7: 1.5 | M7: 1 | N7: Important business workflow | O7: Dashboard/results + stronger control | P7: Higher reliability support | Q7: 1.5x monthly | R7: Setup premium should be explicit via access model/manual add, not hidden in support model.
A8: Reporting layer | B8: 500 | C8: 2000 | D8: 250 | E8: 900 | F8: yes/no | G8: Dashboards, summaries, KPI reports | H8: Managed service | I8: monthly report | K8: Premium transfer support | L8: 2 | M8: 1 | N8: Transferred asset but you still maintain | O8: Full handover | P8: Ongoing maintenance | Q8: 2.0x monthly | R8: Use Access Models / fixed calculator for transfer setup premium.
A9: Sensitive data | B9: 0 | C9: 0 | D9: 0 | E9: 0 | F9: x1.3 to x1.7 | G9: Health/legal/finance/high privacy | H9: Apply mainly to setup and monthly | I9: therapist | K9: Critical support | L9: 3 | M9: 1 | N9: Complex/agentic/high-risk system | O9: Full/controlled | P9: High responsibility | Q9: Up to 3.0x monthly | R9: Use manual setup add/urgency multiplier for critical setup impact.
A10: Urgency | B10: 0 | C10: 0 | D10: 0 | E10: 0 | F10: x1.2 to x1.5 | G10: Fast delivery required | H10: Apply to setup | I10: launch this week
A11: Full handover | B11: 0 | C11: 0 | D11: 0 | E11: 0 | F11: x1.5 to x3.0 | G11: Client receives scenario/blueprint | H11: Build-and-transfer | I11: own Make workspace
A13: Monthly support model | B13: Monthly multiplier | C13: Typical monthly logic | D13: Use when | E13: Client receives | F13: You remain responsible for | G13: Example | H13: Pricing note | I13: Internal decision
A14: No support | B14: 0 | C14: No recurring fee | D14: Build-and-transfer with no support | E14: Delivered automation only | F14: Nothing after handover | G14: client self-maintains | H14: 0x monthly | I14: Use rarely
A15: Light support | B15: 0.5 | C15: Ad-hoc checks / small fixes | D15: Client owns automation but may need help | E15: Occasional support | F15: Limited support only | G15: quarterly help | H15: 0.5x to 1.0x monthly | I15: Define hours
A16: Normal managed support | B16: 1 | C16: Standard monitoring and minor improvements | D16: Managed service default | E16: Reports/support | F16: Normal reliability support | G16: Basic+/Pro managed | H16: 1.0x monthly | I16: Default
A17: High-responsibility maintenance | B17: 1.5 | C17: Strong monitoring, quick fixes, change support | D17: Client owns or depends heavily on system | E17: Higher support availability | F17: Higher operational responsibility | G17: mission-critical workflow | H17: 1.5x to 3.0x monthly | I17: Premium
A18: Premium transfer support | B18: 2 | C18: Transferred asset + ongoing maintenance | D18: Build-and-transfer but you still maintain it | E18: Full asset + managed care | F18: Ongoing maintenance despite transfer | G18: client owns Make, you maintain | H18: 2.0x typical | I18: Charge clearly
A19: Critical support | B19: 3 | C19: High urgency / high responsibility | D19: Complex agentic systems | E19: Priority support | F19: Major ongoing responsibility | G19: Calendar/CRM agent with SLA-like expectation | H19: Up to 3.0x monthly | I19: Custom quote

Sheet Quote Calculator
A1: Quote Calculator — Package / Access Model / Support Model (v8)
A3: Step | B3: Field | C3: Value | D3: Explanation | F3: Client-facing summary | J3: Available Packages | L3: Available Access Models | N3: Available Support Models | Q3: Support model | T3: Meaning
A4: 1 | B4: Client / project name | D4: EDIT | F4: Project | G4: =C4 -> 0 | J4: ='Package Reference'!A4 -> Basic Intake | L4: ='Access Models'!A5 -> Logic visibility | N4: ='Complexity Reference'!K4 -> No support | Q4: No support | T4: build-and-transfer, client owns risk
A5: 2 | B5: Selected package | C5: Basic Intake | D5: EDIT: scope package only — excludes Build-and-Transfer (use Access model C6 = Build-and-transfer for handover projects) | F5: Package | G5: =C5 -> Basic Intake | J5: ='Package Reference'!A5 -> Basic+ AI Triage | L5: ='Access Models'!A6 -> Limited admin | N5: ='Complexity Reference'!K5 -> Light support | Q5: Light support | T5: occasional checks/fixes
A6: 3 | B6: Access / ownership model | C6: Managed service | D6: EDIT: controls setup/handover premium only (not monthly) | F6: Access model | G6: =C6 -> Managed service | J6: ='Package Reference'!A6 -> Pro Multi-Channel | L6: ='Access Models'!A7 -> Client-owned workspace | N6: ='Complexity Reference'!K6 -> Normal managed support | Q6: Normal managed support | T6: default for business workflow
A7: 4 | B7: Support model | C7: Normal managed support | D7: EDIT: controls monthly maintenance cost only (not setup) | F7: Support model | G7: =C7 -> Normal managed support | J7: ='Package Reference'!A7 -> Managed Operations | L7: ='Access Models'!A8 -> Build-and-transfer | N7: ='Complexity Reference'!K7 -> High-responsibility maintenance | Q7: High-responsibility support | T7: stronger monitoring, faster response
F8: Setup range | G8: ="CHF "&ROUND(C34,0)&" - CHF "&ROUND(C35,0) -> CHF 2250 - CHF 6300 | J8: ='Package Reference'!A8 -> Agentic Automation | L8: ='Access Models'!A9 -> 0 | N8: ='Complexity Reference'!K8 -> Premium transfer support | Q8: Agentic Automation | T8: Premium transfer support
A9: 5 | B9: Base setup low | C9: =IFERROR(VLOOKUP(C5,'Package Reference'!$A$4:$E$8,2,FALSE()),0) -> 750 | D9: CALC from Package Reference | F9: Monthly range | G9: ="CHF "&ROUND(C36,0)&" - CHF "&ROUND(C37,0) -> CHF 500 - CHF 1550 | N9: ='Complexity Reference'!K9 -> Critical support | Q9: Critical support | T9: for operationally sensitive workflows
A10: 6 | B10: Base setup high | C10: =IFERROR(VLOOKUP(C5,'Package Reference'!$A$4:$E$8,3,FALSE()),0) -> 1800 | D10: CALC from Package Reference | F10: Recommended setup | G10: ="CHF "&ROUND(C38,0) -> CHF 4300
A11: 7 | B11: Base monthly low | C11: =IFERROR(VLOOKUP(C5,'Package Reference'!$A$4:$E$8,4,FALSE()),0) -> 150 | D11: CALC from Package Reference | F11: Recommended monthly | G11: ="CHF "&ROUND(C39,0) -> CHF 1000
A12: 8 | B12: Base monthly high | C12: =IFERROR(VLOOKUP(C5,'Package Reference'!$A$4:$E$8,5,FALSE()),0) -> 450 | D12: CALC from Package Reference | F12: Notes | G12: Prices exclude third-party tool/API usage unless agreed.
A13: 9 | B13: Auto access setup multiplier | C13: =IFERROR(VLOOKUP(C6,'Access Models'!$A$5:$K$9,10,FALSE()),1) -> 1 | D13: CALC from Access Models col J — access model controls setup premium, not support model | F13: List sources | G13: Package Ref A4:A9 | Access Models A4:A8 | Complexity Ref K4:K9
A14: 10 | B14: Auto monthly support multiplier | C14: =IFERROR(VLOOKUP(C7,'Complexity Reference'!$K$4:$M$9,2,FALSE()),1) -> 1 | D14: CALC from support model (monthly multiplier only)
A16: 11 | B16: Extra data sources / triggers count | C16: 0 | D16: EDIT: count each additional data source, trigger, or inbound channel beyond the base package. In Make.com: each separate webhook endpoint, app trigger, API source, or scheduled data pull. E.g. Instagram DM = 1, invoice email inbox = 1, API poll = 1. Do NOT count the primary source included in the selected package. | F16: Extra data sources / triggers — examples | G16: Each distinct inbound source beyond the base package (separate webhook endpoint, app trigger or API feed).
A17: 12 | B17: AI generation steps count | C17: 1 | D17: EDIT: count each distinct AI generation step — any HTTP module calling OpenAI or Claude for any purpose. Count per generation TYPE, not per execution. E.g. booking reply draft = 1. Invoice field extraction + booking reply draft = 2. Content repurposing call = 1. | F17: Example values:
A18: 13 | B18: CRM integrations count | C18: 1 | D18: EDIT: count each external CRM or database system connected via Make.com (Notion, HubSpot, Airtable, Google Sheets used as a CRM, etc.). Count per SYSTEM, not per module. Notion with 3 Notion modules = still 1. Notion + HubSpot = 2. | F18: Primary source included in package = 0
A19: 14 | B19: Approval workflows count | C19: 1 | D19: EDIT: count each route where Make.com pauses and a human must review and approve before the automation sends or acts. SEEKER draft reviewed by human before reply = 1. Auto folder-move with no human gate = 0. Multiple gated routes = count each gate separately. | F19: Website form on a separate webhook = 1
A20: 15 | B20: Reporting layer count | C20: 0 | D20: EDIT: 0 or 1. Use 1 only if the automation writes structured output to a reporting layer: Google Sheets analytics view, Notion summary dashboard, or similar. Test-folder logging does NOT count. Standard Notion CRM entries do NOT count as reporting. | F20: Website form + Instagram DM = 2; or invoice email + webhook = 2
A21: 16 | B21: Sensitive data multiplier | C21: 1 | D21: EDIT: normal = 1.0. Increase if handling sensitive data: 1.3 for confidential business info (contracts, financials, HR); 1.5 for GDPR-sensitive or EU-only data; 1.7 for health records or personal identity data. Always discuss data handling explicitly with the client before applying. | F21: Website + Instagram + invoice email = 3; or 3 distinct API sources = 3
A22: 17 | B22: Urgency multiplier | C22: 1 | D22: EDIT: normal = 1.0. Use 1.2 for 2–3 week delivery. Use 1.3–1.5 for hard deadlines within days (compressed build, testing and handover). Never exceed 1.5.
A23: 18 | B23: Manual setup multiplier override | D23: OPTIONAL EDIT: leave blank to use the access model auto-value (from the col L lookup). Override only when the auto value does not fit — e.g. Managed service selected but this project has unusually complex API credential setup or multi-environment staging. | F23: AI generation steps — examples | G23: Each distinct HTTP module calling OpenAI / Claude (count per draft type, any email volume).
A24: 19 | B24: Manual monthly support multiplier override | D24: OPTIONAL EDIT: leave blank to use the support model auto-value. Override only when the auto value does not reflect the agreed SLA — e.g. Normal support selected but client has a faster-response agreement that is not yet in the reference table. | F24: Example values:
A25: 20 | B25: Manual custom setup add | C25: 0 | D25: EDIT: add one-time costs not covered by the package adder prices. — Make.com plan upgrade (if client account needs a higher ops tier) — Third-party API onboarding or account setup fee — Domain / DNS configuration — First-month OpenAI / Claude credit (if client pre-funds a budget) OPERATIONAL PASS-THROUGH: Make.com operations and API token costs are variable and best invoiced monthly with actuals. Use this field for a one-time estimate only if the client needs a total upfront budget figure. | F25: Classify or route only, no AI generation call = 0
A26: 21 | B26: Manual custom monthly add | C26: 0 | D26: EDIT: add ongoing monthly operational costs not covered by the support multiplier. These are direct pass-through costs you pay to providers: — Make.com operations budget: CHF 15–30/month simple (< 500 ops/day); CHF 30–60/month moderate (500–2,000 ops/day); CHF 60–120/month complex multi-branch scenario — OpenAI / Claude API tokens: CHF 10–20/month for ~200–500 AI drafts; CHF 20–40/month for ~500–2,000 AI drafts Best practice: leave C26 = 0 in the quote and invoice these monthly with actuals. Only fix a value here if the client requires a total-cost-of-ownership budget upfront. | F26: One AI generation type (reply draft, field extraction, or content call) = 1
F27: Booking reply draft + invoice field extraction = 2; or repurposing + reply = 2
B28: Effective setup/access multiplier | C28: =IF(C23="",C13,C23) -> 1 | D28: CALC
B29: Effective monthly support multiplier | C29: =IF(C24="",C14,C24) -> 1 | D29: CALC | F29: CRM integrations — Make.com context | G29: Each external database / CRM connected (Notion, HubSpot, Airtable, Google Sheets as CRM). Count per system, not per module.
B30: Setup subtotal low (before multipliers) | C30: =C9+C16*IFERROR(VLOOKUP("Extra channel",'Complexity Reference'!$A$4:$E$8,2,FALSE()),0)+C17*IFERROR(VLOOKUP("AI draft workflow",'Complexity Reference'!$A$4:$E$8,2,FALSE()),0)+C18*IFERROR(VLOOKUP("CRM integration",'Complexity Reference'!$A$4:$E$8,2,FALSE()),0)+C19*IFERROR(VLOOKUP("Approval workflow",'Complexity Reference'!$A$4:$E$8,2,FALSE()),0)+C20*IFERROR(VLOOKUP("Reporting layer",'Complexity Reference'!$A$4:$E$8,2,FALSE()),0)+C25 -> 2250 | D30: CALC | F30: Example values:
B31: Setup subtotal high (before multipliers) | C31: =C10+C16*IFERROR(VLOOKUP("Extra channel",'Complexity Reference'!$A$4:$E$8,3,FALSE()),0)+C17*IFERROR(VLOOKUP("AI draft workflow",'Complexity Reference'!$A$4:$E$8,3,FALSE()),0)+C18*IFERROR(VLOOKUP("CRM integration",'Complexity Reference'!$A$4:$E$8,3,FALSE()),0)+C19*IFERROR(VLOOKUP("Approval workflow",'Complexity Reference'!$A$4:$E$8,3,FALSE()),0)+C20*IFERROR(VLOOKUP("Reporting layer",'Complexity Reference'!$A$4:$E$8,3,FALSE()),0)+C25 -> 6300 | D31: CALC | F31: Folder routing only, no CRM = 0
B32: Monthly subtotal low (before support multiplier) | C32: =C11+C16*IFERROR(VLOOKUP("Extra channel",'Complexity Reference'!$A$4:$E$8,4,FALSE()),0)+C17*IFERROR(VLOOKUP("AI draft workflow",'Complexity Reference'!$A$4:$E$8,4,FALSE()),0)+C18*IFERROR(VLOOKUP("CRM integration",'Complexity Reference'!$A$4:$E$8,4,FALSE()),0)+C19*IFERROR(VLOOKUP("Approval workflow",'Complexity Reference'!$A$4:$E$8,4,FALSE()),0)+C20*IFERROR(VLOOKUP("Reporting layer",'Complexity Reference'!$A$4:$E$8,4,FALSE()),0)+C26 -> 500 | D32: CALC | F32: Notion only (any number of Notion modules) = 1
B33: Monthly subtotal high (before support multiplier) | C33: =C12+C16*IFERROR(VLOOKUP("Extra channel",'Complexity Reference'!$A$4:$E$8,5,FALSE()),0)+C17*IFERROR(VLOOKUP("AI draft workflow",'Complexity Reference'!$A$4:$E$8,5,FALSE()),0)+C18*IFERROR(VLOOKUP("CRM integration",'Complexity Reference'!$A$4:$E$8,5,FALSE()),0)+C19*IFERROR(VLOOKUP("Approval workflow",'Complexity Reference'!$A$4:$E$8,5,FALSE()),0)+C20*IFERROR(VLOOKUP("Reporting layer",'Complexity Reference'!$A$4:$E$8,5,FALSE()),0)+C26 -> 1550 | D33: CALC | F33: Notion + HubSpot = 2
B34: Calculated setup low | C34: =ROUND(C30*C21*C22*C28,0) -> 2250 | D34: CALC
B35: Calculated setup high | C35: =ROUND(C31*C21*C22*C28,0) -> 6300 | D35: CALC | F35: Approval workflows — Make.com context | G35: Each route where Make.com pauses and a human must review / approve before it sends or acts.
B36: Calculated monthly low | C36: =ROUND(C32*C21*C29,0) -> 500 | D36: CALC | F36: Example values:
B37: Calculated monthly high | C37: =ROUND(C33*C21*C29,0) -> 1550 | D37: CALC | F37: Auto folder-move only, no human gate = 0
B38: Recommended setup quote | C38: =ROUND((C34+C35)/2,-2) -> 4300 | D38: CALC | F38: SEEKER draft reviewed by human before reply = 1
B39: Recommended monthly quote | C39: =ROUND((C36+C37)/2,-2) -> 1000 | D39: CALC | F39: SEEKER gated + LEAD CRM entry requires approval = 2
B41: Quote Sanity Check (auto) | F41: Reporting layer — Make.com context
B42: Check | C42: Status | D42: Detail | F42: Example values:
B43: Package name matches Reference | C43: =IF(C5="","empty",IF(C9=0,"FAIL","OK")) -> OK | D43: =IF(C5="","Pick a package from column J (5 scope packages only).",IF(C9=0,IF(LOWER(C5)="build-and-transfer","Build-and-Transfer is an access model — select scope package in C5 and set C6 = Build-and-transfer.","Package name doesn't match Package Reference — use column J list."),"Package found in Reference.")) -> Package found in Reference. | F43: Test-folder log only = 0
B44: Access model matches Reference | C44: =IF(C6="","empty",IF(IFERROR(MATCH(C6,'Access Models'!$A$5:$A$9,0),0)=0,"FAIL","OK")) -> FAIL | D44: =IF(C6="","Pick an access model from column L.",IF(IFERROR(MATCH(C6,'Access Models'!$A$5:$A$9,0),0)=0,"Access model doesn't match Access Models — use column L list.","Access model found.")) -> Access model doesn't match Access Models — use column L list. | F44: Notion analytics view or Google Sheets report = 1
B45: Support model matches Reference | C45: =IF(C7="","empty",IF(AND(C14=0,C7<>"No support"),"FAIL","OK")) -> OK | D45: =IF(C7="","Pick a support model from column N.",IF(AND(C14=0,C7<>"No support"),"Support model doesn't match Complexity Reference — use column N list.","Support model found.")) -> Support model found. | F45: Multiple separate reporting dashboards = 2 (rare)
B46: Sensitive data has approval workflow | C46: =IF(C21<=1,"n/a",IF(OR(C19="",C19=0),"WARN","OK")) -> n/a | D46: =IF(C21<=1,"Sensitive multiplier not applied.",IF(OR(C19="",C19=0),"Sensitive data multiplier applied but Approval workflows count is 0 — sensitive content should always have at least 1 approval workflow.","Sensitive + approval workflow OK.")) -> Sensitive multiplier not applied. | F46: C25 one-time add — typical operational uses:
B47: Urgency multiplier reasonable | C47: =IF(OR(C22="",C22<=1),"OK",IF(C22>1.3,"WARN","OK")) -> OK | D47: =IF(OR(C22="",C22<=1),"No urgency premium.",IF(C22>1.3,"Urgency multiplier above 1.3 — confirm client accepts premium delivery cost.","Urgency premium within normal range.")) -> No urgency premium. | F47: Make.com plan upgrade (if client needs higher ops tier)
B48: Handover risk acknowledged | C48: =IF(AND(C6="Build-and-transfer",C7="No support"),"NOTE","n/a") -> n/a | D48: =IF(AND(C6="Build-and-transfer",C7="No support"),"Build-and-transfer + No support: client takes full operational risk after handover. Document this clearly.","") | F48: Third-party API onboarding or account setup fee
B49: Reporting fits package | C49: =IF(AND(C5="Basic Intake",OR(C20="",C20=0)=FALSE()),"WARN","OK") -> OK | D49: =IF(AND(C5="Basic Intake",OR(C20="",C20=0)=FALSE()),"Reporting layer on Basic Intake — consider upgrading to Managed Operations or higher.","Reporting layer fits selected package.") -> Reporting layer fits selected package. | F49: First-month OpenAI / Claude credit (pre-funded budget)
F50: C26 monthly add — operational pass-through costs:
B51: Tip: Status meanings: | C51: OK = no concern; | F51: Make.com ops: CHF 15–30 simple · 30–60 moderate · 60–120 complex /month
C52: WARN = check before sending quote; | F52: OpenAI / Claude tokens: CHF 10–20 / 200–500 drafts · 20–40 / 500–2000 drafts /month
C53: FAIL = formulas returning 0 because name doesn't match;
C54: NOTE = situation worth documenting in the client quote. | F54: MG Red Shift (14-module SEEKER CRM) — example inputs:
F55: Field | G55: Value
F56: Extra channels (C16) | G56: 0
F57: AI draft workflows (C17) | G57: 1
F58: CRM integrations (C18) | G58: 1
F59: Approval workflows (C19) | G59: 1
F60: Reporting layer (C20) | G60: 0
F61: Custom monthly add C26 (ops est.) | G61: CHF 30–60
F62: → Make.com ops estimate | G62: CHF 20–40 / month
F63: → OpenAI tokens estimate (SEEKER drafts) | G63: CHF 10–20 / month

Sheet ROI App
B2: ROI Automation Calculator
B4: Field | C4: Value | D4: Unit / Notes | G4: CASE STUDY | J4: CASE STUDY
B5: 1. CLIENT INPUTS | G5: MG1 | J5: MG2
B6: Hard ROI — Time Savings
B7: Employees Involved | C7: 2 | D7: people | G7: 4 | H7: people | J7: 2 | K7: people
B8: Hours Lost / Week | C8: 5 | D8: hours / week | G8: 2 | H8: hours / week | J8: 2 | K8: hours / week
B9: Hourly Rate (Gross) | C9: 100 | D9: CHF / hour | G9: 80 | H9: CHF / hour | J9: 80 | K9: CHF / hour
B11: Hard ROI — Error Reduction
B12: Mistakes / Week | C12: 5 | D12: mistakes / week | G12: 1 | H12: mistakes / week | J12: 1 | K12: mistakes / week
B13: Cost per Mistake | C13: 200 | D13: CHF / mistake | G13: 75 | H13: CHF / mistake | J13: 125 | K13: CHF / mistake
B15: Soft ROI — Lost Revenue
B16: Lost Leads / Month | C16: 10 | D16: leads / month | G16: 1 | H16: leads / month | J16: 2 | K16: leads / month
B17: Avg Value per Lead | C17: 1500 | D17: CHF / lead | G17: 1000 | H17: CHF / lead | J17: 125 | K17: CHF / lead
B19: Investment & Ongoing Costs
B20: One-Time Setup Cost | C20: 20000 | D20: CHF total | G20: 3500 | H20: CHF total | J20: 2500 | K20: CHF total
B21: Monthly Managed AI Ops Cost | C21: 2350 | D21: CHF / month — paste from Quote Calculator C39 (Recommended monthly quote) | G21: 1600 | H21: CHF / month | J21: 800 | K21: CHF / month
B23: 2. CALCULATED ROI | G23: ROI | J23: ROI
B25: Monthly Cost of Time | C25: =C7*C8*C9*4 -> 4000 | D25: CHF | G25: =G7*G8*G9*4 -> 2560 | H25: CHF | J25: =J7*J8*J9*4 -> 1280 | K25: CHF
B26: Monthly Cost of Errors | C26: =C12*C13*4 -> 4000 | D26: CHF | G26: =G12*G13*4 -> 300 | H26: CHF | J26: =J12*J13*4 -> 500 | K26: CHF
B27: Monthly Lost Revenue | C27: =C16*C17 -> 15000 | D27: CHF | G27: =G16*G17 -> 1000 | H27: CHF | J27: =J16*J17 -> 250 | K27: CHF
B28: Monthly Gross Benefit | C28: =SUM(C25:C27) -> 23000 | D28: CHF — cost of inaction | G28: =SUM(G25:G27) -> 3860 | H28: CHF — cost of inaction | J28: =SUM(J25:J27) -> 2030 | K28: CHF — cost of inaction
B29: (−) Monthly Managed AI Ops | C29: =C21 -> 2350 | D29: CHF | G29: =G21 -> 1600 | H29: CHF | J29: =J21 -> 800 | K29: CHF
B30: Net Monthly Benefit | C30: =C28-C29 -> 20650 | D30: CHF | G30: =G28-G29 -> 2260 | H30: CHF | J30: =J28-J29 -> 1230 | K30: CHF
B31: Annual Net Benefit | C31: =C30*12 -> 247800 | D31: CHF | G31: =G30*12 -> 27120 | H31: CHF | J31: =J30*12 -> 14760 | K31: CHF
B32: Total Year 1 Investment | C32: =C20+C21*12 -> 48200 | D32: CHF — setup + 12× monthly managed | G32: =G20+G21*12 -> 22700 | H32: CHF | J32: =J20+J21*12 -> 12100 | K32: CHF
B33: Payback Period | C33: =IF(C30<=0,"N/A",C20/C30) -> 0.968523 | D33: Months | G33: =IF(G30<=0,"N/A",G20/G30) -> 1.5486726 | H33: Months | J33: =IF(J30<=0,"N/A",J20/J30) -> 2.0325203 | K33: Months
B34: First-Year Net ROI | C34: =IF(C32=0,"N/A",(C31-C20)/C32) -> 4.7261411 | D34: % — net Y1 return ÷ total Y1 investment (setup + 12× monthly) | G34: =IF(G32=0,"N/A",(G31-G20)/G32) -> 1.0405286 | H34: % | J34: =IF(J32=0,"N/A",(J31-J20)/J32) -> 1.0132231 | K34: %
B35: Year 2+ Annual ROI | C35: =IF(C21=0,"N/A",C30*12/(C21*12)) -> 8.787234 | G35: =IF(G21=0,"N/A",G30*12/(G21*12)) -> 1.4125 | H35: % | J35: =IF(J21=0,"N/A",J30*12/(J21*12)) -> 1.5375 | K35: %
B37: 3. NEGOTIATION VIEW
B38: Value Ceiling (monthly) | C38: =IF(C20+C28=0,"N/A",(C28*12-C20)/12) -> 21333.333 | D38: CHF/month — max fee where client still breaks even in Year 1 | G38: =IF(G20+G28=0,"N/A",(G28*12-G20)/12) -> 3568.3333 | H38: CHF/month | J38: =IF(J20+J28=0,"N/A",(J28*12-J20)/12) -> 1821.6667 | K38: CHF/month
B39: Headroom — value kept by client | C39: =IF(C38="N/A","N/A",C38-C21) -> 18983.333 | D39: CHF/month below the ceiling. Use this when client says fee is high. | G39: =IF(G38="N/A","N/A",G38-G21) -> 1968.3333 | H39: CHF/month | J39: =IF(J38="N/A","N/A",J38-J21) -> 1021.6667 | K39: CHF/month
B41: Staffing alternative comparison
B42: Equiv. manual staffing cost | C42: 0 | D42: CHF/month — est. cost of person doing this manually. Rule of thumb CH: CHF 70k salary ≈ CHF 8,300/month fully loaded. Even 1 day/week ≈ CHF 2,000+. | G42: 0 | H42: CHF/month | J42: 0 | K42: CHF/month
B43: Automation saving vs. staffing | C43: =IF(C42=0,"(enter staffing cost above)",C42-C21) -> (enter staffing cost above) | D43: CHF/month saved vs. hiring. Negative = staffing is cheaper. | G43: =IF(G42=0,"(enter staffing cost above)",G42-G21) -> (enter staffing cost above) | H43: CHF/month | J43: =IF(J42=0,"(enter staffing cost above)",J42-J21) -> (enter staffing cost above) | K43: CHF/month
B45: Talking point — monthly fee objection: "Think of it like Krankenkasse. The best months are the ones where you never needed to call us. That's not money wasted — that's the system working. You pay for the guarantee of continuity, not for the number of incidents. And unlike Krankenkasse, here you can calculate the return."
B47: Tip: Monthly Managed AI Ops (C20) should match 'Recommended monthly quote' from Quote Calculator tab. First-Year Net ROI divides by total Year 1 spend (setup + 12× monthly). Year 2+ ROI shows the recurring return once setup is fully amortised.

Sheet ROI App_v1
B2: ROI Automation Calculator
B4: Field | C4: Value | D4: Unit / Notes
B5: 1. CLIENT INPUTS | G5: MGREDSHIFT
B6: Hard ROI — Time Savings
B7: Employees Involved | C7: 2 | D7: people | G7: 4 | H7: people
B8: Hours Lost / Week | C8: 5 | D8: hours / week | G8: 2 | H8: hours / week
B9: Hourly Rate (Gross) | C9: 100 | D9: CHF / hour | G9: 80 | H9: CHF / hour
B11: Hard ROI — Error Reduction
B12: Mistakes / Week | C12: 5 | D12: mistakes / week | G12: 1 | H12: mistakes / week
B13: Cost per Mistake | C13: 200 | D13: CHF / mistake | G13: 75 | H13: CHF / mistake
B15: Soft ROI — Lost Revenue
B16: Lost Leads / Month | C16: 10 | D16: leads / month | G16: 1 | H16: leads / month
B17: Avg Value per Lead | C17: 1500 | D17: CHF / lead | G17: 1000 | H17: CHF / lead
B19: Investment & Ongoing Costs
B20: One-Time Setup Cost | C20: 20000 | D20: CHF total | G20: 3500 | H20: CHF total
B21: Monthly Managed AI Ops Cost | C21: 2350 | D21: CHF / month — paste from Quote Calculator C39 (Recommended monthly quote) | G21: 1600 | H21: CHF / month
B23: 2. CALCULATED ROI | G23: ROI
B25: Monthly Cost of Time | C25: =C7*C8*C9*4 -> 4000 | D25: CHF | G25: =G7*G8*G9*4 -> 2560 | H25: CHF
B26: Monthly Cost of Errors | C26: =C12*C13*4 -> 4000 | D26: CHF | G26: =G12*G13*4 -> 300 | H26: CHF
B27: Monthly Lost Revenue | C27: =C16*C17 -> 15000 | D27: CHF | G27: =G16*G17 -> 1000 | H27: CHF
B28: Monthly Gross Benefit | C28: =SUM(C25:C27) -> 23000 | D28: CHF — cost of inaction | G28: =SUM(G25:G27) -> 3860 | H28: CHF — cost of inaction
B29: (−) Monthly Managed AI Ops | C29: =C21 -> 2350 | D29: CHF | G29: =G21 -> 1600 | H29: CHF
B30: Net Monthly Benefit | C30: =C28-C29 -> 20650 | D30: CHF | G30: =G28-G29 -> 2260 | H30: CHF
B31: Annual Net Benefit | C31: =C30*12 -> 247800 | D31: CHF | G31: =G30*12 -> 27120 | H31: CHF
B32: Total Year 1 Investment | C32: =C20+C21*12 -> 48200 | D32: CHF — setup + 12× monthly managed | G32: =G20+G21*12 -> 22700 | H32: CHF
B33: Payback Period | C33: =IF(C30<=0,"N/A",C20/C30) -> 0.968523 | D33: Months | G33: =IF(G30<=0,"N/A",G20/G30) -> 1.5486726 | H33: Months
B34: First-Year Net ROI | C34: =IF(C32=0,"N/A",(C31-C20)/C32) -> 4.7261411 | D34: % — net Y1 return ÷ total Y1 investment (setup + 12× monthly) | G34: =IF(G32=0,"N/A",(G31-G20)/G32) -> 1.0405286 | H34: %
B35: Year 2+ Annual ROI | C35: =IF(C21=0,"N/A",C30*12/(C21*12)) -> 8.787234 | G35: =IF(G21=0,"N/A",G30*12/(G21*12)) -> 1.4125 | H35: %
B37: Tip: Monthly Managed AI Ops (C20) should match 'Recommended monthly quote' from Quote Calculator tab. First-Year Net ROI divides by total Year 1 spend (setup + 12× monthly). Year 2+ ROI shows the recurring return once setup is fully amortised.

Sheet ROI App_v0
B2: ROI Automation Calculator
B4: Field | C4: Value | D4: Unit / Notes
B5: 1. CLIENT INPUTS | G5: MGREDSHIFT
B6: Hard ROI — Time Savings
B7: Employees Involved | C7: 2 | D7: people | G7: 4 | H7: people
B8: Hours Lost / Week | C8: 5 | D8: hours / week | G8: 2 | H8: hours / week
B9: Hourly Rate (Gross) | C9: 100 | D9: CHF / hour | G9: 80 | H9: CHF / hour
B11: Hard ROI — Error Reduction
B12: Mistakes / Week | C12: 5 | D12: mistakes / week | G12: 1 | H12: mistakes / week
B13: Cost per Mistake | C13: 200 | D13: CHF / mistake | G13: 75 | H13: CHF / mistake
B15: Soft ROI — Lost Revenue
B16: Lost Leads / Month | C16: 10 | D16: leads / month | G16: 1 | H16: leads / month
B17: Avg Value per Lead | C17: 1500 | D17: CHF / lead | G17: 1000 | H17: CHF / lead
B19: Investment & Ongoing Costs
B20: One-Time Setup Cost | C20: 20000 | D20: CHF total | G20: 3500 | H20: CHF total
B21: Monthly Managed AI Ops Cost | C21: 2350 | D21: CHF / month — paste from Quote Calculator C39 (Recommended monthly quote) | G21: 1600 | H21: CHF / month
B23: 2. CALCULATED ROI | G23: ROI
B25: Monthly Cost of Time | C25: =C7*C8*C9*4 -> 4000 | D25: CHF | G25: =G7*G8*G9*4 -> 2560 | H25: CHF
B26: Monthly Cost of Errors | C26: =C12*C13*4 -> 4000 | D26: CHF | G26: =G12*G13*4 -> 300 | H26: CHF
B27: Monthly Lost Revenue | C27: =C16*C17 -> 15000 | D27: CHF | G27: =G16*G17 -> 1000 | H27: CHF
B28: Monthly Gross Benefit | C28: =SUM(C25:C27) -> 23000 | D28: CHF — cost of inaction | G28: =SUM(G25:G27) -> 3860 | H28: CHF — cost of inaction
B29: (−) Monthly Managed AI Ops | C29: =C21 -> 2350 | D29: CHF | G29: =G21 -> 1600 | H29: CHF
B30: Net Monthly Benefit | C30: =C28-C29 -> 20650 | D30: CHF | G30: =G28-G29 -> 2260 | H30: CHF
B31: Annual Net Benefit | C31: =C30*12 -> 247800 | D31: CHF | G31: =G30*12 -> 27120 | H31: CHF
B32: Payback Period | C32: =IF(C30<=0,"N/A",C20/C30) -> 0.968523 | D32: Months | G32: =IF(G30<=0,"N/A",G20/G30) -> 1.5486726 | H32: Months
B33: First-Year Net ROI | C33: =IF(C20=0,"N/A",(C30*12-C20)/C20) -> 11.39 | D33: % (over Year 1) | G33: =IF(G20=0,"N/A",(G30*12-G20)/G20) -> 6.7485714 | H33: % (over Year 1)
B35: Tip: Monthly Managed AI Ops (C20) should match 'Recommended monthly quote' from the Quote Calculator tab (cell C39). Yellow = edit, light blue = calculated.

Sheet Example Quotes
A1: Example Quote Ranges
A3: Example | B3: Package | C3: Setup Low | D3: Setup High | E3: Monthly Low | F3: Monthly High | G3: Why | H3: Access model | I3: Notes | J3: Client label
A4: MG Red Shift v4.0 — AI-drafted SEEKER reply (base) | B4: Basic+ AI Triage | C4: 1500 | D4: 3000 | E4: 250 | F4: 600 | G4: AI classification, Notion DB, folder routing, SEEKER draft support | H4: Managed / hybrid | I4: No automatic sending; AI draft held for review | J4: AI Intake Triage Basic+
A5: Therapist Gmail + booking link | B5: Basic Intake | C5: 1200 | D5: 2500 | E5: 250 | F5: 500 | G5: Email/form intake, booking triage, no direct advice | H5: Managed / hybrid | I5: Human approval | J5: AI Intake Basic
A6: Therapist Instagram + Gmail + drafts | B6: Pro Multi-Channel | C6: 3500 | D6: 7500 | E6: 750 | F6: 1500 | G6: Multiple channels and draft approval workflow | H6: Managed | I6: Sensitive data needs strict boundaries | J6: AI Workflow Pro
A7: Small agency CRM + reporting | B7: Managed Operations | C7: 7500 | D7: 15000 | E7: 1500 | F7: 3500 | G7: CRM, monitoring, reporting, improvement backlog | H7: Managed | I7: Recurring service value | J7: Managed AI Operations
A8: Calendar/CRM agent | B8: Agentic Automation | C8: 12000 | D8: 30000 | E8: 2500 | F8: 6000 | G8: Controlled multi-step actions with approvals | H8: Controlled access | I8: Quote individually | J8: Agentic AI Operations
A9: Client full handover | B9: Build-and-Transfer | C9: 4500 | D9: 15000 | E9: 0 | F9: 1000 | G9: Transfers Make logic and documentation | H9: Client-owned | I9: Price 1.5x to 3x setup | J9: Build & Transfer
A10: MG Red Shift v4.1 — template SEEKER reply | B10: Basic+ AI Triage | C10: 1300 | D10: 2700 | E10: 200 | F10: 500 | G10: Same triage; SEEKER reply is a prepared template (no AI generation). Simplest of the three. | H10: Managed / hybrid | I10: Template reply; no AI draft | J10: AI Intake Triage Basic+
A11: MG Red Shift v4.2 + v4.1 — dual intake (email + webform) | B11: Basic+ AI Triage | C11: 2000 | D11: 4500 | E11: 400 | F11: 900 | G11: v4.1 process across two intake paths (email then webform): extra source + duplicated classify/route. | H11: Managed / hybrid | I11: No automatic sending; two channels | J11: AI Intake Triage Basic+

Sheet Access Models
A1: Access & Ownership Pricing Logic
A3: Model | B3: Client receives | C3: You retain | D3: Pricing effect | E3: Monthly effect | F3: Risk | G3: Use when | H3: Client wording | I3: Internal note | J3: Default setup multiplier | K3: Typical range | L3: Pricing use in FIXED calculator
A4: Managed service | B4: Results, dashboards, reports, approval queue | C4: Make logic, prompts, reusable blueprints | D4: Normal | E4: x1.0 monthly | F4: Low | G4: Default | H4: We manage the automation and provide outputs/support. | I4: Best default model | J4: 1 | K4: x1.0 | L4: Managed service: no handover premium.
A5: Logic visibility | B5: Workflow summary, Mermaid/chart, status rules | C5: Implementation details and reusable logic | D5: Normal or small add-on | E5: x1.0 monthly | F5: Low | G5: Client wants transparency | H5: You receive workflow documentation without internal implementation. | I5: Good trust-building option | J5: 1.1 | K5: x1.0–x1.15 | L5: Transparency/documentation premium.
A6: Limited admin | B6: Dashboard, approvals, run summaries | C6: Scenario edit rights and blueprint export | D6: +10–25% | E6: x1.1–1.25 monthly | F6: Medium | G6: Client needs stronger control | H6: You can review outcomes while we manage the system. | I6: Managed clients | J6: 1.2 | K6: x1.10–x1.25 | L6: Limited admin/client controls.
A7: Client-owned workspace | B7: Automation runs in client workspace | C7: Methodology and reusable templates | D7: +25–75% | E7: x0.5–1.5 monthly depending support | F7: Medium | G7: Compliance/enterprise | H7: Built in your workspace; support remains available. | I7: Higher setup | J7: 1.5 | K7: x1.25–x1.75 | L7: Client-owned workspace/setup burden.
A8: Build-and-transfer | B8: Full Make scenario, export, documentation | C8: General know-how only | D8: x1.5–x3 setup | E8: x0–x3 monthly depending support | F8: High | G8: Client insists on ownership | H8: We build and hand over the automation asset. | I8: Premium only | J8: 2 | K8: x1.5–x3.0 | L8: Build-and-transfer default; override if needed.

Sheet Client Quote Summary
A1: Client-Facing Quote Summary Template
A3: Project name | B3: Enter project name
A4: Package direction | B4: Enter package direction
A5: One-line scope | B5: Example: AI intake triage for website/email inquiries with classification, routing, Notion logging, and draft support.
A6: Included | B6: List included channels, categories, automations, and approvals.
A7: Not included | B7: List postponed or excluded items.
A8: Setup fee | B8: Enter setup fee or range.
A9: Monthly managed service | B9: Enter monthly fee or range.
A10: Access model | B10: Managed service / hybrid / client-owned / build-and-transfer.
A11: Client responsibilities | B11: Provide access, approve test cases, review drafts, confirm go-live.
A12: Provider responsibilities | B12: Build, test, monitor, support, update rules/prompts as agreed.
A13: Approval points | B13: Scope approval, blueprint approval, go-live approval.
A14: Notes | B14: Prices exclude third-party software/API usage unless agreed otherwise.
... A19: Build-and-transfer note | B19: If full automation ownership is transferred, setup and monthly support may be multiplied depending on access and responsibility.

Sheet Pricing Logic
A2: Q | B2: great, but that all has to be calculated before giving Client price
A3: A | B3: Yes, exactly. These “count” fields must be estimated before giving the final client price.
B4: But not too early.
B6: Correct order
B8: 1. After Phase 1 — Discovery
B10: You can give only a rough price direction:
B11: Based on current understanding, this looks like a Basic+ / Pro project, likely in the range of CHF X–Y setup and CHF X–Y/month.
B12: At this point, counts are still approximate.
B14: 2. After Phase 2 — Scope / MVP Design
B16: Now you can calculate more seriously.
B17: Because Phase 2 defines:
B18: included channels
B19: excluded channels
B20: AI draft workflows
... B42: Use the calculator like this:
B44: Project moment | C44: Price type
B45: Before discovery | C45: no real price, only starting-from package
B46: After Phase 1 | C46: rough estimate
B47: After Phase 2 | C47: proposed quote
B48: After Phase 3 | C48: confirmed final offer
B49: After changes | C49: change request / extra cost
B51: For client communication
B53: I would say:
B54: After the discovery call, I can give you an indicative range. The final fixed price is confirmed after we define the MVP scope and automation boundaries.
B55: This protects you from underpricing.
B57: Internally
B59: The calculator is mainly used after Phase 2.
B61: Phase 1 gives you raw answers.
B62: Phase 2 converts them into counts.
B63: Then the Quote Calculator gives the price.
B65: So yes: before giving the client a serious price, you must first define the counts and package/access model.
B67: Direct Email Intake Branch — Pricing Logic / Change Request
B68: Purpose | C68: Price logic | D68: Setup add | E68: Monthly add | F68: When to use
B69: Simple direct-email branch | C69: Add one direct inbox trigger and send messages into the existing classifier after basic normalization. | D69: CHF 500–900 | E69: CHF 100–200 | F69: Client has one inbox and wants same classification logic as website form.
B70: Direct email + filters/logging | C70: Add inbox trigger, normalization, sender/message metadata, duplicate prevention, routing labels/folders, error path and logging. | D70: CHF 900–1’500 | E70: CHF 150–300 | F70: Most realistic business version; recommended default for client quote.
B71: Direct email + draft / approval logic | C71: Add email-specific draft replies, approval handling, status tracking and safer exception handling. | D71: CHF 1’500–2’500 | E71: CHF 300–500 | F71: Client expects AI-assisted replies or approval workflow, not only classification.
B72: Pricing rule | C72: If defined before project start, include it in the package scope and count it as an additional intake channel/source. If requested later, price it as a change request. | D72: Usually +CHF 900–1’500 | E72: Usually +CHF 150–300/month | F72: Use this rule when scope expands from webhook-only to inbox + webhook.
B73: Commercial note | C73: This is not only “add Gmail trigger”. It adds a second source, normalization, deduplication, routing reliability, testing and support responsibility. | F73: This explains why the add-on has both setup and monthly impact.
A77: Q | B77: how this modification enable us to define properly for price calculation each wished or considered, or offered automation?
A78: A | B78: Good question — this is the core workflow gap. The calculator fields give you the inputs, but you still need a clear rule for how to read any automation and translate it into those fields. Here's the complete mapping logic:
B80: Step 1 — Pick the package (C5) by overall complexity
B82: Automation complexity | C82: Package
B83: Single channel, classify/route only, no AI | C83: Basic Intake
B84: Single channel, classify + 1 AI draft type | C84: Basic+ AI Triage
B85: Multiple channels or sources, classify + AI | C85: Pro Multi-Channel
B86: Full ops: multi-channel, AI, CRM, monitoring | C86: Managed Operations
B87: Autonomous agents, self-healing flows | C87: Agentic Automation
B89: Step 2 — Fill the count fields by scanning the Make.com scenario
B91: Go through the scenario module by module and ask one question per field:
B93: Extra channels (C16): how many separate inbound sources exist beyond the one included in the package? Count each distinct webhook endpoint or app trigger.
B94: AI draft workflows (C17): how many distinct HTTP→OpenAI/Claude calls exist? Count per draft type, not per email processed.
B95: CRM integrations (C18): how many different external database systems are written to or read from? Count per system, not per module.
B96: Approval workflows (C19): how many places does the scenario pause and wait for a human before acting?
B97: Reporting layer (C20): is there a structured output to a dashboard or analytics view?
B99: Step 3 — Set the multipliers (C21–C22) by project context
B101: These aren't about the automation itself — they're about the client and delivery situation. Sensitive data and urgency are commercial decisions, not technical ones.
B103: Step 4 — Choose access and support models (C6, C7) by the commercial arrangement
B105: C6 answers who owns the automation after delivery
B106: C7 answers what ongoing support level is agreed
... B114: Applied to your three options, the inputs would be:
B116: Field | C116: Option A (classify only) | D116: Option B (classify + AI draft) | E116: Option C (email service + classify) | F116: MG Red Shift
B117: C5 Package | C117: Basic Intake | D117: Basic+ AI Triage | E117: Basic Intake | F117: Basic Intake
B118: C16 Extra channels | C118: 0 | D118: 0 | E118: 1 | F118: 0
B119: C17 AI draft | C119: 0 | D119: 1 | E119: 0 | F119: 1
B120: C18 CRM | C120: 0 | D120: 0 | E120: 0 | F120: 1
B121: C19 Approval | C121: 0 | D121: 1 | E121: 0 | F121: 1
B122: C20 Reporting | C122: 0 | D122: 0 | E122: 0 | F122: 0
B123: C26 ops/month | C123: CHF 15–20 | D123: CHF 25–45 | E123: CHF 20–30 | F123: CHF 30–60
B125: The calculator can then price each of these as a distinct configuration just by changing those six inputs — which is exactly what the modified D and F columns now guide you through, step by step, for any new automation you design or propose.
A174: Q | B174: quickly back to price calculations: how would you explain pricing? There will be some customers who think price is too expansive. What would you say then?
A175: A | B175: Good question — and an honest one, because some prospects genuinely can't afford it, and some just haven't yet understood what they're paying for. Those are two very different situations and need different responses.
B177: First: understand which objection it actually is
B179: "Too expensive" usually means one of four things:
B181: "I don't see why it costs that much" — a value communication problem
B182: "I can't afford it right now" — a cash flow or budget problem
B183: "I can get something similar cheaper" — a comparison problem
B184: "I don't trust it will work" — a risk problem
B186: Don't respond to all four the same way.
B188: For "I don't see the value"
B190: This is the most common and the most fixable. The answer is a ROI calculation, done in front of them.
B191: "Let's work out the numbers together. How many hours per week does your team currently spend on the tasks we'd automate? What does an hour of that person's time cost you fully loaded — salary, social contributions, overhead?"
B192: A Swiss SME employee with a CHF 70,000 salary costs around CHF 90–100/hour fully loaded. If you're saving 10 hours per week, that's CHF 900–1,000/week, or CHF 4,000/month. The managed service fee suddenly looks very different.
B193: The conversation shifts from "what does this cost?" to "what does NOT doing this cost you every month?"
... B224: Then be quiet and let them think. Most will do the maths themselves.
A227: Q | B227: that is why we have within Helper_Pricing a tab: ROI App which can help estimate quickly spending and errors. many thanks for your feedback
A228: A | B228: That's a great point — and exactly the right tool for that moment. Instead of doing the maths verbally (which can feel like pressure), you just open the ROI tab together with the client and let them enter their own numbers. When they calculate it themselves, the conclusion is theirs, not yours. Much more convincing.
B230: Two small practical suggestions for how to use it:
B231: Use it in the discovery meeting, not after. Don't send it as a follow-up PDF. Walk through it live — screen share or sit next to them. The conversation that happens while filling it in is often more valuable than the output.
B232: Let them drive the inputs. Ask the questions, let them type the numbers. When someone enters their own estimate of "12 hours per week on email triage," they've already committed to that figure. You just show them what 12 hours costs over 12 months and what the automation costs over the same period.
B233: If you ever want to strengthen the ROI tab further — for example adding a "months to break even" line, or a side-by-side of manual cost vs automation cost over 1 and 2 years — that would be a quick addition worth considering.
B235: Good luck building the client base. The framework is solid, the pricing logic is sound, and the meeting prep is ready. Now it's just about getting in the room with the right people.
A238: Q | B238: however our ROI App is not quite exact. It calculate benefit based on Installation an not include Monthl managed Costs or similar? It seems PAyback is also not calculated exactly when One time investment + Monthly Managed Costs are included? Do you have access to : Helper_Pricing a tab: ROI App and can you analyse and revise?
A239: A | B239: Yes — I have the refactored file in outputs. Let me read the ROI App tab fully first before touching anything.Now I have the full picture. Let me diagnose both issues precisely before touching anything.Clear diagnosis:
B241: Payback — correct (C29 already nets out monthly costs)
B242: First-Year ROI — wrong denominator. Uses only setup (CHF 3,500) instead of total year-1 spend (CHF 22,700). Inflates the real client ROI from an honest 104% to a misleading 675%
B244: Fix plan: insert one new "Total Year 1 Investment" row for transparency, fix the ROI denominator, add a "Year 2+ Annual ROI" row (no setup amortisation), update the tip text. Implementing now:Values are correct — 473% and 104% confirmed. The C34 None is likely the formula not stored properly. Let me verify and fix:C34 is a merged cell — a stale merge from the tip row. Let me inspect and fix:Values are raw ratios — the 0% number format displays them correctly in Excel. Let me confirm with proper percentage formatting:All values correct. Copying to outputs:Fixed. Here's what changed in the ROI App tab:
B245: Root cause confirmed: The payback period formula was always correct — dividing setup cost by net monthly benefit is right because the monthly managed cost is already deducted in that net figure. The bug was exclusively in First-Year ROI.
B246: What was wrong: The First-Year ROI denominator only included the setup fee (CHF 3,500), ignoring the 12 months of managed service payments (12 × CHF 1,600 = CHF 19,200). This inflated the ROI from an honest 104% to a misleading 675% for a typical small project.
B248: Three changes made:
B249: New row — "Total Year 1 Investment": Shows the full amount the client actually spends in year one (setup + 12× monthly). For the realistic example: CHF 3,500 + CHF 19,200 = CHF 22,700. This makes the ROI calculation transparent — the client can see exactly what goes into the denominator.
...

Sheet AI Aut Logic
A2: Q | B2: clear, thank you. 1. so when we would add a small router or a pre-loop watching, besides webhook, also emails (and with next steps also some social media), with the same logic, from some email service provider, then we could classify such automation higher? 2. we foreseen also monthly maintenance, which is for us as business and for customer essential, but we understand that it means that until Clinent wants it is kept or how can we evolve it or explain to Client? 3. we also have simple ROI calculators (see examples). How would you explain our MGREDSHIFT automation with ROI calculation? can it be explained clearly for such automation?
A3: A | B3: Yes, that’s a good direction.
B5: 1. Would adding email/social intake classify it higher?
B7: Yes, depending on complexity.
B8: Right now MG Red Shift is best classified as:
B10: Basic+ AI Triage / AI Intake Triage Basic+
B12: Because it does:
B13: website form → AI classification → JSON parse → folder routing → Notion logging → manual review
B14: Your v4.0 flow confirms this structure: OpenAI classification runs before the router, and the router acts only on LEAD / SEEKER / SPAM / TEST.
B16: If you add:
B18: Added scope | C18: Package level
B19: Website form + one inbox, same logic | C19: Basic+ AI Triage
B20: Multiple inboxes / email provider + website form | C20: Basic+ or low Pro
B21: Email + Instagram / WhatsApp / LinkedIn | C21: Pro Multi-Channel
B22: Draft replies + approval workflow | C22: Pro Multi-Channel
B23: Monthly reporting, monitoring, improvements | C23: Managed Operations
B24: CRM/calendar actions with approvals | C24: Agentic Automation
B26: So yes: with email + social media + same classification logic, it can move toward Pro Multi-Channel.
B29: 2. Monthly maintenance — how to explain it
B31: I would not call it “maintenance” only. Better:
B33: Managed AI Operations
B35: Because it includes:
B36: monitoring failed runs
B37: checking classification quality
B38: updating prompts/categories
B39: adapting when client business rules change
B40: fixing API/provider changes
B41: reviewing edge cases
B42: usage/cost monitoring
... B49: Commercially:
B51: Support model | C51: Meaning
B52: No support | C52: build-and-transfer, client owns risk
B53: Light support | C53: occasional checks/fixes
B54: Normal managed support | C54: default for business workflow
B55: High-responsibility support | C55: stronger monitoring, faster response
B56: Critical support | C56: for operationally sensitive workflows
B58: For MG Red Shift, I would use Normal managed support.
B61: 3. ROI explanation for MG Red Shift automation
B63: Yes, ROI can be explained clearly, but use conservative numbers.
B64: The ROI is not only “time saved”. It is also:
B65: fewer wrong manual classifications
B66: faster separation of real CH/LI leads from foreign SEEKERS
B67: less risk of replying wrongly about export/distribution
B68: better CRM/Notion recordkeeping
B69: less inbox clutter
B70: consistent manual review process
B72: Simple ROI formula:
B73: Monthly benefit =
... B78: Example conservative MG Red Shift case:
B80: ROI factor | C80: Example
B81: Time saved: 2 h/week × CHF 80 × 4 | C81: CHF 640/month
B82: Avoided mistakes: 2/month × CHF 150 | C82: CHF 300/month
B83: Preserved commercial opportunity value | C83: CHF 250/month
B84: Total estimated monthly benefit | C84: CHF 1’190/month
B86: If setup is CHF 3’500:
B87: Payback = 3500 / 1190 = approx. 3 months
B89: So for MG Red Shift I would write:
B90: This automation reduces manual inbox triage, separates local customer leads from out-of-scope foreign requests, logs relevant cases, and protects the company from inconsistent replies. A conservative ROI comes from saved handling time, fewer classification mistakes, and better retention of relevant commercial opportunities.
B92: For your pricing sheet, I’d place MG Red Shift as:
B94: Package: Basic+ AI Triage
B95: Setup: CHF 2’500 – 4’500
B96: Monthly: CHF 500 – 900
B97: Support model: Normal managed support
B99: If you add email + social media + draft approvals, then I’d move it to:
B101: Package: Pro Multi-Channel
B102: Setup: CHF 3’500 – 7’500+
... B105: MGREDSHIFT v4.0 vs Direct Email Intake Expansion
B106: Area | C106: Existing MGREDSHIFT v4.0 | D106: Expansion for other clients | E106: Pricing effect | F106: Why it matters
B107: Input source | C107: Website contact form via webhook only. | D107: Add direct inbox trigger, e.g. Gmail/IMAP/Outlook “watch emails”. | E107: Counts as +1 intake channel/source. | F107: Direct emails do not use the website form structure and may never reach the existing webhook scenario.
B108: Message structure | C108: Structured form fields: name, email, phone, subject, message. | D108: Normalize unstructured email into the same internal fields: source_type, sender, subject, body, phone/WhatsApp, detected country. | E108: Small setup increase. | F108: Without normalization, the classifier receives inconsistent inputs and misses cases.
B109: Router / pre-branch | C109: Classifier runs after webhook input and router acts on LEAD / SEEKER / SPAM / TEST. | D109: Add small source router/pre-branch: website_form vs direct_email, then merge both into the same classification logic. | E109: Small to medium setup increase. | F109: Keeps one central classifier while allowing several input channels.
B110: Classification logic | C110: Good for website enquiries. Foreign distributor requests are handled when they arrive through the form. | D110: Add fallback terms for direct emails: India, Gujarat, +91, WhatsApp, distributor, reseller, agency, purchase in [country]. | E110: Usually included in the add-on. | F110: Direct emails often use broken wording, so keyword fallback improves SEEKER detection.
B111: Deduplication | C111: Less critical when each form submission is unique. | D111: Use email message ID / thread ID / timestamp to avoid duplicated processing. | E111: Part of realistic business version. | F111: Inbox triggers can re-read, forward, or re-process messages if not controlled.
B112: Routing and logging | C112: Folder routing + Notion logging + manual review. | D112: Add email labels/folders, status logging, error route and optional reply draft path. | E112: Moves from simple branch to managed workflow. | F112: Client sees a reliable operational process, not only an AI classification.
B113: Recommended classification | C113: Basic+ AI Triage. | D113: Still Basic+ if one inbox and same logic; low Pro if multiple inboxes, email-specific drafts or social channels are added. | E113: Use change request if added later. | F113: Scope expansion changes responsibility, testing and support needs.
B114: Practical conclusion | C114: For MG Red Shift, modification may not be needed now because direct foreign requests can be handled manually. | D114: For client projects, direct email intake should be discussed in discovery and priced as an optional intake-source add-on. | E114: Default quote: CHF 900–1’500 setup + CHF 150–300/month. | F114: This protects against underpricing and makes scope boundaries clear.

Sheet AUDIT Pricing
A1: Pricing Calculator Audit
A2: Workbook | B2: AI_Automation_PM_Helper_Pricing_Calculator_v6_Streamlined_MJS_updated_email_intake.xlsx
A3: Audit focus | B3: Quote Calculator, C5 package + C6 support model, Build-and-Transfer pricing, workbook consistency
A5: Verdict | B5: Status | C5: Detail | D5: Impact | E5: Recommended fix | F5: Priority
A6: Overall | B6: PARTLY OK | C6: Standard managed packages calculate logically for the current inputs. | D6: Usable for Basic/Pro/Managed quotes with care. | E6: Keep package selection and support model, but add stronger checks. | F6: Medium
A7: C5 + C6 combination | B7: TECHNICALLY OK | C7: C5 drives base package via Package Reference; C6 drives support/setup multipliers via Complexity Reference. | D7: Combination works mathematically. | E7: Keep, but separate package/support/access model more clearly. | F7: Medium
A8: Build-and-Transfer | B8: FAIL | C8: Build-and-Transfer has base setup/monthly = 0 in Package Reference, so calculator can return 0 or too-low setup. | D8: Underpricing risk, especially if counts are not entered. | E8: Treat Build-and-Transfer as access/ownership model OR give it a non-zero base. | F8: High
A9: Support multiplier logic | B9: WARN | C9: For Build-and-Transfer, Normal managed support uses setup multiplier 1.0, while No support uses 1.5, so 'normal support' can make setup cheaper than 'no support'. | D9: Commercially inconsistent. | E9: Move handover/setup multiplier to a separate access model field. | F9: High
A10: Hard-coded adders | B10: WARN | C10: Quote formulas C29:C32 use hard-coded adder amounts instead of reading Complexity Reference A:E. | D10: Changing reference prices will not update calculator. | E10: Use lookups / SUMPRODUCT against Complexity Reference. | F10: High
A11: Dropdowns | B11: WARN | C11: C5/C6 dropdowns are fixed text lists, not dynamic ranges from reference sheets. | D11: If reference names change, dropdowns can go stale. | E11: Use data validation references to Package Reference and Complexity Reference ranges. | F11: Medium
A12: Example Quotes | B12: WARN | C12: Example Build-and-Transfer quote is CHF 4'500–15'000 / 0–1'000 monthly, but calculator can output lower values. | D12: Inconsistent client guidance. | E12: Align reference, calculator and examples. | F12: High
A13: ROI App | B13: NOTE | C13: ROI math is coherent, but setup/monthly costs are manual, not linked to Quote Calculator. | D13: Manual copy errors possible. | E13: Link ROI inputs to Quote Calculator cells or clearly mark as manual scenario input. | F13: Low
A14: Client Quote Summary | B14: NOTE | C14: Client summary is manual and not linked to calculator outputs. | D14: Manual quote-copy risk. | E14: Optional: formula-link key outputs. | F14: Low
A15: Pricing Logic tabs | B15: NOTE | C15: Direct Email Intake Branch pricing is documented but not connected to Quote Calculator. | D15: Email-intake scope can be missed or double-counted. | E15: Add an optional Direct Email Branch add-on or map it clearly to Extra Channel + Draft + Approval counts. | F15: Medium
A17: Current Quote Calculator inputs | B17: Value
A18: Selected package (C5) | B18: Basic+ AI Triage
A19: Support model (C6) | B19: Normal managed support
A20: Extra channels count (C15) | B20: 0
A21: AI draft workflows count (C16) | B21: 1
A22: CRM integrations count (C17) | B22: 1
A23: Approval workflows count (C18) | B23: 1
A24: Reporting layer count (C19) | B24: 0
A25: Sensitive data multiplier (C20) | B25: 1
A26: Urgency multiplier (C21) | B26: 1
A28: Current calculated result | B28: Setup low | C28: Setup high | D28: Monthly low | E28: Monthly high | F28: Recommended
A29: Basic+ AI Triage + Normal managed support | B29: 3500 | C29: 10000 | D29: 800 | E29: 2350 | F29: Setup 6800 / Monthly 1600
A31: Build-and-Transfer test with current counts | B31: Setup low | C31: Setup high | D31: Monthly low | E31: Monthly high | F31: Recommended
A32: No support | B32: 3000 | C32: 9750 | D32: 0 | E32: 0 | F32: Setup 6400 / Monthly 0
A33: Light support | B33: 3000 | C33: 9750 | D33: 250 | E33: 800 | F33: Setup 6400 / Monthly 500
A34: Normal managed support | B34: 2000 | C34: 6500 | D34: 500 | E34: 1600 | F34: Setup 4300 / Monthly 1100
A35: High-responsibility maintenance | B35: 3000 | C35: 9750 | D35: 750 | E35: 2400 | F35: Setup 6400 / Monthly 1600
A36: Premium transfer support | B36: 4000 | C36: 13000 | D36: 1000 | E36: 3200 | F36: Setup 8500 / Monthly 2100
A37: Critical support | B37: 6000 | C37: 19500 | D37: 1500 | E37: 4800 | F37: Setup 12800 / Monthly 3200
A39: Build-and-Transfer zero-count test | B39: Setup low | C39: Setup high | D39: Monthly low | E39: Monthly high | F39: Recommended
A40: No support | B40: 0 | C40: 0 | D40: 0 | E40: 0 | F40: Setup 0 / Monthly 0
A41: Light support | B41: 0 | C41: 0 | D41: 0 | E41: 0 | F41: Setup 0 / Monthly 0
A42: Normal managed support | B42: 0 | C42: 0 | D42: 0 | E42: 0 | F42: Setup 0 / Monthly 0
A43: High-responsibility maintenance | B43: 0 | C43: 0 | D43: 0 | E43: 0 | F43: Setup 0 / Monthly 0
A44: Premium transfer support | B44: 0 | C44: 0 | D44: 0 | E44: 0 | F44: Setup 0 / Monthly 0
A45: Critical support | B45: 0 | C45: 0 | D45: 0 | E45: 0 | F45: Setup 0 / Monthly 0
A47: Practical recommendation
A48: Best structure | B48: Package = Basic/Basic+/Pro/Managed/Agentic. Access/ownership model = Managed service / Logic visibility / Limited admin / Client-owned / Build-and-transfer. Support model = No/Light/Normal/High/Premium/Critical.
A49: Minimum quick fix | B49: Set Build-and-Transfer base setup low/high to at least the Example Quotes range CHF 4'500–15'000, or remove it from C5 and handle it as an access multiplier.
A50: Commercial rule | B50: Build-and-Transfer should normally never be cheaper than the same automation as a managed build; it transfers more asset value and needs documentation/testing/handover.

Sheet B&T Matrix
A1: Build-and-Transfer Matrix
A2: Shows current formula outputs for Build-and-Transfer using the current Quote Calculator counts and using zero counts.
A3: Support model | B3: Current counts: setup range | C3: Current counts: monthly range | D3: Current recommended | E3: Zero counts: setup range | F3: Zero counts: monthly range
A4: No support | B4: CHF 3'000 - 9'750 | C4: CHF 0 - 0 | D4: CHF 6'400 / CHF 0 | E4: CHF 0 - 0 | F4: CHF 0 - 0
A5: Light support | B5: CHF 3'000 - 9'750 | C5: CHF 250 - 800 | D5: CHF 6'400 / CHF 500 | E5: CHF 0 - 0 | F5: CHF 0 - 0
A6: Normal managed support | B6: CHF 2'000 - 6'500 | C6: CHF 500 - 1'600 | D6: CHF 4'300 / CHF 1'100 | E6: CHF 0 - 0 | F6: CHF 0 - 0
A7: High-responsibility maintenance | B7: CHF 3'000 - 9'750 | C7: CHF 750 - 2'400 | D7: CHF 6'400 / CHF 1'600 | E7: CHF 0 - 0 | F7: CHF 0 - 0
A8: Premium transfer support | B8: CHF 4'000 - 13'000 | C8: CHF 1'000 - 3'200 | D8: CHF 8'500 / CHF 2'100 | E8: CHF 0 - 0 | F8: CHF 0 - 0
A9: Critical support | B9: CHF 6'000 - 19'500 | C9: CHF 1'500 - 4'800 | D9: CHF 12'800 / CHF 3'200 | E9: CHF 0 - 0 | F9: CHF 0 - 0
A11: Conclusion | B11: Zero-count Build-and-Transfer returns CHF 0 setup/monthly across all support models because the package base is 0.
A12: Conclusion | B12: With current counts, Normal managed support gives lower setup than No support because setup multipliers are attached to support model, not to access/ownership model.

Sheet Numerologia
B2: SSA
B3: Name | D3: V | E3: o | F3: r | G3: t | H3: e | I3: x | J3: D | K3: e | L3: e | M3: p
B4: SSP
B5: SCA
B6: Date | D6: 2 | E6: 7 | F6: 1 | G6: 2 | H6: 1 | I6: 9 | J6: 6 | K6: 1 | L6: = | M6: =IF(LEN(O6)=1,O6,SUM(LEFT(O6,1),RIGHT(O6,1))) -> 2 | O6: =SUM(LEFT(P6,1),RIGHT(P6,1)) -> 11 | P6: =SUM(D6:K6) -> 29 | Q6: =LEFT(P6,1) -> 2 | R6: =RIGHT(P6,1) -> 9
K7: D | L7: = | M7: =CONCATENATE(D6,E6) -> 27
K8: M | L8: = | M8: =CONCATENATE(F6,G6) -> 12
K9: PW (PodWibracja) | L9: = | M9: =P6 -> 29
B11: SSA
B12: Name | D12: l | E12: i | F12: d | G12: i | H12: a | J12: m | K12: a | L12: r | M12: i | N12: a | O12: n | P12: n | Q12: a | S12: k | T12: r | U12: e | V12: t | W12: o | X12: w | Y12: s | Z12: k | AA12: a
B13: SSP
B14: SCA
B15: Date | D15: 2 | E15: 7 | F15: 1 | G15: 2 | H15: 1 | I15: 9 | J15: 6 | K15: 1 | L15: = | M15: =IF(LEN(O15)=1,O15,SUM(LEFT(O15,1),RIGHT(O15,1))) -> 2 | O15: =SUM(LEFT(P15,1),RIGHT(P15,1)) -> 11 | P15: =SUM(D15:K15) -> 29 | Q15: =LEFT(P15,1) -> 2 | R15: =RIGHT(P15,1) -> 9
K16: D | L16: = | M16: =CONCATENATE(D15,E15) -> 27
K17: M | L17: = | M17: =CONCATENATE(F15,G15) -> 12
K18: PW (PodWibracja) | L18: = | M18: =P15 -> 29
B20: SSA
B21: Name | D21: m | E21: a | F21: c | G21: i | H21: e | I21: j | K21: j | L21: e | M21: r | N21: z | O21: y | Q21: s | R21: z | S21: c | T21: z | U21: e | V21: c | W21: h
B22: SSP
B23: SCA
B24: Date | D24: 1 | E24: 1 | F24: 0 | G24: 4 | H24: 1 | I24: 9 | J24: 6 | K24: 8 | L24: = | M24: =IF(LEN(O24)=1,O24,SUM(LEFT(O24,1),RIGHT(O24,1))) -> 3 | O24: =SUM(LEFT(P24,1),RIGHT(P24,1)) -> 3 | P24: =SUM(D24:K24) -> 30 | Q24: =LEFT(P24,1) -> 3 | R24: =RIGHT(P24,1) -> 0
K25: D | L25: = | M25: =CONCATENATE(D24,E24) -> 11
K26: M | L26: = | M26: =CONCATENATE(F24,G24) -> 04
K27: PW (PodWibracja) | L27: = | M27: =P24 -> 30
B29: SSA
B30: Name | D30: m | E30: a | F30: r | G30: c | H30: i | I30: n | K30: j | L30: a | M30: n | O30: k | P30: r | Q30: e | R30: t | S30: o | T30: w | U30: s | V30: k | W30: i
B31: SSP
B32: SCA
B33: Date | D33: 0 | E33: 4 | F33: 1 | G33: 0 | H33: 1 | I33: 9 | J33: 7 | K33: 9 | L33: = | M33: =IF(LEN(O33)=1,O33,SUM(LEFT(O33,1),RIGHT(O33,1))) -> 4 | O33: =SUM(LEFT(P33,1),RIGHT(P33,1)) -> 4 | P33: =SUM(D33:K33) -> 31 | Q33: =LEFT(P33,1) -> 3 | R33: =RIGHT(P33,1) -> 1
K34: D | L34: = | M34: =CONCATENATE(D33,E33) -> 04
K35: M | L35: = | M35: =CONCATENATE(F33,G33) -> 10
K36: PW (PodWibracja) | L36: = | M36: =P33 -> 31
B38: SSA
B39: Name | D39: j | E39: u | F39: s | G39: t | H39: y | I39: n | J39: a | L39: b | M39: o | N39: z | O39: e | P39: n | Q39: a | S39: z | T39: a | U39: w | V39: a | W39: d | X39: z | Y39: k | Z39: a
B40: SSP
B41: SCA
B42: Date | D42: 1 | E42: 6 | F42: 1 | G42: 1 | H42: 1 | I42: 9 | J42: 8 | K42: 2 | L42: = | M42: =IF(LEN(O42)=1,O42,SUM(LEFT(O42,1),RIGHT(O42,1))) -> 2 | O42: =SUM(LEFT(P42,1),RIGHT(P42,1)) -> 11 | P42: =SUM(D42:K42) -> 29 | Q42: =LEFT(P42,1) -> 2 | R42: =RIGHT(P42,1) -> 9
K43: D | L43: = | M43: =CONCATENATE(D42,E42) -> 16
K44: M | L44: = | M44: =CONCATENATE(F42,G42) -> 11
K45: PW (PodWibracja) | L45: = | M45: =P42 -> 29
B47: SSA
B48: Name | D48: s | E48: t | F48: e | G48: f | H48: a | I48: n | K48: m | L48: a | M48: r | N48: c | O48: i | P48: n | R48: k | S48: r | T48: e | U48: t | V48: o | W48: w | X48: s | Y48: k | Z48: i
B49: SSP
B50: SCA
B51: Date | D51: 1 | E51: 2 | F51: 0 | G51: 9 | H51: 2 | I51: 0 | J51: 2 | K51: 3 | L51: = | M51: =IF(LEN(O51)=1,O51,SUM(LEFT(O51,1),RIGHT(O51,1))) -> 1 | O51: =SUM(LEFT(P51,1),RIGHT(P51,1)) -> 10 | P51: =SUM(D51:K51) -> 19 | Q51: =LEFT(P51,1) -> 1 | R51: =RIGHT(P51,1) -> 9
K52: D | L52: = | M52: =CONCATENATE(D51,E51) -> 12
K53: M | L53: = | M53: =CONCATENATE(F51,G51) -> 09
K54: PW (PodWibracja) | L54: = | M54: =P51 -> 19
B60: Alfabet Numerologiczny | H60: Gladys Loobos | K60: System Pitagorejski
D61: 1 | E61: 2 | F61: 3 | G61: 4 | H61: 5 | I61: 6 | J61: 7 | K61: 8 | L61: 9
D62: A | E62: B | F62: C | G62: D | H62: E | I62: F | J62: G | K62: H | L62: I
D63: J | E63: K | F63: L | G63: M | H63: N | I63: O | J63: P | K63: Q | L63: R
D64: S | E64: T | F64: U | G64: V | H64: W | I64: X | J64: Y | K64: Z
B66: SSA | D66: Suma samoglosek
B67: SSP | D67: Suma spolglosek
B68: SCA | D68: Suma calosci

Sheet Numertologia VD
B2: 0 | C2: 6 | D2: 0 | E2: 6 | F2: 2 | G2: 0 | H2: 2 | I2: 6
B5: Dzisiejszy układ sił na niebie daje Ci zielone światło i potężne wsparcie energetyczne dla Twojego niszowego projektu. Twoja niezłomna wiara i przygotowanie idealnie rezonują z kosmicznym klimatem tego dnia.
B7: Kosmiczny układ sił na 6 lipca 2026 roku
B8: • Przełomowy nów Księżyca: Wchodzimy w fazę nowiu, która jest absolutnie najlepszym momentem w całym cyklu na zasiewanie nowych idei i start autorskich projektów.
B9: • Potęga Twojej Siódemki: Dzisiejsza wibracja dnia sprzyja głębokiej intuicji, dzięki czemu bezbłędnie wyczujesz intencje rozmówców i obronisz swoją niszową koncepcję.
B10: • Aspekt Merkurego i Saturna: Ten układ planetarny daje strukturę i trwałość, co oznacza, że omawiane dziś pomysły mają szansę przetrwać lata i przynieść realne zyski.
B12: Jak wykorzystać tę energię podczas rozmowy?
B13: • Emanuj pewnością: Twój wewnętrzny spokój zadziała na rozmówców magnetycznie, budując w ich oczach obraz profesjonalisty.
B14: • Mów językiem wizjonera: Ponieważ nów sprzyja nowym początkom, zaraź innych swoją pasją, ale nie trać z oczu twardych realiów rynkowych.
B15: • Zaufaj pierwszemu impulsowi: Pierwsza myśl, jaka pojawi się w Twojej głowie podczas negocjacji, będzie tą najwłaściwszą i podyktowaną czystą intuicją.
B16: Masz w rękach wszystkie atuty, a wszechświat pcha Cię do przodu – wejdź tam i weź to, co Twoje.
B20: • Prawo rezonansu: Twoje wysokie wibracje i wiara w projekt przyciągną ludzi, którzy myślą podobnie i docenią niszowy charakter Twojej idei.
B21: • Stabilizacja przez niezależność: Dzisiejsza energia nowiu buduje trwałe fundamenty, co oznacza, że ten krok odetnie stare, niepewne schematy i da Ci upragnione poczucie bezpieczeństwa.
... B142: Wykorzystaj tę liczbę przy planowaniu ważnych wydarzeń, np. oficjalnego uruchomienia strony lub wysyłki pierwszych ofert (dobrym momentem może być np. godzina 12:00, czyli 1+2=3, lub 3. dzień tygodnia/miesiąca).
