Workbook
Name Datenschnitt_C: #N/A
Name Datenschnitt_C_L: #N/A
Name Datenschnitt_Off_Status: #N/A
Name Datenschnitt_P_L: #N/A
Name Datenschnitt_PM: #N/A
Name ostatus: 'AT-Listv2'!$B$3:$B$17
Name pick: 'AT-Listsv1'!$D$3:$D$8
Name pm: 'AT-Listsv1'!$E$3:$E$9
Name priority: 'AT-Listsv1'!$C$3:$C$7
Name status: 'AT-Listsv1'!$B$3:$B$11

Sheet 2024_old
B2: Year | C2: Mon | J2: Work hours | AC2: Summ | AE2: Summ | AG2: A | AI2: Overtime | AJ2: F -Leave | AK2: K - Compens | AL2: FT - Frei | AN2: Work | AO2: Work | AU2: Work | BB2: Privat
D3: KW | E3: Day | F3: Year | G3: Month | H3: Day | I3: Data | J3: In | L3: Break | N3: Break | P3: Out | R3: Break | T3: Break | AC3: must | AE3: is | AG3: F | AN3: Days | AO3: Days | AP3: Day | AS3: Project | AT3: Where | AU3: What | AW3: Day | AZ3: Project | BA3: Where | BB3: What
I4: Sa;So | J4: 0 | K4: 0 | L4: 0 | M4: 0 | N4: 0 | O4: 0 | P4: 0 | Q4: 0 | AC4: 0 | AE4: 0 | AG4: FT | AN4: Effective | AO4: Sum
F5: 2035 | G5: 1 | H5: 1 | J5: 7 | K5: 0 | L5: 13 | M5: 0 | N5: 13 | O5: 30 | P5: 15 | Q5: 55 | AC5: 8 | AE5: 25 | AG5: HO | AN5: A | AO5: Sa
AG6: HT
D7: [ - ] | E7: [ - ] | F7: [ - ] | G7: [ - ] | H7: [ - ] | I7: [ - ] | J7: [h] | K7: [m] | L7: [h] | M7: [m] | N7: [h] | O7: [m] | P7: [h] | Q7: [m] | AC7: [h] | AE7: [m] | AG7: K | AN7: HO | AO7: So | AP7: [ - ] | AQ7: [h] | AR7: [m] | AS7: [ - ] | AT7: [ - ] | AU7: [ - ] | AW7: [ - ] | AX7: [h] | AY7: [m] | AZ7: [ - ] | BA7: [ - ] | BB7: [ - ]
AI8: 0 | AJ8: 0 | AK8: 0 | AL8: 0
B9: =$F$5 -> 2035 | C9: =TEXT(I10,"MMM") -> Jan
A10: =$G$5 -> 1 | D10: =IF(E10="Mo",WEEKNUM(I10),"") -> 1 | E10: =TEXT(I10,"TTT") -> Mo | F10: =$F$5 -> 2035 | G10: =$A$10 -> 1 | H10: =$H$5 -> 1 | I10: =DATE(F10,G10,H10) -> 47848 | J10: =IF(OR($E10="Sa",$E10="So"),J$4,J$5) -> 7 | K10: =IF(OR($E10="Sa",$E10="So"),K$4,K$5) -> 0 | L10: =IF(OR($E10="Sa",$E10="So"),L$4,L$5) -> 13 | M10: =IF(OR($E10="Sa",$E10="So"),M$4,M$5) -> 0 | N10: =IF(OR($E10="Sa",$E10="So"),N$4,N$5) -> 13 | O10: =IF(OR($E10="Sa",$E10="So"),O$4,O$5) -> 30 | P10: =IF(OR($E10="Sa",$E10="So"),P$4,P$5) -> 15 | Q10: =IF(OR($E10="Sa",$E10="So"),Q$4,Q$5) -> 55 | R10: =P10 -> 15 | S10: =Q10 -> 55 | T10: =R10 -> 15 | U10: =S10 -> 55 | V10: =TIME(J10,K10,0) -> 0.29166667 | W10: =TIME(L10,M10,0) -> 0.54166667 | X10: =TIME(N10,O10,0) -> 0.5625 | Y10: =TIME(P10,Q10,0) -> 0.66319444 | Z10: =TIME(R10,S10,0) -> 0.66319444 | AA10: =TIME(T10,U10,0) -> 0.66319444 | AC10: =IF(OR(E10="Sa",E10="So"),TIME($AC$4,$AE$4,0),TIME($AC$5,$AE$5,0)) -> 0.35069444 | AE10: =IF(OR(E10="Sa",E10="So"),TIME($AC$4,$AE$4,0),(Y10-V10-(X10-W10)+(AA10-Z10))) -> 0.35069444 | AJ10: =IF(AG10=$AG$3,1,0) -> 0 | AK10: =IF(AG10=$AG$7,1,0) -> 0 | AL10: =IF(AH10=$AG$4,1,0) -> 0 | AN10: =IF(OR(AG10=$AG$2,AG10=$AG$5),1,IF(AG10=$AG$6,0.5,0)) -> 0 | AO10: =IF(OR(E10="Sa",E10="So"),0,1) -> 1
D11: =IF(E11="Mo",WEEKNUM(I11),"") | E11: =TEXT(I11,"TTT") -> Di | F11: =$F$5 -> 2035 | G11: =$A$10 -> 1 | H11: =H10+1 -> 2 | I11: =DATE(F11,G11,H11) -> 47849 | J11: =IF(OR($E11="Sa",$E11="So"),J$4,J$5) -> 7 | K11: =IF(OR($E11="Sa",$E11="So"),K$4,K$5) -> 0 | L11: =IF(OR($E11="Sa",$E11="So"),L$4,L$5) -> 13 | M11: =IF(OR($E11="Sa",$E11="So"),M$4,M$5) -> 0 | N11: =IF(OR($E11="Sa",$E11="So"),N$4,N$5) -> 13 | O11: =IF(OR($E11="Sa",$E11="So"),O$4,O$5) -> 30 | P11: =IF(OR($E11="Sa",$E11="So"),P$4,P$5) -> 15 | Q11: =IF(OR($E11="Sa",$E11="So"),Q$4,Q$5) -> 55 | R11: =P11 -> 15 | S11: =Q11 -> 55 | T11: =R11 -> 15 | U11: =S11 -> 55 | V11: =TIME(J11,K11,0) -> 0.29166667 | W11: =TIME(L11,M11,0) -> 0.54166667 | X11: =TIME(N11,O11,0) -> 0.5625 | Y11: =TIME(P11,Q11,0) -> 0.66319444 | Z11: =TIME(R11,S11,0) -> 0.66319444 | AA11: =TIME(T11,U11,0) -> 0.66319444 | AC11: =IF(OR(E11="Sa",E11="So"),TIME($AC$4,$AE$4,0),TIME($AC$5,$AE$5,0)) -> 0.35069444 | AE11: =IF(OR(E11="Sa",E11="So"),TIME($AC$4,$AE$4,0),(Y11-V11-(X11-W11)+(AA11-Z11))) -> 0.35069444 | AJ11: =IF(AG11=$AG$3,1,0) -> 0 | AK11: =IF(AG11=$AG$7,1,0) -> 0 | AL11: =IF(AH11=$AG$4,1,0) -> 0 | AN11: =IF(OR(AG11=$AG$2,AG11=$AG$5),1,IF(AG11=$AG$6,0.5,0)) -> 0 | AO11: =IF(OR(E11="Sa",E11="So"),0,1) -> 1
D12: =IF(E12="Mo",WEEKNUM(I12),"") | E12: =TEXT(I12,"TTT") -> Mi | F12: =$F$5 -> 2035 | G12: =$A$10 -> 1 | H12: =H11+1 -> 3 | I12: =DATE(F12,G12,H12) -> 47850 | J12: =IF(OR($E12="Sa",$E12="So"),J$4,J$5) -> 7 | K12: =IF(OR($E12="Sa",$E12="So"),K$4,K$5) -> 0 | L12: =IF(OR($E12="Sa",$E12="So"),L$4,L$5) -> 13 | M12: =IF(OR($E12="Sa",$E12="So"),M$4,M$5) -> 0 | N12: =IF(OR($E12="Sa",$E12="So"),N$4,N$5) -> 13 | O12: =IF(OR($E12="Sa",$E12="So"),O$4,O$5) -> 30 | P12: =IF(OR($E12="Sa",$E12="So"),P$4,P$5) -> 15 | Q12: =IF(OR($E12="Sa",$E12="So"),Q$4,Q$5) -> 55 | R12: =P12 -> 15 | S12: =Q12 -> 55 | T12: =R12 -> 15 | U12: =S12 -> 55 | V12: =TIME(J12,K12,0) -> 0.29166667 | W12: =TIME(L12,M12,0) -> 0.54166667 | X12: =TIME(N12,O12,0) -> 0.5625 | Y12: =TIME(P12,Q12,0) -> 0.66319444 | Z12: =TIME(R12,S12,0) -> 0.66319444 | AA12: =TIME(T12,U12,0) -> 0.66319444 | AC12: =IF(OR(E12="Sa",E12="So"),TIME($AC$4,$AE$4,0),TIME($AC$5,$AE$5,0)) -> 0.35069444 | AE12: =IF(OR(E12="Sa",E12="So"),TIME($AC$4,$AE$4,0),(Y12-V12-(X12-W12)+(AA12-Z12))) -> 0.35069444 | AJ12: =IF(AG12=$AG$3,1,0) -> 0 | AK12: =IF(AG12=$AG$7,1,0) -> 0 | AL12: =IF(AH12=$AG$4,1,0) -> 0 | AN12: =IF(OR(AG12=$AG$2,AG12=$AG$5),1,IF(AG12=$AG$6,0.5,0)) -> 0 | AO12: =IF(OR(E12="Sa",E12="So"),0,1) -> 1
D13: =IF(E13="Mo",WEEKNUM(I13),"") | E13: =TEXT(I13,"TTT") -> Do | F13: =$F$5 -> 2035 | G13: =$A$10 -> 1 | H13: =H12+1 -> 4 | I13: =DATE(F13,G13,H13) -> 47851 | J13: =IF(OR($E13="Sa",$E13="So"),J$4,J$5) -> 7 | K13: =IF(OR($E13="Sa",$E13="So"),K$4,K$5) -> 0 | L13: =IF(OR($E13="Sa",$E13="So"),L$4,L$5) -> 13 | M13: =IF(OR($E13="Sa",$E13="So"),M$4,M$5) -> 0 | N13: =IF(OR($E13="Sa",$E13="So"),N$4,N$5) -> 13 | O13: =IF(OR($E13="Sa",$E13="So"),O$4,O$5) -> 30 | P13: =IF(OR($E13="Sa",$E13="So"),P$4,P$5) -> 15 | Q13: =IF(OR($E13="Sa",$E13="So"),Q$4,Q$5) -> 55 | R13: =P13 -> 15 | S13: =Q13 -> 55 | T13: =R13 -> 15 | U13: =S13 -> 55 | V13: =TIME(J13,K13,0) -> 0.29166667 | W13: =TIME(L13,M13,0) -> 0.54166667 | X13: =TIME(N13,O13,0) -> 0.5625 | Y13: =TIME(P13,Q13,0) -> 0.66319444 | Z13: =TIME(R13,S13,0) -> 0.66319444 | AA13: =TIME(T13,U13,0) -> 0.66319444 | AC13: =IF(OR(E13="Sa",E13="So"),TIME($AC$4,$AE$4,0),TIME($AC$5,$AE$5,0)) -> 0.35069444 | AE13: =IF(OR(E13="Sa",E13="So"),TIME($AC$4,$AE$4,0),(Y13-V13-(X13-W13)+(AA13-Z13))) -> 0.35069444 | AJ13: =IF(AG13=$AG$3,1,0) -> 0 | AK13: =IF(AG13=$AG$7,1,0) -> 0 | AL13: =IF(AH13=$AG$4,1,0) -> 0 | AN13: =IF(OR(AG13=$AG$2,AG13=$AG$5),1,IF(AG13=$AG$6,0.5,0)) -> 0 | AO13: =IF(OR(E13="Sa",E13="So"),0,1) -> 1
D14: =IF(E14="Mo",WEEKNUM(I14),"") | E14: =TEXT(I14,"TTT") -> Fr | F14: =$F$5 -> 2035 | G14: =$A$10 -> 1 | H14: =H13+1 -> 5 | I14: =DATE(F14,G14,H14) -> 47852 | J14: =IF(OR($E14="Sa",$E14="So"),J$4,J$5) -> 7 | K14: =IF(OR($E14="Sa",$E14="So"),K$4,K$5) -> 0 | L14: =IF(OR($E14="Sa",$E14="So"),L$4,L$5) -> 13 | M14: =IF(OR($E14="Sa",$E14="So"),M$4,M$5) -> 0 | N14: =IF(OR($E14="Sa",$E14="So"),N$4,N$5) -> 13 | O14: =IF(OR($E14="Sa",$E14="So"),O$4,O$5) -> 30 | P14: =IF(OR($E14="Sa",$E14="So"),P$4,P$5) -> 15 | Q14: =IF(OR($E14="Sa",$E14="So"),Q$4,Q$5) -> 55 | R14: =P14 -> 15 | S14: =Q14 -> 55 | T14: =R14 -> 15 | U14: =S14 -> 55 | V14: =TIME(J14,K14,0) -> 0.29166667 | W14: =TIME(L14,M14,0) -> 0.54166667 | X14: =TIME(N14,O14,0) -> 0.5625 | Y14: =TIME(P14,Q14,0) -> 0.66319444 | Z14: =TIME(R14,S14,0) -> 0.66319444 | AA14: =TIME(T14,U14,0) -> 0.66319444 | AC14: =IF(OR(E14="Sa",E14="So"),TIME($AC$4,$AE$4,0),TIME($AC$5,$AE$5,0)) -> 0.35069444 | AE14: =IF(OR(E14="Sa",E14="So"),TIME($AC$4,$AE$4,0),(Y14-V14-(X14-W14)+(AA14-Z14))) -> 0.35069444 | AJ14: =IF(AG14=$AG$3,1,0) -> 0 | AK14: =IF(AG14=$AG$7,1,0) -> 0 | AL14: =IF(AH14=$AG$4,1,0) -> 0 | AN14: =IF(OR(AG14=$AG$2,AG14=$AG$5),1,IF(AG14=$AG$6,0.5,0)) -> 0 | AO14: =IF(OR(E14="Sa",E14="So"),0,1) -> 1
D15: =IF(E15="Mo",WEEKNUM(I15),"") | E15: =TEXT(I15,"TTT") -> Sa | F15: =$F$5 -> 2035 | G15: =$A$10 -> 1 | H15: =H14+1 -> 6 | I15: =DATE(F15,G15,H15) -> 47853 | J15: =IF(OR($E15="Sa",$E15="So"),J$4,J$5) -> 0 | K15: =IF(OR($E15="Sa",$E15="So"),K$4,K$5) -> 0 | L15: =IF(OR($E15="Sa",$E15="So"),L$4,L$5) -> 0 | M15: =IF(OR($E15="Sa",$E15="So"),M$4,M$5) -> 0 | N15: =IF(OR($E15="Sa",$E15="So"),N$4,N$5) -> 0 | O15: =IF(OR($E15="Sa",$E15="So"),O$4,O$5) -> 0 | P15: =IF(OR($E15="Sa",$E15="So"),P$4,P$5) -> 0 | Q15: =IF(OR($E15="Sa",$E15="So"),Q$4,Q$5) -> 0 | R15: =P15 -> 0 | S15: =Q15 -> 0 | T15: =R15 -> 0 | U15: =S15 -> 0 | V15: =TIME(J15,K15,0) -> 0 | W15: =TIME(L15,M15,0) -> 0 | X15: =TIME(N15,O15,0) -> 0 | Y15: =TIME(P15,Q15,0) -> 0 | Z15: =TIME(R15,S15,0) -> 0 | AA15: =TIME(T15,U15,0) -> 0 | AC15: =IF(OR(E15="Sa",E15="So"),TIME($AC$4,$AE$4,0),TIME($AC$5,$AE$5,0)) -> 0 | AE15: =IF(OR(E15="Sa",E15="So"),TIME($AC$4,$AE$4,0),(Y15-V15-(X15-W15)+(AA15-Z15))) -> 0 | AJ15: =IF(AG15=$AG$3,1,0) -> 0 | AK15: =IF(AG15=$AG$7,1,0) -> 0 | AL15: =IF(AH15=$AG$4,1,0) -> 0 | AN15: =IF(OR(AG15=$AG$2,AG15=$AG$5),1,IF(AG15=$AG$6,0.5,0)) -> 0 | AO15: =IF(OR(E15="Sa",E15="So"),0,1) -> 0
D16: =IF(E16="Mo",WEEKNUM(I16),"") | E16: =TEXT(I16,"TTT") -> So | F16: =$F$5 -> 2035 | G16: =$A$10 -> 1 | H16: =H15+1 -> 7 | I16: =DATE(F16,G16,H16) -> 47854 | J16: =IF(OR($E16="Sa",$E16="So"),J$4,J$5) -> 0 | K16: =IF(OR($E16="Sa",$E16="So"),K$4,K$5) -> 0 | L16: =IF(OR($E16="Sa",$E16="So"),L$4,L$5) -> 0 | M16: =IF(OR($E16="Sa",$E16="So"),M$4,M$5) -> 0 | N16: =IF(OR($E16="Sa",$E16="So"),N$4,N$5) -> 0 | O16: =IF(OR($E16="Sa",$E16="So"),O$4,O$5) -> 0 | P16: =IF(OR($E16="Sa",$E16="So"),P$4,P$5) -> 0 | Q16: =IF(OR($E16="Sa",$E16="So"),Q$4,Q$5) -> 0 | R16: =P16 -> 0 | S16: =Q16 -> 0 | T16: =R16 -> 0 | U16: =S16 -> 0 | V16: =TIME(J16,K16,0) -> 0 | W16: =TIME(L16,M16,0) -> 0 | X16: =TIME(N16,O16,0) -> 0 | Y16: =TIME(P16,Q16,0) -> 0 | Z16: =TIME(R16,S16,0) -> 0 | AA16: =TIME(T16,U16,0) -> 0 | AC16: =IF(OR(E16="Sa",E16="So"),TIME($AC$4,$AE$4,0),TIME($AC$5,$AE$5,0)) -> 0 | AE16: =IF(OR(E16="Sa",E16="So"),TIME($AC$4,$AE$4,0),(Y16-V16-(X16-W16)+(AA16-Z16))) -> 0 | AJ16: =IF(AG16=$AG$3,1,0) -> 0 | AK16: =IF(AG16=$AG$7,1,0) -> 0 | AL16: =IF(AH16=$AG$4,1,0) -> 0 | AN16: =IF(OR(AG16=$AG$2,AG16=$AG$5),1,IF(AG16=$AG$6,0.5,0)) -> 0 | AO16: =IF(OR(E16="Sa",E16="So"),0,1) -> 0
D17: =IF(E17="Mo",WEEKNUM(I17),"") -> 2 | E17: =TEXT(I17,"TTT") -> Mo | F17: =$F$5 -> 2035 | G17: =$A$10 -> 1 | H17: =H16+1 -> 8 | I17: =DATE(F17,G17,H17) -> 47855 | J17: =IF(OR($E17="Sa",$E17="So"),J$4,J$5) -> 7 | K17: =IF(OR($E17="Sa",$E17="So"),K$4,K$5) -> 0 | L17: =IF(OR($E17="Sa",$E17="So"),L$4,L$5) -> 13 | M17: =IF(OR($E17="Sa",$E17="So"),M$4,M$5) -> 0 | N17: =IF(OR($E17="Sa",$E17="So"),N$4,N$5) -> 13 | O17: =IF(OR($E17="Sa",$E17="So"),O$4,O$5) -> 30 | P17: =IF(OR($E17="Sa",$E17="So"),P$4,P$5) -> 15 | Q17: =IF(OR($E17="Sa",$E17="So"),Q$4,Q$5) -> 55 | R17: =P17 -> 15 | S17: =Q17 -> 55 | T17: =R17 -> 15 | U17: =S17 -> 55 | V17: =TIME(J17,K17,0) -> 0.29166667 | W17: =TIME(L17,M17,0) -> 0.54166667 | X17: =TIME(N17,O17,0) -> 0.5625 | Y17: =TIME(P17,Q17,0) -> 0.66319444 | Z17: =TIME(R17,S17,0) -> 0.66319444 | AA17: =TIME(T17,U17,0) -> 0.66319444 | AC17: =IF(OR(E17="Sa",E17="So"),TIME($AC$4,$AE$4,0),TIME($AC$5,$AE$5,0)) -> 0.35069444 | AE17: =IF(OR(E17="Sa",E17="So"),TIME($AC$4,$AE$4,0),(Y17-V17-(X17-W17)+(AA17-Z17))) -> 0.35069444 | AJ17: =IF(AG17=$AG$3,1,0) -> 0 | AK17: =IF(AG17=$AG$7,1,0) -> 0 | AL17: =IF(AH17=$AG$4,1,0) -> 0 | AN17: =IF(OR(AG17=$AG$2,AG17=$AG$5),1,IF(AG17=$AG$6,0.5,0)) -> 0 | AO17: =IF(OR(E17="Sa",E17="So"),0,1) -> 1
D18: =IF(E18="Mo",WEEKNUM(I18),"") | E18: =TEXT(I18,"TTT") -> Di | F18: =$F$5 -> 2035 | G18: =$A$10 -> 1 | H18: =H17+1 -> 9 | I18: =DATE(F18,G18,H18) -> 47856 | J18: =IF(OR($E18="Sa",$E18="So"),J$4,J$5) -> 7 | K18: =IF(OR($E18="Sa",$E18="So"),K$4,K$5) -> 0 | L18: =IF(OR($E18="Sa",$E18="So"),L$4,L$5) -> 13 | M18: =IF(OR($E18="Sa",$E18="So"),M$4,M$5) -> 0 | N18: =IF(OR($E18="Sa",$E18="So"),N$4,N$5) -> 13 | O18: =IF(OR($E18="Sa",$E18="So"),O$4,O$5) -> 30 | P18: =IF(OR($E18="Sa",$E18="So"),P$4,P$5) -> 15 | Q18: =IF(OR($E18="Sa",$E18="So"),Q$4,Q$5) -> 55 | R18: =P18 -> 15 | S18: =Q18 -> 55 | T18: =R18 -> 15 | U18: =S18 -> 55 | V18: =TIME(J18,K18,0) -> 0.29166667 | W18: =TIME(L18,M18,0) -> 0.54166667 | X18: =TIME(N18,O18,0) -> 0.5625 | Y18: =TIME(P18,Q18,0) -> 0.66319444 | Z18: =TIME(R18,S18,0) -> 0.66319444 | AA18: =TIME(T18,U18,0) -> 0.66319444 | AC18: =IF(OR(E18="Sa",E18="So"),TIME($AC$4,$AE$4,0),TIME($AC$5,$AE$5,0)) -> 0.35069444 | AE18: =IF(OR(E18="Sa",E18="So"),TIME($AC$4,$AE$4,0),(Y18-V18-(X18-W18)+(AA18-Z18))) -> 0.35069444 | AJ18: =IF(AG18=$AG$3,1,0) -> 0 | AK18: =IF(AG18=$AG$7,1,0) -> 0 | AL18: =IF(AH18=$AG$4,1,0) -> 0 | AN18: =IF(OR(AG18=$AG$2,AG18=$AG$5),1,IF(AG18=$AG$6,0.5,0)) -> 0 | AO18: =IF(OR(E18="Sa",E18="So"),0,1) -> 1
D19: =IF(E19="Mo",WEEKNUM(I19),"") | E19: =TEXT(I19,"TTT") -> Mi | F19: =$F$5 -> 2035 | G19: =$A$10 -> 1 | H19: =H18+1 -> 10 | I19: =DATE(F19,G19,H19) -> 47857 | J19: =IF(OR($E19="Sa",$E19="So"),J$4,J$5) -> 7 | K19: =IF(OR($E19="Sa",$E19="So"),K$4,K$5) -> 0 | L19: =IF(OR($E19="Sa",$E19="So"),L$4,L$5) -> 13 | M19: =IF(OR($E19="Sa",$E19="So"),M$4,M$5) -> 0 | N19: =IF(OR($E19="Sa",$E19="So"),N$4,N$5) -> 13 | O19: =IF(OR($E19="Sa",$E19="So"),O$4,O$5) -> 30 | P19: =IF(OR($E19="Sa",$E19="So"),P$4,P$5) -> 15 | Q19: =IF(OR($E19="Sa",$E19="So"),Q$4,Q$5) -> 55 | R19: =P19 -> 15 | S19: =Q19 -> 55 | T19: =R19 -> 15 | U19: =S19 -> 55 | V19: =TIME(J19,K19,0) -> 0.29166667 | W19: =TIME(L19,M19,0) -> 0.54166667 | X19: =TIME(N19,O19,0) -> 0.5625 | Y19: =TIME(P19,Q19,0) -> 0.66319444 | Z19: =TIME(R19,S19,0) -> 0.66319444 | AA19: =TIME(T19,U19,0) -> 0.66319444 | AC19: =IF(OR(E19="Sa",E19="So"),TIME($AC$4,$AE$4,0),TIME($AC$5,$AE$5,0)) -> 0.35069444 | AE19: =IF(OR(E19="Sa",E19="So"),TIME($AC$4,$AE$4,0),(Y19-V19-(X19-W19)+(AA19-Z19))) -> 0.35069444 | AJ19: =IF(AG19=$AG$3,1,0) -> 0 | AK19: =IF(AG19=$AG$7,1,0) -> 0 | AL19: =IF(AH19=$AG$4,1,0) -> 0 | AN19: =IF(OR(AG19=$AG$2,AG19=$AG$5),1,IF(AG19=$AG$6,0.5,0)) -> 0 | AO19: =IF(OR(E19="Sa",E19="So"),0,1) -> 1
D20: =IF(E20="Mo",WEEKNUM(I20),"") | E20: =TEXT(I20,"TTT") -> Do | F20: =$F$5 -> 2035 | G20: =$A$10 -> 1 | H20: =H19+1 -> 11 | I20: =DATE(F20,G20,H20) -> 47858 | J20: =IF(OR($E20="Sa",$E20="So"),J$4,J$5) -> 7 | K20: =IF(OR($E20="Sa",$E20="So"),K$4,K$5) -> 0 | L20: =IF(OR($E20="Sa",$E20="So"),L$4,L$5) -> 13 | M20: =IF(OR($E20="Sa",$E20="So"),M$4,M$5) -> 0 | N20: =IF(OR($E20="Sa",$E20="So"),N$4,N$5) -> 13 | O20: =IF(OR($E20="Sa",$E20="So"),O$4,O$5) -> 30 | P20: =IF(OR($E20="Sa",$E20="So"),P$4,P$5) -> 15 | Q20: =IF(OR($E20="Sa",$E20="So"),Q$4,Q$5) -> 55 | R20: =P20 -> 15 | S20: =Q20 -> 55 | T20: =R20 -> 15 | U20: =S20 -> 55 | V20: =TIME(J20,K20,0) -> 0.29166667 | W20: =TIME(L20,M20,0) -> 0.54166667 | X20: =TIME(N20,O20,0) -> 0.5625 | Y20: =TIME(P20,Q20,0) -> 0.66319444 | Z20: =TIME(R20,S20,0) -> 0.66319444 | AA20: =TIME(T20,U20,0) -> 0.66319444 | AC20: =IF(OR(E20="Sa",E20="So"),TIME($AC$4,$AE$4,0),TIME($AC$5,$AE$5,0)) -> 0.35069444 | AE20: =IF(OR(E20="Sa",E20="So"),TIME($AC$4,$AE$4,0),(Y20-V20-(X20-W20)+(AA20-Z20))) -> 0.35069444 | AJ20: =IF(AG20=$AG$3,1,0) -> 0 | AK20: =IF(AG20=$AG$7,1,0) -> 0 | AL20: =IF(AH20=$AG$4,1,0) -> 0 | AN20: =IF(OR(AG20=$AG$2,AG20=$AG$5),1,IF(AG20=$AG$6,0.5,0)) -> 0 | AO20: =IF(OR(E20="Sa",E20="So"),0,1) -> 1
D21: =IF(E21="Mo",WEEKNUM(I21),"") | E21: =TEXT(I21,"TTT") -> Fr | F21: =$F$5 -> 2035 | G21: =$A$10 -> 1 | H21: =H20+1 -> 12 | I21: =DATE(F21,G21,H21) -> 47859 | J21: =IF(OR($E21="Sa",$E21="So"),J$4,J$5) -> 7 | K21: =IF(OR($E21="Sa",$E21="So"),K$4,K$5) -> 0 | L21: =IF(OR($E21="Sa",$E21="So"),L$4,L$5) -> 13 | M21: =IF(OR($E21="Sa",$E21="So"),M$4,M$5) -> 0 | N21: =IF(OR($E21="Sa",$E21="So"),N$4,N$5) -> 13 | O21: =IF(OR($E21="Sa",$E21="So"),O$4,O$5) -> 30 | P21: =IF(OR($E21="Sa",$E21="So"),P$4,P$5) -> 15 | Q21: =IF(OR($E21="Sa",$E21="So"),Q$4,Q$5) -> 55 | R21: =P21 -> 15 | S21: =Q21 -> 55 | T21: =R21 -> 15 | U21: =S21 -> 55 | V21: =TIME(J21,K21,0) -> 0.29166667 | W21: =TIME(L21,M21,0) -> 0.54166667 | X21: =TIME(N21,O21,0) -> 0.5625 | Y21: =TIME(P21,Q21,0) -> 0.66319444 | Z21: =TIME(R21,S21,0) -> 0.66319444 | AA21: =TIME(T21,U21,0) -> 0.66319444 | AC21: =IF(OR(E21="Sa",E21="So"),TIME($AC$4,$AE$4,0),TIME($AC$5,$AE$5,0)) -> 0.35069444 | AE21: =IF(OR(E21="Sa",E21="So"),TIME($AC$4,$AE$4,0),(Y21-V21-(X21-W21)+(AA21-Z21))) -> 0.35069444 | AJ21: =IF(AG21=$AG$3,1,0) -> 0 | AK21: =IF(AG21=$AG$7,1,0) -> 0 | AL21: =IF(AH21=$AG$4,1,0) -> 0 | AN21: =IF(OR(AG21=$AG$2,AG21=$AG$5),1,IF(AG21=$AG$6,0.5,0)) -> 0 | AO21: =IF(OR(E21="Sa",E21="So"),0,1) -> 1
D22: =IF(E22="Mo",WEEKNUM(I22),"") | E22: =TEXT(I22,"TTT") -> Sa | F22: =$F$5 -> 2035 | G22: =$A$10 -> 1 | H22: =H21+1 -> 13 | I22: =DATE(F22,G22,H22) -> 47860 | J22: =IF(OR($E22="Sa",$E22="So"),J$4,J$5) -> 0 | K22: =IF(OR($E22="Sa",$E22="So"),K$4,K$5) -> 0 | L22: =IF(OR($E22="Sa",$E22="So"),L$4,L$5) -> 0 | M22: =IF(OR($E22="Sa",$E22="So"),M$4,M$5) -> 0 | N22: =IF(OR($E22="Sa",$E22="So"),N$4,N$5) -> 0 | O22: =IF(OR($E22="Sa",$E22="So"),O$4,O$5) -> 0 | P22: =IF(OR($E22="Sa",$E22="So"),P$4,P$5) -> 0 | Q22: =IF(OR($E22="Sa",$E22="So"),Q$4,Q$5) -> 0 | R22: =P22 -> 0 | S22: =Q22 -> 0 | T22: =R22 -> 0 | U22: =S22 -> 0 | V22: =TIME(J22,K22,0) -> 0 | W22: =TIME(L22,M22,0) -> 0 | X22: =TIME(N22,O22,0) -> 0 | Y22: =TIME(P22,Q22,0) -> 0 | Z22: =TIME(R22,S22,0) -> 0 | AA22: =TIME(T22,U22,0) -> 0 | AC22: =IF(OR(E22="Sa",E22="So"),TIME($AC$4,$AE$4,0),TIME($AC$5,$AE$5,0)) -> 0 | AE22: =IF(OR(E22="Sa",E22="So"),TIME($AC$4,$AE$4,0),(Y22-V22-(X22-W22)+(AA22-Z22))) -> 0 | AJ22: =IF(AG22=$AG$3,1,0) -> 0 | AK22: =IF(AG22=$AG$7,1,0) -> 0 | AL22: =IF(AH22=$AG$4,1,0) -> 0 | AN22: =IF(OR(AG22=$AG$2,AG22=$AG$5),1,IF(AG22=$AG$6,0.5,0)) -> 0 | AO22: =IF(OR(E22="Sa",E22="So"),0,1) -> 0
... D40: =IF(E40="Mo",WEEKNUM(I40),"") | E40: =TEXT(I40,"TTT") -> Mi | F40: =$F$5 -> 2035 | G40: =$A$10 -> 1 | H40: =H39+1 -> 31 | I40: =DATE(F40,G40,H40) -> 47878 | J40: =IF(OR($E40="Sa",$E40="So"),J$4,J$5) -> 7 | K40: =IF(OR($E40="Sa",$E40="So"),K$4,K$5) -> 0 | L40: =IF(OR($E40="Sa",$E40="So"),L$4,L$5) -> 13 | M40: =IF(OR($E40="Sa",$E40="So"),M$4,M$5) -> 0 | N40: =IF(OR($E40="Sa",$E40="So"),N$4,N$5) -> 13 | O40: =IF(OR($E40="Sa",$E40="So"),O$4,O$5) -> 30 | P40: =IF(OR($E40="Sa",$E40="So"),P$4,P$5) -> 15 | Q40: =IF(OR($E40="Sa",$E40="So"),Q$4,Q$5) -> 55 | R40: =P40 -> 15 | S40: =Q40 -> 55 | T40: =R40 -> 15 | U40: =S40 -> 55 | V40: =TIME(J40,K40,0) -> 0.29166667 | W40: =TIME(L40,M40,0) -> 0.54166667 | X40: =TIME(N40,O40,0) -> 0.5625 | Y40: =TIME(P40,Q40,0) -> 0.66319444 | Z40: =TIME(R40,S40,0) -> 0.66319444 | AA40: =TIME(T40,U40,0) -> 0.66319444 | AC40: =IF(OR(E40="Sa",E40="So"),TIME($AC$4,$AE$4,0),TIME($AC$5,$AE$5,0)) -> 0.35069444 | AE40: =IF(OR(E40="Sa",E40="So"),TIME($AC$4,$AE$4,0),(Y40-V40-(X40-W40)+(AA40-Z40))) -> 0.35069444 | AJ40: =IF(AG40=$AG$3,1,0) -> 0 | AK40: =IF(AG40=$AG$7,1,0) -> 0 | AL40: =IF(AH40=$AG$4,1,0) -> 0 | AN40: =IF(OR(AG40=$AG$2,AG40=$AG$5),1,IF(AG40=$AG$6,0.5,0)) -> 0 | AO40: =IF(OR(E40="Sa",E40="So"),0,1) -> 1
D41: EM | P41: Summ | AC41: =SUM(AC10:AC40) -> 8.0659722 | AE41: =SUM(AE10:AE40) -> 8.0659722 | AI41: =IF(AE41-AC41<0,AC41-AE41,AE41-AC41) -> 3.5527137e-15 | AJ41: =8.425*SUM(AJ10:AJ40)/24 -> 0 | AK41: =8.425*SUM(AK10:AK40)/24 -> 0 | AL41: =8.425*SUM(AL10:AL40)/24 -> 0 | AN41: =SUM(AN10:AN40) -> 0 | AO41: =SUM(AO10:AO40) -> 23
AI42: =AI8+AI41 -> 3.5527137e-15 | AJ42: =AJ8+SUM(AJ9:AJ40) -> 0 | AK42: =AK8+SUM(AK9:AK40) -> 0 | AL42: =AL8+SUM(AL9:AL40) -> 0 | AN42: =AN41*8 -> 0 | AO42: =AO41*8 -> 184
B43: =$F$5 -> 2035 | C43: =TEXT(I44,"MMM") -> Feb
A44: =A10+1 -> 2 | D44: =IF(E44="Mo",WEEKNUM(I44),"") | E44: =TEXT(I44,"TTT") -> Do | F44: =$F$5 -> 2035 | G44: =$A$44 -> 2 | H44: =$H$5 -> 1 | I44: =DATE(F44,G44,H44) -> 47879 | J44: =IF(OR($E44="Sa",$E44="So"),J$4,J$5) -> 7 | K44: =IF(OR($E44="Sa",$E44="So"),K$4,K$5) -> 0 | L44: =IF(OR($E44="Sa",$E44="So"),L$4,L$5) -> 13 | M44: =IF(OR($E44="Sa",$E44="So"),M$4,M$5) -> 0 | N44: =IF(OR($E44="Sa",$E44="So"),N$4,N$5) -> 13 | O44: =IF(OR($E44="Sa",$E44="So"),O$4,O$5) -> 30 | P44: =IF(OR($E44="Sa",$E44="So"),P$4,P$5) -> 15 | Q44: =IF(OR($E44="Sa",$E44="So"),Q$4,Q$5) -> 55 | R44: =P44 -> 15 | S44: =Q44 -> 55 | T44: =R44 -> 15 | U44: =S44 -> 55 | V44: =TIME(J44,K44,0) -> 0.29166667 | W44: =TIME(L44,M44,0) -> 0.54166667 | X44: =TIME(N44,O44,0) -> 0.5625 | Y44: =TIME(P44,Q44,0) -> 0.66319444 | Z44: =TIME(R44,S44,0) -> 0.66319444 | AA44: =TIME(T44,U44,0) -> 0.66319444 | AC44: =IF(OR(E44="Sa",E44="So"),TIME($AC$4,$AE$4,0),TIME($AC$5,$AE$5,0)) -> 0.35069444 | AE44: =IF(OR(E44="Sa",E44="So"),TIME($AC$4,$AE$4,0),(Y44-V44-(X44-W44)+(AA44-Z44))) -> 0.35069444 | AJ44: =IF(AG44=$AG$3,1,0) -> 0 | AK44: =IF(AG44=$AG$7,1,0) -> 0 | AL44: =IF(AH44=$AG$4,1,0) -> 0 | AN44: =IF(OR(AG44=$AG$2,AG44=$AG$5),1,IF(AG44=$AG$6,0.5,0)) -> 0 | AO44: =IF(OR(E44="Sa",E44="So"),0,1) -> 1
D45: =IF(E45="Mo",WEEKNUM(I45),"") | E45: =TEXT(I45,"TTT") -> Fr | F45: =$F$5 -> 2035 | G45: =$A$44 -> 2 | H45: =H44+1 -> 2 | I45: =DATE(F45,G45,H45) -> 47880 | J45: =IF(OR($E45="Sa",$E45="So"),J$4,J$5) -> 7 | K45: =IF(OR($E45="Sa",$E45="So"),K$4,K$5) -> 0 | L45: =IF(OR($E45="Sa",$E45="So"),L$4,L$5) -> 13 | M45: =IF(OR($E45="Sa",$E45="So"),M$4,M$5) -> 0 | N45: =IF(OR($E45="Sa",$E45="So"),N$4,N$5) -> 13 | O45: =IF(OR($E45="Sa",$E45="So"),O$4,O$5) -> 30 | P45: =IF(OR($E45="Sa",$E45="So"),P$4,P$5) -> 15 | Q45: =IF(OR($E45="Sa",$E45="So"),Q$4,Q$5) -> 55 | R45: =P45 -> 15 | S45: =Q45 -> 55 | T45: =R45 -> 15 | U45: =S45 -> 55 | V45: =TIME(J45,K45,0) -> 0.29166667 | W45: =TIME(L45,M45,0) -> 0.54166667 | X45: =TIME(N45,O45,0) -> 0.5625 | Y45: =TIME(P45,Q45,0) -> 0.66319444 | Z45: =TIME(R45,S45,0) -> 0.66319444 | AA45: =TIME(T45,U45,0) -> 0.66319444 | AC45: =IF(OR(E45="Sa",E45="So"),TIME($AC$4,$AE$4,0),TIME($AC$5,$AE$5,0)) -> 0.35069444 | AE45: =IF(OR(E45="Sa",E45="So"),TIME($AC$4,$AE$4,0),(Y45-V45-(X45-W45)+(AA45-Z45))) -> 0.35069444 | AJ45: =IF(AG45=$AG$3,1,0) -> 0 | AK45: =IF(AG45=$AG$7,1,0) -> 0 | AL45: =IF(AH45=$AG$4,1,0) -> 0 | AN45: =IF(OR(AG45=$AG$2,AG45=$AG$5),1,IF(AG45=$AG$6,0.5,0)) -> 0 | AO45: =IF(OR(E45="Sa",E45="So"),0,1) -> 1
D46: =IF(E46="Mo",WEEKNUM(I46),"") | E46: =TEXT(I46,"TTT") -> Sa | F46: =$F$5 -> 2035 | G46: =$A$44 -> 2 | H46: =H45+1 -> 3 | I46: =DATE(F46,G46,H46) -> 47881 | J46: =IF(OR($E46="Sa",$E46="So"),J$4,J$5) -> 0 | K46: =IF(OR($E46="Sa",$E46="So"),K$4,K$5) -> 0 | L46: =IF(OR($E46="Sa",$E46="So"),L$4,L$5) -> 0 | M46: =IF(OR($E46="Sa",$E46="So"),M$4,M$5) -> 0 | N46: =IF(OR($E46="Sa",$E46="So"),N$4,N$5) -> 0 | O46: =IF(OR($E46="Sa",$E46="So"),O$4,O$5) -> 0 | P46: =IF(OR($E46="Sa",$E46="So"),P$4,P$5) -> 0 | Q46: =IF(OR($E46="Sa",$E46="So"),Q$4,Q$5) -> 0 | R46: =P46 -> 0 | S46: =Q46 -> 0 | T46: =R46 -> 0 | U46: =S46 -> 0 | V46: =TIME(J46,K46,0) -> 0 | W46: =TIME(L46,M46,0) -> 0 | X46: =TIME(N46,O46,0) -> 0 | Y46: =TIME(P46,Q46,0) -> 0 | Z46: =TIME(R46,S46,0) -> 0 | AA46: =TIME(T46,U46,0) -> 0 | AC46: =IF(OR(E46="Sa",E46="So"),TIME($AC$4,$AE$4,0),TIME($AC$5,$AE$5,0)) -> 0 | AE46: =IF(OR(E46="Sa",E46="So"),TIME($AC$4,$AE$4,0),(Y46-V46-(X46-W46)+(AA46-Z46))) -> 0 | AJ46: =IF(AG46=$AG$3,1,0) -> 0 | AK46: =IF(AG46=$AG$7,1,0) -> 0 | AL46: =IF(AH46=$AG$4,1,0) -> 0 | AN46: =IF(OR(AG46=$AG$2,AG46=$AG$5),1,IF(AG46=$AG$6,0.5,0)) -> 0 | AO46: =IF(OR(E46="Sa",E46="So"),0,1) -> 0
D47: =IF(E47="Mo",WEEKNUM(I47),"") | E47: =TEXT(I47,"TTT") -> So | F47: =$F$5 -> 2035 | G47: =$A$44 -> 2 | H47: =H46+1 -> 4 | I47: =DATE(F47,G47,H47) -> 47882 | J47: =IF(OR($E47="Sa",$E47="So"),J$4,J$5) -> 0 | K47: =IF(OR($E47="Sa",$E47="So"),K$4,K$5) -> 0 | L47: =IF(OR($E47="Sa",$E47="So"),L$4,L$5) -> 0 | M47: =IF(OR($E47="Sa",$E47="So"),M$4,M$5) -> 0 | N47: =IF(OR($E47="Sa",$E47="So"),N$4,N$5) -> 0 | O47: =IF(OR($E47="Sa",$E47="So"),O$4,O$5) -> 0 | P47: =IF(OR($E47="Sa",$E47="So"),P$4,P$5) -> 0 | Q47: =IF(OR($E47="Sa",$E47="So"),Q$4,Q$5) -> 0 | R47: =P47 -> 0 | S47: =Q47 -> 0 | T47: =R47 -> 0 | U47: =S47 -> 0 | V47: =TIME(J47,K47,0) -> 0 | W47: =TIME(L47,M47,0) -> 0 | X47: =TIME(N47,O47,0) -> 0 | Y47: =TIME(P47,Q47,0) -> 0 | Z47: =TIME(R47,S47,0) -> 0 | AA47: =TIME(T47,U47,0) -> 0 | AC47: =IF(OR(E47="Sa",E47="So"),TIME($AC$4,$AE$4,0),TIME($AC$5,$AE$5,0)) -> 0 | AE47: =IF(OR(E47="Sa",E47="So"),TIME($AC$4,$AE$4,0),(Y47-V47-(X47-W47)+(AA47-Z47))) -> 0 | AJ47: =IF(AG47=$AG$3,1,0) -> 0 | AK47: =IF(AG47=$AG$7,1,0) -> 0 | AL47: =IF(AH47=$AG$4,1,0) -> 0 | AN47: =IF(OR(AG47=$AG$2,AG47=$AG$5),1,IF(AG47=$AG$6,0.5,0)) -> 0 | AO47: =IF(OR(E47="Sa",E47="So"),0,1) -> 0
D48: =IF(E48="Mo",WEEKNUM(I48),"") -> 6 | E48: =TEXT(I48,"TTT") -> Mo | F48: =$F$5 -> 2035 | G48: =$A$44 -> 2 | H48: =H47+1 -> 5 | I48: =DATE(F48,G48,H48) -> 47883 | J48: =IF(OR($E48="Sa",$E48="So"),J$4,J$5) -> 7 | K48: =IF(OR($E48="Sa",$E48="So"),K$4,K$5) -> 0 | L48: =IF(OR($E48="Sa",$E48="So"),L$4,L$5) -> 13 | M48: =IF(OR($E48="Sa",$E48="So"),M$4,M$5) -> 0 | N48: =IF(OR($E48="Sa",$E48="So"),N$4,N$5) -> 13 | O48: =IF(OR($E48="Sa",$E48="So"),O$4,O$5) -> 30 | P48: =IF(OR($E48="Sa",$E48="So"),P$4,P$5) -> 15 | Q48: =IF(OR($E48="Sa",$E48="So"),Q$4,Q$5) -> 55 | R48: =P48 -> 15 | S48: =Q48 -> 55 | T48: =R48 -> 15 | U48: =S48 -> 55 | V48: =TIME(J48,K48,0) -> 0.29166667 | W48: =TIME(L48,M48,0) -> 0.54166667 | X48: =TIME(N48,O48,0) -> 0.5625 | Y48: =TIME(P48,Q48,0) -> 0.66319444 | Z48: =TIME(R48,S48,0) -> 0.66319444 | AA48: =TIME(T48,U48,0) -> 0.66319444 | AC48: =IF(OR(E48="Sa",E48="So"),TIME($AC$4,$AE$4,0),TIME($AC$5,$AE$5,0)) -> 0.35069444 | AE48: =IF(OR(E48="Sa",E48="So"),TIME($AC$4,$AE$4,0),(Y48-V48-(X48-W48)+(AA48-Z48))) -> 0.35069444 | AJ48: =IF(AG48=$AG$3,1,0) -> 0 | AK48: =IF(AG48=$AG$7,1,0) -> 0 | AL48: =IF(AH48=$AG$4,1,0) -> 0 | AN48: =IF(OR(AG48=$AG$2,AG48=$AG$5),1,IF(AG48=$AG$6,0.5,0)) -> 0 | AO48: =IF(OR(E48="Sa",E48="So"),0,1) -> 1
D49: =IF(E49="Mo",WEEKNUM(I49),"") | E49: =TEXT(I49,"TTT") -> Di | F49: =$F$5 -> 2035 | G49: =$A$44 -> 2 | H49: =H48+1 -> 6 | I49: =DATE(F49,G49,H49) -> 47884 | J49: =IF(OR($E49="Sa",$E49="So"),J$4,J$5) -> 7 | K49: =IF(OR($E49="Sa",$E49="So"),K$4,K$5) -> 0 | L49: =IF(OR($E49="Sa",$E49="So"),L$4,L$5) -> 13 | M49: =IF(OR($E49="Sa",$E49="So"),M$4,M$5) -> 0 | N49: =IF(OR($E49="Sa",$E49="So"),N$4,N$5) -> 13 | O49: =IF(OR($E49="Sa",$E49="So"),O$4,O$5) -> 30 | P49: =IF(OR($E49="Sa",$E49="So"),P$4,P$5) -> 15 | Q49: =IF(OR($E49="Sa",$E49="So"),Q$4,Q$5) -> 55 | R49: =P49 -> 15 | S49: =Q49 -> 55 | T49: =R49 -> 15 | U49: =S49 -> 55 | V49: =TIME(J49,K49,0) -> 0.29166667 | W49: =TIME(L49,M49,0) -> 0.54166667 | X49: =TIME(N49,O49,0) -> 0.5625 | Y49: =TIME(P49,Q49,0) -> 0.66319444 | Z49: =TIME(R49,S49,0) -> 0.66319444 | AA49: =TIME(T49,U49,0) -> 0.66319444 | AC49: =IF(OR(E49="Sa",E49="So"),TIME($AC$4,$AE$4,0),TIME($AC$5,$AE$5,0)) -> 0.35069444 | AE49: =IF(OR(E49="Sa",E49="So"),TIME($AC$4,$AE$4,0),(Y49-V49-(X49-W49)+(AA49-Z49))) -> 0.35069444 | AJ49: =IF(AG49=$AG$3,1,0) -> 0 | AK49: =IF(AG49=$AG$7,1,0) -> 0 | AL49: =IF(AH49=$AG$4,1,0) -> 0 | AN49: =IF(OR(AG49=$AG$2,AG49=$AG$5),1,IF(AG49=$AG$6,0.5,0)) -> 0 | AO49: =IF(OR(E49="Sa",E49="So"),0,1) -> 1
D50: =IF(E50="Mo",WEEKNUM(I50),"") | E50: =TEXT(I50,"TTT") -> Mi | F50: =$F$5 -> 2035 | G50: =$A$44 -> 2 | H50: =H49+1 -> 7 | I50: =DATE(F50,G50,H50) -> 47885 | J50: =IF(OR($E50="Sa",$E50="So"),J$4,J$5) -> 7 | K50: =IF(OR($E50="Sa",$E50="So"),K$4,K$5) -> 0 | L50: =IF(OR($E50="Sa",$E50="So"),L$4,L$5) -> 13 | M50: =IF(OR($E50="Sa",$E50="So"),M$4,M$5) -> 0 | N50: =IF(OR($E50="Sa",$E50="So"),N$4,N$5) -> 13 | O50: =IF(OR($E50="Sa",$E50="So"),O$4,O$5) -> 30 | P50: =IF(OR($E50="Sa",$E50="So"),P$4,P$5) -> 15 | Q50: =IF(OR($E50="Sa",$E50="So"),Q$4,Q$5) -> 55 | R50: =P50 -> 15 | S50: =Q50 -> 55 | T50: =R50 -> 15 | U50: =S50 -> 55 | V50: =TIME(J50,K50,0) -> 0.29166667 | W50: =TIME(L50,M50,0) -> 0.54166667 | X50: =TIME(N50,O50,0) -> 0.5625 | Y50: =TIME(P50,Q50,0) -> 0.66319444 | Z50: =TIME(R50,S50,0) -> 0.66319444 | AA50: =TIME(T50,U50,0) -> 0.66319444 | AC50: =IF(OR(E50="Sa",E50="So"),TIME($AC$4,$AE$4,0),TIME($AC$5,$AE$5,0)) -> 0.35069444 | AE50: =IF(OR(E50="Sa",E50="So"),TIME($AC$4,$AE$4,0),(Y50-V50-(X50-W50)+(AA50-Z50))) -> 0.35069444 | AJ50: =IF(AG50=$AG$3,1,0) -> 0 | AK50: =IF(AG50=$AG$7,1,0) -> 0 | AL50: =IF(AH50=$AG$4,1,0) -> 0 | AN50: =IF(OR(AG50=$AG$2,AG50=$AG$5),1,IF(AG50=$AG$6,0.5,0)) -> 0 | AO50: =IF(OR(E50="Sa",E50="So"),0,1) -> 1
D51: =IF(E51="Mo",WEEKNUM(I51),"") | E51: =TEXT(I51,"TTT") -> Do | F51: =$F$5 -> 2035 | G51: =$A$44 -> 2 | H51: =H50+1 -> 8 | I51: =DATE(F51,G51,H51) -> 47886 | J51: =IF(OR($E51="Sa",$E51="So"),J$4,J$5) -> 7 | K51: =IF(OR($E51="Sa",$E51="So"),K$4,K$5) -> 0 | L51: =IF(OR($E51="Sa",$E51="So"),L$4,L$5) -> 13 | M51: =IF(OR($E51="Sa",$E51="So"),M$4,M$5) -> 0 | N51: =IF(OR($E51="Sa",$E51="So"),N$4,N$5) -> 13 | O51: =IF(OR($E51="Sa",$E51="So"),O$4,O$5) -> 30 | P51: =IF(OR($E51="Sa",$E51="So"),P$4,P$5) -> 15 | Q51: =IF(OR($E51="Sa",$E51="So"),Q$4,Q$5) -> 55 | R51: =P51 -> 15 | S51: =Q51 -> 55 | T51: =R51 -> 15 | U51: =S51 -> 55 | V51: =TIME(J51,K51,0) -> 0.29166667 | W51: =TIME(L51,M51,0) -> 0.54166667 | X51: =TIME(N51,O51,0) -> 0.5625 | Y51: =TIME(P51,Q51,0) -> 0.66319444 | Z51: =TIME(R51,S51,0) -> 0.66319444 | AA51: =TIME(T51,U51,0) -> 0.66319444 | AC51: =IF(OR(E51="Sa",E51="So"),TIME($AC$4,$AE$4,0),TIME($AC$5,$AE$5,0)) -> 0.35069444 | AE51: =IF(OR(E51="Sa",E51="So"),TIME($AC$4,$AE$4,0),(Y51-V51-(X51-W51)+(AA51-Z51))) -> 0.35069444 | AJ51: =IF(AG51=$AG$3,1,0) -> 0 | AK51: =IF(AG51=$AG$7,1,0) -> 0 | AL51: =IF(AH51=$AG$4,1,0) -> 0 | AN51: =IF(OR(AG51=$AG$2,AG51=$AG$5),1,IF(AG51=$AG$6,0.5,0)) -> 0 | AO51: =IF(OR(E51="Sa",E51="So"),0,1) -> 1
D52: =IF(E52="Mo",WEEKNUM(I52),"") | E52: =TEXT(I52,"TTT") -> Fr | F52: =$F$5 -> 2035 | G52: =$A$44 -> 2 | H52: =H51+1 -> 9 | I52: =DATE(F52,G52,H52) -> 47887 | J52: =IF(OR($E52="Sa",$E52="So"),J$4,J$5) -> 7 | K52: =IF(OR($E52="Sa",$E52="So"),K$4,K$5) -> 0 | L52: =IF(OR($E52="Sa",$E52="So"),L$4,L$5) -> 13 | M52: =IF(OR($E52="Sa",$E52="So"),M$4,M$5) -> 0 | N52: =IF(OR($E52="Sa",$E52="So"),N$4,N$5) -> 13 | O52: =IF(OR($E52="Sa",$E52="So"),O$4,O$5) -> 30 | P52: =IF(OR($E52="Sa",$E52="So"),P$4,P$5) -> 15 | Q52: =IF(OR($E52="Sa",$E52="So"),Q$4,Q$5) -> 55 | R52: =P52 -> 15 | S52: =Q52 -> 55 | T52: =R52 -> 15 | U52: =S52 -> 55 | V52: =TIME(J52,K52,0) -> 0.29166667 | W52: =TIME(L52,M52,0) -> 0.54166667 | X52: =TIME(N52,O52,0) -> 0.5625 | Y52: =TIME(P52,Q52,0) -> 0.66319444 | Z52: =TIME(R52,S52,0) -> 0.66319444 | AA52: =TIME(T52,U52,0) -> 0.66319444 | AC52: =IF(OR(E52="Sa",E52="So"),TIME($AC$4,$AE$4,0),TIME($AC$5,$AE$5,0)) -> 0.35069444 | AE52: =IF(OR(E52="Sa",E52="So"),TIME($AC$4,$AE$4,0),(Y52-V52-(X52-W52)+(AA52-Z52))) -> 0.35069444 | AJ52: =IF(AG52=$AG$3,1,0) -> 0 | AK52: =IF(AG52=$AG$7,1,0) -> 0 | AL52: =IF(AH52=$AG$4,1,0) -> 0 | AN52: =IF(OR(AG52=$AG$2,AG52=$AG$5),1,IF(AG52=$AG$6,0.5,0)) -> 0 | AO52: =IF(OR(E52="Sa",E52="So"),0,1) -> 1
D53: =IF(E53="Mo",WEEKNUM(I53),"") | E53: =TEXT(I53,"TTT") -> Sa | F53: =$F$5 -> 2035 | G53: =$A$44 -> 2 | H53: =H52+1 -> 10 | I53: =DATE(F53,G53,H53) -> 47888 | J53: =IF(OR($E53="Sa",$E53="So"),J$4,J$5) -> 0 | K53: =IF(OR($E53="Sa",$E53="So"),K$4,K$5) -> 0 | L53: =IF(OR($E53="Sa",$E53="So"),L$4,L$5) -> 0 | M53: =IF(OR($E53="Sa",$E53="So"),M$4,M$5) -> 0 | N53: =IF(OR($E53="Sa",$E53="So"),N$4,N$5) -> 0 | O53: =IF(OR($E53="Sa",$E53="So"),O$4,O$5) -> 0 | P53: =IF(OR($E53="Sa",$E53="So"),P$4,P$5) -> 0 | Q53: =IF(OR($E53="Sa",$E53="So"),Q$4,Q$5) -> 0 | R53: =P53 -> 0 | S53: =Q53 -> 0 | T53: =R53 -> 0 | U53: =S53 -> 0 | V53: =TIME(J53,K53,0) -> 0 | W53: =TIME(L53,M53,0) -> 0 | X53: =TIME(N53,O53,0) -> 0 | Y53: =TIME(P53,Q53,0) -> 0 | Z53: =TIME(R53,S53,0) -> 0 | AA53: =TIME(T53,U53,0) -> 0 | AC53: =IF(OR(E53="Sa",E53="So"),TIME($AC$4,$AE$4,0),TIME($AC$5,$AE$5,0)) -> 0 | AE53: =IF(OR(E53="Sa",E53="So"),TIME($AC$4,$AE$4,0),(Y53-V53-(X53-W53)+(AA53-Z53))) -> 0 | AJ53: =IF(AG53=$AG$3,1,0) -> 0 | AK53: =IF(AG53=$AG$7,1,0) -> 0 | AL53: =IF(AH53=$AG$4,1,0) -> 0 | AN53: =IF(OR(AG53=$AG$2,AG53=$AG$5),1,IF(AG53=$AG$6,0.5,0)) -> 0 | AO53: =IF(OR(E53="Sa",E53="So"),0,1) -> 0
D54: =IF(E54="Mo",WEEKNUM(I54),"") | E54: =TEXT(I54,"TTT") -> So | F54: =$F$5 -> 2035 | G54: =$A$44 -> 2 | H54: =H53+1 -> 11 | I54: =DATE(F54,G54,H54) -> 47889 | J54: =IF(OR($E54="Sa",$E54="So"),J$4,J$5) -> 0 | K54: =IF(OR($E54="Sa",$E54="So"),K$4,K$5) -> 0 | L54: =IF(OR($E54="Sa",$E54="So"),L$4,L$5) -> 0 | M54: =IF(OR($E54="Sa",$E54="So"),M$4,M$5) -> 0 | N54: =IF(OR($E54="Sa",$E54="So"),N$4,N$5) -> 0 | O54: =IF(OR($E54="Sa",$E54="So"),O$4,O$5) -> 0 | P54: =IF(OR($E54="Sa",$E54="So"),P$4,P$5) -> 0 | Q54: =IF(OR($E54="Sa",$E54="So"),Q$4,Q$5) -> 0 | R54: =P54 -> 0 | S54: =Q54 -> 0 | T54: =R54 -> 0 | U54: =S54 -> 0 | V54: =TIME(J54,K54,0) -> 0 | W54: =TIME(L54,M54,0) -> 0 | X54: =TIME(N54,O54,0) -> 0 | Y54: =TIME(P54,Q54,0) -> 0 | Z54: =TIME(R54,S54,0) -> 0 | AA54: =TIME(T54,U54,0) -> 0 | AC54: =IF(OR(E54="Sa",E54="So"),TIME($AC$4,$AE$4,0),TIME($AC$5,$AE$5,0)) -> 0 | AE54: =IF(OR(E54="Sa",E54="So"),TIME($AC$4,$AE$4,0),(Y54-V54-(X54-W54)+(AA54-Z54))) -> 0 | AJ54: =IF(AG54=$AG$3,1,0) -> 0 | AK54: =IF(AG54=$AG$7,1,0) -> 0 | AL54: =IF(AH54=$AG$4,1,0) -> 0 | AN54: =IF(OR(AG54=$AG$2,AG54=$AG$5),1,IF(AG54=$AG$6,0.5,0)) -> 0 | AO54: =IF(OR(E54="Sa",E54="So"),0,1) -> 0
D55: =IF(E55="Mo",WEEKNUM(I55),"") -> 7 | E55: =TEXT(I55,"TTT") -> Mo | F55: =$F$5 -> 2035 | G55: =$A$44 -> 2 | H55: =H54+1 -> 12 | I55: =DATE(F55,G55,H55) -> 47890 | J55: =IF(OR($E55="Sa",$E55="So"),J$4,J$5) -> 7 | K55: =IF(OR($E55="Sa",$E55="So"),K$4,K$5) -> 0 | L55: =IF(OR($E55="Sa",$E55="So"),L$4,L$5) -> 13 | M55: =IF(OR($E55="Sa",$E55="So"),M$4,M$5) -> 0 | N55: =IF(OR($E55="Sa",$E55="So"),N$4,N$5) -> 13 | O55: =IF(OR($E55="Sa",$E55="So"),O$4,O$5) -> 30 | P55: =IF(OR($E55="Sa",$E55="So"),P$4,P$5) -> 15 | Q55: =IF(OR($E55="Sa",$E55="So"),Q$4,Q$5) -> 55 | R55: =P55 -> 15 | S55: =Q55 -> 55 | T55: =R55 -> 15 | U55: =S55 -> 55 | V55: =TIME(J55,K55,0) -> 0.29166667 | W55: =TIME(L55,M55,0) -> 0.54166667 | X55: =TIME(N55,O55,0) -> 0.5625 | Y55: =TIME(P55,Q55,0) -> 0.66319444 | Z55: =TIME(R55,S55,0) -> 0.66319444 | AA55: =TIME(T55,U55,0) -> 0.66319444 | AC55: =IF(OR(E55="Sa",E55="So"),TIME($AC$4,$AE$4,0),TIME($AC$5,$AE$5,0)) -> 0.35069444 | AE55: =IF(OR(E55="Sa",E55="So"),TIME($AC$4,$AE$4,0),(Y55-V55-(X55-W55)+(AA55-Z55))) -> 0.35069444 | AJ55: =IF(AG55=$AG$3,1,0) -> 0 | AK55: =IF(AG55=$AG$7,1,0) -> 0 | AL55: =IF(AH55=$AG$4,1,0) -> 0 | AN55: =IF(OR(AG55=$AG$2,AG55=$AG$5),1,IF(AG55=$AG$6,0.5,0)) -> 0 | AO55: =IF(OR(E55="Sa",E55="So"),0,1) -> 1
D56: =IF(E56="Mo",WEEKNUM(I56),"") | E56: =TEXT(I56,"TTT") -> Di | F56: =$F$5 -> 2035 | G56: =$A$44 -> 2 | H56: =H55+1 -> 13 | I56: =DATE(F56,G56,H56) -> 47891 | J56: =IF(OR($E56="Sa",$E56="So"),J$4,J$5) -> 7 | K56: =IF(OR($E56="Sa",$E56="So"),K$4,K$5) -> 0 | L56: =IF(OR($E56="Sa",$E56="So"),L$4,L$5) -> 13 | M56: =IF(OR($E56="Sa",$E56="So"),M$4,M$5) -> 0 | N56: =IF(OR($E56="Sa",$E56="So"),N$4,N$5) -> 13 | O56: =IF(OR($E56="Sa",$E56="So"),O$4,O$5) -> 30 | P56: =IF(OR($E56="Sa",$E56="So"),P$4,P$5) -> 15 | Q56: =IF(OR($E56="Sa",$E56="So"),Q$4,Q$5) -> 55 | R56: =P56 -> 15 | S56: =Q56 -> 55 | T56: =R56 -> 15 | U56: =S56 -> 55 | V56: =TIME(J56,K56,0) -> 0.29166667 | W56: =TIME(L56,M56,0) -> 0.54166667 | X56: =TIME(N56,O56,0) -> 0.5625 | Y56: =TIME(P56,Q56,0) -> 0.66319444 | Z56: =TIME(R56,S56,0) -> 0.66319444 | AA56: =TIME(T56,U56,0) -> 0.66319444 | AC56: =IF(OR(E56="Sa",E56="So"),TIME($AC$4,$AE$4,0),TIME($AC$5,$AE$5,0)) -> 0.35069444 | AE56: =IF(OR(E56="Sa",E56="So"),TIME($AC$4,$AE$4,0),(Y56-V56-(X56-W56)+(AA56-Z56))) -> 0.35069444 | AJ56: =IF(AG56=$AG$3,1,0) -> 0 | AK56: =IF(AG56=$AG$7,1,0) -> 0 | AL56: =IF(AH56=$AG$4,1,0) -> 0 | AN56: =IF(OR(AG56=$AG$2,AG56=$AG$5),1,IF(AG56=$AG$6,0.5,0)) -> 0 | AO56: =IF(OR(E56="Sa",E56="So"),0,1) -> 1
... D74: =IF(E74="Mo",WEEKNUM(I74),"") | E74: =TEXT(I74,"TTT") -> Sa | F74: =$F$5 -> 2035 | G74: =$A$44 -> 2 | H74: =H73+1 -> 31 | I74: =DATE(F74,G74,H74) -> 47909 | J74: =IF(OR($E74="Sa",$E74="So"),J$4,J$5) -> 0 | K74: =IF(OR($E74="Sa",$E74="So"),K$4,K$5) -> 0 | L74: =IF(OR($E74="Sa",$E74="So"),L$4,L$5) -> 0 | M74: =IF(OR($E74="Sa",$E74="So"),M$4,M$5) -> 0 | N74: =IF(OR($E74="Sa",$E74="So"),N$4,N$5) -> 0 | O74: =IF(OR($E74="Sa",$E74="So"),O$4,O$5) -> 0 | P74: =IF(OR($E74="Sa",$E74="So"),P$4,P$5) -> 0 | Q74: =IF(OR($E74="Sa",$E74="So"),Q$4,Q$5) -> 0 | R74: =P74 -> 0 | S74: =Q74 -> 0 | T74: =R74 -> 0 | U74: =S74 -> 0 | V74: =TIME(J74,K74,0) -> 0 | W74: =TIME(L74,M74,0) -> 0 | X74: =TIME(N74,O74,0) -> 0 | Y74: =TIME(P74,Q74,0) -> 0 | Z74: =TIME(R74,S74,0) -> 0 | AA74: =TIME(T74,U74,0) -> 0 | AC74: =IF(OR(E74="Sa",E74="So"),TIME($AC$4,$AE$4,0),TIME($AC$5,$AE$5,0)) -> 0 | AE74: =IF(OR(E74="Sa",E74="So"),TIME($AC$4,$AE$4,0),(Y74-V74-(X74-W74)+(AA74-Z74))) -> 0 | AJ74: =IF(AG74=$AG$3,1,0) -> 0 | AK74: =IF(AG74=$AG$7,1,0) -> 0 | AL74: =IF(AH74=$AG$4,1,0) -> 0 | AN74: =IF(OR(AG74=$AG$2,AG74=$AG$5),1,IF(AG74=$AG$6,0.5,0)) -> 0 | AO74: =IF(OR(E74="Sa",E74="So"),0,1) -> 0
D75: EM | P75: Summ | AC75: =SUM(AC44:AC74) -> 7.7152778 | AE75: =SUM(AE44:AE74) -> 7.7152778 | AI75: =IF(AE75-AC75<0,AC75-AE75,AE75-AC75) -> 2.6645353e-15 | AJ75: =8.425*SUM(AJ44:AJ74)/24 -> 0 | AK75: =8.425*SUM(AK44:AK74)/24 -> 0 | AL75: =8.425*SUM(AL44:AL74)/24 -> 0 | AN75: =SUM(AN44:AN74) -> 0 | AO75: =SUM(AO44:AO74) -> 22
AI76: =AI42+AI75 -> 6.2172489e-15 | AJ76: =AJ42+SUM(AJ43:AJ74) -> 0 | AK76: =AK42+SUM(AK43:AK74) -> 0 | AL76: =AL42+SUM(AL43:AL74) -> 0 | AN76: =AN75*8 -> 0 | AO76: =AO75*8 -> 176
B77: =$F$5 -> 2035 | C77: =TEXT(I78,"MMM") -> Mär
A78: =A44+1 -> 3 | D78: =IF(E78="Mo",WEEKNUM(I78),"") | E78: =TEXT(I78,"TTT") -> Do | F78: =$F$5 -> 2035 | G78: =$A$78 -> 3 | H78: =$H$5 -> 1 | I78: =DATE(F78,G78,H78) -> 47907 | J78: =IF(OR($E78="Sa",$E78="So"),J$4,J$5) -> 7 | K78: =IF(OR($E78="Sa",$E78="So"),K$4,K$5) -> 0 | L78: =IF(OR($E78="Sa",$E78="So"),L$4,L$5) -> 13 | M78: =IF(OR($E78="Sa",$E78="So"),M$4,M$5) -> 0 | N78: =IF(OR($E78="Sa",$E78="So"),N$4,N$5) -> 13 | O78: =IF(OR($E78="Sa",$E78="So"),O$4,O$5) -> 30 | P78: =IF(OR($E78="Sa",$E78="So"),P$4,P$5) -> 15 | Q78: =IF(OR($E78="Sa",$E78="So"),Q$4,Q$5) -> 55 | R78: =P78 -> 15 | S78: =Q78 -> 55 | T78: =R78 -> 15 | U78: =S78 -> 55 | V78: =TIME(J78,K78,0) -> 0.29166667 | W78: =TIME(L78,M78,0) -> 0.54166667 | X78: =TIME(N78,O78,0) -> 0.5625 | Y78: =TIME(P78,Q78,0) -> 0.66319444 | Z78: =TIME(R78,S78,0) -> 0.66319444 | AA78: =TIME(T78,U78,0) -> 0.66319444 | AC78: =IF(OR(E78="Sa",E78="So"),TIME($AC$4,$AE$4,0),TIME($AC$5,$AE$5,0)) -> 0.35069444 | AE78: =IF(OR(E78="Sa",E78="So"),TIME($AC$4,$AE$4,0),(Y78-V78-(X78-W78)+(AA78-Z78))) -> 0.35069444 | AJ78: =IF(AG78=$AG$3,1,0) -> 0 | AK78: =IF(AG78=$AG$7,1,0) -> 0 | AL78: =IF(AH78=$AG$4,1,0) -> 0 | AN78: =IF(OR(AG78=$AG$2,AG78=$AG$5),1,IF(AG78=$AG$6,0.5,0)) -> 0 | AO78: =IF(OR(E78="Sa",E78="So"),0,1) -> 1
D79: =IF(E79="Mo",WEEKNUM(I79),"") | E79: =TEXT(I79,"TTT") -> Fr | F79: =$F$5 -> 2035 | G79: =$A$78 -> 3 | H79: =H78+1 -> 2 | I79: =DATE(F79,G79,H79) -> 47908 | J79: =IF(OR($E79="Sa",$E79="So"),J$4,J$5) -> 7 | K79: =IF(OR($E79="Sa",$E79="So"),K$4,K$5) -> 0 | L79: =IF(OR($E79="Sa",$E79="So"),L$4,L$5) -> 13 | M79: =IF(OR($E79="Sa",$E79="So"),M$4,M$5) -> 0 | N79: =IF(OR($E79="Sa",$E79="So"),N$4,N$5) -> 13 | O79: =IF(OR($E79="Sa",$E79="So"),O$4,O$5) -> 30 | P79: =IF(OR($E79="Sa",$E79="So"),P$4,P$5) -> 15 | Q79: =IF(OR($E79="Sa",$E79="So"),Q$4,Q$5) -> 55 | R79: =P79 -> 15 | S79: =Q79 -> 55 | T79: =R79 -> 15 | U79: =S79 -> 55 | V79: =TIME(J79,K79,0) -> 0.29166667 | W79: =TIME(L79,M79,0) -> 0.54166667 | X79: =TIME(N79,O79,0) -> 0.5625 | Y79: =TIME(P79,Q79,0) -> 0.66319444 | Z79: =TIME(R79,S79,0) -> 0.66319444 | AA79: =TIME(T79,U79,0) -> 0.66319444 | AC79: =IF(OR(E79="Sa",E79="So"),TIME($AC$4,$AE$4,0),TIME($AC$5,$AE$5,0)) -> 0.35069444 | AE79: =IF(OR(E79="Sa",E79="So"),TIME($AC$4,$AE$4,0),(Y79-V79-(X79-W79)+(AA79-Z79))) -> 0.35069444 | AJ79: =IF(AG79=$AG$3,1,0) -> 0 | AK79: =IF(AG79=$AG$7,1,0) -> 0 | AL79: =IF(AH79=$AG$4,1,0) -> 0 | AN79: =IF(OR(AG79=$AG$2,AG79=$AG$5),1,IF(AG79=$AG$6,0.5,0)) -> 0 | AO79: =IF(OR(E79="Sa",E79="So"),0,1) -> 1
D80: =IF(E80="Mo",WEEKNUM(I80),"") | E80: =TEXT(I80,"TTT") -> Sa | F80: =$F$5 -> 2035 | G80: =$A$78 -> 3 | H80: =H79+1 -> 3 | I80: =DATE(F80,G80,H80) -> 47909 | J80: =IF(OR($E80="Sa",$E80="So"),J$4,J$5) -> 0 | K80: =IF(OR($E80="Sa",$E80="So"),K$4,K$5) -> 0 | L80: =IF(OR($E80="Sa",$E80="So"),L$4,L$5) -> 0 | M80: =IF(OR($E80="Sa",$E80="So"),M$4,M$5) -> 0 | N80: =IF(OR($E80="Sa",$E80="So"),N$4,N$5) -> 0 | O80: =IF(OR($E80="Sa",$E80="So"),O$4,O$5) -> 0 | P80: =IF(OR($E80="Sa",$E80="So"),P$4,P$5) -> 0 | Q80: =IF(OR($E80="Sa",$E80="So"),Q$4,Q$5) -> 0 | R80: =P80 -> 0 | S80: =Q80 -> 0 | T80: =R80 -> 0 | U80: =S80 -> 0 | V80: =TIME(J80,K80,0) -> 0 | W80: =TIME(L80,M80,0) -> 0 | X80: =TIME(N80,O80,0) -> 0 | Y80: =TIME(P80,Q80,0) -> 0 | Z80: =TIME(R80,S80,0) -> 0 | AA80: =TIME(T80,U80,0) -> 0 | AC80: =IF(OR(E80="Sa",E80="So"),TIME($AC$4,$AE$4,0),TIME($AC$5,$AE$5,0)) -> 0 | AE80: =IF(OR(E80="Sa",E80="So"),TIME($AC$4,$AE$4,0),(Y80-V80-(X80-W80)+(AA80-Z80))) -> 0 | AJ80: =IF(AG80=$AG$3,1,0) -> 0 | AK80: =IF(AG80=$AG$7,1,0) -> 0 | AL80: =IF(AH80=$AG$4,1,0) -> 0 | AN80: =IF(OR(AG80=$AG$2,AG80=$AG$5),1,IF(AG80=$AG$6,0.5,0)) -> 0 | AO80: =IF(OR(E80="Sa",E80="So"),0,1) -> 0
D81: =IF(E81="Mo",WEEKNUM(I81),"") | E81: =TEXT(I81,"TTT") -> So | F81: =$F$5 -> 2035 | G81: =$A$78 -> 3 | H81: =H80+1 -> 4 | I81: =DATE(F81,G81,H81) -> 47910 | J81: =IF(OR($E81="Sa",$E81="So"),J$4,J$5) -> 0 | K81: =IF(OR($E81="Sa",$E81="So"),K$4,K$5) -> 0 | L81: =IF(OR($E81="Sa",$E81="So"),L$4,L$5) -> 0 | M81: =IF(OR($E81="Sa",$E81="So"),M$4,M$5) -> 0 | N81: =IF(OR($E81="Sa",$E81="So"),N$4,N$5) -> 0 | O81: =IF(OR($E81="Sa",$E81="So"),O$4,O$5) -> 0 | P81: =IF(OR($E81="Sa",$E81="So"),P$4,P$5) -> 0 | Q81: =IF(OR($E81="Sa",$E81="So"),Q$4,Q$5) -> 0 | R81: =P81 -> 0 | S81: =Q81 -> 0 | T81: =R81 -> 0 | U81: =S81 -> 0 | V81: =TIME(J81,K81,0) -> 0 | W81: =TIME(L81,M81,0) -> 0 | X81: =TIME(N81,O81,0) -> 0 | Y81: =TIME(P81,Q81,0) -> 0 | Z81: =TIME(R81,S81,0) -> 0 | AA81: =TIME(T81,U81,0) -> 0 | AC81: =IF(OR(E81="Sa",E81="So"),TIME($AC$4,$AE$4,0),TIME($AC$5,$AE$5,0)) -> 0 | AE81: =IF(OR(E81="Sa",E81="So"),TIME($AC$4,$AE$4,0),(Y81-V81-(X81-W81)+(AA81-Z81))) -> 0 | AJ81: =IF(AG81=$AG$3,1,0) -> 0 | AK81: =IF(AG81=$AG$7,1,0) -> 0 | AL81: =IF(AH81=$AG$4,1,0) -> 0 | AN81: =IF(OR(AG81=$AG$2,AG81=$AG$5),1,IF(AG81=$AG$6,0.5,0)) -> 0 | AO81: =IF(OR(E81="Sa",E81="So"),0,1) -> 0
D82: =IF(E82="Mo",WEEKNUM(I82),"") -> 10 | E82: =TEXT(I82,"TTT") -> Mo | F82: =$F$5 -> 2035 | G82: =$A$78 -> 3 | H82: =H81+1 -> 5 | I82: =DATE(F82,G82,H82) -> 47911 | J82: =IF(OR($E82="Sa",$E82="So"),J$4,J$5) -> 7 | K82: =IF(OR($E82="Sa",$E82="So"),K$4,K$5) -> 0 | L82: =IF(OR($E82="Sa",$E82="So"),L$4,L$5) -> 13 | M82: =IF(OR($E82="Sa",$E82="So"),M$4,M$5) -> 0 | N82: =IF(OR($E82="Sa",$E82="So"),N$4,N$5) -> 13 | O82: =IF(OR($E82="Sa",$E82="So"),O$4,O$5) -> 30 | P82: =IF(OR($E82="Sa",$E82="So"),P$4,P$5) -> 15 | Q82: =IF(OR($E82="Sa",$E82="So"),Q$4,Q$5) -> 55 | R82: =P82 -> 15 | S82: =Q82 -> 55 | T82: =R82 -> 15 | U82: =S82 -> 55 | V82: =TIME(J82,K82,0) -> 0.29166667 | W82: =TIME(L82,M82,0) -> 0.54166667 | X82: =TIME(N82,O82,0) -> 0.5625 | Y82: =TIME(P82,Q82,0) -> 0.66319444 | Z82: =TIME(R82,S82,0) -> 0.66319444 | AA82: =TIME(T82,U82,0) -> 0.66319444 | AC82: =IF(OR(E82="Sa",E82="So"),TIME($AC$4,$AE$4,0),TIME($AC$5,$AE$5,0)) -> 0.35069444 | AE82: =IF(OR(E82="Sa",E82="So"),TIME($AC$4,$AE$4,0),(Y82-V82-(X82-W82)+(AA82-Z82))) -> 0.35069444 | AJ82: =IF(AG82=$AG$3,1,0) -> 0 | AK82: =IF(AG82=$AG$7,1,0) -> 0 | AL82: =IF(AH82=$AG$4,1,0) -> 0 | AN82: =IF(OR(AG82=$AG$2,AG82=$AG$5),1,IF(AG82=$AG$6,0.5,0)) -> 0 | AO82: =IF(OR(E82="Sa",E82="So"),0,1) -> 1
D83: =IF(E83="Mo",WEEKNUM(I83),"") | E83: =TEXT(I83,"TTT") -> Di | F83: =$F$5 -> 2035 | G83: =$A$78 -> 3 | H83: =H82+1 -> 6 | I83: =DATE(F83,G83,H83) -> 47912 | J83: =IF(OR($E83="Sa",$E83="So"),J$4,J$5) -> 7 | K83: =IF(OR($E83="Sa",$E83="So"),K$4,K$5) -> 0 | L83: =IF(OR($E83="Sa",$E83="So"),L$4,L$5) -> 13 | M83: =IF(OR($E83="Sa",$E83="So"),M$4,M$5) -> 0 | N83: =IF(OR($E83="Sa",$E83="So"),N$4,N$5) -> 13 | O83: =IF(OR($E83="Sa",$E83="So"),O$4,O$5) -> 30 | P83: =IF(OR($E83="Sa",$E83="So"),P$4,P$5) -> 15 | Q83: =IF(OR($E83="Sa",$E83="So"),Q$4,Q$5) -> 55 | R83: =P83 -> 15 | S83: =Q83 -> 55 | T83: =R83 -> 15 | U83: =S83 -> 55 | V83: =TIME(J83,K83,0) -> 0.29166667 | W83: =TIME(L83,M83,0) -> 0.54166667 | X83: =TIME(N83,O83,0) -> 0.5625 | Y83: =TIME(P83,Q83,0) -> 0.66319444 | Z83: =TIME(R83,S83,0) -> 0.66319444 | AA83: =TIME(T83,U83,0) -> 0.66319444 | AC83: =IF(OR(E83="Sa",E83="So"),TIME($AC$4,$AE$4,0),TIME($AC$5,$AE$5,0)) -> 0.35069444 | AE83: =IF(OR(E83="Sa",E83="So"),TIME($AC$4,$AE$4,0),(Y83-V83-(X83-W83)+(AA83-Z83))) -> 0.35069444 | AJ83: =IF(AG83=$AG$3,1,0) -> 0 | AK83: =IF(AG83=$AG$7,1,0) -> 0 | AL83: =IF(AH83=$AG$4,1,0) -> 0 | AN83: =IF(OR(AG83=$AG$2,AG83=$AG$5),1,IF(AG83=$AG$6,0.5,0)) -> 0 | AO83: =IF(OR(E83="Sa",E83="So"),0,1) -> 1
D84: =IF(E84="Mo",WEEKNUM(I84),"") | E84: =TEXT(I84,"TTT") -> Mi | F84: =$F$5 -> 2035 | G84: =$A$78 -> 3 | H84: =H83+1 -> 7 | I84: =DATE(F84,G84,H84) -> 47913 | J84: =IF(OR($E84="Sa",$E84="So"),J$4,J$5) -> 7 | K84: =IF(OR($E84="Sa",$E84="So"),K$4,K$5) -> 0 | L84: =IF(OR($E84="Sa",$E84="So"),L$4,L$5) -> 13 | M84: =IF(OR($E84="Sa",$E84="So"),M$4,M$5) -> 0 | N84: =IF(OR($E84="Sa",$E84="So"),N$4,N$5) -> 13 | O84: =IF(OR($E84="Sa",$E84="So"),O$4,O$5) -> 30 | P84: =IF(OR($E84="Sa",$E84="So"),P$4,P$5) -> 15 | Q84: =IF(OR($E84="Sa",$E84="So"),Q$4,Q$5) -> 55 | R84: =P84 -> 15 | S84: =Q84 -> 55 | T84: =R84 -> 15 | U84: =S84 -> 55 | V84: =TIME(J84,K84,0) -> 0.29166667 | W84: =TIME(L84,M84,0) -> 0.54166667 | X84: =TIME(N84,O84,0) -> 0.5625 | Y84: =TIME(P84,Q84,0) -> 0.66319444 | Z84: =TIME(R84,S84,0) -> 0.66319444 | AA84: =TIME(T84,U84,0) -> 0.66319444 | AC84: =IF(OR(E84="Sa",E84="So"),TIME($AC$4,$AE$4,0),TIME($AC$5,$AE$5,0)) -> 0.35069444 | AE84: =IF(OR(E84="Sa",E84="So"),TIME($AC$4,$AE$4,0),(Y84-V84-(X84-W84)+(AA84-Z84))) -> 0.35069444 | AJ84: =IF(AG84=$AG$3,1,0) -> 0 | AK84: =IF(AG84=$AG$7,1,0) -> 0 | AL84: =IF(AH84=$AG$4,1,0) -> 0 | AN84: =IF(OR(AG84=$AG$2,AG84=$AG$5),1,IF(AG84=$AG$6,0.5,0)) -> 0 | AO84: =IF(OR(E84="Sa",E84="So"),0,1) -> 1
D85: =IF(E85="Mo",WEEKNUM(I85),"") | E85: =TEXT(I85,"TTT") -> Do | F85: =$F$5 -> 2035 | G85: =$A$78 -> 3 | H85: =H84+1 -> 8 | I85: =DATE(F85,G85,H85) -> 47914 | J85: =IF(OR($E85="Sa",$E85="So"),J$4,J$5) -> 7 | K85: =IF(OR($E85="Sa",$E85="So"),K$4,K$5) -> 0 | L85: =IF(OR($E85="Sa",$E85="So"),L$4,L$5) -> 13 | M85: =IF(OR($E85="Sa",$E85="So"),M$4,M$5) -> 0 | N85: =IF(OR($E85="Sa",$E85="So"),N$4,N$5) -> 13 | O85: =IF(OR($E85="Sa",$E85="So"),O$4,O$5) -> 30 | P85: =IF(OR($E85="Sa",$E85="So"),P$4,P$5) -> 15 | Q85: =IF(OR($E85="Sa",$E85="So"),Q$4,Q$5) -> 55 | R85: =P85 -> 15 | S85: =Q85 -> 55 | T85: =R85 -> 15 | U85: =S85 -> 55 | V85: =TIME(J85,K85,0) -> 0.29166667 | W85: =TIME(L85,M85,0) -> 0.54166667 | X85: =TIME(N85,O85,0) -> 0.5625 | Y85: =TIME(P85,Q85,0) -> 0.66319444 | Z85: =TIME(R85,S85,0) -> 0.66319444 | AA85: =TIME(T85,U85,0) -> 0.66319444 | AC85: =IF(OR(E85="Sa",E85="So"),TIME($AC$4,$AE$4,0),TIME($AC$5,$AE$5,0)) -> 0.35069444 | AE85: =IF(OR(E85="Sa",E85="So"),TIME($AC$4,$AE$4,0),(Y85-V85-(X85-W85)+(AA85-Z85))) -> 0.35069444 | AJ85: =IF(AG85=$AG$3,1,0) -> 0 | AK85: =IF(AG85=$AG$7,1,0) -> 0 | AL85: =IF(AH85=$AG$4,1,0) -> 0 | AN85: =IF(OR(AG85=$AG$2,AG85=$AG$5),1,IF(AG85=$AG$6,0.5,0)) -> 0 | AO85: =IF(OR(E85="Sa",E85="So"),0,1) -> 1
D86: =IF(E86="Mo",WEEKNUM(I86),"") | E86: =TEXT(I86,"TTT") -> Fr | F86: =$F$5 -> 2035 | G86: =$A$78 -> 3 | H86: =H85+1 -> 9 | I86: =DATE(F86,G86,H86) -> 47915 | J86: =IF(OR($E86="Sa",$E86="So"),J$4,J$5) -> 7 | K86: =IF(OR($E86="Sa",$E86="So"),K$4,K$5) -> 0 | L86: =IF(OR($E86="Sa",$E86="So"),L$4,L$5) -> 13 | M86: =IF(OR($E86="Sa",$E86="So"),M$4,M$5) -> 0 | N86: =IF(OR($E86="Sa",$E86="So"),N$4,N$5) -> 13 | O86: =IF(OR($E86="Sa",$E86="So"),O$4,O$5) -> 30 | P86: =IF(OR($E86="Sa",$E86="So"),P$4,P$5) -> 15 | Q86: =IF(OR($E86="Sa",$E86="So"),Q$4,Q$5) -> 55 | R86: =P86 -> 15 | S86: =Q86 -> 55 | T86: =R86 -> 15 | U86: =S86 -> 55 | V86: =TIME(J86,K86,0) -> 0.29166667 | W86: =TIME(L86,M86,0) -> 0.54166667 | X86: =TIME(N86,O86,0) -> 0.5625 | Y86: =TIME(P86,Q86,0) -> 0.66319444 | Z86: =TIME(R86,S86,0) -> 0.66319444 | AA86: =TIME(T86,U86,0) -> 0.66319444 | AC86: =IF(OR(E86="Sa",E86="So"),TIME($AC$4,$AE$4,0),TIME($AC$5,$AE$5,0)) -> 0.35069444 | AE86: =IF(OR(E86="Sa",E86="So"),TIME($AC$4,$AE$4,0),(Y86-V86-(X86-W86)+(AA86-Z86))) -> 0.35069444 | AJ86: =IF(AG86=$AG$3,1,0) -> 0 | AK86: =IF(AG86=$AG$7,1,0) -> 0 | AL86: =IF(AH86=$AG$4,1,0) -> 0 | AN86: =IF(OR(AG86=$AG$2,AG86=$AG$5),1,IF(AG86=$AG$6,0.5,0)) -> 0 | AO86: =IF(OR(E86="Sa",E86="So"),0,1) -> 1
D87: =IF(E87="Mo",WEEKNUM(I87),"") | E87: =TEXT(I87,"TTT") -> Sa | F87: =$F$5 -> 2035 | G87: =$A$78 -> 3 | H87: =H86+1 -> 10 | I87: =DATE(F87,G87,H87) -> 47916 | J87: =IF(OR($E87="Sa",$E87="So"),J$4,J$5) -> 0 | K87: =IF(OR($E87="Sa",$E87="So"),K$4,K$5) -> 0 | L87: =IF(OR($E87="Sa",$E87="So"),L$4,L$5) -> 0 | M87: =IF(OR($E87="Sa",$E87="So"),M$4,M$5) -> 0 | N87: =IF(OR($E87="Sa",$E87="So"),N$4,N$5) -> 0 | O87: =IF(OR($E87="Sa",$E87="So"),O$4,O$5) -> 0 | P87: =IF(OR($E87="Sa",$E87="So"),P$4,P$5) -> 0 | Q87: =IF(OR($E87="Sa",$E87="So"),Q$4,Q$5) -> 0 | R87: =P87 -> 0 | S87: =Q87 -> 0 | T87: =R87 -> 0 | U87: =S87 -> 0 | V87: =TIME(J87,K87,0) -> 0 | W87: =TIME(L87,M87,0) -> 0 | X87: =TIME(N87,O87,0) -> 0 | Y87: =TIME(P87,Q87,0) -> 0 | Z87: =TIME(R87,S87,0) -> 0 | AA87: =TIME(T87,U87,0) -> 0 | AC87: =IF(OR(E87="Sa",E87="So"),TIME($AC$4,$AE$4,0),TIME($AC$5,$AE$5,0)) -> 0 | AE87: =IF(OR(E87="Sa",E87="So"),TIME($AC$4,$AE$4,0),(Y87-V87-(X87-W87)+(AA87-Z87))) -> 0 | AJ87: =IF(AG87=$AG$3,1,0) -> 0 | AK87: =IF(AG87=$AG$7,1,0) -> 0 | AL87: =IF(AH87=$AG$4,1,0) -> 0 | AN87: =IF(OR(AG87=$AG$2,AG87=$AG$5),1,IF(AG87=$AG$6,0.5,0)) -> 0 | AO87: =IF(OR(E87="Sa",E87="So"),0,1) -> 0
D88: =IF(E88="Mo",WEEKNUM(I88),"") | E88: =TEXT(I88,"TTT") -> So | F88: =$F$5 -> 2035 | G88: =$A$78 -> 3 | H88: =H87+1 -> 11 | I88: =DATE(F88,G88,H88) -> 47917 | J88: =IF(OR($E88="Sa",$E88="So"),J$4,J$5) -> 0 | K88: =IF(OR($E88="Sa",$E88="So"),K$4,K$5) -> 0 | L88: =IF(OR($E88="Sa",$E88="So"),L$4,L$5) -> 0 | M88: =IF(OR($E88="Sa",$E88="So"),M$4,M$5) -> 0 | N88: =IF(OR($E88="Sa",$E88="So"),N$4,N$5) -> 0 | O88: =IF(OR($E88="Sa",$E88="So"),O$4,O$5) -> 0 | P88: =IF(OR($E88="Sa",$E88="So"),P$4,P$5) -> 0 | Q88: =IF(OR($E88="Sa",$E88="So"),Q$4,Q$5) -> 0 | R88: =P88 -> 0 | S88: =Q88 -> 0 | T88: =R88 -> 0 | U88: =S88 -> 0 | V88: =TIME(J88,K88,0) -> 0 | W88: =TIME(L88,M88,0) -> 0 | X88: =TIME(N88,O88,0) -> 0 | Y88: =TIME(P88,Q88,0) -> 0 | Z88: =TIME(R88,S88,0) -> 0 | AA88: =TIME(T88,U88,0) -> 0 | AC88: =IF(OR(E88="Sa",E88="So"),TIME($AC$4,$AE$4,0),TIME($AC$5,$AE$5,0)) -> 0 | AE88: =IF(OR(E88="Sa",E88="So"),TIME($AC$4,$AE$4,0),(Y88-V88-(X88-W88)+(AA88-Z88))) -> 0 | AJ88: =IF(AG88=$AG$3,1,0) -> 0 | AK88: =IF(AG88=$AG$7,1,0) -> 0 | AL88: =IF(AH88=$AG$4,1,0) -> 0 | AN88: =IF(OR(AG88=$AG$2,AG88=$AG$5),1,IF(AG88=$AG$6,0.5,0)) -> 0 | AO88: =IF(OR(E88="Sa",E88="So"),0,1) -> 0
D89: =IF(E89="Mo",WEEKNUM(I89),"") -> 11 | E89: =TEXT(I89,"TTT") -> Mo | F89: =$F$5 -> 2035 | G89: =$A$78 -> 3 | H89: =H88+1 -> 12 | I89: =DATE(F89,G89,H89) -> 47918 | J89: =IF(OR($E89="Sa",$E89="So"),J$4,J$5) -> 7 | K89: =IF(OR($E89="Sa",$E89="So"),K$4,K$5) -> 0 | L89: =IF(OR($E89="Sa",$E89="So"),L$4,L$5) -> 13 | M89: =IF(OR($E89="Sa",$E89="So"),M$4,M$5) -> 0 | N89: =IF(OR($E89="Sa",$E89="So"),N$4,N$5) -> 13 | O89: =IF(OR($E89="Sa",$E89="So"),O$4,O$5) -> 30 | P89: =IF(OR($E89="Sa",$E89="So"),P$4,P$5) -> 15 | Q89: =IF(OR($E89="Sa",$E89="So"),Q$4,Q$5) -> 55 | R89: =P89 -> 15 | S89: =Q89 -> 55 | T89: =R89 -> 15 | U89: =S89 -> 55 | V89: =TIME(J89,K89,0) -> 0.29166667 | W89: =TIME(L89,M89,0) -> 0.54166667 | X89: =TIME(N89,O89,0) -> 0.5625 | Y89: =TIME(P89,Q89,0) -> 0.66319444 | Z89: =TIME(R89,S89,0) -> 0.66319444 | AA89: =TIME(T89,U89,0) -> 0.66319444 | AC89: =IF(OR(E89="Sa",E89="So"),TIME($AC$4,$AE$4,0),TIME($AC$5,$AE$5,0)) -> 0.35069444 | AE89: =IF(OR(E89="Sa",E89="So"),TIME($AC$4,$AE$4,0),(Y89-V89-(X89-W89)+(AA89-Z89))) -> 0.35069444 | AJ89: =IF(AG89=$AG$3,1,0) -> 0 | AK89: =IF(AG89=$AG$7,1,0) -> 0 | AL89: =IF(AH89=$AG$4,1,0) -> 0 | AN89: =IF(OR(AG89=$AG$2,AG89=$AG$5),1,IF(AG89=$AG$6,0.5,0)) -> 0 | AO89: =IF(OR(E89="Sa",E89="So"),0,1) -> 1
D90: =IF(E90="Mo",WEEKNUM(I90),"") | E90: =TEXT(I90,"TTT") -> Di | F90: =$F$5 -> 2035 | G90: =$A$78 -> 3 | H90: =H89+1 -> 13 | I90: =DATE(F90,G90,H90) -> 47919 | J90: =IF(OR($E90="Sa",$E90="So"),J$4,J$5) -> 7 | K90: =IF(OR($E90="Sa",$E90="So"),K$4,K$5) -> 0 | L90: =IF(OR($E90="Sa",$E90="So"),L$4,L$5) -> 13 | M90: =IF(OR($E90="Sa",$E90="So"),M$4,M$5) -> 0 | N90: =IF(OR($E90="Sa",$E90="So"),N$4,N$5) -> 13 | O90: =IF(OR($E90="Sa",$E90="So"),O$4,O$5) -> 30 | P90: =IF(OR($E90="Sa",$E90="So"),P$4,P$5) -> 15 | Q90: =IF(OR($E90="Sa",$E90="So"),Q$4,Q$5) -> 55 | R90: =P90 -> 15 | S90: =Q90 -> 55 | T90: =R90 -> 15 | U90: =S90 -> 55 | V90: =TIME(J90,K90,0) -> 0.29166667 | W90: =TIME(L90,M90,0) -> 0.54166667 | X90: =TIME(N90,O90,0) -> 0.5625 | Y90: =TIME(P90,Q90,0) -> 0.66319444 | Z90: =TIME(R90,S90,0) -> 0.66319444 | AA90: =TIME(T90,U90,0) -> 0.66319444 | AC90: =IF(OR(E90="Sa",E90="So"),TIME($AC$4,$AE$4,0),TIME($AC$5,$AE$5,0)) -> 0.35069444 | AE90: =IF(OR(E90="Sa",E90="So"),TIME($AC$4,$AE$4,0),(Y90-V90-(X90-W90)+(AA90-Z90))) -> 0.35069444 | AJ90: =IF(AG90=$AG$3,1,0) -> 0 | AK90: =IF(AG90=$AG$7,1,0) -> 0 | AL90: =IF(AH90=$AG$4,1,0) -> 0 | AN90: =IF(OR(AG90=$AG$2,AG90=$AG$5),1,IF(AG90=$AG$6,0.5,0)) -> 0 | AO90: =IF(OR(E90="Sa",E90="So"),0,1) -> 1
... D108: =IF(E108="Mo",WEEKNUM(I108),"") | E108: =TEXT(I108,"TTT") -> Sa | F108: =$F$5 -> 2035 | G108: =$A$78 -> 3 | H108: =H107+1 -> 31 | I108: =DATE(F108,G108,H108) -> 47937 | J108: =IF(OR($E108="Sa",$E108="So"),J$4,J$5) -> 0 | K108: =IF(OR($E108="Sa",$E108="So"),K$4,K$5) -> 0 | L108: =IF(OR($E108="Sa",$E108="So"),L$4,L$5) -> 0 | M108: =IF(OR($E108="Sa",$E108="So"),M$4,M$5) -> 0 | N108: =IF(OR($E108="Sa",$E108="So"),N$4,N$5) -> 0 | O108: =IF(OR($E108="Sa",$E108="So"),O$4,O$5) -> 0 | P108: =IF(OR($E108="Sa",$E108="So"),P$4,P$5) -> 0 | Q108: =IF(OR($E108="Sa",$E108="So"),Q$4,Q$5) -> 0 | R108: =P108 -> 0 | S108: =Q108 -> 0 | T108: =R108 -> 0 | U108: =S108 -> 0 | V108: =TIME(J108,K108,0) -> 0 | W108: =TIME(L108,M108,0) -> 0 | X108: =TIME(N108,O108,0) -> 0 | Y108: =TIME(P108,Q108,0) -> 0 | Z108: =TIME(R108,S108,0) -> 0 | AA108: =TIME(T108,U108,0) -> 0 | AC108: =IF(OR(E108="Sa",E108="So"),TIME($AC$4,$AE$4,0),TIME($AC$5,$AE$5,0)) -> 0 | AE108: =IF(OR(E108="Sa",E108="So"),TIME($AC$4,$AE$4,0),(Y108-V108-(X108-W108)+(AA108-Z108))) -> 0 | AJ108: =IF(AG108=$AG$3,1,0) -> 0 | AK108: =IF(AG108=$AG$7,1,0) -> 0 | AL108: =IF(AH108=$AG$4,1,0) -> 0 | AN108: =IF(OR(AG108=$AG$2,AG108=$AG$5),1,IF(AG108=$AG$6,0.5,0)) -> 0 | AO108: =IF(OR(E108="Sa",E108="So"),0,1) -> 0
D109: EM | P109: Summ | AC109: =SUM(AC78:AC108) -> 7.7152778 | AE109: =SUM(AE78:AE108) -> 7.7152778 | AI109: =IF(AE109-AC109<0,AC109-AE109,AE109-AC109) -> 2.6645353e-15 | AJ109: =8.425*SUM(AJ78:AJ108)/24 -> 0 | AK109: =8.425*SUM(AK78:AK108)/24 -> 0 | AL109: =8.425*SUM(AL78:AL108)/24 -> 0 | AN109: =SUM(AN78:AN108) -> 0 | AO109: =SUM(AO78:AO108) -> 22
AI110: =AI76+AI109 -> 8.8817842e-15 | AJ110: =AJ76+SUM(AJ77:AJ108) -> 0 | AK110: =AK76+SUM(AK77:AK108) -> 0 | AL110: =AL76+SUM(AL77:AL108) -> 0 | AN110: =AN109*8 -> 0 | AO110: =AO109*8 -> 176
B111: =$F$5 -> 2035 | C111: =TEXT(I112,"MMM") -> Apr
A112: =A78+1 -> 4 | D112: =IF(E112="Mo",WEEKNUM(I112),"") | E112: =TEXT(I112,"TTT") -> So | F112: =$F$5 -> 2035 | G112: =$A$112 -> 4 | H112: =$H$5 -> 1 | I112: =DATE(F112,G112,H112) -> 47938 | J112: =IF(OR($E112="Sa",$E112="So"),J$4,J$5) -> 0 | K112: =IF(OR($E112="Sa",$E112="So"),K$4,K$5) -> 0 | L112: =IF(OR($E112="Sa",$E112="So"),L$4,L$5) -> 0 | M112: =IF(OR($E112="Sa",$E112="So"),M$4,M$5) -> 0 | N112: =IF(OR($E112="Sa",$E112="So"),N$4,N$5) -> 0 | O112: =IF(OR($E112="Sa",$E112="So"),O$4,O$5) -> 0 | P112: =IF(OR($E112="Sa",$E112="So"),P$4,P$5) -> 0 | Q112: =IF(OR($E112="Sa",$E112="So"),Q$4,Q$5) -> 0 | R112: =P112 -> 0 | S112: =Q112 -> 0 | T112: =R112 -> 0 | U112: =S112 -> 0 | V112: =TIME(J112,K112,0) -> 0 | W112: =TIME(L112,M112,0) -> 0 | X112: =TIME(N112,O112,0) -> 0 | Y112: =TIME(P112,Q112,0) -> 0 | Z112: =TIME(R112,S112,0) -> 0 | AA112: =TIME(T112,U112,0) -> 0 | AC112: =IF(OR(E112="Sa",E112="So"),TIME($AC$4,$AE$4,0),TIME($AC$5,$AE$5,0)) -> 0 | AE112: =IF(OR(E112="Sa",E112="So"),TIME($AC$4,$AE$4,0),(Y112-V112-(X112-W112)+(AA112-Z112))) -> 0 | AJ112: =IF(AG112=$AG$3,1,0) -> 0 | AK112: =IF(AG112=$AG$7,1,0) -> 0 | AL112: =IF(AH112=$AG$4,1,0) -> 0 | AN112: =IF(OR(AG112=$AG$2,AG112=$AG$5),1,IF(AG112=$AG$6,0.5,0)) -> 0 | AO112: =IF(OR(E112="Sa",E112="So"),0,1) -> 0
D113: =IF(E113="Mo",WEEKNUM(I113),"") -> 14 | E113: =TEXT(I113,"TTT") -> Mo | F113: =$F$5 -> 2035 | G113: =$A$112 -> 4 | H113: =H112+1 -> 2 | I113: =DATE(F113,G113,H113) -> 47939 | J113: =IF(OR($E113="Sa",$E113="So"),J$4,J$5) -> 7 | K113: =IF(OR($E113="Sa",$E113="So"),K$4,K$5) -> 0 | L113: =IF(OR($E113="Sa",$E113="So"),L$4,L$5) -> 13 | M113: =IF(OR($E113="Sa",$E113="So"),M$4,M$5) -> 0 | N113: =IF(OR($E113="Sa",$E113="So"),N$4,N$5) -> 13 | O113: =IF(OR($E113="Sa",$E113="So"),O$4,O$5) -> 30 | P113: =IF(OR($E113="Sa",$E113="So"),P$4,P$5) -> 15 | Q113: =IF(OR($E113="Sa",$E113="So"),Q$4,Q$5) -> 55 | R113: =P113 -> 15 | S113: =Q113 -> 55 | T113: =R113 -> 15 | U113: =S113 -> 55 | V113: =TIME(J113,K113,0) -> 0.29166667 | W113: =TIME(L113,M113,0) -> 0.54166667 | X113: =TIME(N113,O113,0) -> 0.5625 | Y113: =TIME(P113,Q113,0) -> 0.66319444 | Z113: =TIME(R113,S113,0) -> 0.66319444 | AA113: =TIME(T113,U113,0) -> 0.66319444 | AC113: =IF(OR(E113="Sa",E113="So"),TIME($AC$4,$AE$4,0),TIME($AC$5,$AE$5,0)) -> 0.35069444 | AE113: =IF(OR(E113="Sa",E113="So"),TIME($AC$4,$AE$4,0),(Y113-V113-(X113-W113)+(AA113-Z113))) -> 0.35069444 | AJ113: =IF(AG113=$AG$3,1,0) -> 0 | AK113: =IF(AG113=$AG$7,1,0) -> 0 | AL113: =IF(AH113=$AG$4,1,0) -> 0 | AN113: =IF(OR(AG113=$AG$2,AG113=$AG$5),1,IF(AG113=$AG$6,0.5,0)) -> 0 | AO113: =IF(OR(E113="Sa",E113="So"),0,1) -> 1
D114: =IF(E114="Mo",WEEKNUM(I114),"") | E114: =TEXT(I114,"TTT") -> Di | F114: =$F$5 -> 2035 | G114: =$A$112 -> 4 | H114: =H113+1 -> 3 | I114: =DATE(F114,G114,H114) -> 47940 | J114: =IF(OR($E114="Sa",$E114="So"),J$4,J$5) -> 7 | K114: =IF(OR($E114="Sa",$E114="So"),K$4,K$5) -> 0 | L114: =IF(OR($E114="Sa",$E114="So"),L$4,L$5) -> 13 | M114: =IF(OR($E114="Sa",$E114="So"),M$4,M$5) -> 0 | N114: =IF(OR($E114="Sa",$E114="So"),N$4,N$5) -> 13 | O114: =IF(OR($E114="Sa",$E114="So"),O$4,O$5) -> 30 | P114: =IF(OR($E114="Sa",$E114="So"),P$4,P$5) -> 15 | Q114: =IF(OR($E114="Sa",$E114="So"),Q$4,Q$5) -> 55 | R114: =P114 -> 15 | S114: =Q114 -> 55 | T114: =R114 -> 15 | U114: =S114 -> 55 | V114: =TIME(J114,K114,0) -> 0.29166667 | W114: =TIME(L114,M114,0) -> 0.54166667 | X114: =TIME(N114,O114,0) -> 0.5625 | Y114: =TIME(P114,Q114,0) -> 0.66319444 | Z114: =TIME(R114,S114,0) -> 0.66319444 | AA114: =TIME(T114,U114,0) -> 0.66319444 | AC114: =IF(OR(E114="Sa",E114="So"),TIME($AC$4,$AE$4,0),TIME($AC$5,$AE$5,0)) -> 0.35069444 | AE114: =IF(OR(E114="Sa",E114="So"),TIME($AC$4,$AE$4,0),(Y114-V114-(X114-W114)+(AA114-Z114))) -> 0.35069444 | AJ114: =IF(AG114=$AG$3,1,0) -> 0 | AK114: =IF(AG114=$AG$7,1,0) -> 0 | AL114: =IF(AH114=$AG$4,1,0) -> 0 | AN114: =IF(OR(AG114=$AG$2,AG114=$AG$5),1,IF(AG114=$AG$6,0.5,0)) -> 0 | AO114: =IF(OR(E114="Sa",E114="So"),0,1) -> 1
D115: =IF(E115="Mo",WEEKNUM(I115),"") | E115: =TEXT(I115,"TTT") -> Mi | F115: =$F$5 -> 2035 | G115: =$A$112 -> 4 | H115: =H114+1 -> 4 | I115: =DATE(F115,G115,H115) -> 47941 | J115: =IF(OR($E115="Sa",$E115="So"),J$4,J$5) -> 7 | K115: =IF(OR($E115="Sa",$E115="So"),K$4,K$5) -> 0 | L115: =IF(OR($E115="Sa",$E115="So"),L$4,L$5) -> 13 | M115: =IF(OR($E115="Sa",$E115="So"),M$4,M$5) -> 0 | N115: =IF(OR($E115="Sa",$E115="So"),N$4,N$5) -> 13 | O115: =IF(OR($E115="Sa",$E115="So"),O$4,O$5) -> 30 | P115: =IF(OR($E115="Sa",$E115="So"),P$4,P$5) -> 15 | Q115: =IF(OR($E115="Sa",$E115="So"),Q$4,Q$5) -> 55 | R115: =P115 -> 15 | S115: =Q115 -> 55 | T115: =R115 -> 15 | U115: =S115 -> 55 | V115: =TIME(J115,K115,0) -> 0.29166667 | W115: =TIME(L115,M115,0) -> 0.54166667 | X115: =TIME(N115,O115,0) -> 0.5625 | Y115: =TIME(P115,Q115,0) -> 0.66319444 | Z115: =TIME(R115,S115,0) -> 0.66319444 | AA115: =TIME(T115,U115,0) -> 0.66319444 | AC115: =IF(OR(E115="Sa",E115="So"),TIME($AC$4,$AE$4,0),TIME($AC$5,$AE$5,0)) -> 0.35069444 | AE115: =IF(OR(E115="Sa",E115="So"),TIME($AC$4,$AE$4,0),(Y115-V115-(X115-W115)+(AA115-Z115))) -> 0.35069444 | AJ115: =IF(AG115=$AG$3,1,0) -> 0 | AK115: =IF(AG115=$AG$7,1,0) -> 0 | AL115: =IF(AH115=$AG$4,1,0) -> 0 | AN115: =IF(OR(AG115=$AG$2,AG115=$AG$5),1,IF(AG115=$AG$6,0.5,0)) -> 0 | AO115: =IF(OR(E115="Sa",E115="So"),0,1) -> 1
D116: =IF(E116="Mo",WEEKNUM(I116),"") | E116: =TEXT(I116,"TTT") -> Do | F116: =$F$5 -> 2035 | G116: =$A$112 -> 4 | H116: =H115+1 -> 5 | I116: =DATE(F116,G116,H116) -> 47942 | J116: =IF(OR($E116="Sa",$E116="So"),J$4,J$5) -> 7 | K116: =IF(OR($E116="Sa",$E116="So"),K$4,K$5) -> 0 | L116: =IF(OR($E116="Sa",$E116="So"),L$4,L$5) -> 13 | M116: =IF(OR($E116="Sa",$E116="So"),M$4,M$5) -> 0 | N116: =IF(OR($E116="Sa",$E116="So"),N$4,N$5) -> 13 | O116: =IF(OR($E116="Sa",$E116="So"),O$4,O$5) -> 30 | P116: =IF(OR($E116="Sa",$E116="So"),P$4,P$5) -> 15 | Q116: =IF(OR($E116="Sa",$E116="So"),Q$4,Q$5) -> 55 | R116: =P116 -> 15 | S116: =Q116 -> 55 | T116: =R116 -> 15 | U116: =S116 -> 55 | V116: =TIME(J116,K116,0) -> 0.29166667 | W116: =TIME(L116,M116,0) -> 0.54166667 | X116: =TIME(N116,O116,0) -> 0.5625 | Y116: =TIME(P116,Q116,0) -> 0.66319444 | Z116: =TIME(R116,S116,0) -> 0.66319444 | AA116: =TIME(T116,U116,0) -> 0.66319444 | AC116: =IF(OR(E116="Sa",E116="So"),TIME($AC$4,$AE$4,0),TIME($AC$5,$AE$5,0)) -> 0.35069444 | AE116: =IF(OR(E116="Sa",E116="So"),TIME($AC$4,$AE$4,0),(Y116-V116-(X116-W116)+(AA116-Z116))) -> 0.35069444 | AJ116: =IF(AG116=$AG$3,1,0) -> 0 | AK116: =IF(AG116=$AG$7,1,0) -> 0 | AL116: =IF(AH116=$AG$4,1,0) -> 0 | AN116: =IF(OR(AG116=$AG$2,AG116=$AG$5),1,IF(AG116=$AG$6,0.5,0)) -> 0 | AO116: =IF(OR(E116="Sa",E116="So"),0,1) -> 1
D117: =IF(E117="Mo",WEEKNUM(I117),"") | E117: =TEXT(I117,"TTT") -> Fr | F117: =$F$5 -> 2035 | G117: =$A$112 -> 4 | H117: =H116+1 -> 6 | I117: =DATE(F117,G117,H117) -> 47943 | J117: =IF(OR($E117="Sa",$E117="So"),J$4,J$5) -> 7 | K117: =IF(OR($E117="Sa",$E117="So"),K$4,K$5) -> 0 | L117: =IF(OR($E117="Sa",$E117="So"),L$4,L$5) -> 13 | M117: =IF(OR($E117="Sa",$E117="So"),M$4,M$5) -> 0 | N117: =IF(OR($E117="Sa",$E117="So"),N$4,N$5) -> 13 | O117: =IF(OR($E117="Sa",$E117="So"),O$4,O$5) -> 30 | P117: =IF(OR($E117="Sa",$E117="So"),P$4,P$5) -> 15 | Q117: =IF(OR($E117="Sa",$E117="So"),Q$4,Q$5) -> 55 | R117: =P117 -> 15 | S117: =Q117 -> 55 | T117: =R117 -> 15 | U117: =S117 -> 55 | V117: =TIME(J117,K117,0) -> 0.29166667 | W117: =TIME(L117,M117,0) -> 0.54166667 | X117: =TIME(N117,O117,0) -> 0.5625 | Y117: =TIME(P117,Q117,0) -> 0.66319444 | Z117: =TIME(R117,S117,0) -> 0.66319444 | AA117: =TIME(T117,U117,0) -> 0.66319444 | AC117: =IF(OR(E117="Sa",E117="So"),TIME($AC$4,$AE$4,0),TIME($AC$5,$AE$5,0)) -> 0.35069444 | AE117: =IF(OR(E117="Sa",E117="So"),TIME($AC$4,$AE$4,0),(Y117-V117-(X117-W117)+(AA117-Z117))) -> 0.35069444 | AJ117: =IF(AG117=$AG$3,1,0) -> 0 | AK117: =IF(AG117=$AG$7,1,0) -> 0 | AL117: =IF(AH117=$AG$4,1,0) -> 0 | AN117: =IF(OR(AG117=$AG$2,AG117=$AG$5),1,IF(AG117=$AG$6,0.5,0)) -> 0 | AO117: =IF(OR(E117="Sa",E117="So"),0,1) -> 1
D118: =IF(E118="Mo",WEEKNUM(I118),"") | E118: =TEXT(I118,"TTT") -> Sa | F118: =$F$5 -> 2035 | G118: =$A$112 -> 4 | H118: =H117+1 -> 7 | I118: =DATE(F118,G118,H118) -> 47944 | J118: =IF(OR($E118="Sa",$E118="So"),J$4,J$5) -> 0 | K118: =IF(OR($E118="Sa",$E118="So"),K$4,K$5) -> 0 | L118: =IF(OR($E118="Sa",$E118="So"),L$4,L$5) -> 0 | M118: =IF(OR($E118="Sa",$E118="So"),M$4,M$5) -> 0 | N118: =IF(OR($E118="Sa",$E118="So"),N$4,N$5) -> 0 | O118: =IF(OR($E118="Sa",$E118="So"),O$4,O$5) -> 0 | P118: =IF(OR($E118="Sa",$E118="So"),P$4,P$5) -> 0 | Q118: =IF(OR($E118="Sa",$E118="So"),Q$4,Q$5) -> 0 | R118: =P118 -> 0 | S118: =Q118 -> 0 | T118: =R118 -> 0 | U118: =S118 -> 0 | V118: =TIME(J118,K118,0) -> 0 | W118: =TIME(L118,M118,0) -> 0 | X118: =TIME(N118,O118,0) -> 0 | Y118: =TIME(P118,Q118,0) -> 0 | Z118: =TIME(R118,S118,0) -> 0 | AA118: =TIME(T118,U118,0) -> 0 | AC118: =IF(OR(E118="Sa",E118="So"),TIME($AC$4,$AE$4,0),TIME($AC$5,$AE$5,0)) -> 0 | AE118: =IF(OR(E118="Sa",E118="So"),TIME($AC$4,$AE$4,0),(Y118-V118-(X118-W118)+(AA118-Z118))) -> 0 | AJ118: =IF(AG118=$AG$3,1,0) -> 0 | AK118: =IF(AG118=$AG$7,1,0) -> 0 | AL118: =IF(AH118=$AG$4,1,0) -> 0 | AN118: =IF(OR(AG118=$AG$2,AG118=$AG$5),1,IF(AG118=$AG$6,0.5,0)) -> 0 | AO118: =IF(OR(E118="Sa",E118="So"),0,1) -> 0
D119: =IF(E119="Mo",WEEKNUM(I119),"") | E119: =TEXT(I119,"TTT") -> So | F119: =$F$5 -> 2035 | G119: =$A$112 -> 4 | H119: =H118+1 -> 8 | I119: =DATE(F119,G119,H119) -> 47945 | J119: =IF(OR($E119="Sa",$E119="So"),J$4,J$5) -> 0 | K119: =IF(OR($E119="Sa",$E119="So"),K$4,K$5) -> 0 | L119: =IF(OR($E119="Sa",$E119="So"),L$4,L$5) -> 0 | M119: =IF(OR($E119="Sa",$E119="So"),M$4,M$5) -> 0 | N119: =IF(OR($E119="Sa",$E119="So"),N$4,N$5) -> 0 | O119: =IF(OR($E119="Sa",$E119="So"),O$4,O$5) -> 0 | P119: =IF(OR($E119="Sa",$E119="So"),P$4,P$5) -> 0 | Q119: =IF(OR($E119="Sa",$E119="So"),Q$4,Q$5) -> 0 | R119: =P119 -> 0 | S119: =Q119 -> 0 | T119: =R119 -> 0 | U119: =S119 -> 0 | V119: =TIME(J119,K119,0) -> 0 | W119: =TIME(L119,M119,0) -> 0 | X119: =TIME(N119,O119,0) -> 0 | Y119: =TIME(P119,Q119,0) -> 0 | Z119: =TIME(R119,S119,0) -> 0 | AA119: =TIME(T119,U119,0) -> 0 | AC119: =IF(OR(E119="Sa",E119="So"),TIME($AC$4,$AE$4,0),TIME($AC$5,$AE$5,0)) -> 0 | AE119: =IF(OR(E119="Sa",E119="So"),TIME($AC$4,$AE$4,0),(Y119-V119-(X119-W119)+(AA119-Z119))) -> 0 | AJ119: =IF(AG119=$AG$3,1,0) -> 0 | AK119: =IF(AG119=$AG$7,1,0) -> 0 | AL119: =IF(AH119=$AG$4,1,0) -> 0 | AN119: =IF(OR(AG119=$AG$2,AG119=$AG$5),1,IF(AG119=$AG$6,0.5,0)) -> 0 | AO119: =IF(OR(E119="Sa",E119="So"),0,1) -> 0
D120: =IF(E120="Mo",WEEKNUM(I120),"") -> 15 | E120: =TEXT(I120,"TTT") -> Mo | F120: =$F$5 -> 2035 | G120: =$A$112 -> 4 | H120: =H119+1 -> 9 | I120: =DATE(F120,G120,H120) -> 47946 | J120: =IF(OR($E120="Sa",$E120="So"),J$4,J$5) -> 7 | K120: =IF(OR($E120="Sa",$E120="So"),K$4,K$5) -> 0 | L120: =IF(OR($E120="Sa",$E120="So"),L$4,L$5) -> 13 | M120: =IF(OR($E120="Sa",$E120="So"),M$4,M$5) -> 0 | N120: =IF(OR($E120="Sa",$E120="So"),N$4,N$5) -> 13 | O120: =IF(OR($E120="Sa",$E120="So"),O$4,O$5) -> 30 | P120: =IF(OR($E120="Sa",$E120="So"),P$4,P$5) -> 15 | Q120: =IF(OR($E120="Sa",$E120="So"),Q$4,Q$5) -> 55 | R120: =P120 -> 15 | S120: =Q120 -> 55 | T120: =R120 -> 15 | U120: =S120 -> 55 | V120: =TIME(J120,K120,0) -> 0.29166667 | W120: =TIME(L120,M120,0) -> 0.54166667 | X120: =TIME(N120,O120,0) -> 0.5625 | Y120: =TIME(P120,Q120,0) -> 0.66319444 | Z120: =TIME(R120,S120,0) -> 0.66319444 | AA120: =TIME(T120,U120,0) -> 0.66319444 | AC120: =IF(OR(E120="Sa",E120="So"),TIME($AC$4,$AE$4,0),TIME($AC$5,$AE$5,0)) -> 0.35069444 | AE120: =IF(OR(E120="Sa",E120="So"),TIME($AC$4,$AE$4,0),(Y120-V120-(X120-W120)+(AA120-Z120))) -> 0.35069444 | AJ120: =IF(AG120=$AG$3,1,0) -> 0 | AK120: =IF(AG120=$AG$7,1,0) -> 0 | AL120: =IF(AH120=$AG$4,1,0) -> 0 | AN120: =IF(OR(AG120=$AG$2,AG120=$AG$5),1,IF(AG120=$AG$6,0.5,0)) -> 0 | AO120: =IF(OR(E120="Sa",E120="So"),0,1) -> 1
D121: =IF(E121="Mo",WEEKNUM(I121),"") | E121: =TEXT(I121,"TTT") -> Di | F121: =$F$5 -> 2035 | G121: =$A$112 -> 4 | H121: =H120+1 -> 10 | I121: =DATE(F121,G121,H121) -> 47947 | J121: =IF(OR($E121="Sa",$E121="So"),J$4,J$5) -> 7 | K121: =IF(OR($E121="Sa",$E121="So"),K$4,K$5) -> 0 | L121: =IF(OR($E121="Sa",$E121="So"),L$4,L$5) -> 13 | M121: =IF(OR($E121="Sa",$E121="So"),M$4,M$5) -> 0 | N121: =IF(OR($E121="Sa",$E121="So"),N$4,N$5) -> 13 | O121: =IF(OR($E121="Sa",$E121="So"),O$4,O$5) -> 30 | P121: =IF(OR($E121="Sa",$E121="So"),P$4,P$5) -> 15 | Q121: =IF(OR($E121="Sa",$E121="So"),Q$4,Q$5) -> 55 | R121: =P121 -> 15 | S121: =Q121 -> 55 | T121: =R121 -> 15 | U121: =S121 -> 55 | V121: =TIME(J121,K121,0) -> 0.29166667 | W121: =TIME(L121,M121,0) -> 0.54166667 | X121: =TIME(N121,O121,0) -> 0.5625 | Y121: =TIME(P121,Q121,0) -> 0.66319444 | Z121: =TIME(R121,S121,0) -> 0.66319444 | AA121: =TIME(T121,U121,0) -> 0.66319444 | AC121: =IF(OR(E121="Sa",E121="So"),TIME($AC$4,$AE$4,0),TIME($AC$5,$AE$5,0)) -> 0.35069444 | AE121: =IF(OR(E121="Sa",E121="So"),TIME($AC$4,$AE$4,0),(Y121-V121-(X121-W121)+(AA121-Z121))) -> 0.35069444 | AJ121: =IF(AG121=$AG$3,1,0) -> 0 | AK121: =IF(AG121=$AG$7,1,0) -> 0 | AL121: =IF(AH121=$AG$4,1,0) -> 0 | AN121: =IF(OR(AG121=$AG$2,AG121=$AG$5),1,IF(AG121=$AG$6,0.5,0)) -> 0 | AO121: =IF(OR(E121="Sa",E121="So"),0,1) -> 1
D122: =IF(E122="Mo",WEEKNUM(I122),"") | E122: =TEXT(I122,"TTT") -> Mi | F122: =$F$5 -> 2035 | G122: =$A$112 -> 4 | H122: =H121+1 -> 11 | I122: =DATE(F122,G122,H122) -> 47948 | J122: =IF(OR($E122="Sa",$E122="So"),J$4,J$5) -> 7 | K122: =IF(OR($E122="Sa",$E122="So"),K$4,K$5) -> 0 | L122: =IF(OR($E122="Sa",$E122="So"),L$4,L$5) -> 13 | M122: =IF(OR($E122="Sa",$E122="So"),M$4,M$5) -> 0 | N122: =IF(OR($E122="Sa",$E122="So"),N$4,N$5) -> 13 | O122: =IF(OR($E122="Sa",$E122="So"),O$4,O$5) -> 30 | P122: =IF(OR($E122="Sa",$E122="So"),P$4,P$5) -> 15 | Q122: =IF(OR($E122="Sa",$E122="So"),Q$4,Q$5) -> 55 | R122: =P122 -> 15 | S122: =Q122 -> 55 | T122: =R122 -> 15 | U122: =S122 -> 55 | V122: =TIME(J122,K122,0) -> 0.29166667 | W122: =TIME(L122,M122,0) -> 0.54166667 | X122: =TIME(N122,O122,0) -> 0.5625 | Y122: =TIME(P122,Q122,0) -> 0.66319444 | Z122: =TIME(R122,S122,0) -> 0.66319444 | AA122: =TIME(T122,U122,0) -> 0.66319444 | AC122: =IF(OR(E122="Sa",E122="So"),TIME($AC$4,$AE$4,0),TIME($AC$5,$AE$5,0)) -> 0.35069444 | AE122: =IF(OR(E122="Sa",E122="So"),TIME($AC$4,$AE$4,0),(Y122-V122-(X122-W122)+(AA122-Z122))) -> 0.35069444 | AJ122: =IF(AG122=$AG$3,1,0) -> 0 | AK122: =IF(AG122=$AG$7,1,0) -> 0 | AL122: =IF(AH122=$AG$4,1,0) -> 0 | AN122: =IF(OR(AG122=$AG$2,AG122=$AG$5),1,IF(AG122=$AG$6,0.5,0)) -> 0 | AO122: =IF(OR(E122="Sa",E122="So"),0,1) -> 1
D123: =IF(E123="Mo",WEEKNUM(I123),"") | E123: =TEXT(I123,"TTT") -> Do | F123: =$F$5 -> 2035 | G123: =$A$112 -> 4 | H123: =H122+1 -> 12 | I123: =DATE(F123,G123,H123) -> 47949 | J123: =IF(OR($E123="Sa",$E123="So"),J$4,J$5) -> 7 | K123: =IF(OR($E123="Sa",$E123="So"),K$4,K$5) -> 0 | L123: =IF(OR($E123="Sa",$E123="So"),L$4,L$5) -> 13 | M123: =IF(OR($E123="Sa",$E123="So"),M$4,M$5) -> 0 | N123: =IF(OR($E123="Sa",$E123="So"),N$4,N$5) -> 13 | O123: =IF(OR($E123="Sa",$E123="So"),O$4,O$5) -> 30 | P123: =IF(OR($E123="Sa",$E123="So"),P$4,P$5) -> 15 | Q123: =IF(OR($E123="Sa",$E123="So"),Q$4,Q$5) -> 55 | R123: =P123 -> 15 | S123: =Q123 -> 55 | T123: =R123 -> 15 | U123: =S123 -> 55 | V123: =TIME(J123,K123,0) -> 0.29166667 | W123: =TIME(L123,M123,0) -> 0.54166667 | X123: =TIME(N123,O123,0) -> 0.5625 | Y123: =TIME(P123,Q123,0) -> 0.66319444 | Z123: =TIME(R123,S123,0) -> 0.66319444 | AA123: =TIME(T123,U123,0) -> 0.66319444 | AC123: =IF(OR(E123="Sa",E123="So"),TIME($AC$4,$AE$4,0),TIME($AC$5,$AE$5,0)) -> 0.35069444 | AE123: =IF(OR(E123="Sa",E123="So"),TIME($AC$4,$AE$4,0),(Y123-V123-(X123-W123)+(AA123-Z123))) -> 0.35069444 | AJ123: =IF(AG123=$AG$3,1,0) -> 0 | AK123: =IF(AG123=$AG$7,1,0) -> 0 | AL123: =IF(AH123=$AG$4,1,0) -> 0 | AN123: =IF(OR(AG123=$AG$2,AG123=$AG$5),1,IF(AG123=$AG$6,0.5,0)) -> 0 | AO123: =IF(OR(E123="Sa",E123="So"),0,1) -> 1
D124: =IF(E124="Mo",WEEKNUM(I124),"") | E124: =TEXT(I124,"TTT") -> Fr | F124: =$F$5 -> 2035 | G124: =$A$112 -> 4 | H124: =H123+1 -> 13 | I124: =DATE(F124,G124,H124) -> 47950 | J124: =IF(OR($E124="Sa",$E124="So"),J$4,J$5) -> 7 | K124: =IF(OR($E124="Sa",$E124="So"),K$4,K$5) -> 0 | L124: =IF(OR($E124="Sa",$E124="So"),L$4,L$5) -> 13 | M124: =IF(OR($E124="Sa",$E124="So"),M$4,M$5) -> 0 | N124: =IF(OR($E124="Sa",$E124="So"),N$4,N$5) -> 13 | O124: =IF(OR($E124="Sa",$E124="So"),O$4,O$5) -> 30 | P124: =IF(OR($E124="Sa",$E124="So"),P$4,P$5) -> 15 | Q124: =IF(OR($E124="Sa",$E124="So"),Q$4,Q$5) -> 55 | R124: =P124 -> 15 | S124: =Q124 -> 55 | T124: =R124 -> 15 | U124: =S124 -> 55 | V124: =TIME(J124,K124,0) -> 0.29166667 | W124: =TIME(L124,M124,0) -> 0.54166667 | X124: =TIME(N124,O124,0) -> 0.5625 | Y124: =TIME(P124,Q124,0) -> 0.66319444 | Z124: =TIME(R124,S124,0) -> 0.66319444 | AA124: =TIME(T124,U124,0) -> 0.66319444 | AC124: =IF(OR(E124="Sa",E124="So"),TIME($AC$4,$AE$4,0),TIME($AC$5,$AE$5,0)) -> 0.35069444 | AE124: =IF(OR(E124="Sa",E124="So"),TIME($AC$4,$AE$4,0),(Y124-V124-(X124-W124)+(AA124-Z124))) -> 0.35069444 | AJ124: =IF(AG124=$AG$3,1,0) -> 0 | AK124: =IF(AG124=$AG$7,1,0) -> 0 | AL124: =IF(AH124=$AG$4,1,0) -> 0 | AN124: =IF(OR(AG124=$AG$2,AG124=$AG$5),1,IF(AG124=$AG$6,0.5,0)) -> 0 | AO124: =IF(OR(E124="Sa",E124="So"),0,1) -> 1
... D142: =IF(E142="Mo",WEEKNUM(I142),"") | E142: =TEXT(I142,"TTT") -> Di | F142: =$F$5 -> 2035 | G142: =$A$112 -> 4 | H142: =H141+1 -> 31 | I142: =DATE(F142,G142,H142) -> 47968 | J142: =IF(OR($E142="Sa",$E142="So"),J$4,J$5) -> 7 | K142: =IF(OR($E142="Sa",$E142="So"),K$4,K$5) -> 0 | L142: =IF(OR($E142="Sa",$E142="So"),L$4,L$5) -> 13 | M142: =IF(OR($E142="Sa",$E142="So"),M$4,M$5) -> 0 | N142: =IF(OR($E142="Sa",$E142="So"),N$4,N$5) -> 13 | O142: =IF(OR($E142="Sa",$E142="So"),O$4,O$5) -> 30 | P142: =IF(OR($E142="Sa",$E142="So"),P$4,P$5) -> 15 | Q142: =IF(OR($E142="Sa",$E142="So"),Q$4,Q$5) -> 55 | R142: =P142 -> 15 | S142: =Q142 -> 55 | T142: =R142 -> 15 | U142: =S142 -> 55 | V142: =TIME(J142,K142,0) -> 0.29166667 | W142: =TIME(L142,M142,0) -> 0.54166667 | X142: =TIME(N142,O142,0) -> 0.5625 | Y142: =TIME(P142,Q142,0) -> 0.66319444 | Z142: =TIME(R142,S142,0) -> 0.66319444 | AA142: =TIME(T142,U142,0) -> 0.66319444 | AC142: =IF(OR(E142="Sa",E142="So"),TIME($AC$4,$AE$4,0),TIME($AC$5,$AE$5,0)) -> 0.35069444 | AE142: =IF(OR(E142="Sa",E142="So"),TIME($AC$4,$AE$4,0),(Y142-V142-(X142-W142)+(AA142-Z142))) -> 0.35069444 | AJ142: =IF(AG142=$AG$3,1,0) -> 0 | AK142: =IF(AG142=$AG$7,1,0) -> 0 | AL142: =IF(AH142=$AG$4,1,0) -> 0 | AN142: =IF(OR(AG142=$AG$2,AG142=$AG$5),1,IF(AG142=$AG$6,0.5,0)) -> 0 | AO142: =IF(OR(E142="Sa",E142="So"),0,1) -> 1
D143: EM | P143: Summ | AC143: =SUM(AC112:AC142) -> 7.7152778 | AE143: =SUM(AE112:AE142) -> 7.7152778 | AI143: =IF(AE143-AC143<0,AC143-AE143,AE143-AC143) -> 2.6645353e-15 | AJ143: =8.425*SUM(AJ112:AJ142)/24 -> 0 | AK143: =8.425*SUM(AK112:AK142)/24 -> 0 | AL143: =8.425*SUM(AL112:AL142)/24 -> 0 | AN143: =SUM(AN112:AN142) -> 0 | AO143: =SUM(AO112:AO142) -> 22
AI144: =AI110+AI143 -> 1.1546319e-14 | AJ144: =AJ110+SUM(AJ111:AJ142) -> 0 | AK144: =AK110+SUM(AK111:AK142) -> 0 | AL144: =AL110+SUM(AL111:AL142) -> 0 | AN144: =AN143*8 -> 0 | AO144: =AO143*8 -> 176
B145: =$F$5 -> 2035 | C145: =TEXT(I146,"MMM") -> Mai
A146: =A112+1 -> 5 | D146: =IF(E146="Mo",WEEKNUM(I146),"") | E146: =TEXT(I146,"TTT") -> Di | F146: =$F$5 -> 2035 | G146: =$A$146 -> 5 | H146: =$H$5 -> 1 | I146: =DATE(F146,G146,H146) -> 47968 | J146: =IF(OR($E146="Sa",$E146="So"),J$4,J$5) -> 7 | K146: =IF(OR($E146="Sa",$E146="So"),K$4,K$5) -> 0 | L146: =IF(OR($E146="Sa",$E146="So"),L$4,L$5) -> 13 | M146: =IF(OR($E146="Sa",$E146="So"),M$4,M$5) -> 0 | N146: =IF(OR($E146="Sa",$E146="So"),N$4,N$5) -> 13 | O146: =IF(OR($E146="Sa",$E146="So"),O$4,O$5) -> 30 | P146: =IF(OR($E146="Sa",$E146="So"),P$4,P$5) -> 15 | Q146: =IF(OR($E146="Sa",$E146="So"),Q$4,Q$5) -> 55 | R146: =P146 -> 15 | S146: =Q146 -> 55 | T146: =R146 -> 15 | U146: =S146 -> 55 | V146: =TIME(J146,K146,0) -> 0.29166667 | W146: =TIME(L146,M146,0) -> 0.54166667 | X146: =TIME(N146,O146,0) -> 0.5625 | Y146: =TIME(P146,Q146,0) -> 0.66319444 | Z146: =TIME(R146,S146,0) -> 0.66319444 | AA146: =TIME(T146,U146,0) -> 0.66319444 | AC146: =IF(OR(E146="Sa",E146="So"),TIME($AC$4,$AE$4,0),TIME($AC$5,$AE$5,0)) -> 0.35069444 | AE146: =IF(OR(E146="Sa",E146="So"),TIME($AC$4,$AE$4,0),(Y146-V146-(X146-W146)+(AA146-Z146))) -> 0.35069444 | AJ146: =IF(AG146=$AG$3,1,0) -> 0 | AK146: =IF(AG146=$AG$7,1,0) -> 0 | AL146: =IF(AH146=$AG$4,1,0) -> 0 | AN146: =IF(OR(AG146=$AG$2,AG146=$AG$5),1,IF(AG146=$AG$6,0.5,0)) -> 0 | AO146: =IF(OR(E146="Sa",E146="So"),0,1) -> 1
D147: =IF(E147="Mo",WEEKNUM(I147),"") | E147: =TEXT(I147,"TTT") -> Mi | F147: =$F$5 -> 2035 | G147: =$A$146 -> 5 | H147: =H146+1 -> 2 | I147: =DATE(F147,G147,H147) -> 47969 | J147: =IF(OR($E147="Sa",$E147="So"),J$4,J$5) -> 7 | K147: =IF(OR($E147="Sa",$E147="So"),K$4,K$5) -> 0 | L147: =IF(OR($E147="Sa",$E147="So"),L$4,L$5) -> 13 | M147: =IF(OR($E147="Sa",$E147="So"),M$4,M$5) -> 0 | N147: =IF(OR($E147="Sa",$E147="So"),N$4,N$5) -> 13 | O147: =IF(OR($E147="Sa",$E147="So"),O$4,O$5) -> 30 | P147: =IF(OR($E147="Sa",$E147="So"),P$4,P$5) -> 15 | Q147: =IF(OR($E147="Sa",$E147="So"),Q$4,Q$5) -> 55 | R147: =P147 -> 15 | S147: =Q147 -> 55 | T147: =R147 -> 15 | U147: =S147 -> 55 | V147: =TIME(J147,K147,0) -> 0.29166667 | W147: =TIME(L147,M147,0) -> 0.54166667 | X147: =TIME(N147,O147,0) -> 0.5625 | Y147: =TIME(P147,Q147,0) -> 0.66319444 | Z147: =TIME(R147,S147,0) -> 0.66319444 | AA147: =TIME(T147,U147,0) -> 0.66319444 | AC147: =IF(OR(E147="Sa",E147="So"),TIME($AC$4,$AE$4,0),TIME($AC$5,$AE$5,0)) -> 0.35069444 | AE147: =IF(OR(E147="Sa",E147="So"),TIME($AC$4,$AE$4,0),(Y147-V147-(X147-W147)+(AA147-Z147))) -> 0.35069444 | AJ147: =IF(AG147=$AG$3,1,0) -> 0 | AK147: =IF(AG147=$AG$7,1,0) -> 0 | AL147: =IF(AH147=$AG$4,1,0) -> 0 | AN147: =IF(OR(AG147=$AG$2,AG147=$AG$5),1,IF(AG147=$AG$6,0.5,0)) -> 0 | AO147: =IF(OR(E147="Sa",E147="So"),0,1) -> 1
D148: =IF(E148="Mo",WEEKNUM(I148),"") | E148: =TEXT(I148,"TTT") -> Do | F148: =$F$5 -> 2035 | G148: =$A$146 -> 5 | H148: =H147+1 -> 3 | I148: =DATE(F148,G148,H148) -> 47970 | J148: =IF(OR($E148="Sa",$E148="So"),J$4,J$5) -> 7 | K148: =IF(OR($E148="Sa",$E148="So"),K$4,K$5) -> 0 | L148: =IF(OR($E148="Sa",$E148="So"),L$4,L$5) -> 13 | M148: =IF(OR($E148="Sa",$E148="So"),M$4,M$5) -> 0 | N148: =IF(OR($E148="Sa",$E148="So"),N$4,N$5) -> 13 | O148: =IF(OR($E148="Sa",$E148="So"),O$4,O$5) -> 30 | P148: =IF(OR($E148="Sa",$E148="So"),P$4,P$5) -> 15 | Q148: =IF(OR($E148="Sa",$E148="So"),Q$4,Q$5) -> 55 | R148: =P148 -> 15 | S148: =Q148 -> 55 | T148: =R148 -> 15 | U148: =S148 -> 55 | V148: =TIME(J148,K148,0) -> 0.29166667 | W148: =TIME(L148,M148,0) -> 0.54166667 | X148: =TIME(N148,O148,0) -> 0.5625 | Y148: =TIME(P148,Q148,0) -> 0.66319444 | Z148: =TIME(R148,S148,0) -> 0.66319444 | AA148: =TIME(T148,U148,0) -> 0.66319444 | AC148: =IF(OR(E148="Sa",E148="So"),TIME($AC$4,$AE$4,0),TIME($AC$5,$AE$5,0)) -> 0.35069444 | AE148: =IF(OR(E148="Sa",E148="So"),TIME($AC$4,$AE$4,0),(Y148-V148-(X148-W148)+(AA148-Z148))) -> 0.35069444 | AJ148: =IF(AG148=$AG$3,1,0) -> 0 | AK148: =IF(AG148=$AG$7,1,0) -> 0 | AL148: =IF(AH148=$AG$4,1,0) -> 0 | AN148: =IF(OR(AG148=$AG$2,AG148=$AG$5),1,IF(AG148=$AG$6,0.5,0)) -> 0 | AO148: =IF(OR(E148="Sa",E148="So"),0,1) -> 1
D149: =IF(E149="Mo",WEEKNUM(I149),"") | E149: =TEXT(I149,"TTT") -> Fr | F149: =$F$5 -> 2035 | G149: =$A$146 -> 5 | H149: =H148+1 -> 4 | I149: =DATE(F149,G149,H149) -> 47971 | J149: =IF(OR($E149="Sa",$E149="So"),J$4,J$5) -> 7 | K149: =IF(OR($E149="Sa",$E149="So"),K$4,K$5) -> 0 | L149: =IF(OR($E149="Sa",$E149="So"),L$4,L$5) -> 13 | M149: =IF(OR($E149="Sa",$E149="So"),M$4,M$5) -> 0 | N149: =IF(OR($E149="Sa",$E149="So"),N$4,N$5) -> 13 | O149: =IF(OR($E149="Sa",$E149="So"),O$4,O$5) -> 30 | P149: =IF(OR($E149="Sa",$E149="So"),P$4,P$5) -> 15 | Q149: =IF(OR($E149="Sa",$E149="So"),Q$4,Q$5) -> 55 | R149: =P149 -> 15 | S149: =Q149 -> 55 | T149: =R149 -> 15 | U149: =S149 -> 55 | V149: =TIME(J149,K149,0) -> 0.29166667 | W149: =TIME(L149,M149,0) -> 0.54166667 | X149: =TIME(N149,O149,0) -> 0.5625 | Y149: =TIME(P149,Q149,0) -> 0.66319444 | Z149: =TIME(R149,S149,0) -> 0.66319444 | AA149: =TIME(T149,U149,0) -> 0.66319444 | AC149: =IF(OR(E149="Sa",E149="So"),TIME($AC$4,$AE$4,0),TIME($AC$5,$AE$5,0)) -> 0.35069444 | AE149: =IF(OR(E149="Sa",E149="So"),TIME($AC$4,$AE$4,0),(Y149-V149-(X149-W149)+(AA149-Z149))) -> 0.35069444 | AJ149: =IF(AG149=$AG$3,1,0) -> 0 | AK149: =IF(AG149=$AG$7,1,0) -> 0 | AL149: =IF(AH149=$AG$4,1,0) -> 0 | AN149: =IF(OR(AG149=$AG$2,AG149=$AG$5),1,IF(AG149=$AG$6,0.5,0)) -> 0 | AO149: =IF(OR(E149="Sa",E149="So"),0,1) -> 1
D150: =IF(E150="Mo",WEEKNUM(I150),"") | E150: =TEXT(I150,"TTT") -> Sa | F150: =$F$5 -> 2035 | G150: =$A$146 -> 5 | H150: =H149+1 -> 5 | I150: =DATE(F150,G150,H150) -> 47972 | J150: =IF(OR($E150="Sa",$E150="So"),J$4,J$5) -> 0 | K150: =IF(OR($E150="Sa",$E150="So"),K$4,K$5) -> 0 | L150: =IF(OR($E150="Sa",$E150="So"),L$4,L$5) -> 0 | M150: =IF(OR($E150="Sa",$E150="So"),M$4,M$5) -> 0 | N150: =IF(OR($E150="Sa",$E150="So"),N$4,N$5) -> 0 | O150: =IF(OR($E150="Sa",$E150="So"),O$4,O$5) -> 0 | P150: =IF(OR($E150="Sa",$E150="So"),P$4,P$5) -> 0 | Q150: =IF(OR($E150="Sa",$E150="So"),Q$4,Q$5) -> 0 | R150: =P150 -> 0 | S150: =Q150 -> 0 | T150: =R150 -> 0 | U150: =S150 -> 0 | V150: =TIME(J150,K150,0) -> 0 | W150: =TIME(L150,M150,0) -> 0 | X150: =TIME(N150,O150,0) -> 0 | Y150: =TIME(P150,Q150,0) -> 0 | Z150: =TIME(R150,S150,0) -> 0 | AA150: =TIME(T150,U150,0) -> 0 | AC150: =IF(OR(E150="Sa",E150="So"),TIME($AC$4,$AE$4,0),TIME($AC$5,$AE$5,0)) -> 0 | AE150: =IF(OR(E150="Sa",E150="So"),TIME($AC$4,$AE$4,0),(Y150-V150-(X150-W150)+(AA150-Z150))) -> 0 | AJ150: =IF(AG150=$AG$3,1,0) -> 0 | AK150: =IF(AG150=$AG$7,1,0) -> 0 | AL150: =IF(AH150=$AG$4,1,0) -> 0 | AN150: =IF(OR(AG150=$AG$2,AG150=$AG$5),1,IF(AG150=$AG$6,0.5,0)) -> 0 | AO150: =IF(OR(E150="Sa",E150="So"),0,1) -> 0
D151: =IF(E151="Mo",WEEKNUM(I151),"") | E151: =TEXT(I151,"TTT") -> So | F151: =$F$5 -> 2035 | G151: =$A$146 -> 5 | H151: =H150+1 -> 6 | I151: =DATE(F151,G151,H151) -> 47973 | J151: =IF(OR($E151="Sa",$E151="So"),J$4,J$5) -> 0 | K151: =IF(OR($E151="Sa",$E151="So"),K$4,K$5) -> 0 | L151: =IF(OR($E151="Sa",$E151="So"),L$4,L$5) -> 0 | M151: =IF(OR($E151="Sa",$E151="So"),M$4,M$5) -> 0 | N151: =IF(OR($E151="Sa",$E151="So"),N$4,N$5) -> 0 | O151: =IF(OR($E151="Sa",$E151="So"),O$4,O$5) -> 0 | P151: =IF(OR($E151="Sa",$E151="So"),P$4,P$5) -> 0 | Q151: =IF(OR($E151="Sa",$E151="So"),Q$4,Q$5) -> 0 | R151: =P151 -> 0 | S151: =Q151 -> 0 | T151: =R151 -> 0 | U151: =S151 -> 0 | V151: =TIME(J151,K151,0) -> 0 | W151: =TIME(L151,M151,0) -> 0 | X151: =TIME(N151,O151,0) -> 0 | Y151: =TIME(P151,Q151,0) -> 0 | Z151: =TIME(R151,S151,0) -> 0 | AA151: =TIME(T151,U151,0) -> 0 | AC151: =IF(OR(E151="Sa",E151="So"),TIME($AC$4,$AE$4,0),TIME($AC$5,$AE$5,0)) -> 0 | AE151: =IF(OR(E151="Sa",E151="So"),TIME($AC$4,$AE$4,0),(Y151-V151-(X151-W151)+(AA151-Z151))) -> 0 | AJ151: =IF(AG151=$AG$3,1,0) -> 0 | AK151: =IF(AG151=$AG$7,1,0) -> 0 | AL151: =IF(AH151=$AG$4,1,0) -> 0 | AN151: =IF(OR(AG151=$AG$2,AG151=$AG$5),1,IF(AG151=$AG$6,0.5,0)) -> 0 | AO151: =IF(OR(E151="Sa",E151="So"),0,1) -> 0
D152: =IF(E152="Mo",WEEKNUM(I152),"") -> 19 | E152: =TEXT(I152,"TTT") -> Mo | F152: =$F$5 -> 2035 | G152: =$A$146 -> 5 | H152: =H151+1 -> 7 | I152: =DATE(F152,G152,H152) -> 47974 | J152: =IF(OR($E152="Sa",$E152="So"),J$4,J$5) -> 7 | K152: =IF(OR($E152="Sa",$E152="So"),K$4,K$5) -> 0 | L152: =IF(OR($E152="Sa",$E152="So"),L$4,L$5) -> 13 | M152: =IF(OR($E152="Sa",$E152="So"),M$4,M$5) -> 0 | N152: =IF(OR($E152="Sa",$E152="So"),N$4,N$5) -> 13 | O152: =IF(OR($E152="Sa",$E152="So"),O$4,O$5) -> 30 | P152: =IF(OR($E152="Sa",$E152="So"),P$4,P$5) -> 15 | Q152: =IF(OR($E152="Sa",$E152="So"),Q$4,Q$5) -> 55 | R152: =P152 -> 15 | S152: =Q152 -> 55 | T152: =R152 -> 15 | U152: =S152 -> 55 | V152: =TIME(J152,K152,0) -> 0.29166667 | W152: =TIME(L152,M152,0) -> 0.54166667 | X152: =TIME(N152,O152,0) -> 0.5625 | Y152: =TIME(P152,Q152,0) -> 0.66319444 | Z152: =TIME(R152,S152,0) -> 0.66319444 | AA152: =TIME(T152,U152,0) -> 0.66319444 | AC152: =IF(OR(E152="Sa",E152="So"),TIME($AC$4,$AE$4,0),TIME($AC$5,$AE$5,0)) -> 0.35069444 | AE152: =IF(OR(E152="Sa",E152="So"),TIME($AC$4,$AE$4,0),(Y152-V152-(X152-W152)+(AA152-Z152))) -> 0.35069444 | AJ152: =IF(AG152=$AG$3,1,0) -> 0 | AK152: =IF(AG152=$AG$7,1,0) -> 0 | AL152: =IF(AH152=$AG$4,1,0) -> 0 | AN152: =IF(OR(AG152=$AG$2,AG152=$AG$5),1,IF(AG152=$AG$6,0.5,0)) -> 0 | AO152: =IF(OR(E152="Sa",E152="So"),0,1) -> 1
D153: =IF(E153="Mo",WEEKNUM(I153),"") | E153: =TEXT(I153,"TTT") -> Di | F153: =$F$5 -> 2035 | G153: =$A$146 -> 5 | H153: =H152+1 -> 8 | I153: =DATE(F153,G153,H153) -> 47975 | J153: =IF(OR($E153="Sa",$E153="So"),J$4,J$5) -> 7 | K153: =IF(OR($E153="Sa",$E153="So"),K$4,K$5) -> 0 | L153: =IF(OR($E153="Sa",$E153="So"),L$4,L$5) -> 13 | M153: =IF(OR($E153="Sa",$E153="So"),M$4,M$5) -> 0 | N153: =IF(OR($E153="Sa",$E153="So"),N$4,N$5) -> 13 | O153: =IF(OR($E153="Sa",$E153="So"),O$4,O$5) -> 30 | P153: =IF(OR($E153="Sa",$E153="So"),P$4,P$5) -> 15 | Q153: =IF(OR($E153="Sa",$E153="So"),Q$4,Q$5) -> 55 | R153: =P153 -> 15 | S153: =Q153 -> 55 | T153: =R153 -> 15 | U153: =S153 -> 55 | V153: =TIME(J153,K153,0) -> 0.29166667 | W153: =TIME(L153,M153,0) -> 0.54166667 | X153: =TIME(N153,O153,0) -> 0.5625 | Y153: =TIME(P153,Q153,0) -> 0.66319444 | Z153: =TIME(R153,S153,0) -> 0.66319444 | AA153: =TIME(T153,U153,0) -> 0.66319444 | AC153: =IF(OR(E153="Sa",E153="So"),TIME($AC$4,$AE$4,0),TIME($AC$5,$AE$5,0)) -> 0.35069444 | AE153: =IF(OR(E153="Sa",E153="So"),TIME($AC$4,$AE$4,0),(Y153-V153-(X153-W153)+(AA153-Z153))) -> 0.35069444 | AJ153: =IF(AG153=$AG$3,1,0) -> 0 | AK153: =IF(AG153=$AG$7,1,0) -> 0 | AL153: =IF(AH153=$AG$4,1,0) -> 0 | AN153: =IF(OR(AG153=$AG$2,AG153=$AG$5),1,IF(AG153=$AG$6,0.5,0)) -> 0 | AO153: =IF(OR(E153="Sa",E153="So"),0,1) -> 1
D154: =IF(E154="Mo",WEEKNUM(I154),"") | E154: =TEXT(I154,"TTT") -> Mi | F154: =$F$5 -> 2035 | G154: =$A$146 -> 5 | H154: =H153+1 -> 9 | I154: =DATE(F154,G154,H154) -> 47976 | J154: =IF(OR($E154="Sa",$E154="So"),J$4,J$5) -> 7 | K154: =IF(OR($E154="Sa",$E154="So"),K$4,K$5) -> 0 | L154: =IF(OR($E154="Sa",$E154="So"),L$4,L$5) -> 13 | M154: =IF(OR($E154="Sa",$E154="So"),M$4,M$5) -> 0 | N154: =IF(OR($E154="Sa",$E154="So"),N$4,N$5) -> 13 | O154: =IF(OR($E154="Sa",$E154="So"),O$4,O$5) -> 30 | P154: =IF(OR($E154="Sa",$E154="So"),P$4,P$5) -> 15 | Q154: =IF(OR($E154="Sa",$E154="So"),Q$4,Q$5) -> 55 | R154: =P154 -> 15 | S154: =Q154 -> 55 | T154: =R154 -> 15 | U154: =S154 -> 55 | V154: =TIME(J154,K154,0) -> 0.29166667 | W154: =TIME(L154,M154,0) -> 0.54166667 | X154: =TIME(N154,O154,0) -> 0.5625 | Y154: =TIME(P154,Q154,0) -> 0.66319444 | Z154: =TIME(R154,S154,0) -> 0.66319444 | AA154: =TIME(T154,U154,0) -> 0.66319444 | AC154: =IF(OR(E154="Sa",E154="So"),TIME($AC$4,$AE$4,0),TIME($AC$5,$AE$5,0)) -> 0.35069444 | AE154: =IF(OR(E154="Sa",E154="So"),TIME($AC$4,$AE$4,0),(Y154-V154-(X154-W154)+(AA154-Z154))) -> 0.35069444 | AJ154: =IF(AG154=$AG$3,1,0) -> 0 | AK154: =IF(AG154=$AG$7,1,0) -> 0 | AL154: =IF(AH154=$AG$4,1,0) -> 0 | AN154: =IF(OR(AG154=$AG$2,AG154=$AG$5),1,IF(AG154=$AG$6,0.5,0)) -> 0 | AO154: =IF(OR(E154="Sa",E154="So"),0,1) -> 1
D155: =IF(E155="Mo",WEEKNUM(I155),"") | E155: =TEXT(I155,"TTT") -> Do | F155: =$F$5 -> 2035 | G155: =$A$146 -> 5 | H155: =H154+1 -> 10 | I155: =DATE(F155,G155,H155) -> 47977 | J155: =IF(OR($E155="Sa",$E155="So"),J$4,J$5) -> 7 | K155: =IF(OR($E155="Sa",$E155="So"),K$4,K$5) -> 0 | L155: =IF(OR($E155="Sa",$E155="So"),L$4,L$5) -> 13 | M155: =IF(OR($E155="Sa",$E155="So"),M$4,M$5) -> 0 | N155: =IF(OR($E155="Sa",$E155="So"),N$4,N$5) -> 13 | O155: =IF(OR($E155="Sa",$E155="So"),O$4,O$5) -> 30 | P155: =IF(OR($E155="Sa",$E155="So"),P$4,P$5) -> 15 | Q155: =IF(OR($E155="Sa",$E155="So"),Q$4,Q$5) -> 55 | R155: =P155 -> 15 | S155: =Q155 -> 55 | T155: =R155 -> 15 | U155: =S155 -> 55 | V155: =TIME(J155,K155,0) -> 0.29166667 | W155: =TIME(L155,M155,0) -> 0.54166667 | X155: =TIME(N155,O155,0) -> 0.5625 | Y155: =TIME(P155,Q155,0) -> 0.66319444 | Z155: =TIME(R155,S155,0) -> 0.66319444 | AA155: =TIME(T155,U155,0) -> 0.66319444 | AC155: =IF(OR(E155="Sa",E155="So"),TIME($AC$4,$AE$4,0),TIME($AC$5,$AE$5,0)) -> 0.35069444 | AE155: =IF(OR(E155="Sa",E155="So"),TIME($AC$4,$AE$4,0),(Y155-V155-(X155-W155)+(AA155-Z155))) -> 0.35069444 | AJ155: =IF(AG155=$AG$3,1,0) -> 0 | AK155: =IF(AG155=$AG$7,1,0) -> 0 | AL155: =IF(AH155=$AG$4,1,0) -> 0 | AN155: =IF(OR(AG155=$AG$2,AG155=$AG$5),1,IF(AG155=$AG$6,0.5,0)) -> 0 | AO155: =IF(OR(E155="Sa",E155="So"),0,1) -> 1
D156: =IF(E156="Mo",WEEKNUM(I156),"") | E156: =TEXT(I156,"TTT") -> Fr | F156: =$F$5 -> 2035 | G156: =$A$146 -> 5 | H156: =H155+1 -> 11 | I156: =DATE(F156,G156,H156) -> 47978 | J156: =IF(OR($E156="Sa",$E156="So"),J$4,J$5) -> 7 | K156: =IF(OR($E156="Sa",$E156="So"),K$4,K$5) -> 0 | L156: =IF(OR($E156="Sa",$E156="So"),L$4,L$5) -> 13 | M156: =IF(OR($E156="Sa",$E156="So"),M$4,M$5) -> 0 | N156: =IF(OR($E156="Sa",$E156="So"),N$4,N$5) -> 13 | O156: =IF(OR($E156="Sa",$E156="So"),O$4,O$5) -> 30 | P156: =IF(OR($E156="Sa",$E156="So"),P$4,P$5) -> 15 | Q156: =IF(OR($E156="Sa",$E156="So"),Q$4,Q$5) -> 55 | R156: =P156 -> 15 | S156: =Q156 -> 55 | T156: =R156 -> 15 | U156: =S156 -> 55 | V156: =TIME(J156,K156,0) -> 0.29166667 | W156: =TIME(L156,M156,0) -> 0.54166667 | X156: =TIME(N156,O156,0) -> 0.5625 | Y156: =TIME(P156,Q156,0) -> 0.66319444 | Z156: =TIME(R156,S156,0) -> 0.66319444 | AA156: =TIME(T156,U156,0) -> 0.66319444 | AC156: =IF(OR(E156="Sa",E156="So"),TIME($AC$4,$AE$4,0),TIME($AC$5,$AE$5,0)) -> 0.35069444 | AE156: =IF(OR(E156="Sa",E156="So"),TIME($AC$4,$AE$4,0),(Y156-V156-(X156-W156)+(AA156-Z156))) -> 0.35069444 | AJ156: =IF(AG156=$AG$3,1,0) -> 0 | AK156: =IF(AG156=$AG$7,1,0) -> 0 | AL156: =IF(AH156=$AG$4,1,0) -> 0 | AN156: =IF(OR(AG156=$AG$2,AG156=$AG$5),1,IF(AG156=$AG$6,0.5,0)) -> 0 | AO156: =IF(OR(E156="Sa",E156="So"),0,1) -> 1
D157: =IF(E157="Mo",WEEKNUM(I157),"") | E157: =TEXT(I157,"TTT") -> Sa | F157: =$F$5 -> 2035 | G157: =$A$146 -> 5 | H157: =H156+1 -> 12 | I157: =DATE(F157,G157,H157) -> 47979 | J157: =IF(OR($E157="Sa",$E157="So"),J$4,J$5) -> 0 | K157: =IF(OR($E157="Sa",$E157="So"),K$4,K$5) -> 0 | L157: =IF(OR($E157="Sa",$E157="So"),L$4,L$5) -> 0 | M157: =IF(OR($E157="Sa",$E157="So"),M$4,M$5) -> 0 | N157: =IF(OR($E157="Sa",$E157="So"),N$4,N$5) -> 0 | O157: =IF(OR($E157="Sa",$E157="So"),O$4,O$5) -> 0 | P157: =IF(OR($E157="Sa",$E157="So"),P$4,P$5) -> 0 | Q157: =IF(OR($E157="Sa",$E157="So"),Q$4,Q$5) -> 0 | R157: =P157 -> 0 | S157: =Q157 -> 0 | T157: =R157 -> 0 | U157: =S157 -> 0 | V157: =TIME(J157,K157,0) -> 0 | W157: =TIME(L157,M157,0) -> 0 | X157: =TIME(N157,O157,0) -> 0 | Y157: =TIME(P157,Q157,0) -> 0 | Z157: =TIME(R157,S157,0) -> 0 | AA157: =TIME(T157,U157,0) -> 0 | AC157: =IF(OR(E157="Sa",E157="So"),TIME($AC$4,$AE$4,0),TIME($AC$5,$AE$5,0)) -> 0 | AE157: =IF(OR(E157="Sa",E157="So"),TIME($AC$4,$AE$4,0),(Y157-V157-(X157-W157)+(AA157-Z157))) -> 0 | AJ157: =IF(AG157=$AG$3,1,0) -> 0 | AK157: =IF(AG157=$AG$7,1,0) -> 0 | AL157: =IF(AH157=$AG$4,1,0) -> 0 | AN157: =IF(OR(AG157=$AG$2,AG157=$AG$5),1,IF(AG157=$AG$6,0.5,0)) -> 0 | AO157: =IF(OR(E157="Sa",E157="So"),0,1) -> 0
D158: =IF(E158="Mo",WEEKNUM(I158),"") | E158: =TEXT(I158,"TTT") -> So | F158: =$F$5 -> 2035 | G158: =$A$146 -> 5 | H158: =H157+1 -> 13 | I158: =DATE(F158,G158,H158) -> 47980 | J158: =IF(OR($E158="Sa",$E158="So"),J$4,J$5) -> 0 | K158: =IF(OR($E158="Sa",$E158="So"),K$4,K$5) -> 0 | L158: =IF(OR($E158="Sa",$E158="So"),L$4,L$5) -> 0 | M158: =IF(OR($E158="Sa",$E158="So"),M$4,M$5) -> 0 | N158: =IF(OR($E158="Sa",$E158="So"),N$4,N$5) -> 0 | O158: =IF(OR($E158="Sa",$E158="So"),O$4,O$5) -> 0 | P158: =IF(OR($E158="Sa",$E158="So"),P$4,P$5) -> 0 | Q158: =IF(OR($E158="Sa",$E158="So"),Q$4,Q$5) -> 0 | R158: =P158 -> 0 | S158: =Q158 -> 0 | T158: =R158 -> 0 | U158: =S158 -> 0 | V158: =TIME(J158,K158,0) -> 0 | W158: =TIME(L158,M158,0) -> 0 | X158: =TIME(N158,O158,0) -> 0 | Y158: =TIME(P158,Q158,0) -> 0 | Z158: =TIME(R158,S158,0) -> 0 | AA158: =TIME(T158,U158,0) -> 0 | AC158: =IF(OR(E158="Sa",E158="So"),TIME($AC$4,$AE$4,0),TIME($AC$5,$AE$5,0)) -> 0 | AE158: =IF(OR(E158="Sa",E158="So"),TIME($AC$4,$AE$4,0),(Y158-V158-(X158-W158)+(AA158-Z158))) -> 0 | AJ158: =IF(AG158=$AG$3,1,0) -> 0 | AK158: =IF(AG158=$AG$7,1,0) -> 0 | AL158: =IF(AH158=$AG$4,1,0) -> 0 | AN158: =IF(OR(AG158=$AG$2,AG158=$AG$5),1,IF(AG158=$AG$6,0.5,0)) -> 0 | AO158: =IF(OR(E158="Sa",E158="So"),0,1) -> 0
... D176: =IF(E176="Mo",WEEKNUM(I176),"") | E176: =TEXT(I176,"TTT") -> Do | F176: =$F$5 -> 2035 | G176: =$A$146 -> 5 | H176: =H175+1 -> 31 | I176: =DATE(F176,G176,H176) -> 47998 | J176: =IF(OR($E176="Sa",$E176="So"),J$4,J$5) -> 7 | K176: =IF(OR($E176="Sa",$E176="So"),K$4,K$5) -> 0 | L176: =IF(OR($E176="Sa",$E176="So"),L$4,L$5) -> 13 | M176: =IF(OR($E176="Sa",$E176="So"),M$4,M$5) -> 0 | N176: =IF(OR($E176="Sa",$E176="So"),N$4,N$5) -> 13 | O176: =IF(OR($E176="Sa",$E176="So"),O$4,O$5) -> 30 | P176: =IF(OR($E176="Sa",$E176="So"),P$4,P$5) -> 15 | Q176: =IF(OR($E176="Sa",$E176="So"),Q$4,Q$5) -> 55 | R176: =P176 -> 15 | S176: =Q176 -> 55 | T176: =R176 -> 15 | U176: =S176 -> 55 | V176: =TIME(J176,K176,0) -> 0.29166667 | W176: =TIME(L176,M176,0) -> 0.54166667 | X176: =TIME(N176,O176,0) -> 0.5625 | Y176: =TIME(P176,Q176,0) -> 0.66319444 | Z176: =TIME(R176,S176,0) -> 0.66319444 | AA176: =TIME(T176,U176,0) -> 0.66319444 | AC176: =IF(OR(E176="Sa",E176="So"),TIME($AC$4,$AE$4,0),TIME($AC$5,$AE$5,0)) -> 0.35069444 | AE176: =IF(OR(E176="Sa",E176="So"),TIME($AC$4,$AE$4,0),(Y176-V176-(X176-W176)+(AA176-Z176))) -> 0.35069444 | AJ176: =IF(AG176=$AG$3,1,0) -> 0 | AK176: =IF(AG176=$AG$7,1,0) -> 0 | AL176: =IF(AH176=$AG$4,1,0) -> 0 | AN176: =IF(OR(AG176=$AG$2,AG176=$AG$5),1,IF(AG176=$AG$6,0.5,0)) -> 0 | AO176: =IF(OR(E176="Sa",E176="So"),0,1) -> 1
D177: EM | P177: Summ | AC177: =SUM(AC146:AC176) -> 8.0659722 | AE177: =SUM(AE146:AE176) -> 8.0659722 | AI177: =IF(AE177-AC177<0,AC177-AE177,AE177-AC177) -> 3.5527137e-15 | AJ177: =8.425*SUM(AJ146:AJ176)/24 -> 0 | AK177: =8.425*SUM(AK146:AK176)/24 -> 0 | AL177: =8.425*SUM(AL146:AL176)/24 -> 0 | AN177: =SUM(AN146:AN176) -> 0 | AO177: =SUM(AO146:AO176) -> 23
AI178: =AI144+AI177 -> 1.5099033e-14 | AJ178: =AJ144+SUM(AJ145:AJ176) -> 0 | AK178: =AK144+SUM(AK145:AK176) -> 0 | AL178: =AL144+SUM(AL145:AL176) -> 0 | AN178: =AN177*8 -> 0 | AO178: =AO177*8 -> 184
B179: =$F$5 -> 2035 | C179: =TEXT(I180,"MMM") -> Jun
A180: =A146+1 -> 6 | D180: =IF(E180="Mo",WEEKNUM(I180),"") | E180: =TEXT(I180,"TTT") -> Fr | F180: =$F$5 -> 2035 | G180: =$A$180 -> 6 | H180: =$H$5 -> 1 | I180: =DATE(F180,G180,H180) -> 47999 | J180: =IF(OR($E180="Sa",$E180="So"),J$4,J$5) -> 7 | K180: =IF(OR($E180="Sa",$E180="So"),K$4,K$5) -> 0 | L180: =IF(OR($E180="Sa",$E180="So"),L$4,L$5) -> 13 | M180: =IF(OR($E180="Sa",$E180="So"),M$4,M$5) -> 0 | N180: =IF(OR($E180="Sa",$E180="So"),N$4,N$5) -> 13 | O180: =IF(OR($E180="Sa",$E180="So"),O$4,O$5) -> 30 | P180: =IF(OR($E180="Sa",$E180="So"),P$4,P$5) -> 15 | Q180: =IF(OR($E180="Sa",$E180="So"),Q$4,Q$5) -> 55 | R180: =P180 -> 15 | S180: =Q180 -> 55 | T180: =R180 -> 15 | U180: =S180 -> 55 | V180: =TIME(J180,K180,0) -> 0.29166667 | W180: =TIME(L180,M180,0) -> 0.54166667 | X180: =TIME(N180,O180,0) -> 0.5625 | Y180: =TIME(P180,Q180,0) -> 0.66319444 | Z180: =TIME(R180,S180,0) -> 0.66319444 | AA180: =TIME(T180,U180,0) -> 0.66319444 | AC180: =IF(OR(E180="Sa",E180="So"),TIME($AC$4,$AE$4,0),TIME($AC$5,$AE$5,0)) -> 0.35069444 | AE180: =IF(OR(E180="Sa",E180="So"),TIME($AC$4,$AE$4,0),(Y180-V180-(X180-W180)+(AA180-Z180))) -> 0.35069444 | AJ180: =IF(AG180=$AG$3,1,0) -> 0 | AK180: =IF(AG180=$AG$7,1,0) -> 0 | AL180: =IF(AH180=$AG$4,1,0) -> 0 | AN180: =IF(OR(AG180=$AG$2,AG180=$AG$5),1,IF(AG180=$AG$6,0.5,0)) -> 0 | AO180: =IF(OR(E180="Sa",E180="So"),0,1) -> 1
D181: =IF(E181="Mo",WEEKNUM(I181),"") | E181: =TEXT(I181,"TTT") -> Sa | F181: =$F$5 -> 2035 | G181: =$A$180 -> 6 | H181: =H180+1 -> 2 | I181: =DATE(F181,G181,H181) -> 48000 | J181: =IF(OR($E181="Sa",$E181="So"),J$4,J$5) -> 0 | K181: =IF(OR($E181="Sa",$E181="So"),K$4,K$5) -> 0 | L181: =IF(OR($E181="Sa",$E181="So"),L$4,L$5) -> 0 | M181: =IF(OR($E181="Sa",$E181="So"),M$4,M$5) -> 0 | N181: =IF(OR($E181="Sa",$E181="So"),N$4,N$5) -> 0 | O181: =IF(OR($E181="Sa",$E181="So"),O$4,O$5) -> 0 | P181: =IF(OR($E181="Sa",$E181="So"),P$4,P$5) -> 0 | Q181: =IF(OR($E181="Sa",$E181="So"),Q$4,Q$5) -> 0 | R181: =P181 -> 0 | S181: =Q181 -> 0 | T181: =R181 -> 0 | U181: =S181 -> 0 | V181: =TIME(J181,K181,0) -> 0 | W181: =TIME(L181,M181,0) -> 0 | X181: =TIME(N181,O181,0) -> 0 | Y181: =TIME(P181,Q181,0) -> 0 | Z181: =TIME(R181,S181,0) -> 0 | AA181: =TIME(T181,U181,0) -> 0 | AC181: =IF(OR(E181="Sa",E181="So"),TIME($AC$4,$AE$4,0),TIME($AC$5,$AE$5,0)) -> 0 | AE181: =IF(OR(E181="Sa",E181="So"),TIME($AC$4,$AE$4,0),(Y181-V181-(X181-W181)+(AA181-Z181))) -> 0 | AJ181: =IF(AG181=$AG$3,1,0) -> 0 | AK181: =IF(AG181=$AG$7,1,0) -> 0 | AL181: =IF(AH181=$AG$4,1,0) -> 0 | AN181: =IF(OR(AG181=$AG$2,AG181=$AG$5),1,IF(AG181=$AG$6,0.5,0)) -> 0 | AO181: =IF(OR(E181="Sa",E181="So"),0,1) -> 0
D182: =IF(E182="Mo",WEEKNUM(I182),"") | E182: =TEXT(I182,"TTT") -> So | F182: =$F$5 -> 2035 | G182: =$A$180 -> 6 | H182: =H181+1 -> 3 | I182: =DATE(F182,G182,H182) -> 48001 | J182: =IF(OR($E182="Sa",$E182="So"),J$4,J$5) -> 0 | K182: =IF(OR($E182="Sa",$E182="So"),K$4,K$5) -> 0 | L182: =IF(OR($E182="Sa",$E182="So"),L$4,L$5) -> 0 | M182: =IF(OR($E182="Sa",$E182="So"),M$4,M$5) -> 0 | N182: =IF(OR($E182="Sa",$E182="So"),N$4,N$5) -> 0 | O182: =IF(OR($E182="Sa",$E182="So"),O$4,O$5) -> 0 | P182: =IF(OR($E182="Sa",$E182="So"),P$4,P$5) -> 0 | Q182: =IF(OR($E182="Sa",$E182="So"),Q$4,Q$5) -> 0 | R182: =P182 -> 0 | S182: =Q182 -> 0 | T182: =R182 -> 0 | U182: =S182 -> 0 | V182: =TIME(J182,K182,0) -> 0 | W182: =TIME(L182,M182,0) -> 0 | X182: =TIME(N182,O182,0) -> 0 | Y182: =TIME(P182,Q182,0) -> 0 | Z182: =TIME(R182,S182,0) -> 0 | AA182: =TIME(T182,U182,0) -> 0 | AC182: =IF(OR(E182="Sa",E182="So"),TIME($AC$4,$AE$4,0),TIME($AC$5,$AE$5,0)) -> 0 | AE182: =IF(OR(E182="Sa",E182="So"),TIME($AC$4,$AE$4,0),(Y182-V182-(X182-W182)+(AA182-Z182))) -> 0 | AJ182: =IF(AG182=$AG$3,1,0) -> 0 | AK182: =IF(AG182=$AG$7,1,0) -> 0 | AL182: =IF(AH182=$AG$4,1,0) -> 0 | AN182: =IF(OR(AG182=$AG$2,AG182=$AG$5),1,IF(AG182=$AG$6,0.5,0)) -> 0 | AO182: =IF(OR(E182="Sa",E182="So"),0,1) -> 0
D183: =IF(E183="Mo",WEEKNUM(I183),"") -> 23 | E183: =TEXT(I183,"TTT") -> Mo | F183: =$F$5 -> 2035 | G183: =$A$180 -> 6 | H183: =H182+1 -> 4 | I183: =DATE(F183,G183,H183) -> 48002 | J183: =IF(OR($E183="Sa",$E183="So"),J$4,J$5) -> 7 | K183: =IF(OR($E183="Sa",$E183="So"),K$4,K$5) -> 0 | L183: =IF(OR($E183="Sa",$E183="So"),L$4,L$5) -> 13 | M183: =IF(OR($E183="Sa",$E183="So"),M$4,M$5) -> 0 | N183: =IF(OR($E183="Sa",$E183="So"),N$4,N$5) -> 13 | O183: =IF(OR($E183="Sa",$E183="So"),O$4,O$5) -> 30 | P183: =IF(OR($E183="Sa",$E183="So"),P$4,P$5) -> 15 | Q183: =IF(OR($E183="Sa",$E183="So"),Q$4,Q$5) -> 55 | R183: =P183 -> 15 | S183: =Q183 -> 55 | T183: =R183 -> 15 | U183: =S183 -> 55 | V183: =TIME(J183,K183,0) -> 0.29166667 | W183: =TIME(L183,M183,0) -> 0.54166667 | X183: =TIME(N183,O183,0) -> 0.5625 | Y183: =TIME(P183,Q183,0) -> 0.66319444 | Z183: =TIME(R183,S183,0) -> 0.66319444 | AA183: =TIME(T183,U183,0) -> 0.66319444 | AC183: =IF(OR(E183="Sa",E183="So"),TIME($AC$4,$AE$4,0),TIME($AC$5,$AE$5,0)) -> 0.35069444 | AE183: =IF(OR(E183="Sa",E183="So"),TIME($AC$4,$AE$4,0),(Y183-V183-(X183-W183)+(AA183-Z183))) -> 0.35069444 | AJ183: =IF(AG183=$AG$3,1,0) -> 0 | AK183: =IF(AG183=$AG$7,1,0) -> 0 | AL183: =IF(AH183=$AG$4,1,0) -> 0 | AN183: =IF(OR(AG183=$AG$2,AG183=$AG$5),1,IF(AG183=$AG$6,0.5,0)) -> 0 | AO183: =IF(OR(E183="Sa",E183="So"),0,1) -> 1
D184: =IF(E184="Mo",WEEKNUM(I184),"") | E184: =TEXT(I184,"TTT") -> Di | F184: =$F$5 -> 2035 | G184: =$A$180 -> 6 | H184: =H183+1 -> 5 | I184: =DATE(F184,G184,H184) -> 48003 | J184: =IF(OR($E184="Sa",$E184="So"),J$4,J$5) -> 7 | K184: =IF(OR($E184="Sa",$E184="So"),K$4,K$5) -> 0 | L184: =IF(OR($E184="Sa",$E184="So"),L$4,L$5) -> 13 | M184: =IF(OR($E184="Sa",$E184="So"),M$4,M$5) -> 0 | N184: =IF(OR($E184="Sa",$E184="So"),N$4,N$5) -> 13 | O184: =IF(OR($E184="Sa",$E184="So"),O$4,O$5) -> 30 | P184: =IF(OR($E184="Sa",$E184="So"),P$4,P$5) -> 15 | Q184: =IF(OR($E184="Sa",$E184="So"),Q$4,Q$5) -> 55 | R184: =P184 -> 15 | S184: =Q184 -> 55 | T184: =R184 -> 15 | U184: =S184 -> 55 | V184: =TIME(J184,K184,0) -> 0.29166667 | W184: =TIME(L184,M184,0) -> 0.54166667 | X184: =TIME(N184,O184,0) -> 0.5625 | Y184: =TIME(P184,Q184,0) -> 0.66319444 | Z184: =TIME(R184,S184,0) -> 0.66319444 | AA184: =TIME(T184,U184,0) -> 0.66319444 | AC184: =IF(OR(E184="Sa",E184="So"),TIME($AC$4,$AE$4,0),TIME($AC$5,$AE$5,0)) -> 0.35069444 | AE184: =IF(OR(E184="Sa",E184="So"),TIME($AC$4,$AE$4,0),(Y184-V184-(X184-W184)+(AA184-Z184))) -> 0.35069444 | AJ184: =IF(AG184=$AG$3,1,0) -> 0 | AK184: =IF(AG184=$AG$7,1,0) -> 0 | AL184: =IF(AH184=$AG$4,1,0) -> 0 | AN184: =IF(OR(AG184=$AG$2,AG184=$AG$5),1,IF(AG184=$AG$6,0.5,0)) -> 0 | AO184: =IF(OR(E184="Sa",E184="So"),0,1) -> 1
D185: =IF(E185="Mo",WEEKNUM(I185),"") | E185: =TEXT(I185,"TTT") -> Mi | F185: =$F$5 -> 2035 | G185: =$A$180 -> 6 | H185: =H184+1 -> 6 | I185: =DATE(F185,G185,H185) -> 48004 | J185: =IF(OR($E185="Sa",$E185="So"),J$4,J$5) -> 7 | K185: =IF(OR($E185="Sa",$E185="So"),K$4,K$5) -> 0 | L185: =IF(OR($E185="Sa",$E185="So"),L$4,L$5) -> 13 | M185: =IF(OR($E185="Sa",$E185="So"),M$4,M$5) -> 0 | N185: =IF(OR($E185="Sa",$E185="So"),N$4,N$5) -> 13 | O185: =IF(OR($E185="Sa",$E185="So"),O$4,O$5) -> 30 | P185: =IF(OR($E185="Sa",$E185="So"),P$4,P$5) -> 15 | Q185: =IF(OR($E185="Sa",$E185="So"),Q$4,Q$5) -> 55 | R185: =P185 -> 15 | S185: =Q185 -> 55 | T185: =R185 -> 15 | U185: =S185 -> 55 | V185: =TIME(J185,K185,0) -> 0.29166667 | W185: =TIME(L185,M185,0) -> 0.54166667 | X185: =TIME(N185,O185,0) -> 0.5625 | Y185: =TIME(P185,Q185,0) -> 0.66319444 | Z185: =TIME(R185,S185,0) -> 0.66319444 | AA185: =TIME(T185,U185,0) -> 0.66319444 | AC185: =IF(OR(E185="Sa",E185="So"),TIME($AC$4,$AE$4,0),TIME($AC$5,$AE$5,0)) -> 0.35069444 | AE185: =IF(OR(E185="Sa",E185="So"),TIME($AC$4,$AE$4,0),(Y185-V185-(X185-W185)+(AA185-Z185))) -> 0.35069444 | AJ185: =IF(AG185=$AG$3,1,0) -> 0 | AK185: =IF(AG185=$AG$7,1,0) -> 0 | AL185: =IF(AH185=$AG$4,1,0) -> 0 | AN185: =IF(OR(AG185=$AG$2,AG185=$AG$5),1,IF(AG185=$AG$6,0.5,0)) -> 0 | AO185: =IF(OR(E185="Sa",E185="So"),0,1) -> 1
D186: =IF(E186="Mo",WEEKNUM(I186),"") | E186: =TEXT(I186,"TTT") -> Do | F186: =$F$5 -> 2035 | G186: =$A$180 -> 6 | H186: =H185+1 -> 7 | I186: =DATE(F186,G186,H186) -> 48005 | J186: =IF(OR($E186="Sa",$E186="So"),J$4,J$5) -> 7 | K186: =IF(OR($E186="Sa",$E186="So"),K$4,K$5) -> 0 | L186: =IF(OR($E186="Sa",$E186="So"),L$4,L$5) -> 13 | M186: =IF(OR($E186="Sa",$E186="So"),M$4,M$5) -> 0 | N186: =IF(OR($E186="Sa",$E186="So"),N$4,N$5) -> 13 | O186: =IF(OR($E186="Sa",$E186="So"),O$4,O$5) -> 30 | P186: =IF(OR($E186="Sa",$E186="So"),P$4,P$5) -> 15 | Q186: =IF(OR($E186="Sa",$E186="So"),Q$4,Q$5) -> 55 | R186: =P186 -> 15 | S186: =Q186 -> 55 | T186: =R186 -> 15 | U186: =S186 -> 55 | V186: =TIME(J186,K186,0) -> 0.29166667 | W186: =TIME(L186,M186,0) -> 0.54166667 | X186: =TIME(N186,O186,0) -> 0.5625 | Y186: =TIME(P186,Q186,0) -> 0.66319444 | Z186: =TIME(R186,S186,0) -> 0.66319444 | AA186: =TIME(T186,U186,0) -> 0.66319444 | AC186: =IF(OR(E186="Sa",E186="So"),TIME($AC$4,$AE$4,0),TIME($AC$5,$AE$5,0)) -> 0.35069444 | AE186: =IF(OR(E186="Sa",E186="So"),TIME($AC$4,$AE$4,0),(Y186-V186-(X186-W186)+(AA186-Z186))) -> 0.35069444 | AJ186: =IF(AG186=$AG$3,1,0) -> 0 | AK186: =IF(AG186=$AG$7,1,0) -> 0 | AL186: =IF(AH186=$AG$4,1,0) -> 0 | AN186: =IF(OR(AG186=$AG$2,AG186=$AG$5),1,IF(AG186=$AG$6,0.5,0)) -> 0 | AO186: =IF(OR(E186="Sa",E186="So"),0,1) -> 1
...

Sheet 2025
BG1: WHA | BH1: WAH | BI1: ECO | BJ1: ECO | BL1: WHA | BM1: WAH | BN1: ECO | BO1: ECO
B2: Year | C2: Mon | K2: Work hours | AD2: Summ | AF2: Summ | AH2: A | AJ2: Overtime | AK2: F -Leave | AL2: K - Compens | AM2: FT - Frei | AO2: Work | AP2: Work | AV2: Work | BC2: Privat | BF2: WGTST | BG2: 80.9 | BH2: 1h 10min
D3: KW | E3: Day | F3: Year | G3: Month | H3: Day | I3: Data | K3: In | M3: Break | O3: Break | Q3: Out | S3: Break | U3: Break | AD3: must | AF3: is | AH3: F | AO3: Days | AP3: Days | AQ3: Day | AT3: Project | AU3: Where | AV3: What | AX3: Day | BA3: Project | BB3: Where | BC3: What | BF3: WGKWT | BG3: 68.5 | BH3: 1h 02min
I4: Sa;So | K4: 0 | L4: 0 | M4: 0 | N4: 0 | O4: 0 | P4: 0 | Q4: 0 | R4: 0 | AD4: 0 | AF4: 0 | AH4: FT | AO4: Effective | AP4: Sum | BF4: WGMLFT | BG4: 67.8 | BH4: 1h 09min
F5: 2025 | G5: 1 | H5: 1 | K5: 7 | L5: 0 | M5: 13 | N5: 0 | O5: 13 | P5: 30 | Q5: 15 | R5: 55 | AD5: 8 | AF5: 25 | AH5: HO | AO5: A | AP5: Sa | BF5: WGMWT | BG5: 72.2 | BH5: 1h 03min
AH6: HT | BF6: WLSLHT | BG6: 67.3 | BH6: 1h 13min
D7: [ - ] | E7: [ - ] | F7: [ - ] | G7: [ - ] | H7: [ - ] | I7: [ - ] | K7: [h] | L7: [m] | M7: [h] | N7: [m] | O7: [h] | P7: [m] | Q7: [h] | R7: [m] | AD7: [h] | AF7: [m] | AH7: K | AO7: HO | AP7: So | AQ7: [ - ] | AR7: [h] | AS7: [m] | AT7: [ - ] | AU7: [ - ] | AV7: [ - ] | AX7: [ - ] | AY7: [h] | AZ7: [m] | BA7: [ - ] | BB7: [ - ] | BC7: [ - ] | BF7: WLSFT | BG7: 72.3 | BH7: 1h 12min | BL7: km | BM7: km
AJ8: 0 | AK8: 0 | AL8: 0 | AM8: 0 | BF8: WLSWT | BG8: 77.4 | BH8: 1h 09min | BL8: WGTST | BN8: ECO | BO8: ECO
B9: =$F$5 -> 2025 | C9: =TEXT(I10,"MMM") -> Jan | BL9: =INDEX($BF$2:$BG$8,MATCH(BL8,$BF$2:$BF$8,0),2) -> 80.9 | BM9: =INDEX($BF$2:$BG$8,MATCH(BL8,$BF$2:$BF$8,0),2) -> 80.9 | BN9: 15 | BO9: 15
A10: =$G$5 -> 1 | D10: =IF(E10="Mo",WEEKNUM(I10),"") | E10: =TEXT(I10,"TTT") -> Mi | F10: =$F$5 -> 2025 | G10: =$A$10 -> 1 | H10: =$H$5 -> 1 | I10: =DATE(F10,G10,H10) -> 44196 | J10: =IF(OR(G10="",G10=MONTH(I10)),1,0) -> 1 | K10: =IF(OR($E10="Sa",$E10="So",$J10=0),K$4,K$5) -> 7 | L10: =IF(OR($E10="Sa",$E10="So",$J10=0),L$4,L$5) -> 0 | M10: =IF(OR($E10="Sa",$E10="So",$J10=0),M$4,M$5) -> 13 | N10: =IF(OR($E10="Sa",$E10="So",$J10=0),N$4,N$5) -> 0 | O10: =IF(OR($E10="Sa",$E10="So",$J10=0),O$4,O$5) -> 13 | P10: =IF(OR($E10="Sa",$E10="So",$J10=0),P$4,P$5) -> 30 | Q10: =IF(OR($E10="Sa",$E10="So",$J10=0),Q$4,Q$5) -> 15 | R10: =IF(OR($E10="Sa",$E10="So",$J10=0),R$4,R$5) -> 55 | S10: =Q10 -> 15 | T10: =R10 -> 55 | U10: =S10 -> 15 | V10: =T10 -> 55 | W10: =TIME(K10,L10,0) -> 0.29166667 | X10: =TIME(M10,N10,0) -> 0.54166667 | Y10: =TIME(O10,P10,0) -> 0.5625 | Z10: =TIME(Q10,R10,0) -> 0.66319444 | AA10: =TIME(S10,T10,0) -> 0.66319444 | AB10: =TIME(U10,V10,0) -> 0.66319444 | AD10: =IF(J10=0,0,IF(OR(E10="Sa",E10="So"),TIME($AD$4,$AF$4,0),TIME($AD$5,$AF$5,0))) -> 0.35069444 | AF10: =IF(J10=0,0,Z10-W10-(Y10-X10)) -> 0.35069444 | AK10: =IF(AH10=$AH$3,1,0) -> 0 | AL10: =IF(AH10=$AH$7,1,0) -> 0 | AM10: =IF(AI10=$AH$4,1,0) -> 0 | AO10: =IF(OR(AH10=$AH$2,AH10=$AH$5),1,IF(AH10=$AH$6,0.5,0)) -> 0 | AP10: =IF(OR(E10="Sa",E10="So",E10="",J10=0,AH10="FT"),0,1) -> 1 | BL10: =BL9 -> 80.9 | BM10: =BM9 -> 80.9 | BN10: =BN9 -> 15 | BO10: =BN10+BO9 -> 30
D11: =IF(E11="Mo",WEEKNUM(I11),"") | E11: =TEXT(I11,"TTT") -> Do | F11: =$F$5 -> 2025 | G11: =$A$10 -> 1 | H11: =H10+1 -> 2 | I11: =DATE(F11,G11,H11) -> 44197 | J11: =IF(OR(G11="",G11=MONTH(I11)),1,0) -> 1 | K11: =IF(OR($E11="Sa",$E11="So",$J11=0),K$4,K$5) -> 7 | L11: =IF(OR($E11="Sa",$E11="So",$J11=0),L$4,L$5) -> 0 | M11: =IF(OR($E11="Sa",$E11="So",$J11=0),M$4,M$5) -> 13 | N11: =IF(OR($E11="Sa",$E11="So",$J11=0),N$4,N$5) -> 0 | O11: =IF(OR($E11="Sa",$E11="So",$J11=0),O$4,O$5) -> 13 | P11: =IF(OR($E11="Sa",$E11="So",$J11=0),P$4,P$5) -> 30 | Q11: =IF(OR($E11="Sa",$E11="So",$J11=0),Q$4,Q$5) -> 15 | R11: =IF(OR($E11="Sa",$E11="So",$J11=0),R$4,R$5) -> 55 | S11: =Q11 -> 15 | T11: =R11 -> 55 | U11: =S11 -> 15 | V11: =T11 -> 55 | W11: =TIME(K11,L11,0) -> 0.29166667 | X11: =TIME(M11,N11,0) -> 0.54166667 | Y11: =TIME(O11,P11,0) -> 0.5625 | Z11: =TIME(Q11,R11,0) -> 0.66319444 | AA11: =TIME(S11,T11,0) -> 0.66319444 | AB11: =TIME(U11,V11,0) -> 0.66319444 | AD11: =IF(J11=0,0,IF(OR(E11="Sa",E11="So"),TIME($AD$4,$AF$4,0),TIME($AD$5,$AF$5,0))) -> 0.35069444 | AF11: =IF(J11=0,0,Z11-W11-(Y11-X11)) -> 0.35069444 | AK11: =IF(AH11=$AH$3,1,0) -> 0 | AL11: =IF(AH11=$AH$7,1,0) -> 0 | AM11: =IF(AI11=$AH$4,1,0) -> 0 | AO11: =IF(OR(AH11=$AH$2,AH11=$AH$5),1,IF(AH11=$AH$6,0.5,0)) -> 0 | AP11: =IF(OR(E11="Sa",E11="So",E11="",J11=0,AH11="FT"),0,1) -> 1 | BL11: =BL9 -> 80.9 | BM11: =BM9 -> 80.9 | BN11: =BO10+BN9 -> 45 | BO11: =BN11+BO9 -> 60
D12: =IF(E12="Mo",WEEKNUM(I12),"") | E12: =TEXT(I12,"TTT") -> Fr | F12: =$F$5 -> 2025 | G12: =$A$10 -> 1 | H12: =H11+1 -> 3 | I12: =DATE(F12,G12,H12) -> 44198 | J12: =IF(OR(G12="",G12=MONTH(I12)),1,0) -> 1 | K12: =IF(OR($E12="Sa",$E12="So",$J12=0),K$4,K$5) -> 7 | L12: =IF(OR($E12="Sa",$E12="So",$J12=0),L$4,L$5) -> 0 | M12: =IF(OR($E12="Sa",$E12="So",$J12=0),M$4,M$5) -> 13 | N12: =IF(OR($E12="Sa",$E12="So",$J12=0),N$4,N$5) -> 0 | O12: =IF(OR($E12="Sa",$E12="So",$J12=0),O$4,O$5) -> 13 | P12: =IF(OR($E12="Sa",$E12="So",$J12=0),P$4,P$5) -> 30 | Q12: =IF(OR($E12="Sa",$E12="So",$J12=0),Q$4,Q$5) -> 15 | R12: =IF(OR($E12="Sa",$E12="So",$J12=0),R$4,R$5) -> 55 | S12: =Q12 -> 15 | T12: =R12 -> 55 | U12: =S12 -> 15 | V12: =T12 -> 55 | W12: =TIME(K12,L12,0) -> 0.29166667 | X12: =TIME(M12,N12,0) -> 0.54166667 | Y12: =TIME(O12,P12,0) -> 0.5625 | Z12: =TIME(Q12,R12,0) -> 0.66319444 | AA12: =TIME(S12,T12,0) -> 0.66319444 | AB12: =TIME(U12,V12,0) -> 0.66319444 | AD12: =IF(J12=0,0,IF(OR(E12="Sa",E12="So"),TIME($AD$4,$AF$4,0),TIME($AD$5,$AF$5,0))) -> 0.35069444 | AF12: =IF(J12=0,0,Z12-W12-(Y12-X12)) -> 0.35069444 | AK12: =IF(AH12=$AH$3,1,0) -> 0 | AL12: =IF(AH12=$AH$7,1,0) -> 0 | AM12: =IF(AI12=$AH$4,1,0) -> 0 | AO12: =IF(OR(AH12=$AH$2,AH12=$AH$5),1,IF(AH12=$AH$6,0.5,0)) -> 0 | AP12: =IF(OR(E12="Sa",E12="So",E12="",J12=0,AH12="FT"),0,1) -> 1 | BL12: =BL9 -> 80.9 | BM12: =BM9 -> 80.9 | BN12: =BO11+BN9 -> 75 | BO12: =BN12+BO9 -> 90
D13: =IF(E13="Mo",WEEKNUM(I13),"") | E13: =TEXT(I13,"TTT") -> Sa | F13: =$F$5 -> 2025 | G13: =$A$10 -> 1 | H13: =H12+1 -> 4 | I13: =DATE(F13,G13,H13) -> 44199 | J13: =IF(OR(G13="",G13=MONTH(I13)),1,0) -> 1 | K13: =IF(OR($E13="Sa",$E13="So",$J13=0),K$4,K$5) -> 0 | L13: =IF(OR($E13="Sa",$E13="So",$J13=0),L$4,L$5) -> 0 | M13: =IF(OR($E13="Sa",$E13="So",$J13=0),M$4,M$5) -> 0 | N13: =IF(OR($E13="Sa",$E13="So",$J13=0),N$4,N$5) -> 0 | O13: =IF(OR($E13="Sa",$E13="So",$J13=0),O$4,O$5) -> 0 | P13: =IF(OR($E13="Sa",$E13="So",$J13=0),P$4,P$5) -> 0 | Q13: =IF(OR($E13="Sa",$E13="So",$J13=0),Q$4,Q$5) -> 0 | R13: =IF(OR($E13="Sa",$E13="So",$J13=0),R$4,R$5) -> 0 | S13: =Q13 -> 0 | T13: =R13 -> 0 | U13: =S13 -> 0 | V13: =T13 -> 0 | W13: =TIME(K13,L13,0) -> 0 | X13: =TIME(M13,N13,0) -> 0 | Y13: =TIME(O13,P13,0) -> 0 | Z13: =TIME(Q13,R13,0) -> 0 | AA13: =TIME(S13,T13,0) -> 0 | AB13: =TIME(U13,V13,0) -> 0 | AD13: =IF(J13=0,0,IF(OR(E13="Sa",E13="So"),TIME($AD$4,$AF$4,0),TIME($AD$5,$AF$5,0))) -> 0 | AF13: =IF(J13=0,0,Z13-W13-(Y13-X13)) -> 0 | AK13: =IF(AH13=$AH$3,1,0) -> 0 | AL13: =IF(AH13=$AH$7,1,0) -> 0 | AM13: =IF(AI13=$AH$4,1,0) -> 0 | AO13: =IF(OR(AH13=$AH$2,AH13=$AH$5),1,IF(AH13=$AH$6,0.5,0)) -> 0 | AP13: =IF(OR(E13="Sa",E13="So",E13="",J13=0,AH13="FT"),0,1) -> 0 | BL13: =BL9 -> 80.9 | BM13: =BM9 -> 80.9 | BN13: =BO12+BN9 -> 105 | BO13: =BN13+BO9 -> 120
D14: =IF(E14="Mo",WEEKNUM(I14),"") | E14: =TEXT(I14,"TTT") -> So | F14: =$F$5 -> 2025 | G14: =$A$10 -> 1 | H14: =H13+1 -> 5 | I14: =DATE(F14,G14,H14) -> 44200 | J14: =IF(OR(G14="",G14=MONTH(I14)),1,0) -> 1 | K14: =IF(OR($E14="Sa",$E14="So",$J14=0),K$4,K$5) -> 0 | L14: =IF(OR($E14="Sa",$E14="So",$J14=0),L$4,L$5) -> 0 | M14: =IF(OR($E14="Sa",$E14="So",$J14=0),M$4,M$5) -> 0 | N14: =IF(OR($E14="Sa",$E14="So",$J14=0),N$4,N$5) -> 0 | O14: =IF(OR($E14="Sa",$E14="So",$J14=0),O$4,O$5) -> 0 | P14: =IF(OR($E14="Sa",$E14="So",$J14=0),P$4,P$5) -> 0 | Q14: =IF(OR($E14="Sa",$E14="So",$J14=0),Q$4,Q$5) -> 0 | R14: =IF(OR($E14="Sa",$E14="So",$J14=0),R$4,R$5) -> 0 | S14: =Q14 -> 0 | T14: =R14 -> 0 | U14: =S14 -> 0 | V14: =T14 -> 0 | W14: =TIME(K14,L14,0) -> 0 | X14: =TIME(M14,N14,0) -> 0 | Y14: =TIME(O14,P14,0) -> 0 | Z14: =TIME(Q14,R14,0) -> 0 | AA14: =TIME(S14,T14,0) -> 0 | AB14: =TIME(U14,V14,0) -> 0 | AD14: =IF(J14=0,0,IF(OR(E14="Sa",E14="So"),TIME($AD$4,$AF$4,0),TIME($AD$5,$AF$5,0))) -> 0 | AF14: =IF(J14=0,0,Z14-W14-(Y14-X14)) -> 0 | AK14: =IF(AH14=$AH$3,1,0) -> 0 | AL14: =IF(AH14=$AH$7,1,0) -> 0 | AM14: =IF(AI14=$AH$4,1,0) -> 0 | AO14: =IF(OR(AH14=$AH$2,AH14=$AH$5),1,IF(AH14=$AH$6,0.5,0)) -> 0 | AP14: =IF(OR(E14="Sa",E14="So",E14="",J14=0,AH14="FT"),0,1) -> 0 | BL14: =BL9 -> 80.9 | BM14: =BM9 -> 80.9 | BN14: =BO13+BN9 -> 135 | BO14: =BN14+BO9 -> 150
D15: =IF(E15="Mo",WEEKNUM(I15),"") -> 2 | E15: =TEXT(I15,"TTT") -> Mo | F15: =$F$5 -> 2025 | G15: =$A$10 -> 1 | H15: =H14+1 -> 6 | I15: =DATE(F15,G15,H15) -> 44201 | J15: =IF(OR(G15="",G15=MONTH(I15)),1,0) -> 1 | K15: =IF(OR($E15="Sa",$E15="So",$J15=0),K$4,K$5) -> 7 | L15: =IF(OR($E15="Sa",$E15="So",$J15=0),L$4,L$5) -> 0 | M15: =IF(OR($E15="Sa",$E15="So",$J15=0),M$4,M$5) -> 13 | N15: =IF(OR($E15="Sa",$E15="So",$J15=0),N$4,N$5) -> 0 | O15: =IF(OR($E15="Sa",$E15="So",$J15=0),O$4,O$5) -> 13 | P15: =IF(OR($E15="Sa",$E15="So",$J15=0),P$4,P$5) -> 30 | Q15: =IF(OR($E15="Sa",$E15="So",$J15=0),Q$4,Q$5) -> 15 | R15: =IF(OR($E15="Sa",$E15="So",$J15=0),R$4,R$5) -> 55 | S15: =Q15 -> 15 | T15: =R15 -> 55 | U15: =S15 -> 15 | V15: =T15 -> 55 | W15: =TIME(K15,L15,0) -> 0.29166667 | X15: =TIME(M15,N15,0) -> 0.54166667 | Y15: =TIME(O15,P15,0) -> 0.5625 | Z15: =TIME(Q15,R15,0) -> 0.66319444 | AA15: =TIME(S15,T15,0) -> 0.66319444 | AB15: =TIME(U15,V15,0) -> 0.66319444 | AD15: =IF(J15=0,0,IF(OR(E15="Sa",E15="So"),TIME($AD$4,$AF$4,0),TIME($AD$5,$AF$5,0))) -> 0.35069444 | AF15: =IF(J15=0,0,Z15-W15-(Y15-X15)) -> 0.35069444 | AK15: =IF(AH15=$AH$3,1,0) -> 0 | AL15: =IF(AH15=$AH$7,1,0) -> 0 | AM15: =IF(AI15=$AH$4,1,0) -> 0 | AO15: =IF(OR(AH15=$AH$2,AH15=$AH$5),1,IF(AH15=$AH$6,0.5,0)) -> 0 | AP15: =IF(OR(E15="Sa",E15="So",E15="",J15=0,AH15="FT"),0,1) -> 1 | BL15: WGTST | BM15: =SUM(BL10:BL14)+SUM(BM10:BM14) -> 809 | BN15: ECO | BO15: ECO
D16: =IF(E16="Mo",WEEKNUM(I16),"") | E16: =TEXT(I16,"TTT") -> Di | F16: =$F$5 -> 2025 | G16: =$A$10 -> 1 | H16: =H15+1 -> 7 | I16: =DATE(F16,G16,H16) -> 44202 | J16: =IF(OR(G16="",G16=MONTH(I16)),1,0) -> 1 | K16: =IF(OR($E16="Sa",$E16="So",$J16=0),K$4,K$5) -> 7 | L16: =IF(OR($E16="Sa",$E16="So",$J16=0),L$4,L$5) -> 0 | M16: =IF(OR($E16="Sa",$E16="So",$J16=0),M$4,M$5) -> 13 | N16: =IF(OR($E16="Sa",$E16="So",$J16=0),N$4,N$5) -> 0 | O16: =IF(OR($E16="Sa",$E16="So",$J16=0),O$4,O$5) -> 13 | P16: =IF(OR($E16="Sa",$E16="So",$J16=0),P$4,P$5) -> 30 | Q16: =IF(OR($E16="Sa",$E16="So",$J16=0),Q$4,Q$5) -> 15 | R16: =IF(OR($E16="Sa",$E16="So",$J16=0),R$4,R$5) -> 55 | S16: =Q16 -> 15 | T16: =R16 -> 55 | U16: =S16 -> 15 | V16: =T16 -> 55 | W16: =TIME(K16,L16,0) -> 0.29166667 | X16: =TIME(M16,N16,0) -> 0.54166667 | Y16: =TIME(O16,P16,0) -> 0.5625 | Z16: =TIME(Q16,R16,0) -> 0.66319444 | AA16: =TIME(S16,T16,0) -> 0.66319444 | AB16: =TIME(U16,V16,0) -> 0.66319444 | AD16: =IF(J16=0,0,IF(OR(E16="Sa",E16="So"),TIME($AD$4,$AF$4,0),TIME($AD$5,$AF$5,0))) -> 0.35069444 | AF16: =IF(J16=0,0,Z16-W16-(Y16-X16)) -> 0.35069444 | AK16: =IF(AH16=$AH$3,1,0) -> 0 | AL16: =IF(AH16=$AH$7,1,0) -> 0 | AM16: =IF(AI16=$AH$4,1,0) -> 0 | AO16: =IF(OR(AH16=$AH$2,AH16=$AH$5),1,IF(AH16=$AH$6,0.5,0)) -> 0 | AP16: =IF(OR(E16="Sa",E16="So",E16="",J16=0,AH16="FT"),0,1) -> 1 | BL16: =INDEX($BF$2:$BG$8,MATCH(BL15,$BF$2:$BF$8,0),2) -> 80.9 | BM16: =INDEX($BF$2:$BG$8,MATCH(BL15,$BF$2:$BF$8,0),2) -> 80.9 | BN16: 15 | BO16: 15
D17: =IF(E17="Mo",WEEKNUM(I17),"") | E17: =TEXT(I17,"TTT") -> Mi | F17: =$F$5 -> 2025 | G17: =$A$10 -> 1 | H17: =H16+1 -> 8 | I17: =DATE(F17,G17,H17) -> 44203 | J17: =IF(OR(G17="",G17=MONTH(I17)),1,0) -> 1 | K17: =IF(OR($E17="Sa",$E17="So",$J17=0),K$4,K$5) -> 7 | L17: =IF(OR($E17="Sa",$E17="So",$J17=0),L$4,L$5) -> 0 | M17: =IF(OR($E17="Sa",$E17="So",$J17=0),M$4,M$5) -> 13 | N17: =IF(OR($E17="Sa",$E17="So",$J17=0),N$4,N$5) -> 0 | O17: =IF(OR($E17="Sa",$E17="So",$J17=0),O$4,O$5) -> 13 | P17: =IF(OR($E17="Sa",$E17="So",$J17=0),P$4,P$5) -> 30 | Q17: =IF(OR($E17="Sa",$E17="So",$J17=0),Q$4,Q$5) -> 15 | R17: =IF(OR($E17="Sa",$E17="So",$J17=0),R$4,R$5) -> 55 | S17: =Q17 -> 15 | T17: =R17 -> 55 | U17: =S17 -> 15 | V17: =T17 -> 55 | W17: =TIME(K17,L17,0) -> 0.29166667 | X17: =TIME(M17,N17,0) -> 0.54166667 | Y17: =TIME(O17,P17,0) -> 0.5625 | Z17: =TIME(Q17,R17,0) -> 0.66319444 | AA17: =TIME(S17,T17,0) -> 0.66319444 | AB17: =TIME(U17,V17,0) -> 0.66319444 | AD17: =IF(J17=0,0,IF(OR(E17="Sa",E17="So"),TIME($AD$4,$AF$4,0),TIME($AD$5,$AF$5,0))) -> 0.35069444 | AF17: =IF(J17=0,0,Z17-W17-(Y17-X17)) -> 0.35069444 | AK17: =IF(AH17=$AH$3,1,0) -> 0 | AL17: =IF(AH17=$AH$7,1,0) -> 0 | AM17: =IF(AI17=$AH$4,1,0) -> 0 | AO17: =IF(OR(AH17=$AH$2,AH17=$AH$5),1,IF(AH17=$AH$6,0.5,0)) -> 0 | AP17: =IF(OR(E17="Sa",E17="So",E17="",J17=0,AH17="FT"),0,1) -> 1 | BL17: =BL16 -> 80.9 | BM17: =BM16 -> 80.9 | BN17: =BN16 -> 15 | BO17: =BN17+BO16 -> 30
D18: =IF(E18="Mo",WEEKNUM(I18),"") | E18: =TEXT(I18,"TTT") -> Do | F18: =$F$5 -> 2025 | G18: =$A$10 -> 1 | H18: =H17+1 -> 9 | I18: =DATE(F18,G18,H18) -> 44204 | J18: =IF(OR(G18="",G18=MONTH(I18)),1,0) -> 1 | K18: =IF(OR($E18="Sa",$E18="So",$J18=0),K$4,K$5) -> 7 | L18: =IF(OR($E18="Sa",$E18="So",$J18=0),L$4,L$5) -> 0 | M18: =IF(OR($E18="Sa",$E18="So",$J18=0),M$4,M$5) -> 13 | N18: =IF(OR($E18="Sa",$E18="So",$J18=0),N$4,N$5) -> 0 | O18: =IF(OR($E18="Sa",$E18="So",$J18=0),O$4,O$5) -> 13 | P18: =IF(OR($E18="Sa",$E18="So",$J18=0),P$4,P$5) -> 30 | Q18: =IF(OR($E18="Sa",$E18="So",$J18=0),Q$4,Q$5) -> 15 | R18: =IF(OR($E18="Sa",$E18="So",$J18=0),R$4,R$5) -> 55 | S18: =Q18 -> 15 | T18: =R18 -> 55 | U18: =S18 -> 15 | V18: =T18 -> 55 | W18: =TIME(K18,L18,0) -> 0.29166667 | X18: =TIME(M18,N18,0) -> 0.54166667 | Y18: =TIME(O18,P18,0) -> 0.5625 | Z18: =TIME(Q18,R18,0) -> 0.66319444 | AA18: =TIME(S18,T18,0) -> 0.66319444 | AB18: =TIME(U18,V18,0) -> 0.66319444 | AD18: =IF(J18=0,0,IF(OR(E18="Sa",E18="So"),TIME($AD$4,$AF$4,0),TIME($AD$5,$AF$5,0))) -> 0.35069444 | AF18: =IF(J18=0,0,Z18-W18-(Y18-X18)) -> 0.35069444 | AK18: =IF(AH18=$AH$3,1,0) -> 0 | AL18: =IF(AH18=$AH$7,1,0) -> 0 | AM18: =IF(AI18=$AH$4,1,0) -> 0 | AO18: =IF(OR(AH18=$AH$2,AH18=$AH$5),1,IF(AH18=$AH$6,0.5,0)) -> 0 | AP18: =IF(OR(E18="Sa",E18="So",E18="",J18=0,AH18="FT"),0,1) -> 1 | BL18: =BL16 -> 80.9 | BM18: =BM16 -> 80.9 | BN18: =BO17+BN16 -> 45 | BO18: =BN18+BO16 -> 60
D19: =IF(E19="Mo",WEEKNUM(I19),"") | E19: =TEXT(I19,"TTT") -> Fr | F19: =$F$5 -> 2025 | G19: =$A$10 -> 1 | H19: =H18+1 -> 10 | I19: =DATE(F19,G19,H19) -> 44205 | J19: =IF(OR(G19="",G19=MONTH(I19)),1,0) -> 1 | K19: =IF(OR($E19="Sa",$E19="So",$J19=0),K$4,K$5) -> 7 | L19: =IF(OR($E19="Sa",$E19="So",$J19=0),L$4,L$5) -> 0 | M19: =IF(OR($E19="Sa",$E19="So",$J19=0),M$4,M$5) -> 13 | N19: =IF(OR($E19="Sa",$E19="So",$J19=0),N$4,N$5) -> 0 | O19: =IF(OR($E19="Sa",$E19="So",$J19=0),O$4,O$5) -> 13 | P19: =IF(OR($E19="Sa",$E19="So",$J19=0),P$4,P$5) -> 30 | Q19: =IF(OR($E19="Sa",$E19="So",$J19=0),Q$4,Q$5) -> 15 | R19: =IF(OR($E19="Sa",$E19="So",$J19=0),R$4,R$5) -> 55 | S19: =Q19 -> 15 | T19: =R19 -> 55 | U19: =S19 -> 15 | V19: =T19 -> 55 | W19: =TIME(K19,L19,0) -> 0.29166667 | X19: =TIME(M19,N19,0) -> 0.54166667 | Y19: =TIME(O19,P19,0) -> 0.5625 | Z19: =TIME(Q19,R19,0) -> 0.66319444 | AA19: =TIME(S19,T19,0) -> 0.66319444 | AB19: =TIME(U19,V19,0) -> 0.66319444 | AD19: =IF(J19=0,0,IF(OR(E19="Sa",E19="So"),TIME($AD$4,$AF$4,0),TIME($AD$5,$AF$5,0))) -> 0.35069444 | AF19: =IF(J19=0,0,Z19-W19-(Y19-X19)) -> 0.35069444 | AK19: =IF(AH19=$AH$3,1,0) -> 0 | AL19: =IF(AH19=$AH$7,1,0) -> 0 | AM19: =IF(AI19=$AH$4,1,0) -> 0 | AO19: =IF(OR(AH19=$AH$2,AH19=$AH$5),1,IF(AH19=$AH$6,0.5,0)) -> 0 | AP19: =IF(OR(E19="Sa",E19="So",E19="",J19=0,AH19="FT"),0,1) -> 1 | BL19: =BL16 -> 80.9 | BM19: =BM16 -> 80.9 | BN19: =BO18+BN16 -> 75 | BO19: =BN19+BO16 -> 90
D20: =IF(E20="Mo",WEEKNUM(I20),"") | E20: =TEXT(I20,"TTT") -> Sa | F20: =$F$5 -> 2025 | G20: =$A$10 -> 1 | H20: =H19+1 -> 11 | I20: =DATE(F20,G20,H20) -> 44206 | J20: =IF(OR(G20="",G20=MONTH(I20)),1,0) -> 1 | K20: =IF(OR($E20="Sa",$E20="So",$J20=0),K$4,K$5) -> 0 | L20: =IF(OR($E20="Sa",$E20="So",$J20=0),L$4,L$5) -> 0 | M20: =IF(OR($E20="Sa",$E20="So",$J20=0),M$4,M$5) -> 0 | N20: =IF(OR($E20="Sa",$E20="So",$J20=0),N$4,N$5) -> 0 | O20: =IF(OR($E20="Sa",$E20="So",$J20=0),O$4,O$5) -> 0 | P20: =IF(OR($E20="Sa",$E20="So",$J20=0),P$4,P$5) -> 0 | Q20: =IF(OR($E20="Sa",$E20="So",$J20=0),Q$4,Q$5) -> 0 | R20: =IF(OR($E20="Sa",$E20="So",$J20=0),R$4,R$5) -> 0 | S20: =Q20 -> 0 | T20: =R20 -> 0 | U20: =S20 -> 0 | V20: =T20 -> 0 | W20: =TIME(K20,L20,0) -> 0 | X20: =TIME(M20,N20,0) -> 0 | Y20: =TIME(O20,P20,0) -> 0 | Z20: =TIME(Q20,R20,0) -> 0 | AA20: =TIME(S20,T20,0) -> 0 | AB20: =TIME(U20,V20,0) -> 0 | AD20: =IF(J20=0,0,IF(OR(E20="Sa",E20="So"),TIME($AD$4,$AF$4,0),TIME($AD$5,$AF$5,0))) -> 0 | AF20: =IF(J20=0,0,Z20-W20-(Y20-X20)) -> 0 | AK20: =IF(AH20=$AH$3,1,0) -> 0 | AL20: =IF(AH20=$AH$7,1,0) -> 0 | AM20: =IF(AI20=$AH$4,1,0) -> 0 | AO20: =IF(OR(AH20=$AH$2,AH20=$AH$5),1,IF(AH20=$AH$6,0.5,0)) -> 0 | AP20: =IF(OR(E20="Sa",E20="So",E20="",J20=0,AH20="FT"),0,1) -> 0 | BL20: =BL16 -> 80.9 | BM20: =BM16 -> 80.9 | BN20: =BO19+BN16 -> 105 | BO20: =BN20+BO16 -> 120
D21: =IF(E21="Mo",WEEKNUM(I21),"") | E21: =TEXT(I21,"TTT") -> So | F21: =$F$5 -> 2025 | G21: =$A$10 -> 1 | H21: =H20+1 -> 12 | I21: =DATE(F21,G21,H21) -> 44207 | J21: =IF(OR(G21="",G21=MONTH(I21)),1,0) -> 1 | K21: =IF(OR($E21="Sa",$E21="So",$J21=0),K$4,K$5) -> 0 | L21: =IF(OR($E21="Sa",$E21="So",$J21=0),L$4,L$5) -> 0 | M21: =IF(OR($E21="Sa",$E21="So",$J21=0),M$4,M$5) -> 0 | N21: =IF(OR($E21="Sa",$E21="So",$J21=0),N$4,N$5) -> 0 | O21: =IF(OR($E21="Sa",$E21="So",$J21=0),O$4,O$5) -> 0 | P21: =IF(OR($E21="Sa",$E21="So",$J21=0),P$4,P$5) -> 0 | Q21: =IF(OR($E21="Sa",$E21="So",$J21=0),Q$4,Q$5) -> 0 | R21: =IF(OR($E21="Sa",$E21="So",$J21=0),R$4,R$5) -> 0 | S21: =Q21 -> 0 | T21: =R21 -> 0 | U21: =S21 -> 0 | V21: =T21 -> 0 | W21: =TIME(K21,L21,0) -> 0 | X21: =TIME(M21,N21,0) -> 0 | Y21: =TIME(O21,P21,0) -> 0 | Z21: =TIME(Q21,R21,0) -> 0 | AA21: =TIME(S21,T21,0) -> 0 | AB21: =TIME(U21,V21,0) -> 0 | AD21: =IF(J21=0,0,IF(OR(E21="Sa",E21="So"),TIME($AD$4,$AF$4,0),TIME($AD$5,$AF$5,0))) -> 0 | AF21: =IF(J21=0,0,Z21-W21-(Y21-X21)) -> 0 | AK21: =IF(AH21=$AH$3,1,0) -> 0 | AL21: =IF(AH21=$AH$7,1,0) -> 0 | AM21: =IF(AI21=$AH$4,1,0) -> 0 | AO21: =IF(OR(AH21=$AH$2,AH21=$AH$5),1,IF(AH21=$AH$6,0.5,0)) -> 0 | AP21: =IF(OR(E21="Sa",E21="So",E21="",J21=0,AH21="FT"),0,1) -> 0 | BL21: =BL16 -> 80.9 | BM21: =BM16 -> 80.9 | BN21: =BO20+BN16 -> 135 | BO21: =BN21+BO16 -> 150
D22: =IF(E22="Mo",WEEKNUM(I22),"") -> 3 | E22: =TEXT(I22,"TTT") -> Mo | F22: =$F$5 -> 2025 | G22: =$A$10 -> 1 | H22: =H21+1 -> 13 | I22: =DATE(F22,G22,H22) -> 44208 | J22: =IF(OR(G22="",G22=MONTH(I22)),1,0) -> 1 | K22: =IF(OR($E22="Sa",$E22="So",$J22=0),K$4,K$5) -> 7 | L22: =IF(OR($E22="Sa",$E22="So",$J22=0),L$4,L$5) -> 0 | M22: =IF(OR($E22="Sa",$E22="So",$J22=0),M$4,M$5) -> 13 | N22: =IF(OR($E22="Sa",$E22="So",$J22=0),N$4,N$5) -> 0 | O22: =IF(OR($E22="Sa",$E22="So",$J22=0),O$4,O$5) -> 13 | P22: =IF(OR($E22="Sa",$E22="So",$J22=0),P$4,P$5) -> 30 | Q22: =IF(OR($E22="Sa",$E22="So",$J22=0),Q$4,Q$5) -> 15 | R22: =IF(OR($E22="Sa",$E22="So",$J22=0),R$4,R$5) -> 55 | S22: =Q22 -> 15 | T22: =R22 -> 55 | U22: =S22 -> 15 | V22: =T22 -> 55 | W22: =TIME(K22,L22,0) -> 0.29166667 | X22: =TIME(M22,N22,0) -> 0.54166667 | Y22: =TIME(O22,P22,0) -> 0.5625 | Z22: =TIME(Q22,R22,0) -> 0.66319444 | AA22: =TIME(S22,T22,0) -> 0.66319444 | AB22: =TIME(U22,V22,0) -> 0.66319444 | AD22: =IF(J22=0,0,IF(OR(E22="Sa",E22="So"),TIME($AD$4,$AF$4,0),TIME($AD$5,$AF$5,0))) -> 0.35069444 | AF22: =IF(J22=0,0,Z22-W22-(Y22-X22)) -> 0.35069444 | AK22: =IF(AH22=$AH$3,1,0) -> 0 | AL22: =IF(AH22=$AH$7,1,0) -> 0 | AM22: =IF(AI22=$AH$4,1,0) -> 0 | AO22: =IF(OR(AH22=$AH$2,AH22=$AH$5),1,IF(AH22=$AH$6,0.5,0)) -> 0 | AP22: =IF(OR(E22="Sa",E22="So",E22="",J22=0,AH22="FT"),0,1) -> 1 | BG22: WGTST | BI22: ECO | BJ22: ECO | BL22: 60 | BM22: =SUM(BL17:BL21)+SUM(BM17:BM21) -> 809
D23: =IF(E23="Mo",WEEKNUM(I23),"") | E23: =TEXT(I23,"TTT") -> Di | F23: =$F$5 -> 2025 | G23: =$A$10 -> 1 | H23: =H22+1 -> 14 | I23: =DATE(F23,G23,H23) -> 44209 | J23: =IF(OR(G23="",G23=MONTH(I23)),1,0) -> 1 | K23: =IF(OR($E23="Sa",$E23="So",$J23=0),K$4,K$5) -> 7 | L23: =IF(OR($E23="Sa",$E23="So",$J23=0),L$4,L$5) -> 0 | M23: =IF(OR($E23="Sa",$E23="So",$J23=0),M$4,M$5) -> 13 | N23: =IF(OR($E23="Sa",$E23="So",$J23=0),N$4,N$5) -> 0 | O23: =IF(OR($E23="Sa",$E23="So",$J23=0),O$4,O$5) -> 13 | P23: =IF(OR($E23="Sa",$E23="So",$J23=0),P$4,P$5) -> 30 | Q23: =IF(OR($E23="Sa",$E23="So",$J23=0),Q$4,Q$5) -> 15 | R23: =IF(OR($E23="Sa",$E23="So",$J23=0),R$4,R$5) -> 55 | S23: =Q23 -> 15 | T23: =R23 -> 55 | U23: =S23 -> 15 | V23: =T23 -> 55 | W23: =TIME(K23,L23,0) -> 0.29166667 | X23: =TIME(M23,N23,0) -> 0.54166667 | Y23: =TIME(O23,P23,0) -> 0.5625 | Z23: =TIME(Q23,R23,0) -> 0.66319444 | AA23: =TIME(S23,T23,0) -> 0.66319444 | AB23: =TIME(U23,V23,0) -> 0.66319444 | AD23: =IF(J23=0,0,IF(OR(E23="Sa",E23="So"),TIME($AD$4,$AF$4,0),TIME($AD$5,$AF$5,0))) -> 0.35069444 | AF23: =IF(J23=0,0,Z23-W23-(Y23-X23)) -> 0.35069444 | AK23: =IF(AH23=$AH$3,1,0) -> 0 | AL23: =IF(AH23=$AH$7,1,0) -> 0 | AM23: =IF(AI23=$AH$4,1,0) -> 0 | AO23: =IF(OR(AH23=$AH$2,AH23=$AH$5),1,IF(AH23=$AH$6,0.5,0)) -> 0 | AP23: =IF(OR(E23="Sa",E23="So",E23="",J23=0,AH23="FT"),0,1) -> 1 | BG23: =INDEX($BF$2:$BG$8,MATCH(BG22,$BF$2:$BF$8,0),2) -> 80.9 | BH23: =INDEX($BF$2:$BG$8,MATCH(BG22,$BF$2:$BF$8,0),2) -> 80.9 | BI23: 15 | BJ23: 15 | BL23: =BM23/BL22 -> 26.966667 | BM23: =SUM(BM15,BM22) -> 1618
D24: =IF(E24="Mo",WEEKNUM(I24),"") | E24: =TEXT(I24,"TTT") -> Mi | F24: =$F$5 -> 2025 | G24: =$A$10 -> 1 | H24: =H23+1 -> 15 | I24: =DATE(F24,G24,H24) -> 44210 | J24: =IF(OR(G24="",G24=MONTH(I24)),1,0) -> 1 | K24: =IF(OR($E24="Sa",$E24="So",$J24=0),K$4,K$5) -> 7 | L24: =IF(OR($E24="Sa",$E24="So",$J24=0),L$4,L$5) -> 0 | M24: =IF(OR($E24="Sa",$E24="So",$J24=0),M$4,M$5) -> 13 | N24: =IF(OR($E24="Sa",$E24="So",$J24=0),N$4,N$5) -> 0 | O24: =IF(OR($E24="Sa",$E24="So",$J24=0),O$4,O$5) -> 13 | P24: =IF(OR($E24="Sa",$E24="So",$J24=0),P$4,P$5) -> 30 | Q24: =IF(OR($E24="Sa",$E24="So",$J24=0),Q$4,Q$5) -> 15 | R24: =IF(OR($E24="Sa",$E24="So",$J24=0),R$4,R$5) -> 55 | S24: =Q24 -> 15 | T24: =R24 -> 55 | U24: =S24 -> 15 | V24: =T24 -> 55 | W24: =TIME(K24,L24,0) -> 0.29166667 | X24: =TIME(M24,N24,0) -> 0.54166667 | Y24: =TIME(O24,P24,0) -> 0.5625 | Z24: =TIME(Q24,R24,0) -> 0.66319444 | AA24: =TIME(S24,T24,0) -> 0.66319444 | AB24: =TIME(U24,V24,0) -> 0.66319444 | AD24: =IF(J24=0,0,IF(OR(E24="Sa",E24="So"),TIME($AD$4,$AF$4,0),TIME($AD$5,$AF$5,0))) -> 0.35069444 | AF24: =IF(J24=0,0,Z24-W24-(Y24-X24)) -> 0.35069444 | AK24: =IF(AH24=$AH$3,1,0) -> 0 | AL24: =IF(AH24=$AH$7,1,0) -> 0 | AM24: =IF(AI24=$AH$4,1,0) -> 0 | AO24: =IF(OR(AH24=$AH$2,AH24=$AH$5),1,IF(AH24=$AH$6,0.5,0)) -> 0 | AP24: =IF(OR(E24="Sa",E24="So",E24="",J24=0,AH24="FT"),0,1) -> 1 | BG24: =BG23 -> 80.9 | BH24: =BH23 -> 80.9 | BI24: =BI23 -> 15 | BJ24: =BI24+BJ23 -> 30 | BL24: =100*BL22/BM23 -> 3.7082818
D25: =IF(E25="Mo",WEEKNUM(I25),"") | E25: =TEXT(I25,"TTT") -> Do | F25: =$F$5 -> 2025 | G25: =$A$10 -> 1 | H25: =H24+1 -> 16 | I25: =DATE(F25,G25,H25) -> 44211 | J25: =IF(OR(G25="",G25=MONTH(I25)),1,0) -> 1 | K25: =IF(OR($E25="Sa",$E25="So",$J25=0),K$4,K$5) -> 7 | L25: =IF(OR($E25="Sa",$E25="So",$J25=0),L$4,L$5) -> 0 | M25: =IF(OR($E25="Sa",$E25="So",$J25=0),M$4,M$5) -> 13 | N25: =IF(OR($E25="Sa",$E25="So",$J25=0),N$4,N$5) -> 0 | O25: =IF(OR($E25="Sa",$E25="So",$J25=0),O$4,O$5) -> 13 | P25: =IF(OR($E25="Sa",$E25="So",$J25=0),P$4,P$5) -> 30 | Q25: =IF(OR($E25="Sa",$E25="So",$J25=0),Q$4,Q$5) -> 15 | R25: =IF(OR($E25="Sa",$E25="So",$J25=0),R$4,R$5) -> 55 | S25: =Q25 -> 15 | T25: =R25 -> 55 | U25: =S25 -> 15 | V25: =T25 -> 55 | W25: =TIME(K25,L25,0) -> 0.29166667 | X25: =TIME(M25,N25,0) -> 0.54166667 | Y25: =TIME(O25,P25,0) -> 0.5625 | Z25: =TIME(Q25,R25,0) -> 0.66319444 | AA25: =TIME(S25,T25,0) -> 0.66319444 | AB25: =TIME(U25,V25,0) -> 0.66319444 | AD25: =IF(J25=0,0,IF(OR(E25="Sa",E25="So"),TIME($AD$4,$AF$4,0),TIME($AD$5,$AF$5,0))) -> 0.35069444 | AF25: =IF(J25=0,0,Z25-W25-(Y25-X25)) -> 0.35069444 | AK25: =IF(AH25=$AH$3,1,0) -> 0 | AL25: =IF(AH25=$AH$7,1,0) -> 0 | AM25: =IF(AI25=$AH$4,1,0) -> 0 | AO25: =IF(OR(AH25=$AH$2,AH25=$AH$5),1,IF(AH25=$AH$6,0.5,0)) -> 0 | AP25: =IF(OR(E25="Sa",E25="So",E25="",J25=0,AH25="FT"),0,1) -> 1 | BG25: =BG23 -> 80.9 | BH25: =BH23 -> 80.9 | BI25: =BJ24+BI23 -> 45 | BJ25: =BI25+BJ23 -> 60
D26: =IF(E26="Mo",WEEKNUM(I26),"") | E26: =TEXT(I26,"TTT") -> Fr | F26: =$F$5 -> 2025 | G26: =$A$10 -> 1 | H26: =H25+1 -> 17 | I26: =DATE(F26,G26,H26) -> 44212 | J26: =IF(OR(G26="",G26=MONTH(I26)),1,0) -> 1 | K26: =IF(OR($E26="Sa",$E26="So",$J26=0),K$4,K$5) -> 7 | L26: =IF(OR($E26="Sa",$E26="So",$J26=0),L$4,L$5) -> 0 | M26: =IF(OR($E26="Sa",$E26="So",$J26=0),M$4,M$5) -> 13 | N26: =IF(OR($E26="Sa",$E26="So",$J26=0),N$4,N$5) -> 0 | O26: =IF(OR($E26="Sa",$E26="So",$J26=0),O$4,O$5) -> 13 | P26: =IF(OR($E26="Sa",$E26="So",$J26=0),P$4,P$5) -> 30 | Q26: =IF(OR($E26="Sa",$E26="So",$J26=0),Q$4,Q$5) -> 15 | R26: =IF(OR($E26="Sa",$E26="So",$J26=0),R$4,R$5) -> 55 | S26: =Q26 -> 15 | T26: =R26 -> 55 | U26: =S26 -> 15 | V26: =T26 -> 55 | W26: =TIME(K26,L26,0) -> 0.29166667 | X26: =TIME(M26,N26,0) -> 0.54166667 | Y26: =TIME(O26,P26,0) -> 0.5625 | Z26: =TIME(Q26,R26,0) -> 0.66319444 | AA26: =TIME(S26,T26,0) -> 0.66319444 | AB26: =TIME(U26,V26,0) -> 0.66319444 | AD26: =IF(J26=0,0,IF(OR(E26="Sa",E26="So"),TIME($AD$4,$AF$4,0),TIME($AD$5,$AF$5,0))) -> 0.35069444 | AF26: =IF(J26=0,0,Z26-W26-(Y26-X26)) -> 0.35069444 | AK26: =IF(AH26=$AH$3,1,0) -> 0 | AL26: =IF(AH26=$AH$7,1,0) -> 0 | AM26: =IF(AI26=$AH$4,1,0) -> 0 | AO26: =IF(OR(AH26=$AH$2,AH26=$AH$5),1,IF(AH26=$AH$6,0.5,0)) -> 0 | AP26: =IF(OR(E26="Sa",E26="So",E26="",J26=0,AH26="FT"),0,1) -> 1 | BG26: =BG23 -> 80.9 | BH26: =BH23 -> 80.9 | BI26: =BJ25+BI23 -> 75 | BJ26: =BI26+BJ23 -> 90
D27: =IF(E27="Mo",WEEKNUM(I27),"") | E27: =TEXT(I27,"TTT") -> Sa | F27: =$F$5 -> 2025 | G27: =$A$10 -> 1 | H27: =H26+1 -> 18 | I27: =DATE(F27,G27,H27) -> 44213 | J27: =IF(OR(G27="",G27=MONTH(I27)),1,0) -> 1 | K27: =IF(OR($E27="Sa",$E27="So",$J27=0),K$4,K$5) -> 0 | L27: =IF(OR($E27="Sa",$E27="So",$J27=0),L$4,L$5) -> 0 | M27: =IF(OR($E27="Sa",$E27="So",$J27=0),M$4,M$5) -> 0 | N27: =IF(OR($E27="Sa",$E27="So",$J27=0),N$4,N$5) -> 0 | O27: =IF(OR($E27="Sa",$E27="So",$J27=0),O$4,O$5) -> 0 | P27: =IF(OR($E27="Sa",$E27="So",$J27=0),P$4,P$5) -> 0 | Q27: =IF(OR($E27="Sa",$E27="So",$J27=0),Q$4,Q$5) -> 0 | R27: =IF(OR($E27="Sa",$E27="So",$J27=0),R$4,R$5) -> 0 | S27: =Q27 -> 0 | T27: =R27 -> 0 | U27: =S27 -> 0 | V27: =T27 -> 0 | W27: =TIME(K27,L27,0) -> 0 | X27: =TIME(M27,N27,0) -> 0 | Y27: =TIME(O27,P27,0) -> 0 | Z27: =TIME(Q27,R27,0) -> 0 | AA27: =TIME(S27,T27,0) -> 0 | AB27: =TIME(U27,V27,0) -> 0 | AD27: =IF(J27=0,0,IF(OR(E27="Sa",E27="So"),TIME($AD$4,$AF$4,0),TIME($AD$5,$AF$5,0))) -> 0 | AF27: =IF(J27=0,0,Z27-W27-(Y27-X27)) -> 0 | AK27: =IF(AH27=$AH$3,1,0) -> 0 | AL27: =IF(AH27=$AH$7,1,0) -> 0 | AM27: =IF(AI27=$AH$4,1,0) -> 0 | AO27: =IF(OR(AH27=$AH$2,AH27=$AH$5),1,IF(AH27=$AH$6,0.5,0)) -> 0 | AP27: =IF(OR(E27="Sa",E27="So",E27="",J27=0,AH27="FT"),0,1) -> 0 | BG27: =BG23 -> 80.9 | BH27: =BH23 -> 80.9 | BI27: =BJ26+BI23 -> 105 | BJ27: =BI27+BJ23 -> 120
D28: =IF(E28="Mo",WEEKNUM(I28),"") | E28: =TEXT(I28,"TTT") -> So | F28: =$F$5 -> 2025 | G28: =$A$10 -> 1 | H28: =H27+1 -> 19 | I28: =DATE(F28,G28,H28) -> 44214 | J28: =IF(OR(G28="",G28=MONTH(I28)),1,0) -> 1 | K28: =IF(OR($E28="Sa",$E28="So",$J28=0),K$4,K$5) -> 0 | L28: =IF(OR($E28="Sa",$E28="So",$J28=0),L$4,L$5) -> 0 | M28: =IF(OR($E28="Sa",$E28="So",$J28=0),M$4,M$5) -> 0 | N28: =IF(OR($E28="Sa",$E28="So",$J28=0),N$4,N$5) -> 0 | O28: =IF(OR($E28="Sa",$E28="So",$J28=0),O$4,O$5) -> 0 | P28: =IF(OR($E28="Sa",$E28="So",$J28=0),P$4,P$5) -> 0 | Q28: =IF(OR($E28="Sa",$E28="So",$J28=0),Q$4,Q$5) -> 0 | R28: =IF(OR($E28="Sa",$E28="So",$J28=0),R$4,R$5) -> 0 | S28: =Q28 -> 0 | T28: =R28 -> 0 | U28: =S28 -> 0 | V28: =T28 -> 0 | W28: =TIME(K28,L28,0) -> 0 | X28: =TIME(M28,N28,0) -> 0 | Y28: =TIME(O28,P28,0) -> 0 | Z28: =TIME(Q28,R28,0) -> 0 | AA28: =TIME(S28,T28,0) -> 0 | AB28: =TIME(U28,V28,0) -> 0 | AD28: =IF(J28=0,0,IF(OR(E28="Sa",E28="So"),TIME($AD$4,$AF$4,0),TIME($AD$5,$AF$5,0))) -> 0 | AF28: =IF(J28=0,0,Z28-W28-(Y28-X28)) -> 0 | AK28: =IF(AH28=$AH$3,1,0) -> 0 | AL28: =IF(AH28=$AH$7,1,0) -> 0 | AM28: =IF(AI28=$AH$4,1,0) -> 0 | AO28: =IF(OR(AH28=$AH$2,AH28=$AH$5),1,IF(AH28=$AH$6,0.5,0)) -> 0 | AP28: =IF(OR(E28="Sa",E28="So",E28="",J28=0,AH28="FT"),0,1) -> 0 | BG28: =BG23 -> 80.9 | BH28: =BH23 -> 80.9 | BI28: =BJ27+BI23 -> 135 | BJ28: =BI28+BJ23 -> 150
D29: =IF(E29="Mo",WEEKNUM(I29),"") -> 4 | E29: =TEXT(I29,"TTT") -> Mo | F29: =$F$5 -> 2025 | G29: =$A$10 -> 1 | H29: =H28+1 -> 20 | I29: =DATE(F29,G29,H29) -> 44215 | J29: =IF(OR(G29="",G29=MONTH(I29)),1,0) -> 1 | K29: =IF(OR($E29="Sa",$E29="So",$J29=0),K$4,K$5) -> 7 | L29: =IF(OR($E29="Sa",$E29="So",$J29=0),L$4,L$5) -> 0 | M29: =IF(OR($E29="Sa",$E29="So",$J29=0),M$4,M$5) -> 13 | N29: =IF(OR($E29="Sa",$E29="So",$J29=0),N$4,N$5) -> 0 | O29: =IF(OR($E29="Sa",$E29="So",$J29=0),O$4,O$5) -> 13 | P29: =IF(OR($E29="Sa",$E29="So",$J29=0),P$4,P$5) -> 30 | Q29: =IF(OR($E29="Sa",$E29="So",$J29=0),Q$4,Q$5) -> 15 | R29: =IF(OR($E29="Sa",$E29="So",$J29=0),R$4,R$5) -> 55 | S29: =Q29 -> 15 | T29: =R29 -> 55 | U29: =S29 -> 15 | V29: =T29 -> 55 | W29: =TIME(K29,L29,0) -> 0.29166667 | X29: =TIME(M29,N29,0) -> 0.54166667 | Y29: =TIME(O29,P29,0) -> 0.5625 | Z29: =TIME(Q29,R29,0) -> 0.66319444 | AA29: =TIME(S29,T29,0) -> 0.66319444 | AB29: =TIME(U29,V29,0) -> 0.66319444 | AD29: =IF(J29=0,0,IF(OR(E29="Sa",E29="So"),TIME($AD$4,$AF$4,0),TIME($AD$5,$AF$5,0))) -> 0.35069444 | AF29: =IF(J29=0,0,Z29-W29-(Y29-X29)) -> 0.35069444 | AK29: =IF(AH29=$AH$3,1,0) -> 0 | AL29: =IF(AH29=$AH$7,1,0) -> 0 | AM29: =IF(AI29=$AH$4,1,0) -> 0 | AO29: =IF(OR(AH29=$AH$2,AH29=$AH$5),1,IF(AH29=$AH$6,0.5,0)) -> 0 | AP29: =IF(OR(E29="Sa",E29="So",E29="",J29=0,AH29="FT"),0,1) -> 1 | BG29: WGTST | BH29: =SUM(BG24:BG28)+SUM(BH24:BH28) -> 809 | BI29: ECO | BJ29: ECO
D30: =IF(E30="Mo",WEEKNUM(I30),"") | E30: =TEXT(I30,"TTT") -> Di | F30: =$F$5 -> 2025 | G30: =$A$10 -> 1 | H30: =H29+1 -> 21 | I30: =DATE(F30,G30,H30) -> 44216 | J30: =IF(OR(G30="",G30=MONTH(I30)),1,0) -> 1 | K30: =IF(OR($E30="Sa",$E30="So",$J30=0),K$4,K$5) -> 7 | L30: =IF(OR($E30="Sa",$E30="So",$J30=0),L$4,L$5) -> 0 | M30: =IF(OR($E30="Sa",$E30="So",$J30=0),M$4,M$5) -> 13 | N30: =IF(OR($E30="Sa",$E30="So",$J30=0),N$4,N$5) -> 0 | O30: =IF(OR($E30="Sa",$E30="So",$J30=0),O$4,O$5) -> 13 | P30: =IF(OR($E30="Sa",$E30="So",$J30=0),P$4,P$5) -> 30 | Q30: =IF(OR($E30="Sa",$E30="So",$J30=0),Q$4,Q$5) -> 15 | R30: =IF(OR($E30="Sa",$E30="So",$J30=0),R$4,R$5) -> 55 | S30: =Q30 -> 15 | T30: =R30 -> 55 | U30: =S30 -> 15 | V30: =T30 -> 55 | W30: =TIME(K30,L30,0) -> 0.29166667 | X30: =TIME(M30,N30,0) -> 0.54166667 | Y30: =TIME(O30,P30,0) -> 0.5625 | Z30: =TIME(Q30,R30,0) -> 0.66319444 | AA30: =TIME(S30,T30,0) -> 0.66319444 | AB30: =TIME(U30,V30,0) -> 0.66319444 | AD30: =IF(J30=0,0,IF(OR(E30="Sa",E30="So"),TIME($AD$4,$AF$4,0),TIME($AD$5,$AF$5,0))) -> 0.35069444 | AF30: =IF(J30=0,0,Z30-W30-(Y30-X30)) -> 0.35069444 | AK30: =IF(AH30=$AH$3,1,0) -> 0 | AL30: =IF(AH30=$AH$7,1,0) -> 0 | AM30: =IF(AI30=$AH$4,1,0) -> 0 | AO30: =IF(OR(AH30=$AH$2,AH30=$AH$5),1,IF(AH30=$AH$6,0.5,0)) -> 0 | AP30: =IF(OR(E30="Sa",E30="So",E30="",J30=0,AH30="FT"),0,1) -> 1 | BG30: =INDEX($BF$2:$BG$8,MATCH(BG29,$BF$2:$BF$8,0),2) -> 80.9 | BH30: =INDEX($BF$2:$BG$8,MATCH(BG29,$BF$2:$BF$8,0),2) -> 80.9 | BI30: 15 | BJ30: 15
D31: =IF(E31="Mo",WEEKNUM(I31),"") | E31: =TEXT(I31,"TTT") -> Mi | F31: =$F$5 -> 2025 | G31: =$A$10 -> 1 | H31: =H30+1 -> 22 | I31: =DATE(F31,G31,H31) -> 44217 | J31: =IF(OR(G31="",G31=MONTH(I31)),1,0) -> 1 | K31: =IF(OR($E31="Sa",$E31="So",$J31=0),K$4,K$5) -> 7 | L31: =IF(OR($E31="Sa",$E31="So",$J31=0),L$4,L$5) -> 0 | M31: =IF(OR($E31="Sa",$E31="So",$J31=0),M$4,M$5) -> 13 | N31: =IF(OR($E31="Sa",$E31="So",$J31=0),N$4,N$5) -> 0 | O31: =IF(OR($E31="Sa",$E31="So",$J31=0),O$4,O$5) -> 13 | P31: =IF(OR($E31="Sa",$E31="So",$J31=0),P$4,P$5) -> 30 | Q31: =IF(OR($E31="Sa",$E31="So",$J31=0),Q$4,Q$5) -> 15 | R31: =IF(OR($E31="Sa",$E31="So",$J31=0),R$4,R$5) -> 55 | S31: =Q31 -> 15 | T31: =R31 -> 55 | U31: =S31 -> 15 | V31: =T31 -> 55 | W31: =TIME(K31,L31,0) -> 0.29166667 | X31: =TIME(M31,N31,0) -> 0.54166667 | Y31: =TIME(O31,P31,0) -> 0.5625 | Z31: =TIME(Q31,R31,0) -> 0.66319444 | AA31: =TIME(S31,T31,0) -> 0.66319444 | AB31: =TIME(U31,V31,0) -> 0.66319444 | AD31: =IF(J31=0,0,IF(OR(E31="Sa",E31="So"),TIME($AD$4,$AF$4,0),TIME($AD$5,$AF$5,0))) -> 0.35069444 | AF31: =IF(J31=0,0,Z31-W31-(Y31-X31)) -> 0.35069444 | AK31: =IF(AH31=$AH$3,1,0) -> 0 | AL31: =IF(AH31=$AH$7,1,0) -> 0 | AM31: =IF(AI31=$AH$4,1,0) -> 0 | AO31: =IF(OR(AH31=$AH$2,AH31=$AH$5),1,IF(AH31=$AH$6,0.5,0)) -> 0 | AP31: =IF(OR(E31="Sa",E31="So",E31="",J31=0,AH31="FT"),0,1) -> 1 | BG31: =BG30 -> 80.9 | BH31: =BH30 -> 80.9 | BI31: =BI30 -> 15 | BJ31: =BI31+BJ30 -> 30
D32: =IF(E32="Mo",WEEKNUM(I32),"") | E32: =TEXT(I32,"TTT") -> Do | F32: =$F$5 -> 2025 | G32: =$A$10 -> 1 | H32: =H31+1 -> 23 | I32: =DATE(F32,G32,H32) -> 44218 | J32: =IF(OR(G32="",G32=MONTH(I32)),1,0) -> 1 | K32: =IF(OR($E32="Sa",$E32="So",$J32=0),K$4,K$5) -> 7 | L32: =IF(OR($E32="Sa",$E32="So",$J32=0),L$4,L$5) -> 0 | M32: =IF(OR($E32="Sa",$E32="So",$J32=0),M$4,M$5) -> 13 | N32: =IF(OR($E32="Sa",$E32="So",$J32=0),N$4,N$5) -> 0 | O32: =IF(OR($E32="Sa",$E32="So",$J32=0),O$4,O$5) -> 13 | P32: =IF(OR($E32="Sa",$E32="So",$J32=0),P$4,P$5) -> 30 | Q32: =IF(OR($E32="Sa",$E32="So",$J32=0),Q$4,Q$5) -> 15 | R32: =IF(OR($E32="Sa",$E32="So",$J32=0),R$4,R$5) -> 55 | S32: =Q32 -> 15 | T32: =R32 -> 55 | U32: =S32 -> 15 | V32: =T32 -> 55 | W32: =TIME(K32,L32,0) -> 0.29166667 | X32: =TIME(M32,N32,0) -> 0.54166667 | Y32: =TIME(O32,P32,0) -> 0.5625 | Z32: =TIME(Q32,R32,0) -> 0.66319444 | AA32: =TIME(S32,T32,0) -> 0.66319444 | AB32: =TIME(U32,V32,0) -> 0.66319444 | AD32: =IF(J32=0,0,IF(OR(E32="Sa",E32="So"),TIME($AD$4,$AF$4,0),TIME($AD$5,$AF$5,0))) -> 0.35069444 | AF32: =IF(J32=0,0,Z32-W32-(Y32-X32)) -> 0.35069444 | AK32: =IF(AH32=$AH$3,1,0) -> 0 | AL32: =IF(AH32=$AH$7,1,0) -> 0 | AM32: =IF(AI32=$AH$4,1,0) -> 0 | AO32: =IF(OR(AH32=$AH$2,AH32=$AH$5),1,IF(AH32=$AH$6,0.5,0)) -> 0 | AP32: =IF(OR(E32="Sa",E32="So",E32="",J32=0,AH32="FT"),0,1) -> 1 | BG32: =BG30 -> 80.9 | BH32: =BH30 -> 80.9 | BI32: =BJ31+BI30 -> 45 | BJ32: =BI32+BJ30 -> 60
D33: =IF(E33="Mo",WEEKNUM(I33),"") | E33: =TEXT(I33,"TTT") -> Fr | F33: =$F$5 -> 2025 | G33: =$A$10 -> 1 | H33: =H32+1 -> 24 | I33: =DATE(F33,G33,H33) -> 44219 | J33: =IF(OR(G33="",G33=MONTH(I33)),1,0) -> 1 | K33: =IF(OR($E33="Sa",$E33="So",$J33=0),K$4,K$5) -> 7 | L33: =IF(OR($E33="Sa",$E33="So",$J33=0),L$4,L$5) -> 0 | M33: =IF(OR($E33="Sa",$E33="So",$J33=0),M$4,M$5) -> 13 | N33: =IF(OR($E33="Sa",$E33="So",$J33=0),N$4,N$5) -> 0 | O33: =IF(OR($E33="Sa",$E33="So",$J33=0),O$4,O$5) -> 13 | P33: =IF(OR($E33="Sa",$E33="So",$J33=0),P$4,P$5) -> 30 | Q33: =IF(OR($E33="Sa",$E33="So",$J33=0),Q$4,Q$5) -> 15 | R33: =IF(OR($E33="Sa",$E33="So",$J33=0),R$4,R$5) -> 55 | S33: =Q33 -> 15 | T33: =R33 -> 55 | U33: =S33 -> 15 | V33: =T33 -> 55 | W33: =TIME(K33,L33,0) -> 0.29166667 | X33: =TIME(M33,N33,0) -> 0.54166667 | Y33: =TIME(O33,P33,0) -> 0.5625 | Z33: =TIME(Q33,R33,0) -> 0.66319444 | AA33: =TIME(S33,T33,0) -> 0.66319444 | AB33: =TIME(U33,V33,0) -> 0.66319444 | AD33: =IF(J33=0,0,IF(OR(E33="Sa",E33="So"),TIME($AD$4,$AF$4,0),TIME($AD$5,$AF$5,0))) -> 0.35069444 | AF33: =IF(J33=0,0,Z33-W33-(Y33-X33)) -> 0.35069444 | AK33: =IF(AH33=$AH$3,1,0) -> 0 | AL33: =IF(AH33=$AH$7,1,0) -> 0 | AM33: =IF(AI33=$AH$4,1,0) -> 0 | AO33: =IF(OR(AH33=$AH$2,AH33=$AH$5),1,IF(AH33=$AH$6,0.5,0)) -> 0 | AP33: =IF(OR(E33="Sa",E33="So",E33="",J33=0,AH33="FT"),0,1) -> 1 | BG33: =BG30 -> 80.9 | BH33: =BH30 -> 80.9 | BI33: =BJ32+BI30 -> 75 | BJ33: =BI33+BJ30 -> 90
D34: =IF(E34="Mo",WEEKNUM(I34),"") | E34: =TEXT(I34,"TTT") -> Sa | F34: =$F$5 -> 2025 | G34: =$A$10 -> 1 | H34: =H33+1 -> 25 | I34: =DATE(F34,G34,H34) -> 44220 | J34: =IF(OR(G34="",G34=MONTH(I34)),1,0) -> 1 | K34: =IF(OR($E34="Sa",$E34="So",$J34=0),K$4,K$5) -> 0 | L34: =IF(OR($E34="Sa",$E34="So",$J34=0),L$4,L$5) -> 0 | M34: =IF(OR($E34="Sa",$E34="So",$J34=0),M$4,M$5) -> 0 | N34: =IF(OR($E34="Sa",$E34="So",$J34=0),N$4,N$5) -> 0 | O34: =IF(OR($E34="Sa",$E34="So",$J34=0),O$4,O$5) -> 0 | P34: =IF(OR($E34="Sa",$E34="So",$J34=0),P$4,P$5) -> 0 | Q34: =IF(OR($E34="Sa",$E34="So",$J34=0),Q$4,Q$5) -> 0 | R34: =IF(OR($E34="Sa",$E34="So",$J34=0),R$4,R$5) -> 0 | S34: =Q34 -> 0 | T34: =R34 -> 0 | U34: =S34 -> 0 | V34: =T34 -> 0 | W34: =TIME(K34,L34,0) -> 0 | X34: =TIME(M34,N34,0) -> 0 | Y34: =TIME(O34,P34,0) -> 0 | Z34: =TIME(Q34,R34,0) -> 0 | AA34: =TIME(S34,T34,0) -> 0 | AB34: =TIME(U34,V34,0) -> 0 | AD34: =IF(J34=0,0,IF(OR(E34="Sa",E34="So"),TIME($AD$4,$AF$4,0),TIME($AD$5,$AF$5,0))) -> 0 | AF34: =IF(J34=0,0,Z34-W34-(Y34-X34)) -> 0 | AK34: =IF(AH34=$AH$3,1,0) -> 0 | AL34: =IF(AH34=$AH$7,1,0) -> 0 | AM34: =IF(AI34=$AH$4,1,0) -> 0 | AO34: =IF(OR(AH34=$AH$2,AH34=$AH$5),1,IF(AH34=$AH$6,0.5,0)) -> 0 | AP34: =IF(OR(E34="Sa",E34="So",E34="",J34=0,AH34="FT"),0,1) -> 0 | BG34: =BG30 -> 80.9 | BH34: =BH30 -> 80.9 | BI34: =BJ33+BI30 -> 105 | BJ34: =BI34+BJ30 -> 120
D35: =IF(E35="Mo",WEEKNUM(I35),"") | E35: =TEXT(I35,"TTT") -> So | F35: =$F$5 -> 2025 | G35: =$A$10 -> 1 | H35: =H34+1 -> 26 | I35: =DATE(F35,G35,H35) -> 44221 | J35: =IF(OR(G35="",G35=MONTH(I35)),1,0) -> 1 | K35: =IF(OR($E35="Sa",$E35="So",$J35=0),K$4,K$5) -> 0 | L35: =IF(OR($E35="Sa",$E35="So",$J35=0),L$4,L$5) -> 0 | M35: =IF(OR($E35="Sa",$E35="So",$J35=0),M$4,M$5) -> 0 | N35: =IF(OR($E35="Sa",$E35="So",$J35=0),N$4,N$5) -> 0 | O35: =IF(OR($E35="Sa",$E35="So",$J35=0),O$4,O$5) -> 0 | P35: =IF(OR($E35="Sa",$E35="So",$J35=0),P$4,P$5) -> 0 | Q35: =IF(OR($E35="Sa",$E35="So",$J35=0),Q$4,Q$5) -> 0 | R35: =IF(OR($E35="Sa",$E35="So",$J35=0),R$4,R$5) -> 0 | S35: =Q35 -> 0 | T35: =R35 -> 0 | U35: =S35 -> 0 | V35: =T35 -> 0 | W35: =TIME(K35,L35,0) -> 0 | X35: =TIME(M35,N35,0) -> 0 | Y35: =TIME(O35,P35,0) -> 0 | Z35: =TIME(Q35,R35,0) -> 0 | AA35: =TIME(S35,T35,0) -> 0 | AB35: =TIME(U35,V35,0) -> 0 | AD35: =IF(J35=0,0,IF(OR(E35="Sa",E35="So"),TIME($AD$4,$AF$4,0),TIME($AD$5,$AF$5,0))) -> 0 | AF35: =IF(J35=0,0,Z35-W35-(Y35-X35)) -> 0 | AK35: =IF(AH35=$AH$3,1,0) -> 0 | AL35: =IF(AH35=$AH$7,1,0) -> 0 | AM35: =IF(AI35=$AH$4,1,0) -> 0 | AO35: =IF(OR(AH35=$AH$2,AH35=$AH$5),1,IF(AH35=$AH$6,0.5,0)) -> 0 | AP35: =IF(OR(E35="Sa",E35="So",E35="",J35=0,AH35="FT"),0,1) -> 0 | BG35: =BG30 -> 80.9 | BH35: =BH30 -> 80.9 | BI35: =BJ34+BI30 -> 135 | BJ35: =BI35+BJ30 -> 150
D36: =IF(E36="Mo",WEEKNUM(I36),"") -> 5 | E36: =TEXT(I36,"TTT") -> Mo | F36: =$F$5 -> 2025 | G36: =$A$10 -> 1 | H36: =H35+1 -> 27 | I36: =DATE(F36,G36,H36) -> 44222 | J36: =IF(OR(G36="",G36=MONTH(I36)),1,0) -> 1 | K36: =IF(OR($E36="Sa",$E36="So",$J36=0),K$4,K$5) -> 7 | L36: =IF(OR($E36="Sa",$E36="So",$J36=0),L$4,L$5) -> 0 | M36: =IF(OR($E36="Sa",$E36="So",$J36=0),M$4,M$5) -> 13 | N36: =IF(OR($E36="Sa",$E36="So",$J36=0),N$4,N$5) -> 0 | O36: =IF(OR($E36="Sa",$E36="So",$J36=0),O$4,O$5) -> 13 | P36: =IF(OR($E36="Sa",$E36="So",$J36=0),P$4,P$5) -> 30 | Q36: =IF(OR($E36="Sa",$E36="So",$J36=0),Q$4,Q$5) -> 15 | R36: =IF(OR($E36="Sa",$E36="So",$J36=0),R$4,R$5) -> 55 | S36: =Q36 -> 15 | T36: =R36 -> 55 | U36: =S36 -> 15 | V36: =T36 -> 55 | W36: =TIME(K36,L36,0) -> 0.29166667 | X36: =TIME(M36,N36,0) -> 0.54166667 | Y36: =TIME(O36,P36,0) -> 0.5625 | Z36: =TIME(Q36,R36,0) -> 0.66319444 | AA36: =TIME(S36,T36,0) -> 0.66319444 | AB36: =TIME(U36,V36,0) -> 0.66319444 | AD36: =IF(J36=0,0,IF(OR(E36="Sa",E36="So"),TIME($AD$4,$AF$4,0),TIME($AD$5,$AF$5,0))) -> 0.35069444 | AF36: =IF(J36=0,0,Z36-W36-(Y36-X36)) -> 0.35069444 | AK36: =IF(AH36=$AH$3,1,0) -> 0 | AL36: =IF(AH36=$AH$7,1,0) -> 0 | AM36: =IF(AI36=$AH$4,1,0) -> 0 | AO36: =IF(OR(AH36=$AH$2,AH36=$AH$5),1,IF(AH36=$AH$6,0.5,0)) -> 0 | AP36: =IF(OR(E36="Sa",E36="So",E36="",J36=0,AH36="FT"),0,1) -> 1 | BG36: 60 | BH36: =SUM(BG31:BG35)+SUM(BH31:BH35) -> 809 | BL36: WGTST | BN36: ECO | BO36: ECO
D37: =IF(E37="Mo",WEEKNUM(I37),"") | E37: =TEXT(I37,"TTT") -> Di | F37: =$F$5 -> 2025 | G37: =$A$10 -> 1 | H37: =H36+1 -> 28 | I37: =DATE(F37,G37,H37) -> 44223 | J37: =IF(OR(G37="",G37=MONTH(I37)),1,0) -> 1 | K37: =IF(OR($E37="Sa",$E37="So",$J37=0),K$4,K$5) -> 7 | L37: =IF(OR($E37="Sa",$E37="So",$J37=0),L$4,L$5) -> 0 | M37: =IF(OR($E37="Sa",$E37="So",$J37=0),M$4,M$5) -> 13 | N37: =IF(OR($E37="Sa",$E37="So",$J37=0),N$4,N$5) -> 0 | O37: =IF(OR($E37="Sa",$E37="So",$J37=0),O$4,O$5) -> 13 | P37: =IF(OR($E37="Sa",$E37="So",$J37=0),P$4,P$5) -> 30 | Q37: =IF(OR($E37="Sa",$E37="So",$J37=0),Q$4,Q$5) -> 15 | R37: =IF(OR($E37="Sa",$E37="So",$J37=0),R$4,R$5) -> 55 | S37: =Q37 -> 15 | T37: =R37 -> 55 | U37: =S37 -> 15 | V37: =T37 -> 55 | W37: =TIME(K37,L37,0) -> 0.29166667 | X37: =TIME(M37,N37,0) -> 0.54166667 | Y37: =TIME(O37,P37,0) -> 0.5625 | Z37: =TIME(Q37,R37,0) -> 0.66319444 | AA37: =TIME(S37,T37,0) -> 0.66319444 | AB37: =TIME(U37,V37,0) -> 0.66319444 | AD37: =IF(J37=0,0,IF(OR(E37="Sa",E37="So"),TIME($AD$4,$AF$4,0),TIME($AD$5,$AF$5,0))) -> 0.35069444 | AF37: =IF(J37=0,0,Z37-W37-(Y37-X37)) -> 0.35069444 | AK37: =IF(AH37=$AH$3,1,0) -> 0 | AL37: =IF(AH37=$AH$7,1,0) -> 0 | AM37: =IF(AI37=$AH$4,1,0) -> 0 | AO37: =IF(OR(AH37=$AH$2,AH37=$AH$5),1,IF(AH37=$AH$6,0.5,0)) -> 0 | AP37: =IF(OR(E37="Sa",E37="So",E37="",J37=0,AH37="FT"),0,1) -> 1 | BG37: =BH37/BG36 -> 26.966667 | BH37: =SUM(BH29,BH36) -> 1618 | BL37: =INDEX($BF$2:$BG$8,MATCH(BL36,$BF$2:$BF$8,0),2) -> 80.9 | BM37: =INDEX($BF$2:$BG$8,MATCH(BL36,$BF$2:$BF$8,0),2) -> 80.9 | BN37: 15 | BO37: 15
D38: =IF(E38="Mo",WEEKNUM(I38),"") | E38: =TEXT(I38,"TTT") -> Mi | F38: =$F$5 -> 2025 | G38: =$A$10 -> 1 | H38: =H37+1 -> 29 | I38: =DATE(F38,G38,H38) -> 44224 | J38: =IF(OR(G38="",G38=MONTH(I38)),1,0) -> 1 | K38: =IF(OR($E38="Sa",$E38="So",$J38=0),K$4,K$5) -> 7 | L38: =IF(OR($E38="Sa",$E38="So",$J38=0),L$4,L$5) -> 0 | M38: =IF(OR($E38="Sa",$E38="So",$J38=0),M$4,M$5) -> 13 | N38: =IF(OR($E38="Sa",$E38="So",$J38=0),N$4,N$5) -> 0 | O38: =IF(OR($E38="Sa",$E38="So",$J38=0),O$4,O$5) -> 13 | P38: =IF(OR($E38="Sa",$E38="So",$J38=0),P$4,P$5) -> 30 | Q38: =IF(OR($E38="Sa",$E38="So",$J38=0),Q$4,Q$5) -> 15 | R38: =IF(OR($E38="Sa",$E38="So",$J38=0),R$4,R$5) -> 55 | S38: =Q38 -> 15 | T38: =R38 -> 55 | U38: =S38 -> 15 | V38: =T38 -> 55 | W38: =TIME(K38,L38,0) -> 0.29166667 | X38: =TIME(M38,N38,0) -> 0.54166667 | Y38: =TIME(O38,P38,0) -> 0.5625 | Z38: =TIME(Q38,R38,0) -> 0.66319444 | AA38: =TIME(S38,T38,0) -> 0.66319444 | AB38: =TIME(U38,V38,0) -> 0.66319444 | AD38: =IF(J38=0,0,IF(OR(E38="Sa",E38="So"),TIME($AD$4,$AF$4,0),TIME($AD$5,$AF$5,0))) -> 0.35069444 | AF38: =IF(J38=0,0,Z38-W38-(Y38-X38)) -> 0.35069444 | AK38: =IF(AH38=$AH$3,1,0) -> 0 | AL38: =IF(AH38=$AH$7,1,0) -> 0 | AM38: =IF(AI38=$AH$4,1,0) -> 0 | AO38: =IF(OR(AH38=$AH$2,AH38=$AH$5),1,IF(AH38=$AH$6,0.5,0)) -> 0 | AP38: =IF(OR(E38="Sa",E38="So",E38="",J38=0,AH38="FT"),0,1) -> 1 | BG38: =100*BG36/BH37 -> 3.7082818 | BL38: =BL37 -> 80.9 | BM38: =BM37 -> 80.9 | BN38: =BN37 -> 15 | BO38: =BN38+BO37 -> 30
D39: =IF(E39="Mo",WEEKNUM(I39),"") | E39: =TEXT(I39,"TTT") -> Do | F39: =$F$5 -> 2025 | G39: =$A$10 -> 1 | H39: =H38+1 -> 30 | I39: =DATE(F39,G39,H39) -> 44225 | J39: =IF(OR(G39="",G39=MONTH(I39)),1,0) -> 1 | K39: =IF(OR($E39="Sa",$E39="So",$J39=0),K$4,K$5) -> 7 | L39: =IF(OR($E39="Sa",$E39="So",$J39=0),L$4,L$5) -> 0 | M39: =IF(OR($E39="Sa",$E39="So",$J39=0),M$4,M$5) -> 13 | N39: =IF(OR($E39="Sa",$E39="So",$J39=0),N$4,N$5) -> 0 | O39: =IF(OR($E39="Sa",$E39="So",$J39=0),O$4,O$5) -> 13 | P39: =IF(OR($E39="Sa",$E39="So",$J39=0),P$4,P$5) -> 30 | Q39: =IF(OR($E39="Sa",$E39="So",$J39=0),Q$4,Q$5) -> 15 | R39: =IF(OR($E39="Sa",$E39="So",$J39=0),R$4,R$5) -> 55 | S39: =Q39 -> 15 | T39: =R39 -> 55 | U39: =S39 -> 15 | V39: =T39 -> 55 | W39: =TIME(K39,L39,0) -> 0.29166667 | X39: =TIME(M39,N39,0) -> 0.54166667 | Y39: =TIME(O39,P39,0) -> 0.5625 | Z39: =TIME(Q39,R39,0) -> 0.66319444 | AA39: =TIME(S39,T39,0) -> 0.66319444 | AB39: =TIME(U39,V39,0) -> 0.66319444 | AD39: =IF(J39=0,0,IF(OR(E39="Sa",E39="So"),TIME($AD$4,$AF$4,0),TIME($AD$5,$AF$5,0))) -> 0.35069444 | AF39: =IF(J39=0,0,Z39-W39-(Y39-X39)) -> 0.35069444 | AK39: =IF(AH39=$AH$3,1,0) -> 0 | AL39: =IF(AH39=$AH$7,1,0) -> 0 | AM39: =IF(AI39=$AH$4,1,0) -> 0 | AO39: =IF(OR(AH39=$AH$2,AH39=$AH$5),1,IF(AH39=$AH$6,0.5,0)) -> 0 | AP39: =IF(OR(E39="Sa",E39="So",E39="",J39=0,AH39="FT"),0,1) -> 1 | BL39: =BL37 -> 80.9 | BM39: =BM37 -> 80.9 | BN39: =BO38+BN37 -> 45 | BO39: =BN39+BO37 -> 60
D40: =IF(E40="Mo",WEEKNUM(I40),"") | E40: =TEXT(I40,"TTT") -> Fr | F40: =$F$5 -> 2025 | G40: =$A$10 -> 1 | H40: =H39+1 -> 31 | I40: =DATE(F40,G40,H40) -> 44226 | J40: =IF(OR(G40="",G40=MONTH(I40)),1,0) -> 1 | K40: =IF(OR($E40="Sa",$E40="So",$J40=0),K$4,K$5) -> 7 | L40: =IF(OR($E40="Sa",$E40="So",$J40=0),L$4,L$5) -> 0 | M40: =IF(OR($E40="Sa",$E40="So",$J40=0),M$4,M$5) -> 13 | N40: =IF(OR($E40="Sa",$E40="So",$J40=0),N$4,N$5) -> 0 | O40: =IF(OR($E40="Sa",$E40="So",$J40=0),O$4,O$5) -> 13 | P40: =IF(OR($E40="Sa",$E40="So",$J40=0),P$4,P$5) -> 30 | Q40: =IF(OR($E40="Sa",$E40="So",$J40=0),Q$4,Q$5) -> 15 | R40: =IF(OR($E40="Sa",$E40="So",$J40=0),R$4,R$5) -> 55 | S40: =Q40 -> 15 | T40: =R40 -> 55 | U40: =S40 -> 15 | V40: =T40 -> 55 | W40: =TIME(K40,L40,0) -> 0.29166667 | X40: =TIME(M40,N40,0) -> 0.54166667 | Y40: =TIME(O40,P40,0) -> 0.5625 | Z40: =TIME(Q40,R40,0) -> 0.66319444 | AA40: =TIME(S40,T40,0) -> 0.66319444 | AB40: =TIME(U40,V40,0) -> 0.66319444 | AD40: =IF(J40=0,0,IF(OR(E40="Sa",E40="So"),TIME($AD$4,$AF$4,0),TIME($AD$5,$AF$5,0))) -> 0.35069444 | AF40: =IF(J40=0,0,Z40-W40-(Y40-X40)) -> 0.35069444 | AK40: =IF(AH40=$AH$3,1,0) -> 0 | AL40: =IF(AH40=$AH$7,1,0) -> 0 | AM40: =IF(AI40=$AH$4,1,0) -> 0 | AO40: =IF(OR(AH40=$AH$2,AH40=$AH$5),1,IF(AH40=$AH$6,0.5,0)) -> 0 | AP40: =IF(OR(E40="Sa",E40="So",E40="",J40=0,AH40="FT"),0,1) -> 1 | BL40: =BL37 -> 80.9 | BM40: =BM37 -> 80.9 | BN40: =BO39+BN37 -> 75 | BO40: =BN40+BO37 -> 90
D41: EM | J41: =IF(OR(G41="",G41=MONTH(I41)),1,0) -> 1 | Q41: Summ | AD41: =SUM(AD10:AD40) -> 8.0659722 | AF41: =SUM(AF10:AF40) -> 8.0659722 | AI41: =IF(AF41-AD41<0,0,1) -> 0 | AJ41: =IF(AF41-AD41<0,AD41-AF41,AF41-AD41) -> 3.5527137e-15 | AK41: =8.425*SUM(AK10:AK40)/24 -> 0 | AL41: =8.425*SUM(AL10:AL40)/24 -> 0 | AM41: =8.425*SUM(AM10:AM40)/24 -> 0 | AO41: =SUM(AO10:AO40) -> 0 | AP41: =SUM(AP10:AP40) -> 23
AJ42: =IF(AI41=1,AJ8+AJ41,IF(AI41=0,AJ8-AJ41,"Error")) -> -3.5527137e-15 | AK42: =AK8+SUM(AK9:AK40) -> 0 | AL42: =AL8+SUM(AL9:AL40) -> 0 | AM42: =AM8+SUM(AM9:AM40) -> 0 | AO42: =AO41*8 -> 0 | AP42: =AP41*8 -> 184
B43: =$F$5 -> 2025 | C43: =TEXT(I44,"MMM") -> Feb
A44: =A10+1 -> 2 | D44: =IF(E44="Mo",WEEKNUM(I44),"") | E44: =TEXT(I44,"TTT") -> Sa | F44: =$F$5 -> 2025 | G44: =$A$44 -> 2 | H44: =$H$5 -> 1 | I44: =DATE(F44,G44,H44) -> 44227 | J44: =IF(OR(G44="",G44=MONTH(I44)),1,0) -> 1 | K44: =IF(OR($E44="Sa",$E44="So",$J44=0),K$4,K$5) -> 0 | L44: =IF(OR($E44="Sa",$E44="So",$J44=0),L$4,L$5) -> 0 | M44: =IF(OR($E44="Sa",$E44="So",$J44=0),M$4,M$5) -> 0 | N44: =IF(OR($E44="Sa",$E44="So",$J44=0),N$4,N$5) -> 0 | O44: =IF(OR($E44="Sa",$E44="So",$J44=0),O$4,O$5) -> 0 | P44: =IF(OR($E44="Sa",$E44="So",$J44=0),P$4,P$5) -> 0 | Q44: =IF(OR($E44="Sa",$E44="So",$J44=0),Q$4,Q$5) -> 0 | R44: =IF(OR($E44="Sa",$E44="So",$J44=0),R$4,R$5) -> 0 | S44: =Q44 -> 0 | T44: =R44 -> 0 | U44: =S44 -> 0 | V44: =T44 -> 0 | W44: =TIME(K44,L44,0) -> 0 | X44: =TIME(M44,N44,0) -> 0 | Y44: =TIME(O44,P44,0) -> 0 | Z44: =TIME(Q44,R44,0) -> 0 | AA44: =TIME(S44,T44,0) -> 0 | AB44: =TIME(U44,V44,0) -> 0 | AD44: =IF(J44=0,0,IF(OR(E44="Sa",E44="So"),TIME($AD$4,$AF$4,0),TIME($AD$5,$AF$5,0))) -> 0 | AF44: =IF(J44=0,0,Z44-W44-(Y44-X44)) -> 0 | AK44: =IF(AH44=$AH$3,1,0) -> 0 | AL44: =IF(AH44=$AH$7,1,0) -> 0 | AM44: =IF(AI44=$AH$4,1,0) -> 0 | AO44: =IF(OR(AH44=$AH$2,AH44=$AH$5),1,IF(AH44=$AH$6,0.5,0)) -> 0 | AP44: =IF(OR(E44="Sa",E44="So",E44="",J44=0,AH44="FT"),0,1) -> 0 | BL44: =BL37 -> 80.9 | BM44: =BM37 -> 80.9 | BN44: =BO40+BN37 -> 105 | BO44: =BN44+BO37 -> 120
D45: =IF(E45="Mo",WEEKNUM(I45),"") | E45: =TEXT(I45,"TTT") -> So | F45: =$F$5 -> 2025 | G45: =$A$44 -> 2 | H45: =H44+1 -> 2 | I45: =DATE(F45,G45,H45) -> 44228 | J45: =IF(OR(G45="",G45=MONTH(I45)),1,0) -> 1 | K45: =IF(OR($E45="Sa",$E45="So",$J45=0),K$4,K$5) -> 0 | L45: =IF(OR($E45="Sa",$E45="So",$J45=0),L$4,L$5) -> 0 | M45: =IF(OR($E45="Sa",$E45="So",$J45=0),M$4,M$5) -> 0 | N45: =IF(OR($E45="Sa",$E45="So",$J45=0),N$4,N$5) -> 0 | O45: =IF(OR($E45="Sa",$E45="So",$J45=0),O$4,O$5) -> 0 | P45: =IF(OR($E45="Sa",$E45="So",$J45=0),P$4,P$5) -> 0 | Q45: =IF(OR($E45="Sa",$E45="So",$J45=0),Q$4,Q$5) -> 0 | R45: =IF(OR($E45="Sa",$E45="So",$J45=0),R$4,R$5) -> 0 | S45: =Q45 -> 0 | T45: =R45 -> 0 | U45: =S45 -> 0 | V45: =T45 -> 0 | W45: =TIME(K45,L45,0) -> 0 | X45: =TIME(M45,N45,0) -> 0 | Y45: =TIME(O45,P45,0) -> 0 | Z45: =TIME(Q45,R45,0) -> 0 | AA45: =TIME(S45,T45,0) -> 0 | AB45: =TIME(U45,V45,0) -> 0 | AD45: =IF(J45=0,0,IF(OR(E45="Sa",E45="So"),TIME($AD$4,$AF$4,0),TIME($AD$5,$AF$5,0))) -> 0 | AF45: =IF(J45=0,0,Z45-W45-(Y45-X45)) -> 0 | AK45: =IF(AH45=$AH$3,1,0) -> 0 | AL45: =IF(AH45=$AH$7,1,0) -> 0 | AM45: =IF(AI45=$AH$4,1,0) -> 0 | AO45: =IF(OR(AH45=$AH$2,AH45=$AH$5),1,IF(AH45=$AH$6,0.5,0)) -> 0 | AP45: =IF(OR(E45="Sa",E45="So",E45="",J45=0,AH45="FT"),0,1) -> 0 | BL45: =BL37 -> 80.9 | BM45: =BM37 -> 80.9 | BN45: =BO44+BN37 -> 135 | BO45: =BN45+BO37 -> 150
D46: =IF(E46="Mo",WEEKNUM(I46),"") -> 6 | E46: =TEXT(I46,"TTT") -> Mo | F46: =$F$5 -> 2025 | G46: =$A$44 -> 2 | H46: =H45+1 -> 3 | I46: =DATE(F46,G46,H46) -> 44229 | J46: =IF(OR(G46="",G46=MONTH(I46)),1,0) -> 1 | K46: =IF(OR($E46="Sa",$E46="So",$J46=0),K$4,K$5) -> 7 | L46: =IF(OR($E46="Sa",$E46="So",$J46=0),L$4,L$5) -> 0 | M46: =IF(OR($E46="Sa",$E46="So",$J46=0),M$4,M$5) -> 13 | N46: =IF(OR($E46="Sa",$E46="So",$J46=0),N$4,N$5) -> 0 | O46: =IF(OR($E46="Sa",$E46="So",$J46=0),O$4,O$5) -> 13 | P46: =IF(OR($E46="Sa",$E46="So",$J46=0),P$4,P$5) -> 30 | Q46: =IF(OR($E46="Sa",$E46="So",$J46=0),Q$4,Q$5) -> 15 | R46: =IF(OR($E46="Sa",$E46="So",$J46=0),R$4,R$5) -> 55 | S46: =Q46 -> 15 | T46: =R46 -> 55 | U46: =S46 -> 15 | V46: =T46 -> 55 | W46: =TIME(K46,L46,0) -> 0.29166667 | X46: =TIME(M46,N46,0) -> 0.54166667 | Y46: =TIME(O46,P46,0) -> 0.5625 | Z46: =TIME(Q46,R46,0) -> 0.66319444 | AA46: =TIME(S46,T46,0) -> 0.66319444 | AB46: =TIME(U46,V46,0) -> 0.66319444 | AD46: =IF(J46=0,0,IF(OR(E46="Sa",E46="So"),TIME($AD$4,$AF$4,0),TIME($AD$5,$AF$5,0))) -> 0.35069444 | AF46: =IF(J46=0,0,Z46-W46-(Y46-X46)) -> 0.35069444 | AK46: =IF(AH46=$AH$3,1,0) -> 0 | AL46: =IF(AH46=$AH$7,1,0) -> 0 | AM46: =IF(AI46=$AH$4,1,0) -> 0 | AO46: =IF(OR(AH46=$AH$2,AH46=$AH$5),1,IF(AH46=$AH$6,0.5,0)) -> 0 | AP46: =IF(OR(E46="Sa",E46="So",E46="",J46=0,AH46="FT"),0,1) -> 1 | BL46: WGTST | BM46: =SUM(BL38:BL45)+SUM(BM38:BM45) -> 809 | BN46: ECO | BO46: ECO
D47: =IF(E47="Mo",WEEKNUM(I47),"") | E47: =TEXT(I47,"TTT") -> Di | F47: =$F$5 -> 2025 | G47: =$A$44 -> 2 | H47: =H46+1 -> 4 | I47: =DATE(F47,G47,H47) -> 44230 | J47: =IF(OR(G47="",G47=MONTH(I47)),1,0) -> 1 | K47: =IF(OR($E47="Sa",$E47="So",$J47=0),K$4,K$5) -> 7 | L47: =IF(OR($E47="Sa",$E47="So",$J47=0),L$4,L$5) -> 0 | M47: =IF(OR($E47="Sa",$E47="So",$J47=0),M$4,M$5) -> 13 | N47: =IF(OR($E47="Sa",$E47="So",$J47=0),N$4,N$5) -> 0 | O47: =IF(OR($E47="Sa",$E47="So",$J47=0),O$4,O$5) -> 13 | P47: =IF(OR($E47="Sa",$E47="So",$J47=0),P$4,P$5) -> 30 | Q47: =IF(OR($E47="Sa",$E47="So",$J47=0),Q$4,Q$5) -> 15 | R47: =IF(OR($E47="Sa",$E47="So",$J47=0),R$4,R$5) -> 55 | S47: =Q47 -> 15 | T47: =R47 -> 55 | U47: =S47 -> 15 | V47: =T47 -> 55 | W47: =TIME(K47,L47,0) -> 0.29166667 | X47: =TIME(M47,N47,0) -> 0.54166667 | Y47: =TIME(O47,P47,0) -> 0.5625 | Z47: =TIME(Q47,R47,0) -> 0.66319444 | AA47: =TIME(S47,T47,0) -> 0.66319444 | AB47: =TIME(U47,V47,0) -> 0.66319444 | AD47: =IF(J47=0,0,IF(OR(E47="Sa",E47="So"),TIME($AD$4,$AF$4,0),TIME($AD$5,$AF$5,0))) -> 0.35069444 | AF47: =IF(J47=0,0,Z47-W47-(Y47-X47)) -> 0.35069444 | AK47: =IF(AH47=$AH$3,1,0) -> 0 | AL47: =IF(AH47=$AH$7,1,0) -> 0 | AM47: =IF(AI47=$AH$4,1,0) -> 0 | AO47: =IF(OR(AH47=$AH$2,AH47=$AH$5),1,IF(AH47=$AH$6,0.5,0)) -> 0 | AP47: =IF(OR(E47="Sa",E47="So",E47="",J47=0,AH47="FT"),0,1) -> 1 | BL47: =INDEX($BF$2:$BG$8,MATCH(BL46,$BF$2:$BF$8,0),2) -> 80.9 | BM47: =INDEX($BF$2:$BG$8,MATCH(BL46,$BF$2:$BF$8,0),2) -> 80.9 | BN47: 15 | BO47: 15
D48: =IF(E48="Mo",WEEKNUM(I48),"") | E48: =TEXT(I48,"TTT") -> Mi | F48: =$F$5 -> 2025 | G48: =$A$44 -> 2 | H48: =H47+1 -> 5 | I48: =DATE(F48,G48,H48) -> 44231 | J48: =IF(OR(G48="",G48=MONTH(I48)),1,0) -> 1 | K48: =IF(OR($E48="Sa",$E48="So",$J48=0),K$4,K$5) -> 7 | L48: =IF(OR($E48="Sa",$E48="So",$J48=0),L$4,L$5) -> 0 | M48: =IF(OR($E48="Sa",$E48="So",$J48=0),M$4,M$5) -> 13 | N48: =IF(OR($E48="Sa",$E48="So",$J48=0),N$4,N$5) -> 0 | O48: =IF(OR($E48="Sa",$E48="So",$J48=0),O$4,O$5) -> 13 | P48: =IF(OR($E48="Sa",$E48="So",$J48=0),P$4,P$5) -> 30 | Q48: =IF(OR($E48="Sa",$E48="So",$J48=0),Q$4,Q$5) -> 15 | R48: =IF(OR($E48="Sa",$E48="So",$J48=0),R$4,R$5) -> 55 | S48: =Q48 -> 15 | T48: =R48 -> 55 | U48: =S48 -> 15 | V48: =T48 -> 55 | W48: =TIME(K48,L48,0) -> 0.29166667 | X48: =TIME(M48,N48,0) -> 0.54166667 | Y48: =TIME(O48,P48,0) -> 0.5625 | Z48: =TIME(Q48,R48,0) -> 0.66319444 | AA48: =TIME(S48,T48,0) -> 0.66319444 | AB48: =TIME(U48,V48,0) -> 0.66319444 | AD48: =IF(J48=0,0,IF(OR(E48="Sa",E48="So"),TIME($AD$4,$AF$4,0),TIME($AD$5,$AF$5,0))) -> 0.35069444 | AF48: =IF(J48=0,0,Z48-W48-(Y48-X48)) -> 0.35069444 | AK48: =IF(AH48=$AH$3,1,0) -> 0 | AL48: =IF(AH48=$AH$7,1,0) -> 0 | AM48: =IF(AI48=$AH$4,1,0) -> 0 | AO48: =IF(OR(AH48=$AH$2,AH48=$AH$5),1,IF(AH48=$AH$6,0.5,0)) -> 0 | AP48: =IF(OR(E48="Sa",E48="So",E48="",J48=0,AH48="FT"),0,1) -> 1 | BL48: =BL47 -> 80.9 | BM48: =BM47 -> 80.9 | BN48: =BN47 -> 15 | BO48: =BN48+BO47 -> 30
D49: =IF(E49="Mo",WEEKNUM(I49),"") | E49: =TEXT(I49,"TTT") -> Do | F49: =$F$5 -> 2025 | G49: =$A$44 -> 2 | H49: =H48+1 -> 6 | I49: =DATE(F49,G49,H49) -> 44232 | J49: =IF(OR(G49="",G49=MONTH(I49)),1,0) -> 1 | K49: =IF(OR($E49="Sa",$E49="So",$J49=0),K$4,K$5) -> 7 | L49: =IF(OR($E49="Sa",$E49="So",$J49=0),L$4,L$5) -> 0 | M49: =IF(OR($E49="Sa",$E49="So",$J49=0),M$4,M$5) -> 13 | N49: =IF(OR($E49="Sa",$E49="So",$J49=0),N$4,N$5) -> 0 | O49: =IF(OR($E49="Sa",$E49="So",$J49=0),O$4,O$5) -> 13 | P49: =IF(OR($E49="Sa",$E49="So",$J49=0),P$4,P$5) -> 30 | Q49: =IF(OR($E49="Sa",$E49="So",$J49=0),Q$4,Q$5) -> 15 | R49: =IF(OR($E49="Sa",$E49="So",$J49=0),R$4,R$5) -> 55 | S49: =Q49 -> 15 | T49: =R49 -> 55 | U49: =S49 -> 15 | V49: =T49 -> 55 | W49: =TIME(K49,L49,0) -> 0.29166667 | X49: =TIME(M49,N49,0) -> 0.54166667 | Y49: =TIME(O49,P49,0) -> 0.5625 | Z49: =TIME(Q49,R49,0) -> 0.66319444 | AA49: =TIME(S49,T49,0) -> 0.66319444 | AB49: =TIME(U49,V49,0) -> 0.66319444 | AD49: =IF(J49=0,0,IF(OR(E49="Sa",E49="So"),TIME($AD$4,$AF$4,0),TIME($AD$5,$AF$5,0))) -> 0.35069444 | AF49: =IF(J49=0,0,Z49-W49-(Y49-X49)) -> 0.35069444 | AK49: =IF(AH49=$AH$3,1,0) -> 0 | AL49: =IF(AH49=$AH$7,1,0) -> 0 | AM49: =IF(AI49=$AH$4,1,0) -> 0 | AO49: =IF(OR(AH49=$AH$2,AH49=$AH$5),1,IF(AH49=$AH$6,0.5,0)) -> 0 | AP49: =IF(OR(E49="Sa",E49="So",E49="",J49=0,AH49="FT"),0,1) -> 1 | BL49: =BL47 -> 80.9 | BM49: =BM47 -> 80.9 | BN49: =BO48+BN47 -> 45 | BO49: =BN49+BO47 -> 60
D50: =IF(E50="Mo",WEEKNUM(I50),"") | E50: =TEXT(I50,"TTT") -> Fr | F50: =$F$5 -> 2025 | G50: =$A$44 -> 2 | H50: =H49+1 -> 7 | I50: =DATE(F50,G50,H50) -> 44233 | J50: =IF(OR(G50="",G50=MONTH(I50)),1,0) -> 1 | K50: =IF(OR($E50="Sa",$E50="So",$J50=0),K$4,K$5) -> 7 | L50: =IF(OR($E50="Sa",$E50="So",$J50=0),L$4,L$5) -> 0 | M50: =IF(OR($E50="Sa",$E50="So",$J50=0),M$4,M$5) -> 13 | N50: =IF(OR($E50="Sa",$E50="So",$J50=0),N$4,N$5) -> 0 | O50: =IF(OR($E50="Sa",$E50="So",$J50=0),O$4,O$5) -> 13 | P50: =IF(OR($E50="Sa",$E50="So",$J50=0),P$4,P$5) -> 30 | Q50: =IF(OR($E50="Sa",$E50="So",$J50=0),Q$4,Q$5) -> 15 | R50: =IF(OR($E50="Sa",$E50="So",$J50=0),R$4,R$5) -> 55 | S50: =Q50 -> 15 | T50: =R50 -> 55 | U50: =S50 -> 15 | V50: =T50 -> 55 | W50: =TIME(K50,L50,0) -> 0.29166667 | X50: =TIME(M50,N50,0) -> 0.54166667 | Y50: =TIME(O50,P50,0) -> 0.5625 | Z50: =TIME(Q50,R50,0) -> 0.66319444 | AA50: =TIME(S50,T50,0) -> 0.66319444 | AB50: =TIME(U50,V50,0) -> 0.66319444 | AD50: =IF(J50=0,0,IF(OR(E50="Sa",E50="So"),TIME($AD$4,$AF$4,0),TIME($AD$5,$AF$5,0))) -> 0.35069444 | AF50: =IF(J50=0,0,Z50-W50-(Y50-X50)) -> 0.35069444 | AK50: =IF(AH50=$AH$3,1,0) -> 0 | AL50: =IF(AH50=$AH$7,1,0) -> 0 | AM50: =IF(AI50=$AH$4,1,0) -> 0 | AO50: =IF(OR(AH50=$AH$2,AH50=$AH$5),1,IF(AH50=$AH$6,0.5,0)) -> 0 | AP50: =IF(OR(E50="Sa",E50="So",E50="",J50=0,AH50="FT"),0,1) -> 1 | BL50: =BL47 -> 80.9 | BM50: =BM47 -> 80.9 | BN50: =BO49+BN47 -> 75 | BO50: =BN50+BO47 -> 90
D51: =IF(E51="Mo",WEEKNUM(I51),"") | E51: =TEXT(I51,"TTT") -> Sa | F51: =$F$5 -> 2025 | G51: =$A$44 -> 2 | H51: =H50+1 -> 8 | I51: =DATE(F51,G51,H51) -> 44234 | J51: =IF(OR(G51="",G51=MONTH(I51)),1,0) -> 1 | K51: =IF(OR($E51="Sa",$E51="So",$J51=0),K$4,K$5) -> 0 | L51: =IF(OR($E51="Sa",$E51="So",$J51=0),L$4,L$5) -> 0 | M51: =IF(OR($E51="Sa",$E51="So",$J51=0),M$4,M$5) -> 0 | N51: =IF(OR($E51="Sa",$E51="So",$J51=0),N$4,N$5) -> 0 | O51: =IF(OR($E51="Sa",$E51="So",$J51=0),O$4,O$5) -> 0 | P51: =IF(OR($E51="Sa",$E51="So",$J51=0),P$4,P$5) -> 0 | Q51: =IF(OR($E51="Sa",$E51="So",$J51=0),Q$4,Q$5) -> 0 | R51: =IF(OR($E51="Sa",$E51="So",$J51=0),R$4,R$5) -> 0 | S51: =Q51 -> 0 | T51: =R51 -> 0 | U51: =S51 -> 0 | V51: =T51 -> 0 | W51: =TIME(K51,L51,0) -> 0 | X51: =TIME(M51,N51,0) -> 0 | Y51: =TIME(O51,P51,0) -> 0 | Z51: =TIME(Q51,R51,0) -> 0 | AA51: =TIME(S51,T51,0) -> 0 | AB51: =TIME(U51,V51,0) -> 0 | AD51: =IF(J51=0,0,IF(OR(E51="Sa",E51="So"),TIME($AD$4,$AF$4,0),TIME($AD$5,$AF$5,0))) -> 0 | AF51: =IF(J51=0,0,Z51-W51-(Y51-X51)) -> 0 | AK51: =IF(AH51=$AH$3,1,0) -> 0 | AL51: =IF(AH51=$AH$7,1,0) -> 0 | AM51: =IF(AI51=$AH$4,1,0) -> 0 | AO51: =IF(OR(AH51=$AH$2,AH51=$AH$5),1,IF(AH51=$AH$6,0.5,0)) -> 0 | AP51: =IF(OR(E51="Sa",E51="So",E51="",J51=0,AH51="FT"),0,1) -> 0 | BL51: =BL47 -> 80.9 | BM51: =BM47 -> 80.9 | BN51: =BO50+BN47 -> 105 | BO51: =BN51+BO47 -> 120
D52: =IF(E52="Mo",WEEKNUM(I52),"") | E52: =TEXT(I52,"TTT") -> So | F52: =$F$5 -> 2025 | G52: =$A$44 -> 2 | H52: =H51+1 -> 9 | I52: =DATE(F52,G52,H52) -> 44235 | J52: =IF(OR(G52="",G52=MONTH(I52)),1,0) -> 1 | K52: =IF(OR($E52="Sa",$E52="So",$J52=0),K$4,K$5) -> 0 | L52: =IF(OR($E52="Sa",$E52="So",$J52=0),L$4,L$5) -> 0 | M52: =IF(OR($E52="Sa",$E52="So",$J52=0),M$4,M$5) -> 0 | N52: =IF(OR($E52="Sa",$E52="So",$J52=0),N$4,N$5) -> 0 | O52: =IF(OR($E52="Sa",$E52="So",$J52=0),O$4,O$5) -> 0 | P52: =IF(OR($E52="Sa",$E52="So",$J52=0),P$4,P$5) -> 0 | Q52: =IF(OR($E52="Sa",$E52="So",$J52=0),Q$4,Q$5) -> 0 | R52: =IF(OR($E52="Sa",$E52="So",$J52=0),R$4,R$5) -> 0 | S52: =Q52 -> 0 | T52: =R52 -> 0 | U52: =S52 -> 0 | V52: =T52 -> 0 | W52: =TIME(K52,L52,0) -> 0 | X52: =TIME(M52,N52,0) -> 0 | Y52: =TIME(O52,P52,0) -> 0 | Z52: =TIME(Q52,R52,0) -> 0 | AA52: =TIME(S52,T52,0) -> 0 | AB52: =TIME(U52,V52,0) -> 0 | AD52: =IF(J52=0,0,IF(OR(E52="Sa",E52="So"),TIME($AD$4,$AF$4,0),TIME($AD$5,$AF$5,0))) -> 0 | AF52: =IF(J52=0,0,Z52-W52-(Y52-X52)) -> 0 | AK52: =IF(AH52=$AH$3,1,0) -> 0 | AL52: =IF(AH52=$AH$7,1,0) -> 0 | AM52: =IF(AI52=$AH$4,1,0) -> 0 | AO52: =IF(OR(AH52=$AH$2,AH52=$AH$5),1,IF(AH52=$AH$6,0.5,0)) -> 0 | AP52: =IF(OR(E52="Sa",E52="So",E52="",J52=0,AH52="FT"),0,1) -> 0 | BL52: =BL47 -> 80.9 | BM52: =BM47 -> 80.9 | BN52: =BO51+BN47 -> 135 | BO52: =BN52+BO47 -> 150
D53: =IF(E53="Mo",WEEKNUM(I53),"") -> 7 | E53: =TEXT(I53,"TTT") -> Mo | F53: =$F$5 -> 2025 | G53: =$A$44 -> 2 | H53: =H52+1 -> 10 | I53: =DATE(F53,G53,H53) -> 44236 | J53: =IF(OR(G53="",G53=MONTH(I53)),1,0) -> 1 | K53: =IF(OR($E53="Sa",$E53="So",$J53=0),K$4,K$5) -> 7 | L53: =IF(OR($E53="Sa",$E53="So",$J53=0),L$4,L$5) -> 0 | M53: =IF(OR($E53="Sa",$E53="So",$J53=0),M$4,M$5) -> 13 | N53: =IF(OR($E53="Sa",$E53="So",$J53=0),N$4,N$5) -> 0 | O53: =IF(OR($E53="Sa",$E53="So",$J53=0),O$4,O$5) -> 13 | P53: =IF(OR($E53="Sa",$E53="So",$J53=0),P$4,P$5) -> 30 | Q53: =IF(OR($E53="Sa",$E53="So",$J53=0),Q$4,Q$5) -> 15 | R53: =IF(OR($E53="Sa",$E53="So",$J53=0),R$4,R$5) -> 55 | S53: =Q53 -> 15 | T53: =R53 -> 55 | U53: =S53 -> 15 | V53: =T53 -> 55 | W53: =TIME(K53,L53,0) -> 0.29166667 | X53: =TIME(M53,N53,0) -> 0.54166667 | Y53: =TIME(O53,P53,0) -> 0.5625 | Z53: =TIME(Q53,R53,0) -> 0.66319444 | AA53: =TIME(S53,T53,0) -> 0.66319444 | AB53: =TIME(U53,V53,0) -> 0.66319444 | AD53: =IF(J53=0,0,IF(OR(E53="Sa",E53="So"),TIME($AD$4,$AF$4,0),TIME($AD$5,$AF$5,0))) -> 0.35069444 | AF53: =IF(J53=0,0,Z53-W53-(Y53-X53)) -> 0.35069444 | AK53: =IF(AH53=$AH$3,1,0) -> 0 | AL53: =IF(AH53=$AH$7,1,0) -> 0 | AM53: =IF(AI53=$AH$4,1,0) -> 0 | AO53: =IF(OR(AH53=$AH$2,AH53=$AH$5),1,IF(AH53=$AH$6,0.5,0)) -> 0 | AP53: =IF(OR(E53="Sa",E53="So",E53="",J53=0,AH53="FT"),0,1) -> 1 | BG53: WGTST | BI53: ECO | BJ53: ECO | BL53: 60 | BM53: =SUM(BL48:BL52)+SUM(BM48:BM52) -> 809
D54: =IF(E54="Mo",WEEKNUM(I54),"") | E54: =TEXT(I54,"TTT") -> Di | F54: =$F$5 -> 2025 | G54: =$A$44 -> 2 | H54: =H53+1 -> 11 | I54: =DATE(F54,G54,H54) -> 44237 | J54: =IF(OR(G54="",G54=MONTH(I54)),1,0) -> 1 | K54: =IF(OR($E54="Sa",$E54="So",$J54=0),K$4,K$5) -> 7 | L54: =IF(OR($E54="Sa",$E54="So",$J54=0),L$4,L$5) -> 0 | M54: =IF(OR($E54="Sa",$E54="So",$J54=0),M$4,M$5) -> 13 | N54: =IF(OR($E54="Sa",$E54="So",$J54=0),N$4,N$5) -> 0 | O54: =IF(OR($E54="Sa",$E54="So",$J54=0),O$4,O$5) -> 13 | P54: =IF(OR($E54="Sa",$E54="So",$J54=0),P$4,P$5) -> 30 | Q54: =IF(OR($E54="Sa",$E54="So",$J54=0),Q$4,Q$5) -> 15 | R54: =IF(OR($E54="Sa",$E54="So",$J54=0),R$4,R$5) -> 55 | S54: =Q54 -> 15 | T54: =R54 -> 55 | U54: =S54 -> 15 | V54: =T54 -> 55 | W54: =TIME(K54,L54,0) -> 0.29166667 | X54: =TIME(M54,N54,0) -> 0.54166667 | Y54: =TIME(O54,P54,0) -> 0.5625 | Z54: =TIME(Q54,R54,0) -> 0.66319444 | AA54: =TIME(S54,T54,0) -> 0.66319444 | AB54: =TIME(U54,V54,0) -> 0.66319444 | AD54: =IF(J54=0,0,IF(OR(E54="Sa",E54="So"),TIME($AD$4,$AF$4,0),TIME($AD$5,$AF$5,0))) -> 0.35069444 | AF54: =IF(J54=0,0,Z54-W54-(Y54-X54)) -> 0.35069444 | AK54: =IF(AH54=$AH$3,1,0) -> 0 | AL54: =IF(AH54=$AH$7,1,0) -> 0 | AM54: =IF(AI54=$AH$4,1,0) -> 0 | AO54: =IF(OR(AH54=$AH$2,AH54=$AH$5),1,IF(AH54=$AH$6,0.5,0)) -> 0 | AP54: =IF(OR(E54="Sa",E54="So",E54="",J54=0,AH54="FT"),0,1) -> 1 | BG54: =INDEX($BF$2:$BG$8,MATCH(BG53,$BF$2:$BF$8,0),2) -> 80.9 | BH54: =INDEX($BF$2:$BG$8,MATCH(BG53,$BF$2:$BF$8,0),2) -> 80.9 | BI54: 15 | BJ54: 15 | BL54: =BM54/BL53 -> 26.966667 | BM54: =SUM(BM46,BM53) -> 1618
D55: =IF(E55="Mo",WEEKNUM(I55),"") | E55: =TEXT(I55,"TTT") -> Mi | F55: =$F$5 -> 2025 | G55: =$A$44 -> 2 | H55: =H54+1 -> 12 | I55: =DATE(F55,G55,H55) -> 44238 | J55: =IF(OR(G55="",G55=MONTH(I55)),1,0) -> 1 | K55: =IF(OR($E55="Sa",$E55="So",$J55=0),K$4,K$5) -> 7 | L55: =IF(OR($E55="Sa",$E55="So",$J55=0),L$4,L$5) -> 0 | M55: =IF(OR($E55="Sa",$E55="So",$J55=0),M$4,M$5) -> 13 | N55: =IF(OR($E55="Sa",$E55="So",$J55=0),N$4,N$5) -> 0 | O55: =IF(OR($E55="Sa",$E55="So",$J55=0),O$4,O$5) -> 13 | P55: =IF(OR($E55="Sa",$E55="So",$J55=0),P$4,P$5) -> 30 | Q55: =IF(OR($E55="Sa",$E55="So",$J55=0),Q$4,Q$5) -> 15 | R55: =IF(OR($E55="Sa",$E55="So",$J55=0),R$4,R$5) -> 55 | S55: =Q55 -> 15 | T55: =R55 -> 55 | U55: =S55 -> 15 | V55: =T55 -> 55 | W55: =TIME(K55,L55,0) -> 0.29166667 | X55: =TIME(M55,N55,0) -> 0.54166667 | Y55: =TIME(O55,P55,0) -> 0.5625 | Z55: =TIME(Q55,R55,0) -> 0.66319444 | AA55: =TIME(S55,T55,0) -> 0.66319444 | AB55: =TIME(U55,V55,0) -> 0.66319444 | AD55: =IF(J55=0,0,IF(OR(E55="Sa",E55="So"),TIME($AD$4,$AF$4,0),TIME($AD$5,$AF$5,0))) -> 0.35069444 | AF55: =IF(J55=0,0,Z55-W55-(Y55-X55)) -> 0.35069444 | AK55: =IF(AH55=$AH$3,1,0) -> 0 | AL55: =IF(AH55=$AH$7,1,0) -> 0 | AM55: =IF(AI55=$AH$4,1,0) -> 0 | AO55: =IF(OR(AH55=$AH$2,AH55=$AH$5),1,IF(AH55=$AH$6,0.5,0)) -> 0 | AP55: =IF(OR(E55="Sa",E55="So",E55="",J55=0,AH55="FT"),0,1) -> 1 | BG55: =BG54 -> 80.9 | BH55: =BH54 -> 80.9 | BI55: =BI54 -> 15 | BJ55: =BI55+BJ54 -> 30 | BL55: =100*BL53/BM54 -> 3.7082818
D56: =IF(E56="Mo",WEEKNUM(I56),"") | E56: =TEXT(I56,"TTT") -> Do | F56: =$F$5 -> 2025 | G56: =$A$44 -> 2 | H56: =H55+1 -> 13 | I56: =DATE(F56,G56,H56) -> 44239 | J56: =IF(OR(G56="",G56=MONTH(I56)),1,0) -> 1 | K56: =IF(OR($E56="Sa",$E56="So",$J56=0),K$4,K$5) -> 7 | L56: =IF(OR($E56="Sa",$E56="So",$J56=0),L$4,L$5) -> 0 | M56: =IF(OR($E56="Sa",$E56="So",$J56=0),M$4,M$5) -> 13 | N56: =IF(OR($E56="Sa",$E56="So",$J56=0),N$4,N$5) -> 0 | O56: =IF(OR($E56="Sa",$E56="So",$J56=0),O$4,O$5) -> 13 | P56: =IF(OR($E56="Sa",$E56="So",$J56=0),P$4,P$5) -> 30 | Q56: =IF(OR($E56="Sa",$E56="So",$J56=0),Q$4,Q$5) -> 15 | R56: =IF(OR($E56="Sa",$E56="So",$J56=0),R$4,R$5) -> 55 | S56: =Q56 -> 15 | T56: =R56 -> 55 | U56: =S56 -> 15 | V56: =T56 -> 55 | W56: =TIME(K56,L56,0) -> 0.29166667 | X56: =TIME(M56,N56,0) -> 0.54166667 | Y56: =TIME(O56,P56,0) -> 0.5625 | Z56: =TIME(Q56,R56,0) -> 0.66319444 | AA56: =TIME(S56,T56,0) -> 0.66319444 | AB56: =TIME(U56,V56,0) -> 0.66319444 | AD56: =IF(J56=0,0,IF(OR(E56="Sa",E56="So"),TIME($AD$4,$AF$4,0),TIME($AD$5,$AF$5,0))) -> 0.35069444 | AF56: =IF(J56=0,0,Z56-W56-(Y56-X56)) -> 0.35069444 | AK56: =IF(AH56=$AH$3,1,0) -> 0 | AL56: =IF(AH56=$AH$7,1,0) -> 0 | AM56: =IF(AI56=$AH$4,1,0) -> 0 | AO56: =IF(OR(AH56=$AH$2,AH56=$AH$5),1,IF(AH56=$AH$6,0.5,0)) -> 0 | AP56: =IF(OR(E56="Sa",E56="So",E56="",J56=0,AH56="FT"),0,1) -> 1 | BG56: =BG54 -> 80.9 | BH56: =BH54 -> 80.9 | BI56: =BJ55+BI54 -> 45 | BJ56: =BI56+BJ54 -> 60
D57: =IF(E57="Mo",WEEKNUM(I57),"") | E57: =TEXT(I57,"TTT") -> Fr | F57: =$F$5 -> 2025 | G57: =$A$44 -> 2 | H57: =H56+1 -> 14 | I57: =DATE(F57,G57,H57) -> 44240 | J57: =IF(OR(G57="",G57=MONTH(I57)),1,0) -> 1 | K57: =IF(OR($E57="Sa",$E57="So",$J57=0),K$4,K$5) -> 7 | L57: =IF(OR($E57="Sa",$E57="So",$J57=0),L$4,L$5) -> 0 | M57: =IF(OR($E57="Sa",$E57="So",$J57=0),M$4,M$5) -> 13 | N57: =IF(OR($E57="Sa",$E57="So",$J57=0),N$4,N$5) -> 0 | O57: =IF(OR($E57="Sa",$E57="So",$J57=0),O$4,O$5) -> 13 | P57: =IF(OR($E57="Sa",$E57="So",$J57=0),P$4,P$5) -> 30 | Q57: =IF(OR($E57="Sa",$E57="So",$J57=0),Q$4,Q$5) -> 15 | R57: =IF(OR($E57="Sa",$E57="So",$J57=0),R$4,R$5) -> 55 | S57: =Q57 -> 15 | T57: =R57 -> 55 | U57: =S57 -> 15 | V57: =T57 -> 55 | W57: =TIME(K57,L57,0) -> 0.29166667 | X57: =TIME(M57,N57,0) -> 0.54166667 | Y57: =TIME(O57,P57,0) -> 0.5625 | Z57: =TIME(Q57,R57,0) -> 0.66319444 | AA57: =TIME(S57,T57,0) -> 0.66319444 | AB57: =TIME(U57,V57,0) -> 0.66319444 | AD57: =IF(J57=0,0,IF(OR(E57="Sa",E57="So"),TIME($AD$4,$AF$4,0),TIME($AD$5,$AF$5,0))) -> 0.35069444 | AF57: =IF(J57=0,0,Z57-W57-(Y57-X57)) -> 0.35069444 | AK57: =IF(AH57=$AH$3,1,0) -> 0 | AL57: =IF(AH57=$AH$7,1,0) -> 0 | AM57: =IF(AI57=$AH$4,1,0) -> 0 | AO57: =IF(OR(AH57=$AH$2,AH57=$AH$5),1,IF(AH57=$AH$6,0.5,0)) -> 0 | AP57: =IF(OR(E57="Sa",E57="So",E57="",J57=0,AH57="FT"),0,1) -> 1 | BG57: =BG54 -> 80.9 | BH57: =BH54 -> 80.9 | BI57: =BJ56+BI54 -> 75 | BJ57: =BI57+BJ54 -> 90
D58: =IF(E58="Mo",WEEKNUM(I58),"") | E58: =TEXT(I58,"TTT") -> Sa | F58: =$F$5 -> 2025 | G58: =$A$44 -> 2 | H58: =H57+1 -> 15 | I58: =DATE(F58,G58,H58) -> 44241 | J58: =IF(OR(G58="",G58=MONTH(I58)),1,0) -> 1 | K58: =IF(OR($E58="Sa",$E58="So",$J58=0),K$4,K$5) -> 0 | L58: =IF(OR($E58="Sa",$E58="So",$J58=0),L$4,L$5) -> 0 | M58: =IF(OR($E58="Sa",$E58="So",$J58=0),M$4,M$5) -> 0 | N58: =IF(OR($E58="Sa",$E58="So",$J58=0),N$4,N$5) -> 0 | O58: =IF(OR($E58="Sa",$E58="So",$J58=0),O$4,O$5) -> 0 | P58: =IF(OR($E58="Sa",$E58="So",$J58=0),P$4,P$5) -> 0 | Q58: =IF(OR($E58="Sa",$E58="So",$J58=0),Q$4,Q$5) -> 0 | R58: =IF(OR($E58="Sa",$E58="So",$J58=0),R$4,R$5) -> 0 | S58: =Q58 -> 0 | T58: =R58 -> 0 | U58: =S58 -> 0 | V58: =T58 -> 0 | W58: =TIME(K58,L58,0) -> 0 | X58: =TIME(M58,N58,0) -> 0 | Y58: =TIME(O58,P58,0) -> 0 | Z58: =TIME(Q58,R58,0) -> 0 | AA58: =TIME(S58,T58,0) -> 0 | AB58: =TIME(U58,V58,0) -> 0 | AD58: =IF(J58=0,0,IF(OR(E58="Sa",E58="So"),TIME($AD$4,$AF$4,0),TIME($AD$5,$AF$5,0))) -> 0 | AF58: =IF(J58=0,0,Z58-W58-(Y58-X58)) -> 0 | AK58: =IF(AH58=$AH$3,1,0) -> 0 | AL58: =IF(AH58=$AH$7,1,0) -> 0 | AM58: =IF(AI58=$AH$4,1,0) -> 0 | AO58: =IF(OR(AH58=$AH$2,AH58=$AH$5),1,IF(AH58=$AH$6,0.5,0)) -> 0 | AP58: =IF(OR(E58="Sa",E58="So",E58="",J58=0,AH58="FT"),0,1) -> 0 | BG58: =BG54 -> 80.9 | BH58: =BH54 -> 80.9 | BI58: =BJ57+BI54 -> 105 | BJ58: =BI58+BJ54 -> 120
D59: =IF(E59="Mo",WEEKNUM(I59),"") | E59: =TEXT(I59,"TTT") -> So | F59: =$F$5 -> 2025 | G59: =$A$44 -> 2 | H59: =H58+1 -> 16 | I59: =DATE(F59,G59,H59) -> 44242 | J59: =IF(OR(G59="",G59=MONTH(I59)),1,0) -> 1 | K59: =IF(OR($E59="Sa",$E59="So",$J59=0),K$4,K$5) -> 0 | L59: =IF(OR($E59="Sa",$E59="So",$J59=0),L$4,L$5) -> 0 | M59: =IF(OR($E59="Sa",$E59="So",$J59=0),M$4,M$5) -> 0 | N59: =IF(OR($E59="Sa",$E59="So",$J59=0),N$4,N$5) -> 0 | O59: =IF(OR($E59="Sa",$E59="So",$J59=0),O$4,O$5) -> 0 | P59: =IF(OR($E59="Sa",$E59="So",$J59=0),P$4,P$5) -> 0 | Q59: =IF(OR($E59="Sa",$E59="So",$J59=0),Q$4,Q$5) -> 0 | R59: =IF(OR($E59="Sa",$E59="So",$J59=0),R$4,R$5) -> 0 | S59: =Q59 -> 0 | T59: =R59 -> 0 | U59: =S59 -> 0 | V59: =T59 -> 0 | W59: =TIME(K59,L59,0) -> 0 | X59: =TIME(M59,N59,0) -> 0 | Y59: =TIME(O59,P59,0) -> 0 | Z59: =TIME(Q59,R59,0) -> 0 | AA59: =TIME(S59,T59,0) -> 0 | AB59: =TIME(U59,V59,0) -> 0 | AD59: =IF(J59=0,0,IF(OR(E59="Sa",E59="So"),TIME($AD$4,$AF$4,0),TIME($AD$5,$AF$5,0))) -> 0 | AF59: =IF(J59=0,0,Z59-W59-(Y59-X59)) -> 0 | AK59: =IF(AH59=$AH$3,1,0) -> 0 | AL59: =IF(AH59=$AH$7,1,0) -> 0 | AM59: =IF(AI59=$AH$4,1,0) -> 0 | AO59: =IF(OR(AH59=$AH$2,AH59=$AH$5),1,IF(AH59=$AH$6,0.5,0)) -> 0 | AP59: =IF(OR(E59="Sa",E59="So",E59="",J59=0,AH59="FT"),0,1) -> 0 | BG59: =BG54 -> 80.9 | BH59: =BH54 -> 80.9 | BI59: =BJ58+BI54 -> 135 | BJ59: =BI59+BJ54 -> 150
D60: =IF(E60="Mo",WEEKNUM(I60),"") -> 8 | E60: =TEXT(I60,"TTT") -> Mo | F60: =$F$5 -> 2025 | G60: =$A$44 -> 2 | H60: =H59+1 -> 17 | I60: =DATE(F60,G60,H60) -> 44243 | J60: =IF(OR(G60="",G60=MONTH(I60)),1,0) -> 1 | K60: =IF(OR($E60="Sa",$E60="So",$J60=0),K$4,K$5) -> 7 | L60: =IF(OR($E60="Sa",$E60="So",$J60=0),L$4,L$5) -> 0 | M60: =IF(OR($E60="Sa",$E60="So",$J60=0),M$4,M$5) -> 13 | N60: =IF(OR($E60="Sa",$E60="So",$J60=0),N$4,N$5) -> 0 | O60: =IF(OR($E60="Sa",$E60="So",$J60=0),O$4,O$5) -> 13 | P60: =IF(OR($E60="Sa",$E60="So",$J60=0),P$4,P$5) -> 30 | Q60: =IF(OR($E60="Sa",$E60="So",$J60=0),Q$4,Q$5) -> 15 | R60: =IF(OR($E60="Sa",$E60="So",$J60=0),R$4,R$5) -> 55 | S60: =Q60 -> 15 | T60: =R60 -> 55 | U60: =S60 -> 15 | V60: =T60 -> 55 | W60: =TIME(K60,L60,0) -> 0.29166667 | X60: =TIME(M60,N60,0) -> 0.54166667 | Y60: =TIME(O60,P60,0) -> 0.5625 | Z60: =TIME(Q60,R60,0) -> 0.66319444 | AA60: =TIME(S60,T60,0) -> 0.66319444 | AB60: =TIME(U60,V60,0) -> 0.66319444 | AD60: =IF(J60=0,0,IF(OR(E60="Sa",E60="So"),TIME($AD$4,$AF$4,0),TIME($AD$5,$AF$5,0))) -> 0.35069444 | AF60: =IF(J60=0,0,Z60-W60-(Y60-X60)) -> 0.35069444 | AK60: =IF(AH60=$AH$3,1,0) -> 0 | AL60: =IF(AH60=$AH$7,1,0) -> 0 | AM60: =IF(AI60=$AH$4,1,0) -> 0 | AO60: =IF(OR(AH60=$AH$2,AH60=$AH$5),1,IF(AH60=$AH$6,0.5,0)) -> 0 | AP60: =IF(OR(E60="Sa",E60="So",E60="",J60=0,AH60="FT"),0,1) -> 1 | BG60: WGTST | BH60: =SUM(BG55:BG59)+SUM(BH55:BH59) -> 809 | BI60: ECO | BJ60: ECO
D61: =IF(E61="Mo",WEEKNUM(I61),"") | E61: =TEXT(I61,"TTT") -> Di | F61: =$F$5 -> 2025 | G61: =$A$44 -> 2 | H61: =H60+1 -> 18 | I61: =DATE(F61,G61,H61) -> 44244 | J61: =IF(OR(G61="",G61=MONTH(I61)),1,0) -> 1 | K61: =IF(OR($E61="Sa",$E61="So",$J61=0),K$4,K$5) -> 7 | L61: =IF(OR($E61="Sa",$E61="So",$J61=0),L$4,L$5) -> 0 | M61: =IF(OR($E61="Sa",$E61="So",$J61=0),M$4,M$5) -> 13 | N61: =IF(OR($E61="Sa",$E61="So",$J61=0),N$4,N$5) -> 0 | O61: =IF(OR($E61="Sa",$E61="So",$J61=0),O$4,O$5) -> 13 | P61: =IF(OR($E61="Sa",$E61="So",$J61=0),P$4,P$5) -> 30 | Q61: =IF(OR($E61="Sa",$E61="So",$J61=0),Q$4,Q$5) -> 15 | R61: =IF(OR($E61="Sa",$E61="So",$J61=0),R$4,R$5) -> 55 | S61: =Q61 -> 15 | T61: =R61 -> 55 | U61: =S61 -> 15 | V61: =T61 -> 55 | W61: =TIME(K61,L61,0) -> 0.29166667 | X61: =TIME(M61,N61,0) -> 0.54166667 | Y61: =TIME(O61,P61,0) -> 0.5625 | Z61: =TIME(Q61,R61,0) -> 0.66319444 | AA61: =TIME(S61,T61,0) -> 0.66319444 | AB61: =TIME(U61,V61,0) -> 0.66319444 | AD61: =IF(J61=0,0,IF(OR(E61="Sa",E61="So"),TIME($AD$4,$AF$4,0),TIME($AD$5,$AF$5,0))) -> 0.35069444 | AF61: =IF(J61=0,0,Z61-W61-(Y61-X61)) -> 0.35069444 | AK61: =IF(AH61=$AH$3,1,0) -> 0 | AL61: =IF(AH61=$AH$7,1,0) -> 0 | AM61: =IF(AI61=$AH$4,1,0) -> 0 | AO61: =IF(OR(AH61=$AH$2,AH61=$AH$5),1,IF(AH61=$AH$6,0.5,0)) -> 0 | AP61: =IF(OR(E61="Sa",E61="So",E61="",J61=0,AH61="FT"),0,1) -> 1 | BG61: =INDEX($BF$2:$BG$8,MATCH(BG60,$BF$2:$BF$8,0),2) -> 80.9 | BH61: =INDEX($BF$2:$BG$8,MATCH(BG60,$BF$2:$BF$8,0),2) -> 80.9 | BI61: 15 | BJ61: 15
D62: =IF(E62="Mo",WEEKNUM(I62),"") | E62: =TEXT(I62,"TTT") -> Mi | F62: =$F$5 -> 2025 | G62: =$A$44 -> 2 | H62: =H61+1 -> 19 | I62: =DATE(F62,G62,H62) -> 44245 | J62: =IF(OR(G62="",G62=MONTH(I62)),1,0) -> 1 | K62: =IF(OR($E62="Sa",$E62="So",$J62=0),K$4,K$5) -> 7 | L62: =IF(OR($E62="Sa",$E62="So",$J62=0),L$4,L$5) -> 0 | M62: =IF(OR($E62="Sa",$E62="So",$J62=0),M$4,M$5) -> 13 | N62: =IF(OR($E62="Sa",$E62="So",$J62=0),N$4,N$5) -> 0 | O62: =IF(OR($E62="Sa",$E62="So",$J62=0),O$4,O$5) -> 13 | P62: =IF(OR($E62="Sa",$E62="So",$J62=0),P$4,P$5) -> 30 | Q62: =IF(OR($E62="Sa",$E62="So",$J62=0),Q$4,Q$5) -> 15 | R62: =IF(OR($E62="Sa",$E62="So",$J62=0),R$4,R$5) -> 55 | S62: =Q62 -> 15 | T62: =R62 -> 55 | U62: =S62 -> 15 | V62: =T62 -> 55 | W62: =TIME(K62,L62,0) -> 0.29166667 | X62: =TIME(M62,N62,0) -> 0.54166667 | Y62: =TIME(O62,P62,0) -> 0.5625 | Z62: =TIME(Q62,R62,0) -> 0.66319444 | AA62: =TIME(S62,T62,0) -> 0.66319444 | AB62: =TIME(U62,V62,0) -> 0.66319444 | AD62: =IF(J62=0,0,IF(OR(E62="Sa",E62="So"),TIME($AD$4,$AF$4,0),TIME($AD$5,$AF$5,0))) -> 0.35069444 | AF62: =IF(J62=0,0,Z62-W62-(Y62-X62)) -> 0.35069444 | AK62: =IF(AH62=$AH$3,1,0) -> 0 | AL62: =IF(AH62=$AH$7,1,0) -> 0 | AM62: =IF(AI62=$AH$4,1,0) -> 0 | AO62: =IF(OR(AH62=$AH$2,AH62=$AH$5),1,IF(AH62=$AH$6,0.5,0)) -> 0 | AP62: =IF(OR(E62="Sa",E62="So",E62="",J62=0,AH62="FT"),0,1) -> 1 | BG62: =BG61 -> 80.9 | BH62: =BH61 -> 80.9 | BI62: =BI61 -> 15 | BJ62: =BI62+BJ61 -> 30
D63: =IF(E63="Mo",WEEKNUM(I63),"") | E63: =TEXT(I63,"TTT") -> Do | F63: =$F$5 -> 2025 | G63: =$A$44 -> 2 | H63: =H62+1 -> 20 | I63: =DATE(F63,G63,H63) -> 44246 | J63: =IF(OR(G63="",G63=MONTH(I63)),1,0) -> 1 | K63: =IF(OR($E63="Sa",$E63="So",$J63=0),K$4,K$5) -> 7 | L63: =IF(OR($E63="Sa",$E63="So",$J63=0),L$4,L$5) -> 0 | M63: =IF(OR($E63="Sa",$E63="So",$J63=0),M$4,M$5) -> 13 | N63: =IF(OR($E63="Sa",$E63="So",$J63=0),N$4,N$5) -> 0 | O63: =IF(OR($E63="Sa",$E63="So",$J63=0),O$4,O$5) -> 13 | P63: =IF(OR($E63="Sa",$E63="So",$J63=0),P$4,P$5) -> 30 | Q63: =IF(OR($E63="Sa",$E63="So",$J63=0),Q$4,Q$5) -> 15 | R63: =IF(OR($E63="Sa",$E63="So",$J63=0),R$4,R$5) -> 55 | S63: =Q63 -> 15 | T63: =R63 -> 55 | U63: =S63 -> 15 | V63: =T63 -> 55 | W63: =TIME(K63,L63,0) -> 0.29166667 | X63: =TIME(M63,N63,0) -> 0.54166667 | Y63: =TIME(O63,P63,0) -> 0.5625 | Z63: =TIME(Q63,R63,0) -> 0.66319444 | AA63: =TIME(S63,T63,0) -> 0.66319444 | AB63: =TIME(U63,V63,0) -> 0.66319444 | AD63: =IF(J63=0,0,IF(OR(E63="Sa",E63="So"),TIME($AD$4,$AF$4,0),TIME($AD$5,$AF$5,0))) -> 0.35069444 | AF63: =IF(J63=0,0,Z63-W63-(Y63-X63)) -> 0.35069444 | AK63: =IF(AH63=$AH$3,1,0) -> 0 | AL63: =IF(AH63=$AH$7,1,0) -> 0 | AM63: =IF(AI63=$AH$4,1,0) -> 0 | AO63: =IF(OR(AH63=$AH$2,AH63=$AH$5),1,IF(AH63=$AH$6,0.5,0)) -> 0 | AP63: =IF(OR(E63="Sa",E63="So",E63="",J63=0,AH63="FT"),0,1) -> 1 | BG63: =BG61 -> 80.9 | BH63: =BH61 -> 80.9 | BI63: =BJ62+BI61 -> 45 | BJ63: =BI63+BJ61 -> 60
D64: =IF(E64="Mo",WEEKNUM(I64),"") | E64: =TEXT(I64,"TTT") -> Fr | F64: =$F$5 -> 2025 | G64: =$A$44 -> 2 | H64: =H63+1 -> 21 | I64: =DATE(F64,G64,H64) -> 44247 | J64: =IF(OR(G64="",G64=MONTH(I64)),1,0) -> 1 | K64: =IF(OR($E64="Sa",$E64="So",$J64=0),K$4,K$5) -> 7 | L64: =IF(OR($E64="Sa",$E64="So",$J64=0),L$4,L$5) -> 0 | M64: =IF(OR($E64="Sa",$E64="So",$J64=0),M$4,M$5) -> 13 | N64: =IF(OR($E64="Sa",$E64="So",$J64=0),N$4,N$5) -> 0 | O64: =IF(OR($E64="Sa",$E64="So",$J64=0),O$4,O$5) -> 13 | P64: =IF(OR($E64="Sa",$E64="So",$J64=0),P$4,P$5) -> 30 | Q64: =IF(OR($E64="Sa",$E64="So",$J64=0),Q$4,Q$5) -> 15 | R64: =IF(OR($E64="Sa",$E64="So",$J64=0),R$4,R$5) -> 55 | S64: =Q64 -> 15 | T64: =R64 -> 55 | U64: =S64 -> 15 | V64: =T64 -> 55 | W64: =TIME(K64,L64,0) -> 0.29166667 | X64: =TIME(M64,N64,0) -> 0.54166667 | Y64: =TIME(O64,P64,0) -> 0.5625 | Z64: =TIME(Q64,R64,0) -> 0.66319444 | AA64: =TIME(S64,T64,0) -> 0.66319444 | AB64: =TIME(U64,V64,0) -> 0.66319444 | AD64: =IF(J64=0,0,IF(OR(E64="Sa",E64="So"),TIME($AD$4,$AF$4,0),TIME($AD$5,$AF$5,0))) -> 0.35069444 | AF64: =IF(J64=0,0,Z64-W64-(Y64-X64)) -> 0.35069444 | AK64: =IF(AH64=$AH$3,1,0) -> 0 | AL64: =IF(AH64=$AH$7,1,0) -> 0 | AM64: =IF(AI64=$AH$4,1,0) -> 0 | AO64: =IF(OR(AH64=$AH$2,AH64=$AH$5),1,IF(AH64=$AH$6,0.5,0)) -> 0 | AP64: =IF(OR(E64="Sa",E64="So",E64="",J64=0,AH64="FT"),0,1) -> 1 | BG64: =BG61 -> 80.9 | BH64: =BH61 -> 80.9 | BI64: =BJ63+BI61 -> 75 | BJ64: =BI64+BJ61 -> 90
D65: =IF(E65="Mo",WEEKNUM(I65),"") | E65: =TEXT(I65,"TTT") -> Sa | F65: =$F$5 -> 2025 | G65: =$A$44 -> 2 | H65: =H64+1 -> 22 | I65: =DATE(F65,G65,H65) -> 44248 | J65: =IF(OR(G65="",G65=MONTH(I65)),1,0) -> 1 | K65: =IF(OR($E65="Sa",$E65="So",$J65=0),K$4,K$5) -> 0 | L65: =IF(OR($E65="Sa",$E65="So",$J65=0),L$4,L$5) -> 0 | M65: =IF(OR($E65="Sa",$E65="So",$J65=0),M$4,M$5) -> 0 | N65: =IF(OR($E65="Sa",$E65="So",$J65=0),N$4,N$5) -> 0 | O65: =IF(OR($E65="Sa",$E65="So",$J65=0),O$4,O$5) -> 0 | P65: =IF(OR($E65="Sa",$E65="So",$J65=0),P$4,P$5) -> 0 | Q65: =IF(OR($E65="Sa",$E65="So",$J65=0),Q$4,Q$5) -> 0 | R65: =IF(OR($E65="Sa",$E65="So",$J65=0),R$4,R$5) -> 0 | S65: =Q65 -> 0 | T65: =R65 -> 0 | U65: =S65 -> 0 | V65: =T65 -> 0 | W65: =TIME(K65,L65,0) -> 0 | X65: =TIME(M65,N65,0) -> 0 | Y65: =TIME(O65,P65,0) -> 0 | Z65: =TIME(Q65,R65,0) -> 0 | AA65: =TIME(S65,T65,0) -> 0 | AB65: =TIME(U65,V65,0) -> 0 | AD65: =IF(J65=0,0,IF(OR(E65="Sa",E65="So"),TIME($AD$4,$AF$4,0),TIME($AD$5,$AF$5,0))) -> 0 | AF65: =IF(J65=0,0,Z65-W65-(Y65-X65)) -> 0 | AK65: =IF(AH65=$AH$3,1,0) -> 0 | AL65: =IF(AH65=$AH$7,1,0) -> 0 | AM65: =IF(AI65=$AH$4,1,0) -> 0 | AO65: =IF(OR(AH65=$AH$2,AH65=$AH$5),1,IF(AH65=$AH$6,0.5,0)) -> 0 | AP65: =IF(OR(E65="Sa",E65="So",E65="",J65=0,AH65="FT"),0,1) -> 0 | BG65: =BG61 -> 80.9 | BH65: =BH61 -> 80.9 | BI65: =BJ64+BI61 -> 105 | BJ65: =BI65+BJ61 -> 120
D66: =IF(E66="Mo",WEEKNUM(I66),"") | E66: =TEXT(I66,"TTT") -> So | F66: =$F$5 -> 2025 | G66: =$A$44 -> 2 | H66: =H65+1 -> 23 | I66: =DATE(F66,G66,H66) -> 44249 | J66: =IF(OR(G66="",G66=MONTH(I66)),1,0) -> 1 | K66: =IF(OR($E66="Sa",$E66="So",$J66=0),K$4,K$5) -> 0 | L66: =IF(OR($E66="Sa",$E66="So",$J66=0),L$4,L$5) -> 0 | M66: =IF(OR($E66="Sa",$E66="So",$J66=0),M$4,M$5) -> 0 | N66: =IF(OR($E66="Sa",$E66="So",$J66=0),N$4,N$5) -> 0 | O66: =IF(OR($E66="Sa",$E66="So",$J66=0),O$4,O$5) -> 0 | P66: =IF(OR($E66="Sa",$E66="So",$J66=0),P$4,P$5) -> 0 | Q66: =IF(OR($E66="Sa",$E66="So",$J66=0),Q$4,Q$5) -> 0 | R66: =IF(OR($E66="Sa",$E66="So",$J66=0),R$4,R$5) -> 0 | S66: =Q66 -> 0 | T66: =R66 -> 0 | U66: =S66 -> 0 | V66: =T66 -> 0 | W66: =TIME(K66,L66,0) -> 0 | X66: =TIME(M66,N66,0) -> 0 | Y66: =TIME(O66,P66,0) -> 0 | Z66: =TIME(Q66,R66,0) -> 0 | AA66: =TIME(S66,T66,0) -> 0 | AB66: =TIME(U66,V66,0) -> 0 | AD66: =IF(J66=0,0,IF(OR(E66="Sa",E66="So"),TIME($AD$4,$AF$4,0),TIME($AD$5,$AF$5,0))) -> 0 | AF66: =IF(J66=0,0,Z66-W66-(Y66-X66)) -> 0 | AK66: =IF(AH66=$AH$3,1,0) -> 0 | AL66: =IF(AH66=$AH$7,1,0) -> 0 | AM66: =IF(AI66=$AH$4,1,0) -> 0 | AO66: =IF(OR(AH66=$AH$2,AH66=$AH$5),1,IF(AH66=$AH$6,0.5,0)) -> 0 | AP66: =IF(OR(E66="Sa",E66="So",E66="",J66=0,AH66="FT"),0,1) -> 0 | BG66: =BG61 -> 80.9 | BH66: =BH61 -> 80.9 | BI66: =BJ65+BI61 -> 135 | BJ66: =BI66+BJ61 -> 150
D67: =IF(E67="Mo",WEEKNUM(I67),"") -> 9 | E67: =TEXT(I67,"TTT") -> Mo | F67: =$F$5 -> 2025 | G67: =$A$44 -> 2 | H67: =H66+1 -> 24 | I67: =DATE(F67,G67,H67) -> 44250 | J67: =IF(OR(G67="",G67=MONTH(I67)),1,0) -> 1 | K67: =IF(OR($E67="Sa",$E67="So",$J67=0),K$4,K$5) -> 7 | L67: =IF(OR($E67="Sa",$E67="So",$J67=0),L$4,L$5) -> 0 | M67: =IF(OR($E67="Sa",$E67="So",$J67=0),M$4,M$5) -> 13 | N67: =IF(OR($E67="Sa",$E67="So",$J67=0),N$4,N$5) -> 0 | O67: =IF(OR($E67="Sa",$E67="So",$J67=0),O$4,O$5) -> 13 | P67: =IF(OR($E67="Sa",$E67="So",$J67=0),P$4,P$5) -> 30 | Q67: =IF(OR($E67="Sa",$E67="So",$J67=0),Q$4,Q$5) -> 15 | R67: =IF(OR($E67="Sa",$E67="So",$J67=0),R$4,R$5) -> 55 | S67: =Q67 -> 15 | T67: =R67 -> 55 | U67: =S67 -> 15 | V67: =T67 -> 55 | W67: =TIME(K67,L67,0) -> 0.29166667 | X67: =TIME(M67,N67,0) -> 0.54166667 | Y67: =TIME(O67,P67,0) -> 0.5625 | Z67: =TIME(Q67,R67,0) -> 0.66319444 | AA67: =TIME(S67,T67,0) -> 0.66319444 | AB67: =TIME(U67,V67,0) -> 0.66319444 | AD67: =IF(J67=0,0,IF(OR(E67="Sa",E67="So"),TIME($AD$4,$AF$4,0),TIME($AD$5,$AF$5,0))) -> 0.35069444 | AF67: =IF(J67=0,0,Z67-W67-(Y67-X67)) -> 0.35069444 | AK67: =IF(AH67=$AH$3,1,0) -> 0 | AL67: =IF(AH67=$AH$7,1,0) -> 0 | AM67: =IF(AI67=$AH$4,1,0) -> 0 | AO67: =IF(OR(AH67=$AH$2,AH67=$AH$5),1,IF(AH67=$AH$6,0.5,0)) -> 0 | AP67: =IF(OR(E67="Sa",E67="So",E67="",J67=0,AH67="FT"),0,1) -> 1 | BG67: 60 | BH67: =SUM(BG62:BG66)+SUM(BH62:BH66) -> 809 | BL67: WGTST | BN67: ECO | BO67: ECO
D68: =IF(E68="Mo",WEEKNUM(I68),"") | E68: =TEXT(I68,"TTT") -> Di | F68: =$F$5 -> 2025 | G68: =$A$44 -> 2 | H68: =H67+1 -> 25 | I68: =DATE(F68,G68,H68) -> 44251 | J68: =IF(OR(G68="",G68=MONTH(I68)),1,0) -> 1 | K68: =IF(OR($E68="Sa",$E68="So",$J68=0),K$4,K$5) -> 7 | L68: =IF(OR($E68="Sa",$E68="So",$J68=0),L$4,L$5) -> 0 | M68: =IF(OR($E68="Sa",$E68="So",$J68=0),M$4,M$5) -> 13 | N68: =IF(OR($E68="Sa",$E68="So",$J68=0),N$4,N$5) -> 0 | O68: =IF(OR($E68="Sa",$E68="So",$J68=0),O$4,O$5) -> 13 | P68: =IF(OR($E68="Sa",$E68="So",$J68=0),P$4,P$5) -> 30 | Q68: =IF(OR($E68="Sa",$E68="So",$J68=0),Q$4,Q$5) -> 15 | R68: =IF(OR($E68="Sa",$E68="So",$J68=0),R$4,R$5) -> 55 | S68: =Q68 -> 15 | T68: =R68 -> 55 | U68: =S68 -> 15 | V68: =T68 -> 55 | W68: =TIME(K68,L68,0) -> 0.29166667 | X68: =TIME(M68,N68,0) -> 0.54166667 | Y68: =TIME(O68,P68,0) -> 0.5625 | Z68: =TIME(Q68,R68,0) -> 0.66319444 | AA68: =TIME(S68,T68,0) -> 0.66319444 | AB68: =TIME(U68,V68,0) -> 0.66319444 | AD68: =IF(J68=0,0,IF(OR(E68="Sa",E68="So"),TIME($AD$4,$AF$4,0),TIME($AD$5,$AF$5,0))) -> 0.35069444 | AF68: =IF(J68=0,0,Z68-W68-(Y68-X68)) -> 0.35069444 | AK68: =IF(AH68=$AH$3,1,0) -> 0 | AL68: =IF(AH68=$AH$7,1,0) -> 0 | AM68: =IF(AI68=$AH$4,1,0) -> 0 | AO68: =IF(OR(AH68=$AH$2,AH68=$AH$5),1,IF(AH68=$AH$6,0.5,0)) -> 0 | AP68: =IF(OR(E68="Sa",E68="So",E68="",J68=0,AH68="FT"),0,1) -> 1 | BG68: =BH68/BG67 -> 26.966667 | BH68: =SUM(BH60,BH67) -> 1618 | BL68: =INDEX($BF$2:$BG$8,MATCH(BL67,$BF$2:$BF$8,0),2) -> 80.9 | BM68: =INDEX($BF$2:$BG$8,MATCH(BL67,$BF$2:$BF$8,0),2) -> 80.9 | BN68: 15 | BO68: 15
D69: =IF(E69="Mo",WEEKNUM(I69),"") | E69: =TEXT(I69,"TTT") -> Mi | F69: =$F$5 -> 2025 | G69: =$A$44 -> 2 | H69: =H68+1 -> 26 | I69: =DATE(F69,G69,H69) -> 44252 | J69: =IF(OR(G69="",G69=MONTH(I69)),1,0) -> 1 | K69: =IF(OR($E69="Sa",$E69="So",$J69=0),K$4,K$5) -> 7 | L69: =IF(OR($E69="Sa",$E69="So",$J69=0),L$4,L$5) -> 0 | M69: =IF(OR($E69="Sa",$E69="So",$J69=0),M$4,M$5) -> 13 | N69: =IF(OR($E69="Sa",$E69="So",$J69=0),N$4,N$5) -> 0 | O69: =IF(OR($E69="Sa",$E69="So",$J69=0),O$4,O$5) -> 13 | P69: =IF(OR($E69="Sa",$E69="So",$J69=0),P$4,P$5) -> 30 | Q69: =IF(OR($E69="Sa",$E69="So",$J69=0),Q$4,Q$5) -> 15 | R69: =IF(OR($E69="Sa",$E69="So",$J69=0),R$4,R$5) -> 55 | S69: =Q69 -> 15 | T69: =R69 -> 55 | U69: =S69 -> 15 | V69: =T69 -> 55 | W69: =TIME(K69,L69,0) -> 0.29166667 | X69: =TIME(M69,N69,0) -> 0.54166667 | Y69: =TIME(O69,P69,0) -> 0.5625 | Z69: =TIME(Q69,R69,0) -> 0.66319444 | AA69: =TIME(S69,T69,0) -> 0.66319444 | AB69: =TIME(U69,V69,0) -> 0.66319444 | AD69: =IF(J69=0,0,IF(OR(E69="Sa",E69="So"),TIME($AD$4,$AF$4,0),TIME($AD$5,$AF$5,0))) -> 0.35069444 | AF69: =IF(J69=0,0,Z69-W69-(Y69-X69)) -> 0.35069444 | AK69: =IF(AH69=$AH$3,1,0) -> 0 | AL69: =IF(AH69=$AH$7,1,0) -> 0 | AM69: =IF(AI69=$AH$4,1,0) -> 0 | AO69: =IF(OR(AH69=$AH$2,AH69=$AH$5),1,IF(AH69=$AH$6,0.5,0)) -> 0 | AP69: =IF(OR(E69="Sa",E69="So",E69="",J69=0,AH69="FT"),0,1) -> 1 | BG69: =100*BG67/BH68 -> 3.7082818 | BL69: =BL68 -> 80.9 | BM69: =BM68 -> 80.9 | BN69: =BN68 -> 15 | BO69: =BN69+BO68 -> 30
D70: =IF(E70="Mo",WEEKNUM(I70),"") | E70: =TEXT(I70,"TTT") -> Do | F70: =$F$5 -> 2025 | G70: =$A$44 -> 2 | H70: =H69+1 -> 27 | I70: =DATE(F70,G70,H70) -> 44253 | J70: =IF(OR(G70="",G70=MONTH(I70)),1,0) -> 1 | K70: =IF(OR($E70="Sa",$E70="So",$J70=0),K$4,K$5) -> 7 | L70: =IF(OR($E70="Sa",$E70="So",$J70=0),L$4,L$5) -> 0 | M70: =IF(OR($E70="Sa",$E70="So",$J70=0),M$4,M$5) -> 13 | N70: =IF(OR($E70="Sa",$E70="So",$J70=0),N$4,N$5) -> 0 | O70: =IF(OR($E70="Sa",$E70="So",$J70=0),O$4,O$5) -> 13 | P70: =IF(OR($E70="Sa",$E70="So",$J70=0),P$4,P$5) -> 30 | Q70: =IF(OR($E70="Sa",$E70="So",$J70=0),Q$4,Q$5) -> 15 | R70: =IF(OR($E70="Sa",$E70="So",$J70=0),R$4,R$5) -> 55 | S70: =Q70 -> 15 | T70: =R70 -> 55 | U70: =S70 -> 15 | V70: =T70 -> 55 | W70: =TIME(K70,L70,0) -> 0.29166667 | X70: =TIME(M70,N70,0) -> 0.54166667 | Y70: =TIME(O70,P70,0) -> 0.5625 | Z70: =TIME(Q70,R70,0) -> 0.66319444 | AA70: =TIME(S70,T70,0) -> 0.66319444 | AB70: =TIME(U70,V70,0) -> 0.66319444 | AD70: =IF(J70=0,0,IF(OR(E70="Sa",E70="So"),TIME($AD$4,$AF$4,0),TIME($AD$5,$AF$5,0))) -> 0.35069444 | AF70: =IF(J70=0,0,Z70-W70-(Y70-X70)) -> 0.35069444 | AK70: =IF(AH70=$AH$3,1,0) -> 0 | AL70: =IF(AH70=$AH$7,1,0) -> 0 | AM70: =IF(AI70=$AH$4,1,0) -> 0 | AO70: =IF(OR(AH70=$AH$2,AH70=$AH$5),1,IF(AH70=$AH$6,0.5,0)) -> 0 | AP70: =IF(OR(E70="Sa",E70="So",E70="",J70=0,AH70="FT"),0,1) -> 1 | BL70: =BL68 -> 80.9 | BM70: =BM68 -> 80.9 | BN70: =BO69+BN68 -> 45 | BO70: =BN70+BO68 -> 60
D71: =IF(E71="Mo",WEEKNUM(I71),"") | E71: =TEXT(I71,"TTT") -> Fr | F71: =$F$5 -> 2025 | G71: =$A$44 -> 2 | H71: =H70+1 -> 28 | I71: =DATE(F71,G71,H71) -> 44254 | J71: =IF(OR(G71="",G71=MONTH(I71)),1,0) -> 1 | K71: =IF(OR($E71="Sa",$E71="So",$J71=0),K$4,K$5) -> 7 | L71: =IF(OR($E71="Sa",$E71="So",$J71=0),L$4,L$5) -> 0 | M71: =IF(OR($E71="Sa",$E71="So",$J71=0),M$4,M$5) -> 13 | N71: =IF(OR($E71="Sa",$E71="So",$J71=0),N$4,N$5) -> 0 | O71: =IF(OR($E71="Sa",$E71="So",$J71=0),O$4,O$5) -> 13 | P71: =IF(OR($E71="Sa",$E71="So",$J71=0),P$4,P$5) -> 30 | Q71: =IF(OR($E71="Sa",$E71="So",$J71=0),Q$4,Q$5) -> 15 | R71: =IF(OR($E71="Sa",$E71="So",$J71=0),R$4,R$5) -> 55 | S71: =Q71 -> 15 | T71: =R71 -> 55 | U71: =S71 -> 15 | V71: =T71 -> 55 | W71: =TIME(K71,L71,0) -> 0.29166667 | X71: =TIME(M71,N71,0) -> 0.54166667 | Y71: =TIME(O71,P71,0) -> 0.5625 | Z71: =TIME(Q71,R71,0) -> 0.66319444 | AA71: =TIME(S71,T71,0) -> 0.66319444 | AB71: =TIME(U71,V71,0) -> 0.66319444 | AD71: =IF(J71=0,0,IF(OR(E71="Sa",E71="So"),TIME($AD$4,$AF$4,0),TIME($AD$5,$AF$5,0))) -> 0.35069444 | AF71: =IF(J71=0,0,Z71-W71-(Y71-X71)) -> 0.35069444 | AK71: =IF(AH71=$AH$3,1,0) -> 0 | AL71: =IF(AH71=$AH$7,1,0) -> 0 | AM71: =IF(AI71=$AH$4,1,0) -> 0 | AO71: =IF(OR(AH71=$AH$2,AH71=$AH$5),1,IF(AH71=$AH$6,0.5,0)) -> 0 | AP71: =IF(OR(E71="Sa",E71="So",E71="",J71=0,AH71="FT"),0,1) -> 1 | BL71: =BL68 -> 80.9 | BM71: =BM68 -> 80.9 | BN71: =BO70+BN68 -> 75 | BO71: =BN71+BO68 -> 90
D72: =IF(E72="Mo",WEEKNUM(I72),"") | E72: =TEXT(I72,"TTT") -> Sa | F72: =$F$5 -> 2025 | G72: =$A$44 -> 2 | H72: =H71+1 -> 29 | I72: =DATE(F72,G72,H72) -> 44255 | J72: =IF(OR(G72="",G72=MONTH(I72)),1,0) -> 0 | K72: =IF(OR($E72="Sa",$E72="So",$J72=0),K$4,K$5) -> 0 | L72: =IF(OR($E72="Sa",$E72="So",$J72=0),L$4,L$5) -> 0 | M72: =IF(OR($E72="Sa",$E72="So",$J72=0),M$4,M$5) -> 0 | N72: =IF(OR($E72="Sa",$E72="So",$J72=0),N$4,N$5) -> 0 | O72: =IF(OR($E72="Sa",$E72="So",$J72=0),O$4,O$5) -> 0 | P72: =IF(OR($E72="Sa",$E72="So",$J72=0),P$4,P$5) -> 0 | Q72: =IF(OR($E72="Sa",$E72="So",$J72=0),Q$4,Q$5) -> 0 | R72: =IF(OR($E72="Sa",$E72="So",$J72=0),R$4,R$5) -> 0 | S72: =Q72 -> 0 | T72: =R72 -> 0 | U72: =S72 -> 0 | V72: =T72 -> 0 | W72: =TIME(K72,L72,0) -> 0 | X72: =TIME(M72,N72,0) -> 0 | Y72: =TIME(O72,P72,0) -> 0 | Z72: =TIME(Q72,R72,0) -> 0 | AA72: =TIME(S72,T72,0) -> 0 | AB72: =TIME(U72,V72,0) -> 0 | AD72: =IF(J72=0,0,IF(OR(E72="Sa",E72="So"),TIME($AD$4,$AF$4,0),TIME($AD$5,$AF$5,0))) -> 0 | AF72: =IF(J72=0,0,Z72-W72-(Y72-X72)) -> 0 | AK72: =IF(AH72=$AH$3,1,0) -> 0 | AL72: =IF(AH72=$AH$7,1,0) -> 0 | AM72: =IF(AI72=$AH$4,1,0) -> 0 | AO72: =IF(OR(AH72=$AH$2,AH72=$AH$5),1,IF(AH72=$AH$6,0.5,0)) -> 0 | AP72: =IF(OR(E72="Sa",E72="So",E72="",J72=0,AH72="FT"),0,1) -> 0 | BL72: =BL68 -> 80.9 | BM72: =BM68 -> 80.9 | BN72: =BO71+BN68 -> 105 | BO72: =BN72+BO68 -> 120
D73: =IF(E73="Mo",WEEKNUM(I73),"") | E73: =TEXT(I73,"TTT") -> So | F73: =$F$5 -> 2025 | G73: =$A$44 -> 2 | H73: =H72+1 -> 30 | I73: =DATE(F73,G73,H73) -> 44256 | J73: =IF(OR(G73="",G73=MONTH(I73)),1,0) -> 0 | K73: =IF(OR($E73="Sa",$E73="So",$J73=0),K$4,K$5) -> 0 | L73: =IF(OR($E73="Sa",$E73="So",$J73=0),L$4,L$5) -> 0 | M73: =IF(OR($E73="Sa",$E73="So",$J73=0),M$4,M$5) -> 0 | N73: =IF(OR($E73="Sa",$E73="So",$J73=0),N$4,N$5) -> 0 | O73: =IF(OR($E73="Sa",$E73="So",$J73=0),O$4,O$5) -> 0 | P73: =IF(OR($E73="Sa",$E73="So",$J73=0),P$4,P$5) -> 0 | Q73: =IF(OR($E73="Sa",$E73="So",$J73=0),Q$4,Q$5) -> 0 | R73: =IF(OR($E73="Sa",$E73="So",$J73=0),R$4,R$5) -> 0 | S73: =Q73 -> 0 | T73: =R73 -> 0 | U73: =S73 -> 0 | V73: =T73 -> 0 | W73: =TIME(K73,L73,0) -> 0 | X73: =TIME(M73,N73,0) -> 0 | Y73: =TIME(O73,P73,0) -> 0 | Z73: =TIME(Q73,R73,0) -> 0 | AA73: =TIME(S73,T73,0) -> 0 | AB73: =TIME(U73,V73,0) -> 0 | AD73: =IF(J73=0,0,IF(OR(E73="Sa",E73="So"),TIME($AD$4,$AF$4,0),TIME($AD$5,$AF$5,0))) -> 0 | AF73: =IF(J73=0,0,Z73-W73-(Y73-X73)) -> 0 | AK73: =IF(AH73=$AH$3,1,0) -> 0 | AL73: =IF(AH73=$AH$7,1,0) -> 0 | AM73: =IF(AI73=$AH$4,1,0) -> 0 | AO73: =IF(OR(AH73=$AH$2,AH73=$AH$5),1,IF(AH73=$AH$6,0.5,0)) -> 0 | AP73: =IF(OR(E73="Sa",E73="So",E73="",J73=0,AH73="FT"),0,1) -> 0
D74: =IF(E74="Mo",WEEKNUM(I74),"") -> 10 | E74: =TEXT(I74,"TTT") -> Mo | F74: =$F$5 -> 2025 | G74: =$A$44 -> 2 | H74: =H73+1 -> 31 | I74: =DATE(F74,G74,H74) -> 44257 | J74: =IF(OR(G74="",G74=MONTH(I74)),1,0) -> 0 | K74: =IF(OR($E74="Sa",$E74="So",$J74=0),K$4,K$5) -> 0 | L74: =IF(OR($E74="Sa",$E74="So",$J74=0),L$4,L$5) -> 0 | M74: =IF(OR($E74="Sa",$E74="So",$J74=0),M$4,M$5) -> 0 | N74: =IF(OR($E74="Sa",$E74="So",$J74=0),N$4,N$5) -> 0 | O74: =IF(OR($E74="Sa",$E74="So",$J74=0),O$4,O$5) -> 0 | P74: =IF(OR($E74="Sa",$E74="So",$J74=0),P$4,P$5) -> 0 | Q74: =IF(OR($E74="Sa",$E74="So",$J74=0),Q$4,Q$5) -> 0 | R74: =IF(OR($E74="Sa",$E74="So",$J74=0),R$4,R$5) -> 0 | S74: =Q74 -> 0 | T74: =R74 -> 0 | U74: =S74 -> 0 | V74: =T74 -> 0 | W74: =TIME(K74,L74,0) -> 0 | X74: =TIME(M74,N74,0) -> 0 | Y74: =TIME(O74,P74,0) -> 0 | Z74: =TIME(Q74,R74,0) -> 0 | AA74: =TIME(S74,T74,0) -> 0 | AB74: =TIME(U74,V74,0) -> 0 | AD74: =IF(J74=0,0,IF(OR(E74="Sa",E74="So"),TIME($AD$4,$AF$4,0),TIME($AD$5,$AF$5,0))) -> 0 | AF74: =IF(J74=0,0,Z74-W74-(Y74-X74)) -> 0 | AK74: =IF(AH74=$AH$3,1,0) -> 0 | AL74: =IF(AH74=$AH$7,1,0) -> 0 | AM74: =IF(AI74=$AH$4,1,0) -> 0 | AO74: =IF(OR(AH74=$AH$2,AH74=$AH$5),1,IF(AH74=$AH$6,0.5,0)) -> 0 | AP74: =IF(OR(E74="Sa",E74="So",E74="",J74=0,AH74="FT"),0,1) -> 0
D75: EM | J75: =IF(OR(G75="",G75=MONTH(I75)),1,0) -> 1 | Q75: Summ | AD75: =SUM(AD44:AD74) -> 7.0138889 | AF75: =SUM(AF44:AF74) -> 7.0138889 | AI75: =IF(AF75-AD75<0,0,1) -> 0 | AJ75: =IF(AF75-AD75<0,AD75-AF75,AF75-AD75) -> 2.6645353e-15 | AK75: =8.425*SUM(AK44:AK74)/24 -> 0 | AL75: =8.425*SUM(AL44:AL74)/24 -> 0 | AM75: =8.425*SUM(AM44:AM74)/24 -> 0 | AO75: =SUM(AO44:AO74) -> 0 | AP75: =SUM(AP44:AP74) -> 20
AJ76: =IF(AI75=1,AJ42+AJ75,IF(AI75=0,AJ42-AJ75,"Error")) -> -6.2172489e-15 | AK76: =AK42+SUM(AK43:AK74) -> 0 | AL76: =AL42+SUM(AL43:AL74) -> 0 | AM76: =AM42+SUM(AM43:AM74) -> 0 | AO76: =AO75*8 -> 0 | AP76: =AP75*8 -> 160
B77: =$F$5 -> 2025 | C77: =TEXT(I78,"MMM") -> Mär
A78: =A44+1 -> 3 | D78: =IF(E78="Mo",WEEKNUM(I78),"") | E78: =TEXT(I78,"TTT") -> Sa | F78: =$F$5 -> 2025 | G78: =$A$78 -> 3 | H78: =$H$5 -> 1 | I78: =DATE(F78,G78,H78) -> 44255 | J78: =IF(OR(G78="",G78=MONTH(I78)),1,0) -> 1 | K78: =IF(OR($E78="Sa",$E78="So",$J78=0),K$4,K$5) -> 0 | L78: =IF(OR($E78="Sa",$E78="So",$J78=0),L$4,L$5) -> 0 | M78: =IF(OR($E78="Sa",$E78="So",$J78=0),M$4,M$5) -> 0 | N78: =IF(OR($E78="Sa",$E78="So",$J78=0),N$4,N$5) -> 0 | O78: =IF(OR($E78="Sa",$E78="So",$J78=0),O$4,O$5) -> 0 | P78: =IF(OR($E78="Sa",$E78="So",$J78=0),P$4,P$5) -> 0 | Q78: =IF(OR($E78="Sa",$E78="So",$J78=0),Q$4,Q$5) -> 0 | R78: =IF(OR($E78="Sa",$E78="So",$J78=0),R$4,R$5) -> 0 | S78: =Q78 -> 0 | T78: =R78 -> 0 | U78: =S78 -> 0 | V78: =T78 -> 0 | W78: =TIME(K78,L78,0) -> 0 | X78: =TIME(M78,N78,0) -> 0 | Y78: =TIME(O78,P78,0) -> 0 | Z78: =TIME(Q78,R78,0) -> 0 | AA78: =TIME(S78,T78,0) -> 0 | AB78: =TIME(U78,V78,0) -> 0 | AD78: =IF(J78=0,0,IF(OR(E78="Sa",E78="So"),TIME($AD$4,$AF$4,0),TIME($AD$5,$AF$5,0))) -> 0 | AF78: =IF(J78=0,0,Z78-W78-(Y78-X78)) -> 0 | AK78: =IF(AH78=$AH$3,1,0) -> 0 | AL78: =IF(AH78=$AH$7,1,0) -> 0 | AM78: =IF(AI78=$AH$4,1,0) -> 0 | AO78: =IF(OR(AH78=$AH$2,AH78=$AH$5),1,IF(AH78=$AH$6,0.5,0)) -> 0 | AP78: =IF(OR(E78="Sa",E78="So",E78="",J78=0,AH78="FT"),0,1) -> 0 | BL78: =BL68 -> 80.9 | BM78: =BM68 -> 80.9 | BN78: =BO72+BN68 -> 135 | BO78: =BN78+BO68 -> 150
D79: =IF(E79="Mo",WEEKNUM(I79),"") | E79: =TEXT(I79,"TTT") -> So | F79: =$F$5 -> 2025 | G79: =$A$78 -> 3 | H79: =H78+1 -> 2 | I79: =DATE(F79,G79,H79) -> 44256 | J79: =IF(OR(G79="",G79=MONTH(I79)),1,0) -> 1 | K79: =IF(OR($E79="Sa",$E79="So",$J79=0),K$4,K$5) -> 0 | L79: =IF(OR($E79="Sa",$E79="So",$J79=0),L$4,L$5) -> 0 | M79: =IF(OR($E79="Sa",$E79="So",$J79=0),M$4,M$5) -> 0 | N79: =IF(OR($E79="Sa",$E79="So",$J79=0),N$4,N$5) -> 0 | O79: =IF(OR($E79="Sa",$E79="So",$J79=0),O$4,O$5) -> 0 | P79: =IF(OR($E79="Sa",$E79="So",$J79=0),P$4,P$5) -> 0 | Q79: =IF(OR($E79="Sa",$E79="So",$J79=0),Q$4,Q$5) -> 0 | R79: =IF(OR($E79="Sa",$E79="So",$J79=0),R$4,R$5) -> 0 | S79: =Q79 -> 0 | T79: =R79 -> 0 | U79: =S79 -> 0 | V79: =T79 -> 0 | W79: =TIME(K79,L79,0) -> 0 | X79: =TIME(M79,N79,0) -> 0 | Y79: =TIME(O79,P79,0) -> 0 | Z79: =TIME(Q79,R79,0) -> 0 | AA79: =TIME(S79,T79,0) -> 0 | AB79: =TIME(U79,V79,0) -> 0 | AD79: =IF(J79=0,0,IF(OR(E79="Sa",E79="So"),TIME($AD$4,$AF$4,0),TIME($AD$5,$AF$5,0))) -> 0 | AF79: =IF(J79=0,0,Z79-W79-(Y79-X79)) -> 0 | AK79: =IF(AH79=$AH$3,1,0) -> 0 | AL79: =IF(AH79=$AH$7,1,0) -> 0 | AM79: =IF(AI79=$AH$4,1,0) -> 0 | AO79: =IF(OR(AH79=$AH$2,AH79=$AH$5),1,IF(AH79=$AH$6,0.5,0)) -> 0 | AP79: =IF(OR(E79="Sa",E79="So",E79="",J79=0,AH79="FT"),0,1) -> 0 | BL79: WGTST | BM79: =SUM(BL69:BL78)+SUM(BM69:BM78) -> 809 | BN79: ECO | BO79: ECO
D80: =IF(E80="Mo",WEEKNUM(I80),"") -> 10 | E80: =TEXT(I80,"TTT") -> Mo | F80: =$F$5 -> 2025 | G80: =$A$78 -> 3 | H80: =H79+1 -> 3 | I80: =DATE(F80,G80,H80) -> 44257 | J80: =IF(OR(G80="",G80=MONTH(I80)),1,0) -> 1 | K80: =IF(OR($E80="Sa",$E80="So",$J80=0),K$4,K$5) -> 7 | L80: =IF(OR($E80="Sa",$E80="So",$J80=0),L$4,L$5) -> 0 | M80: =IF(OR($E80="Sa",$E80="So",$J80=0),M$4,M$5) -> 13 | N80: =IF(OR($E80="Sa",$E80="So",$J80=0),N$4,N$5) -> 0 | O80: =IF(OR($E80="Sa",$E80="So",$J80=0),O$4,O$5) -> 13 | P80: =IF(OR($E80="Sa",$E80="So",$J80=0),P$4,P$5) -> 30 | Q80: =IF(OR($E80="Sa",$E80="So",$J80=0),Q$4,Q$5) -> 15 | R80: =IF(OR($E80="Sa",$E80="So",$J80=0),R$4,R$5) -> 55 | S80: =Q80 -> 15 | T80: =R80 -> 55 | U80: =S80 -> 15 | V80: =T80 -> 55 | W80: =TIME(K80,L80,0) -> 0.29166667 | X80: =TIME(M80,N80,0) -> 0.54166667 | Y80: =TIME(O80,P80,0) -> 0.5625 | Z80: =TIME(Q80,R80,0) -> 0.66319444 | AA80: =TIME(S80,T80,0) -> 0.66319444 | AB80: =TIME(U80,V80,0) -> 0.66319444 | AD80: =IF(J80=0,0,IF(OR(E80="Sa",E80="So"),TIME($AD$4,$AF$4,0),TIME($AD$5,$AF$5,0))) -> 0.35069444 | AF80: =IF(J80=0,0,Z80-W80-(Y80-X80)) -> 0.35069444 | AK80: =IF(AH80=$AH$3,1,0) -> 0 | AL80: =IF(AH80=$AH$7,1,0) -> 0 | AM80: =IF(AI80=$AH$4,1,0) -> 0 | AO80: =IF(OR(AH80=$AH$2,AH80=$AH$5),1,IF(AH80=$AH$6,0.5,0)) -> 0 | AP80: =IF(OR(E80="Sa",E80="So",E80="",J80=0,AH80="FT"),0,1) -> 1 | BL80: =INDEX($BF$2:$BG$8,MATCH(BL79,$BF$2:$BF$8,0),2) -> 80.9 | BM80: =INDEX($BF$2:$BG$8,MATCH(BL79,$BF$2:$BF$8,0),2) -> 80.9 | BN80: 15 | BO80: 15
D81: =IF(E81="Mo",WEEKNUM(I81),"") | E81: =TEXT(I81,"TTT") -> Di | F81: =$F$5 -> 2025 | G81: =$A$78 -> 3 | H81: =H80+1 -> 4 | I81: =DATE(F81,G81,H81) -> 44258 | J81: =IF(OR(G81="",G81=MONTH(I81)),1,0) -> 1 | K81: =IF(OR($E81="Sa",$E81="So",$J81=0),K$4,K$5) -> 7 | L81: =IF(OR($E81="Sa",$E81="So",$J81=0),L$4,L$5) -> 0 | M81: =IF(OR($E81="Sa",$E81="So",$J81=0),M$4,M$5) -> 13 | N81: =IF(OR($E81="Sa",$E81="So",$J81=0),N$4,N$5) -> 0 | O81: =IF(OR($E81="Sa",$E81="So",$J81=0),O$4,O$5) -> 13 | P81: =IF(OR($E81="Sa",$E81="So",$J81=0),P$4,P$5) -> 30 | Q81: =IF(OR($E81="Sa",$E81="So",$J81=0),Q$4,Q$5) -> 15 | R81: =IF(OR($E81="Sa",$E81="So",$J81=0),R$4,R$5) -> 55 | S81: =Q81 -> 15 | T81: =R81 -> 55 | U81: =S81 -> 15 | V81: =T81 -> 55 | W81: =TIME(K81,L81,0) -> 0.29166667 | X81: =TIME(M81,N81,0) -> 0.54166667 | Y81: =TIME(O81,P81,0) -> 0.5625 | Z81: =TIME(Q81,R81,0) -> 0.66319444 | AA81: =TIME(S81,T81,0) -> 0.66319444 | AB81: =TIME(U81,V81,0) -> 0.66319444 | AD81: =IF(J81=0,0,IF(OR(E81="Sa",E81="So"),TIME($AD$4,$AF$4,0),TIME($AD$5,$AF$5,0))) -> 0.35069444 | AF81: =IF(J81=0,0,Z81-W81-(Y81-X81)) -> 0.35069444 | AK81: =IF(AH81=$AH$3,1,0) -> 0 | AL81: =IF(AH81=$AH$7,1,0) -> 0 | AM81: =IF(AI81=$AH$4,1,0) -> 0 | AO81: =IF(OR(AH81=$AH$2,AH81=$AH$5),1,IF(AH81=$AH$6,0.5,0)) -> 0 | AP81: =IF(OR(E81="Sa",E81="So",E81="",J81=0,AH81="FT"),0,1) -> 1 | BL81: =BL80 -> 80.9 | BM81: =BM80 -> 80.9 | BN81: =BN80 -> 15 | BO81: =BN81+BO80 -> 30
